Workbook
Name Desinsum: Insumo[DESCRIPCION]
Name Precios: #REF!

Sheet Presupuesto
A1: ALCALDIA DE PEREIRA
A2: VERSION O BASE DE DATOS ALCALDIA DE PEREIRA 2026
A3: FORMULARIO DE PRECIOS
A4: CAPITULO | B4: ACTIVIDAD | C4: UNIDAD | D4: CANTIDAD | E4: VLR UNIT | F4: VLR TOTAL | G4: %
A5: 1 | B5: PRELIMINARES | F5: =SUM(F6:F49) -> 5114815 | G5: =IFERROR(F5/$F$1279,"") -> 1
A6: 1,01 | B6: Arrendamiento inmueble - campamento | C6: M2-Mes | E6: =ROUND(IFERROR(VLOOKUP(A6,'CAP1-3'!$A:$G,7,FALSE()),""),0) -> 26388 | F6: =IFERROR(E6*D6,"") -> 0
A7: 1,02 | B7: Alquiler de baño portátil (2 aseos semanales) | C7: Mes | D7: 5 | E7: =ROUND(IFERROR(VLOOKUP(A7,'CAP1-3'!$A:$G,7,FALSE()),""),0) -> 1022963 | F7: =IFERROR(E7*D7,"") -> 5114815
A8: 1,03 | B8: Apuntalado provisional de estructuras | C8: M2 | E8: =ROUND(IFERROR(VLOOKUP(A8,'CAP1-3'!$A:$G,7,FALSE()),""),0) -> 42814 | F8: =IFERROR(E8*D8,"") -> 0
A9: 1,04 | B9: Barricada seguridad desmontable L=3m | C9: Un | E9: =ROUND(IFERROR(VLOOKUP(A9,'CAP1-3'!$A:$G,7,FALSE()),""),0) -> 637637 | F9: =IFERROR(E9*D9,"") -> 0
A10: 1,05 | B10: Campamento (esterilla + teja zinc + piso) | C10: M2 | E10: =ROUND(IFERROR(VLOOKUP(A10,'CAP1-3'!$A:$G,7,FALSE()),""),0) -> 217769 | F10: =IFERROR(E10*D10,"") -> 0
A11: 1,06 | B11: Campamento (tabla + teja FC + piso) | C11: M2 | E11: =ROUND(IFERROR(VLOOKUP(A11,'CAP1-3'!$A:$G,7,FALSE()),""),0) -> 210970 | F11: =IFERROR(E11*D11,"") -> 0
A12: 1,07 | B12: Cerramiento guadua + alambre Púa 7 H=1.8 m | C12: M | E12: =ROUND(IFERROR(VLOOKUP(A12,'CAP1-3'!$A:$G,7,FALSE()),""),0) -> 28486 | F12: =IFERROR(E12*D12,"") -> 0
A13: 1,08 | B13: Cerramiento guadua + alambre Púa 7 H=2.2 m | C13: M | E13: =ROUND(IFERROR(VLOOKUP(A13,'CAP1-3'!$A:$G,7,FALSE()),""),0) -> 30503 | F13: =IFERROR(E13*D13,"") -> 0
A14: 1,09 | B14: Cerramiento guadua + esterilla H=1.8 m | C14: M | E14: =ROUND(IFERROR(VLOOKUP(A14,'CAP1-3'!$A:$G,7,FALSE()),""),0) -> 45434 | F14: =IFERROR(E14*D14,"") -> 0
A15: 1,10 | B15: Cerramiento guadua + tabla | C15: M | E15: =ROUND(IFERROR(VLOOKUP(A15,'CAP1-3'!$A:$G,7,FALSE()),""),0) -> 51503 | F15: =IFERROR(E15*D15,"") -> 0
A16: 1,11 | B16: Cerramiento guadua + tela verde | C16: M | E16: =ROUND(IFERROR(VLOOKUP(A16,'CAP1-3'!$A:$G,7,FALSE()),""),0) -> 20582 | F16: =IFERROR(E16*D16,"") -> 0
A17: 1,12 | B17: Cerramiento guadua + zinc | C17: M | E17: =ROUND(IFERROR(VLOOKUP(A17,'CAP1-3'!$A:$G,7,FALSE()),""),0) -> 150949 | F17: =IFERROR(E17*D17,"") -> 0
A18: 1,13 | B18: Cerramiento malla electrosoldada U89 H=1.8 m | C18: M | E18: =ROUND(IFERROR(VLOOKUP(A18,'CAP1-3'!$A:$G,7,FALSE()),""),0) -> 42810 | F18: =IFERROR(E18*D18,"") -> 0
A19: 1,14 | B19: Cinta plástica seguridad C 6 | C19: M | E19: =ROUND(IFERROR(VLOOKUP(A19,'CAP1-3'!$A:$G,7,FALSE()),""),0) -> 427 | F19: =IFERROR(E19*D19,"") -> 0
... A49: 1,44 | B49: Volantes monocromáticos | C49: Un | E49: =ROUND(IFERROR(VLOOKUP(A49,'CAP1-3'!$A:$G,7,FALSE()),""),0) -> 3983 | F49: =IFERROR(E49*D49,"") -> 0
A50: 2 | B50: DESMONTES Y DEMOLICIONES | F50: =SUM(F51:F99) -> 0 | G50: =IFERROR(F50/$F$1279,"") -> 0
A51: 2,01 | B51: Demolición andenes | C51: M2 | E51: =ROUND(IFERROR(VLOOKUP(A51,'CAP1-3'!$A:$G,7,FALSE()),""),0) -> 16302 | F51: =IFERROR(E51*D51,"") -> 0
A52: 2,02 | B52: Demolición calados 0.25 x 0.25 | C52: M2 | E52: =ROUND(IFERROR(VLOOKUP(A52,'CAP1-3'!$A:$G,7,FALSE()),""),0) -> 7236 | F52: =IFERROR(E52*D52,"") -> 0
A53: 2,03 | B53: Demolición cerramiento malla y muro | C53: M | E53: =ROUND(IFERROR(VLOOKUP(A53,'CAP1-3'!$A:$G,7,FALSE()),""),0) -> 39768 | F53: =IFERROR(E53*D53,"") -> 0
A54: 2,04 | B54: Demolición de viviendas - incluye cargue + retiro + material sobrante mecánica | C54: M2 | E54: =ROUND(IFERROR(VLOOKUP(A54,'CAP1-3'!$A:$G,7,FALSE()),""),0) -> 86250 | F54: =IFERROR(E54*D54,"") -> 0
A55: 2,05 | B55: Demolición estructuras en concreto reforzados | C55: M3 | E55: =ROUND(IFERROR(VLOOKUP(A55,'CAP1-3'!$A:$G,7,FALSE()),""),0) -> 285383 | F55: =IFERROR(E55*D55,"") -> 0
A56: 2,06 | B56: Demolición cámara inspección | C56: M | E56: =ROUND(IFERROR(VLOOKUP(A56,'CAP1-3'!$A:$G,7,FALSE()),""),0) -> 171230 | F56: =IFERROR(E56*D56,"") -> 0
A57: 2,07 | B57: Demolición cono cámara concreto manual | C57: Un | E57: =ROUND(IFERROR(VLOOKUP(A57,'CAP1-3'!$A:$G,7,FALSE()),""),0) -> 211535 | F57: =IFERROR(E57*D57,"") -> 0
A58: 2,08 | B58: Demolición concreto ciclópeo manual | C58: M3 | E58: =ROUND(IFERROR(VLOOKUP(A58,'CAP1-3'!$A:$G,7,FALSE()),""),0) -> 253841 | F58: =IFERROR(E58*D58,"") -> 0
A59: 2,09 | B59: Demolición concreto mecánico | C59: M3 | E59: =ROUND(IFERROR(VLOOKUP(A59,'CAP1-3'!$A:$G,7,FALSE()),""),0) -> 302170 | F59: =IFERROR(E59*D59,"") -> 0
A60: 2,10 | B60: Demolición de portadas | C60: Un | E60: =ROUND(IFERROR(VLOOKUP(A60,'CAP1-3'!$A:$G,7,FALSE()),""),0) -> 142692 | F60: =IFERROR(E60*D60,"") -> 0
A61: 2,11 | B61: Demolición meson en concreto | C61: M2 | E61: =ROUND(IFERROR(VLOOKUP(A61,'CAP1-3'!$A:$G,7,FALSE()),""),0) -> 12226 | F61: =IFERROR(E61*D61,"") -> 0
A62: 2,12 | B62: Demolición mortero manual | C62: M2 | E62: =ROUND(IFERROR(VLOOKUP(A62,'CAP1-3'!$A:$G,7,FALSE()),""),0) -> 7192 | F62: =IFERROR(E62*D62,"") -> 0
... A99: 2,49 | B99: Desmonte y ajuste puerta / ventana aluminio | C99: M2 | E99: =ROUND(IFERROR(VLOOKUP(A99,'CAP1-3'!$A:$G,7,FALSE()),""),0) -> 68537 | F99: =IFERROR(E99*D99,"") -> 0
A100: 3 | B100: MOVIMIENTOS DE TIERRA Y LLENOS | E100: =IFERROR(VLOOKUP(#REF!,#REF!,8,FALSE()),"") | F100: =SUM(F101:F147) -> 0 | G100: =IFERROR(F100/$F$1279,"") -> 0
A101: 3,02 | B101: Descapote y limpieza manual | C101: M2 | E101: =ROUND(IFERROR(VLOOKUP(A101,'CAP1-3'!$A:$G,7,FALSE()),""),0) -> 9177 | F101: =IFERROR(E101*D101,"") -> 0
A102: 3,03 | B102: Descapote y limpieza manual (incluye retiro) | C102: M2 | E102: =ROUND(IFERROR(VLOOKUP(A102,'CAP1-3'!$A:$G,7,FALSE()),""),0) -> 15216 | F102: =IFERROR(E102*D102,"") -> 0
A103: 3,04 | B103: Descapote y limpieza mecánica | C103: M2 | E103: =ROUND(IFERROR(VLOOKUP(A103,'CAP1-3'!$A:$G,7,FALSE()),""),0) -> 2612 | F103: =IFERROR(E103*D103,"") -> 0
A104: 3,05 | B104: Entibado para excavaciones profundidad mayor a 1.5 m | C104: M2 | E104: =ROUND(IFERROR(VLOOKUP(A104,'CAP1-3'!$A:$G,7,FALSE()),""),0) -> 89352 | F104: =IFERROR(E104*D104,"") -> 0
A105: 3,06 | B105: Excavación caisson / pila en roca | C105: M3 | E105: =ROUND(IFERROR(VLOOKUP(A105,'CAP1-3'!$A:$G,7,FALSE()),""),0) -> 598659 | F105: =IFERROR(E105*D105,"") -> 0
A106: 3,07 | B106: Excavación caisson en conglomerado H= > 10 m | C106: M3 | E106: =ROUND(IFERROR(VLOOKUP(A106,'CAP1-3'!$A:$G,7,FALSE()),""),0) -> 334503 | F106: =IFERROR(E106*D106,"") -> 0
A107: 3,08 | B107: Excavación caisson en conglomerado H= 0 - 10 m | C107: M3 | E107: =ROUND(IFERROR(VLOOKUP(A107,'CAP1-3'!$A:$G,7,FALSE()),""),0) -> 289965 | F107: =IFERROR(E107*D107,"") -> 0
A108: 3,09 | B108: Excavación caisson en material común H= > 10 m | C108: M3 | E108: =ROUND(IFERROR(VLOOKUP(A108,'CAP1-3'!$A:$G,7,FALSE()),""),0) -> 310521 | F108: =IFERROR(E108*D108,"") -> 0
A109: 3,10 | B109: Excavación caisson en material común H= 0 - 10 m | C109: M3 | E109: =ROUND(IFERROR(VLOOKUP(A109,'CAP1-3'!$A:$G,7,FALSE()),""),0) -> 272149 | F109: =IFERROR(E109*D109,"") -> 0
A110: 3,11 | B110: Excavación configuración subrasante manual | C110: M2 | E110: =ROUND(IFERROR(VLOOKUP(A110,'CAP1-3'!$A:$G,7,FALSE()),""),0) -> 2894 | F110: =IFERROR(E110*D110,"") -> 0
A111: 3,12 | B111: Excavación configuración subrasante mecánica | C111: M2 | E111: =ROUND(IFERROR(VLOOKUP(A111,'CAP1-3'!$A:$G,7,FALSE()),""),0) -> 1755 | F111: =IFERROR(E111*D111,"") -> 0
A112: 3,13 | B112: Excavación conglomerado seco H= 0-1.5 m manual | C112: M3 | E112: =ROUND(IFERROR(VLOOKUP(A112,'CAP1-3'!$A:$G,7,FALSE()),""),0) -> 54395 | F112: =IFERROR(E112*D112,"") -> 0
... A147: 3,48 | B147: Restitución afirmado + cemento 5 % peso | C147: M3 | E147: =ROUND(IFERROR(VLOOKUP(A147,'CAP1-3'!$A:$G,7,FALSE()),""),0) -> 264307 | F147: =IFERROR(E147*D147,"") -> 0
A148: 4 | B148: INSTALACIONES SUBTERRANEAS | E148: =IFERROR(VLOOKUP(#REF!,#REF!,8,FALSE()),"") | F148: =SUM(F149:F162) -> 0 | G148: =IFERROR(F148/$F$1279,"") -> 0
A149: 4,01 | B149: Caja inspección concreto 17.2 Mpa 0.20 m libre + tapa | C149: Un | E149: =ROUND(IFERROR(VLOOKUP(A149,'CAP4-5'!$A:$G,7,FALSE()),""),0) -> 152212 | F149: =IFERROR(E149*D149,"") -> 0
A150: 4,02 | B150: Caja inspección concreto 17.2 Mpa 0.30 m libre + tapa | C150: Un | E150: =ROUND(IFERROR(VLOOKUP(A150,'CAP4-5'!$A:$G,7,FALSE()),""),0) -> 205024 | F150: =IFERROR(E150*D150,"") -> 0
A151: 4,03 | B151: Caja inspección concreto 17.2 Mpa 0.60 m libre + tapa | C151: Un | E151: =ROUND(IFERROR(VLOOKUP(A151,'CAP4-5'!$A:$G,7,FALSE()),""),0) -> 500553 | F151: =IFERROR(E151*D151,"") -> 0
A152: 4,04 | B152: Caja inspección concreto 17.2 Mpa 0.75 m libre + tapa | C152: Un | E152: =ROUND(IFERROR(VLOOKUP(A152,'CAP4-5'!$A:$G,7,FALSE()),""),0) -> 720011 | F152: =IFERROR(E152*D152,"") -> 0
A153: 4,05 | B153: Caja inspección concreto 17.2 Mpa 0.80 m libre + tapa | C153: Un | E153: =ROUND(IFERROR(VLOOKUP(A153,'CAP4-5'!$A:$G,7,FALSE()),""),0) -> 751276 | F153: =IFERROR(E153*D153,"") -> 0
A154: 4,06 | B154: Caja inspección concreto 17.2 Mpa 1.00 m libre + tapa | C154: Un | E154: =ROUND(IFERROR(VLOOKUP(A154,'CAP4-5'!$A:$G,7,FALSE()),""),0) -> 933448 | F154: =IFERROR(E154*D154,"") -> 0
A155: 4,07 | B155: Caja inspección concreto 20.7 Mpa 0.80 m h=1.3 libre | C155: Un | E155: =ROUND(IFERROR(VLOOKUP(A155,'CAP4-5'!$A:$G,7,FALSE()),""),0) -> 764147 | F155: =IFERROR(E155*D155,"") -> 0
A156: 4,08 | B156: Caja inspección concreto 20.7 Mpa 1.00 m h=1.3 libre | C156: Un | E156: =ROUND(IFERROR(VLOOKUP(A156,'CAP4-5'!$A:$G,7,FALSE()),""),0) -> 1006279 | F156: =IFERROR(E156*D156,"") -> 0
A157: 4,09 | B157: Caja contador con tapa HD | C157: Un | E157: =ROUND(IFERROR(VLOOKUP(A157,'CAP4-5'!$A:$G,7,FALSE()),""),0) -> 317530 | F157: =IFERROR(E157*D157,"") -> 0
A158: 4,10 | B158: Caja contador polipropileno | C158: Un | E158: =ROUND(IFERROR(VLOOKUP(A158,'CAP4-5'!$A:$G,7,FALSE()),""),0) -> 75315 | F158: =IFERROR(E158*D158,"") -> 0
A159: 4,11 | B159: Empalme a redes de alcantarillado | C159: Un | E159: =ROUND(IFERROR(VLOOKUP(A159,'CAP4-5'!$A:$G,7,FALSE()),""),0) -> 293504 | F159: =IFERROR(E159*D159,"") -> 0
A160: 4,12 | B160: Fijación de tubería de 6" a 8" (incluye abrazadera metálica) | C160: Un | E160: =ROUND(IFERROR(VLOOKUP(A160,'CAP4-5'!$A:$G,7,FALSE()),""),0) -> 63200 | F160: =IFERROR(E160*D160,"") -> 0
... A162: 4,14 | B162: Reparación caja domiciliaria área neta 0.6x0.6 + tapa | C162: Un | E162: =ROUND(IFERROR(VLOOKUP(A162,'CAP4-5'!$A:$G,7,FALSE()),""),0) -> 128026 | F162: =IFERROR(E162*D162,"") -> 0
A163: 5 | B163: ESTRUCTURAS | F163: =SUM(F164:F293) -> 0 | G163: =IFERROR(F163/$F$1279,"") -> 0
A164: 5,01 | B164: Acero de refuerzo 420 Mpa | C164: Kg | E164: =ROUND(IFERROR(VLOOKUP(A164,'CAP4-5'!$A:$G,7,FALSE()),""),0) -> 9340 | F164: =IFERROR(E164*D164,"") -> 0
A165: 5,02 | B165: Cinta amarre confinamiento | C165: M | E165: =ROUND(IFERROR(VLOOKUP(A165,'CAP4-5'!$A:$G,7,FALSE()),""),0) -> 62761 | F165: =IFERROR(E165*D165,"") -> 0
A166: 5,03 | B166: Columna rectangular confinamiento concreto 20.7 Mpa | C166: M | E166: =ROUND(IFERROR(VLOOKUP(A166,'CAP4-5'!$A:$G,7,FALSE()),""),0) -> 119015 | F166: =IFERROR(E166*D166,"") -> 0
A167: 5,04 | B167: Columna circular 20.7 Mpa (área <=1.600 cm2) | C167: M3 | E167: =ROUND(IFERROR(VLOOKUP(A167,'CAP4-5'!$A:$G,7,FALSE()),""),0) -> 1188484 | F167: =IFERROR(E167*D167,"") -> 0
A168: 5,05 | B168: Columna circular 20.7 Mpa (1.600 cm2 <área<= 2.500 cm2) | C168: M3 | E168: =ROUND(IFERROR(VLOOKUP(A168,'CAP4-5'!$A:$G,7,FALSE()),""),0) -> 1141184 | F168: =IFERROR(E168*D168,"") -> 0
A169: 5,06 | B169: Columna circular 20.7 Mpa (2.500 cm2 <área<= 3.600 cm2) | C169: M3 | E169: =ROUND(IFERROR(VLOOKUP(A169,'CAP4-5'!$A:$G,7,FALSE()),""),0) -> 1117007 | F169: =IFERROR(E169*D169,"") -> 0
A170: 5,07 | B170: Columna circular 20.7 Mpa (área >=3.600 cm2) | C170: M3 | E170: =ROUND(IFERROR(VLOOKUP(A170,'CAP4-5'!$A:$G,7,FALSE()),""),0) -> 1086034 | F170: =IFERROR(E170*D170,"") -> 0
A171: 5,08 | B171: Columna circular 24.1 Mpa (área <=1.600 cm2) | C171: M3 | E171: =ROUND(IFERROR(VLOOKUP(A171,'CAP4-5'!$A:$G,7,FALSE()),""),0) -> 1208047 | F171: =IFERROR(E171*D171,"") -> 0
A172: 5,09 | B172: Columna circular 24.1 Mpa (1.600 cm2 <área<= 2.500 cm2) | C172: M3 | E172: =ROUND(IFERROR(VLOOKUP(A172,'CAP4-5'!$A:$G,7,FALSE()),""),0) -> 1160746 | F172: =IFERROR(E172*D172,"") -> 0
A173: 5,10 | B173: Columna circular 24.1 Mpa (2.500 cm2 <área<= 3.600 cm2) | C173: M3 | E173: =ROUND(IFERROR(VLOOKUP(A173,'CAP4-5'!$A:$G,7,FALSE()),""),0) -> 1136569 | F173: =IFERROR(E173*D173,"") -> 0
A174: 5,11 | B174: Columna circular 24.1 Mpa (área >=3.600 cm2) | C174: M3 | E174: =ROUND(IFERROR(VLOOKUP(A174,'CAP4-5'!$A:$G,7,FALSE()),""),0) -> 1105596 | F174: =IFERROR(E174*D174,"") -> 0
A175: 5,12 | B175: Columna circular 27.6 Mpa (área <=1.600 cm2) | C175: M3 | E175: =ROUND(IFERROR(VLOOKUP(A175,'CAP4-5'!$A:$G,7,FALSE()),""),0) -> 1238143 | F175: =IFERROR(E175*D175,"") -> 0
... A293: 5,130 | B293: Zarpa concreto ciclópeo | C293: M3 | E293: =ROUND(IFERROR(VLOOKUP(A293,'CAP4-5'!$A:$G,7,FALSE()),""),0) -> 594820 | F293: =IFERROR(E293*D293,"") -> 0
A294: 6 | B294: MAMPOSTERIA Y REVOQUES | F294: =SUM(F295:F343) -> 0 | G294: =IFERROR(F294/$F$1279,"") -> 0
A295: 6,01 | B295: Abuzardado de concreto | C295: M2 | E295: =ROUND(IFERROR(VLOOKUP(A295,'CAP6-7'!$A:$G,7,FALSE()),""),0) -> 36824 | F295: =IFERROR(E295*D295,"") -> 0
A296: 6,02 | B296: Alfajía ladrillo visto pandereta | C296: M | E296: =ROUND(IFERROR(VLOOKUP(A296,'CAP6-7'!$A:$G,7,FALSE()),""),0) -> 58919 | F296: =IFERROR(E296*D296,"") -> 0
A297: 6,03 | B297: Alfajía lámina C 22 S=0.30 m | C297: M | E297: =ROUND(IFERROR(VLOOKUP(A297,'CAP6-7'!$A:$G,7,FALSE()),""),0) -> 98952 | F297: =IFERROR(E297*D297,"") -> 0
A298: 6,04 | B298: Alfajía remate ancho = 0.3 m concreto 20.7 Mpa reforzado | C298: M | E298: =ROUND(IFERROR(VLOOKUP(A298,'CAP6-7'!$A:$G,7,FALSE()),""),0) -> 80182 | F298: =IFERROR(E298*D298,"") -> 0
A299: 6,05 | B299: Alfajía remate ancho = 0.4 m concreto 20.7 Mpa reforzado | C299: M | E299: =ROUND(IFERROR(VLOOKUP(A299,'CAP6-7'!$A:$G,7,FALSE()),""),0) -> 85345 | F299: =IFERROR(E299*D299,"") -> 0
A300: 6,06 | B300: Alfajía remate ancho = 0.5 m concreto 20.7 Mpa reforzado | C300: M | E300: =ROUND(IFERROR(VLOOKUP(A300,'CAP6-7'!$A:$G,7,FALSE()),""),0) -> 91018 | F300: =IFERROR(E300*D300,"") -> 0
A301: 6,07 | B301: Alfajía remate ancho = 0.6 m concreto 20.7 Mpa reforzado | C301: M | E301: =ROUND(IFERROR(VLOOKUP(A301,'CAP6-7'!$A:$G,7,FALSE()),""),0) -> 101826 | F301: =IFERROR(E301*D301,"") -> 0
A302: 6,08 | B302: Anclaje manual varilla Ø =3/8" L< Ø =0.30m | C302: Un | E302: =ROUND(IFERROR(VLOOKUP(A302,'CAP6-7'!$A:$G,7,FALSE()),""),0) -> 15218 | F302: =IFERROR(E302*D302,"") -> 0
A303: 6,09 | B303: Anclaje manual varilla Ø=1/2" L< Ø =0.40m | C303: Un | E303: =ROUND(IFERROR(VLOOKUP(A303,'CAP6-7'!$A:$G,7,FALSE()),""),0) -> 19133 | F303: =IFERROR(E303*D303,"") -> 0
A304: 6,10 | B304: Anclaje manual varilla Ø =3/4" L< Ø =0.70m | C304: Un | E304: =ROUND(IFERROR(VLOOKUP(A304,'CAP6-7'!$A:$G,7,FALSE()),""),0) -> 38999 | F304: =IFERROR(E304*D304,"") -> 0
A305: 6,11 | B305: Anclaje manual varilla Ø =5/8" L< Ø =0.50m | C305: Un | E305: =ROUND(IFERROR(VLOOKUP(A305,'CAP6-7'!$A:$G,7,FALSE()),""),0) -> 26829 | F305: =IFERROR(E305*D305,"") -> 0
A306: 6,12 | B306: Calado cerámica figuras 0.20x0.20x0.10/0.12 | C306: M2 | E306: =ROUND(IFERROR(VLOOKUP(A306,'CAP6-7'!$A:$G,7,FALSE()),""),0) -> 151105 | F306: =IFERROR(E306*D306,"") -> 0
... A343: 6,49 | B343: Sobrecimiento ladrillo tolete tizón + soga | C343: M2 | E343: =ROUND(IFERROR(VLOOKUP(A343,'CAP6-7'!$A:$G,7,FALSE()),""),0) -> 149562 | F343: =IFERROR(E343*D343,"") -> 0
A344: 7 | B344: INSTALACIONES HIDROSANITARIAS | F344: =SUM(F345:F432) -> 0 | G344: =IFERROR(F344/$F$1279,"") -> 0
A345: 7,01 | B345: Acometida hidráulica domicilio PF+UAD todo costo | C345: Un | E345: =ROUND(IFERROR(VLOOKUP(A345,'CAP6-7'!$A:$G,7,FALSE()),""),0) -> 91477 | F345: =IFERROR(E345*D345,"") -> 0
A346: 7,02 | B346: Abrazadera de fijación tuberia de presión | C346: Un | E346: =ROUND(IFERROR(VLOOKUP(A346,'CAP6-7'!$A:$G,7,FALSE()),""),0) -> 40468 | F346: =IFERROR(E346*D346,"") -> 0
A347: 7,03 | B347: Abrazadera de fijación tuberia sanitaria | C347: Un | E347: =ROUND(IFERROR(VLOOKUP(A347,'CAP6-7'!$A:$G,7,FALSE()),""),0) -> 65611 | F347: =IFERROR(E347*D347,"") -> 0
A348: 7,04 | B348: Bajante PVC 3" aguas negras + accesorios | C348: M | E348: =ROUND(IFERROR(VLOOKUP(A348,'CAP6-7'!$A:$G,7,FALSE()),""),0) -> 40679 | F348: =IFERROR(E348*D348,"") -> 0
A349: 7,05 | B349: Bajante PVC 4" aguas negras + accesorios | C349: M | E349: =ROUND(IFERROR(VLOOKUP(A349,'CAP6-7'!$A:$G,7,FALSE()),""),0) -> 56378 | F349: =IFERROR(E349*D349,"") -> 0
A350: 7,06 | B350: Bajante PVC 3" aguas lluvias + accesorios | C350: M | E350: =ROUND(IFERROR(VLOOKUP(A350,'CAP6-7'!$A:$G,7,FALSE()),""),0) -> 28404 | F350: =IFERROR(E350*D350,"") -> 0
A351: 7,07 | B351: Bajante PVC 4" aguas lluvias + accesorios | C351: M | E351: =ROUND(IFERROR(VLOOKUP(A351,'CAP6-7'!$A:$G,7,FALSE()),""),0) -> 45001 | F351: =IFERROR(E351*D351,"") -> 0
A352: 7,08 | B352: Bajante PVC aguas lluvias cuadrado | C352: M | E352: =ROUND(IFERROR(VLOOKUP(A352,'CAP6-7'!$A:$G,7,FALSE()),""),0) -> 31397 | F352: =IFERROR(E352*D352,"") -> 0
A353: 7,09 | B353: Cámaras de aire | C353: Un | E353: =ROUND(IFERROR(VLOOKUP(A353,'CAP6-7'!$A:$G,7,FALSE()),""),0) -> 19923 | F353: =IFERROR(E353*D353,"") -> 0
...

Sheet Insumos
A1: =+Presupuesto!A1 -> ALCALDIA DE PEREIRA
A2: =+Presupuesto!A2 -> VERSION O BASE DE DATOS ALCALDIA DE PEREIRA 2026
A3: LISTA DE MATERIALES | T3: 1.05
A4: DESCRIPCION | B4: UND | C4: VALOR | D4: CANTIDAD | E4: TOTAL | F4: CAP1-3 | G4: CAP4-5 | H4: CAP6-7 | I4: CAP8 | J4: CAP9-13 | K4: CAP14-15 | L4: CAP16-18 | M4: CAP19-22 | N4: CAP23-24 | O4: CAP25 | P4: CAP26-28 | Q4: CAP29 | R4: OBSERVACIONES | T4: VALOR
A5: Abrazadera metalica para tuberia pvc presion | B5: Un | C5: =T5*$T$3 -> 28416.15 | D5: {=IF(Insumo[[#This Row],[VALOR]]=0,Insumo[TOTAL],E5/C5)} -> 0 | E5: =SUM(Insumo[[#This Row],[CAP1-3]:[CAP29]]) -> 0 | F5: =SUMIF('CAP1-3'!$B:$H,Insumo[[#This Row],[DESCRIPCION]],'CAP1-3'!$H:$H) -> 0 | G5: =SUMIF('CAP4-5'!$B:$H,Insumo[[#This Row],[DESCRIPCION]],'CAP4-5'!$H:$H) -> 0 | H5: =SUMIF('CAP6-7'!$B:$H,Insumo[[#This Row],[DESCRIPCION]],'CAP6-7'!$H:$H) -> 0 | I5: =SUMIF('CAP8'!$B:$H,Insumo[[#This Row],[DESCRIPCION]],'CAP8'!$H:$H) -> 0 | J5: =SUMIF('CAP9-13'!$B:$H,Insumo[[#This Row],[DESCRIPCION]],'CAP9-13'!$H:$H) -> 0 | K5: =SUMIF('CAP14-15'!$B:$H,Insumo[[#This Row],[DESCRIPCION]],'CAP14-15'!$H:$H) -> 0 | L5: =SUMIF('CAP16-18'!$B:$H,Insumo[[#This Row],[DESCRIPCION]],'CAP16-18'!$H:$H) -> 0 | M5: =SUMIF('CAP19-22'!$B:$H,Insumo[[#This Row],[DESCRIPCION]],'CAP19-22'!$H:$H) -> 0 | N5: =SUMIF('CAP23-24'!$B:$H,Insumo[[#This Row],[DESCRIPCION]],'CAP23-24'!$H:$H) -> 0 | O5: =SUMIF('CAP25'!$B:$H,Insumo[[#This Row],[DESCRIPCION]],'CAP25'!$H:$H) -> 0 | P5: =SUMIF('CAP26-28'!$B:$H,Insumo[[#This Row],[DESCRIPCION]],'CAP26-28'!$H:$H) -> 0 | Q5: =SUMIF('CAP29'!$B:$H,Insumo[[#This Row],[DESCRIPCION]],'CAP29'!$H:$H) -> 0 | T5: 27063
A6: Abrazadera metalica para tuberia pvc sanitaria | B6: Un | C6: =T6*$T$3 -> 51148.65 | D6: {=IF(Insumo[[#This Row],[VALOR]]=0,Insumo[TOTAL],E6/C6)} -> 0 | E6: =SUM(Insumo[[#This Row],[CAP1-3]:[CAP29]]) -> 0 | F6: =SUMIF('CAP1-3'!$B:$H,Insumo[[#This Row],[DESCRIPCION]],'CAP1-3'!$H:$H) -> 0 | G6: =SUMIF('CAP4-5'!$B:$H,Insumo[[#This Row],[DESCRIPCION]],'CAP4-5'!$H:$H) -> 0 | H6: =SUMIF('CAP6-7'!$B:$H,Insumo[[#This Row],[DESCRIPCION]],'CAP6-7'!$H:$H) -> 0 | I6: =SUMIF('CAP8'!$B:$H,Insumo[[#This Row],[DESCRIPCION]],'CAP8'!$H:$H) -> 0 | J6: =SUMIF('CAP9-13'!$B:$H,Insumo[[#This Row],[DESCRIPCION]],'CAP9-13'!$H:$H) -> 0 | K6: =SUMIF('CAP14-15'!$B:$H,Insumo[[#This Row],[DESCRIPCION]],'CAP14-15'!$H:$H) -> 0 | L6: =SUMIF('CAP16-18'!$B:$H,Insumo[[#This Row],[DESCRIPCION]],'CAP16-18'!$H:$H) -> 0 | M6: =SUMIF('CAP19-22'!$B:$H,Insumo[[#This Row],[DESCRIPCION]],'CAP19-22'!$H:$H) -> 0 | N6: =SUMIF('CAP23-24'!$B:$H,Insumo[[#This Row],[DESCRIPCION]],'CAP23-24'!$H:$H) -> 0 | O6: =SUMIF('CAP25'!$B:$H,Insumo[[#This Row],[DESCRIPCION]],'CAP25'!$H:$H) -> 0 | P6: =SUMIF('CAP26-28'!$B:$H,Insumo[[#This Row],[DESCRIPCION]],'CAP26-28'!$H:$H) -> 0 | Q6: =SUMIF('CAP29'!$B:$H,Insumo[[#This Row],[DESCRIPCION]],'CAP29'!$H:$H) -> 0 | T6: 48713
A7: Abrazadera tipo mecanico 1 1/2" | B7: Un | C7: =T7*$T$3 -> 10230.15 | D7: {=IF(Insumo[[#This Row],[VALOR]]=0,Insumo[TOTAL],E7/C7)} -> 0 | E7: =SUM(Insumo[[#This Row],[CAP1-3]:[CAP29]]) -> 0 | F7: =SUMIF('CAP1-3'!$B:$H,Insumo[[#This Row],[DESCRIPCION]],'CAP1-3'!$H:$H) -> 0 | G7: =SUMIF('CAP4-5'!$B:$H,Insumo[[#This Row],[DESCRIPCION]],'CAP4-5'!$H:$H) -> 0 | H7: =SUMIF('CAP6-7'!$B:$H,Insumo[[#This Row],[DESCRIPCION]],'CAP6-7'!$H:$H) -> 0 | I7: =SUMIF('CAP8'!$B:$H,Insumo[[#This Row],[DESCRIPCION]],'CAP8'!$H:$H) -> 0 | J7: =SUMIF('CAP9-13'!$B:$H,Insumo[[#This Row],[DESCRIPCION]],'CAP9-13'!$H:$H) -> 0 | K7: =SUMIF('CAP14-15'!$B:$H,Insumo[[#This Row],[DESCRIPCION]],'CAP14-15'!$H:$H) -> 0 | L7: =SUMIF('CAP16-18'!$B:$H,Insumo[[#This Row],[DESCRIPCION]],'CAP16-18'!$H:$H) -> 0 | M7: =SUMIF('CAP19-22'!$B:$H,Insumo[[#This Row],[DESCRIPCION]],'CAP19-22'!$H:$H) -> 0 | N7: =SUMIF('CAP23-24'!$B:$H,Insumo[[#This Row],[DESCRIPCION]],'CAP23-24'!$H:$H) -> 0 | O7: =SUMIF('CAP25'!$B:$H,Insumo[[#This Row],[DESCRIPCION]],'CAP25'!$H:$H) -> 0 | P7: =SUMIF('CAP26-28'!$B:$H,Insumo[[#This Row],[DESCRIPCION]],'CAP26-28'!$H:$H) -> 0 | Q7: =SUMIF('CAP29'!$B:$H,Insumo[[#This Row],[DESCRIPCION]],'CAP29'!$H:$H) -> 0 | T7: 9743
A8: Abrazadera tipo mecanico 1 1/4" | B8: Un | C8: =T8*$T$3 -> 6819.75 | D8: {=IF(Insumo[[#This Row],[VALOR]]=0,Insumo[TOTAL],E8/C8)} -> 0 | E8: =SUM(Insumo[[#This Row],[CAP1-3]:[CAP29]]) -> 0 | F8: =SUMIF('CAP1-3'!$B:$H,Insumo[[#This Row],[DESCRIPCION]],'CAP1-3'!$H:$H) -> 0 | G8: =SUMIF('CAP4-5'!$B:$H,Insumo[[#This Row],[DESCRIPCION]],'CAP4-5'!$H:$H) -> 0 | H8: =SUMIF('CAP6-7'!$B:$H,Insumo[[#This Row],[DESCRIPCION]],'CAP6-7'!$H:$H) -> 0 | I8: =SUMIF('CAP8'!$B:$H,Insumo[[#This Row],[DESCRIPCION]],'CAP8'!$H:$H) -> 0 | J8: =SUMIF('CAP9-13'!$B:$H,Insumo[[#This Row],[DESCRIPCION]],'CAP9-13'!$H:$H) -> 0 | K8: =SUMIF('CAP14-15'!$B:$H,Insumo[[#This Row],[DESCRIPCION]],'CAP14-15'!$H:$H) -> 0 | L8: =SUMIF('CAP16-18'!$B:$H,Insumo[[#This Row],[DESCRIPCION]],'CAP16-18'!$H:$H) -> 0 | M8: =SUMIF('CAP19-22'!$B:$H,Insumo[[#This Row],[DESCRIPCION]],'CAP19-22'!$H:$H) -> 0 | N8: =SUMIF('CAP23-24'!$B:$H,Insumo[[#This Row],[DESCRIPCION]],'CAP23-24'!$H:$H) -> 0 | O8: =SUMIF('CAP25'!$B:$H,Insumo[[#This Row],[DESCRIPCION]],'CAP25'!$H:$H) -> 0 | P8: =SUMIF('CAP26-28'!$B:$H,Insumo[[#This Row],[DESCRIPCION]],'CAP26-28'!$H:$H) -> 0 | Q8: =SUMIF('CAP29'!$B:$H,Insumo[[#This Row],[DESCRIPCION]],'CAP29'!$H:$H) -> 0 | T8: 6495
A9: Abrazadera tipo mecanico 1" | B9: Un | C9: =T9*$T$3 -> 5683.65 | D9: {=IF(Insumo[[#This Row],[VALOR]]=0,Insumo[TOTAL],E9/C9)} -> 0 | E9: =SUM(Insumo[[#This Row],[CAP1-3]:[CAP29]]) -> 0 | F9: =SUMIF('CAP1-3'!$B:$H,Insumo[[#This Row],[DESCRIPCION]],'CAP1-3'!$H:$H) -> 0 | G9: =SUMIF('CAP4-5'!$B:$H,Insumo[[#This Row],[DESCRIPCION]],'CAP4-5'!$H:$H) -> 0 | H9: =SUMIF('CAP6-7'!$B:$H,Insumo[[#This Row],[DESCRIPCION]],'CAP6-7'!$H:$H) -> 0 | I9: =SUMIF('CAP8'!$B:$H,Insumo[[#This Row],[DESCRIPCION]],'CAP8'!$H:$H) -> 0 | J9: =SUMIF('CAP9-13'!$B:$H,Insumo[[#This Row],[DESCRIPCION]],'CAP9-13'!$H:$H) -> 0 | K9: =SUMIF('CAP14-15'!$B:$H,Insumo[[#This Row],[DESCRIPCION]],'CAP14-15'!$H:$H) -> 0 | L9: =SUMIF('CAP16-18'!$B:$H,Insumo[[#This Row],[DESCRIPCION]],'CAP16-18'!$H:$H) -> 0 | M9: =SUMIF('CAP19-22'!$B:$H,Insumo[[#This Row],[DESCRIPCION]],'CAP19-22'!$H:$H) -> 0 | N9: =SUMIF('CAP23-24'!$B:$H,Insumo[[#This Row],[DESCRIPCION]],'CAP23-24'!$H:$H) -> 0 | O9: =SUMIF('CAP25'!$B:$H,Insumo[[#This Row],[DESCRIPCION]],'CAP25'!$H:$H) -> 0 | P9: =SUMIF('CAP26-28'!$B:$H,Insumo[[#This Row],[DESCRIPCION]],'CAP26-28'!$H:$H) -> 0 | Q9: =SUMIF('CAP29'!$B:$H,Insumo[[#This Row],[DESCRIPCION]],'CAP29'!$H:$H) -> 0 | T9: 5413
A10: Abrazadera tipo mecanico 2 1/2" | B10: Un | C10: =T10*$T$3 -> 15912.75 | D10: {=IF(Insumo[[#This Row],[VALOR]]=0,Insumo[TOTAL],E10/C10)} -> 0 | E10: =SUM(Insumo[[#This Row],[CAP1-3]:[CAP29]]) -> 0 | F10: =SUMIF('CAP1-3'!$B:$H,Insumo[[#This Row],[DESCRIPCION]],'CAP1-3'!$H:$H) -> 0 | G10: =SUMIF('CAP4-5'!$B:$H,Insumo[[#This Row],[DESCRIPCION]],'CAP4-5'!$H:$H) -> 0 | H10: =SUMIF('CAP6-7'!$B:$H,Insumo[[#This Row],[DESCRIPCION]],'CAP6-7'!$H:$H) -> 0 | I10: =SUMIF('CAP8'!$B:$H,Insumo[[#This Row],[DESCRIPCION]],'CAP8'!$H:$H) -> 0 | J10: =SUMIF('CAP9-13'!$B:$H,Insumo[[#This Row],[DESCRIPCION]],'CAP9-13'!$H:$H) -> 0 | K10: =SUMIF('CAP14-15'!$B:$H,Insumo[[#This Row],[DESCRIPCION]],'CAP14-15'!$H:$H) -> 0 | L10: =SUMIF('CAP16-18'!$B:$H,Insumo[[#This Row],[DESCRIPCION]],'CAP16-18'!$H:$H) -> 0 | M10: =SUMIF('CAP19-22'!$B:$H,Insumo[[#This Row],[DESCRIPCION]],'CAP19-22'!$H:$H) -> 0 | N10: =SUMIF('CAP23-24'!$B:$H,Insumo[[#This Row],[DESCRIPCION]],'CAP23-24'!$H:$H) -> 0 | O10: =SUMIF('CAP25'!$B:$H,Insumo[[#This Row],[DESCRIPCION]],'CAP25'!$H:$H) -> 0 | P10: =SUMIF('CAP26-28'!$B:$H,Insumo[[#This Row],[DESCRIPCION]],'CAP26-28'!$H:$H) -> 0 | Q10: =SUMIF('CAP29'!$B:$H,Insumo[[#This Row],[DESCRIPCION]],'CAP29'!$H:$H) -> 0 | T10: 15155
A11: Abrazadera tipo mecanico 2" | B11: Un | C11: =T11*$T$3 -> 12503.4 | D11: {=IF(Insumo[[#This Row],[VALOR]]=0,Insumo[TOTAL],E11/C11)} -> 0 | E11: =SUM(Insumo[[#This Row],[CAP1-3]:[CAP29]]) -> 0 | F11: =SUMIF('CAP1-3'!$B:$H,Insumo[[#This Row],[DESCRIPCION]],'CAP1-3'!$H:$H) -> 0 | G11: =SUMIF('CAP4-5'!$B:$H,Insumo[[#This Row],[DESCRIPCION]],'CAP4-5'!$H:$H) -> 0 | H11: =SUMIF('CAP6-7'!$B:$H,Insumo[[#This Row],[DESCRIPCION]],'CAP6-7'!$H:$H) -> 0 | I11: =SUMIF('CAP8'!$B:$H,Insumo[[#This Row],[DESCRIPCION]],'CAP8'!$H:$H) -> 0 | J11: =SUMIF('CAP9-13'!$B:$H,Insumo[[#This Row],[DESCRIPCION]],'CAP9-13'!$H:$H) -> 0 | K11: =SUMIF('CAP14-15'!$B:$H,Insumo[[#This Row],[DESCRIPCION]],'CAP14-15'!$H:$H) -> 0 | L11: =SUMIF('CAP16-18'!$B:$H,Insumo[[#This Row],[DESCRIPCION]],'CAP16-18'!$H:$H) -> 0 | M11: =SUMIF('CAP19-22'!$B:$H,Insumo[[#This Row],[DESCRIPCION]],'CAP19-22'!$H:$H) -> 0 | N11: =SUMIF('CAP23-24'!$B:$H,Insumo[[#This Row],[DESCRIPCION]],'CAP23-24'!$H:$H) -> 0 | O11: =SUMIF('CAP25'!$B:$H,Insumo[[#This Row],[DESCRIPCION]],'CAP25'!$H:$H) -> 0 | P11: =SUMIF('CAP26-28'!$B:$H,Insumo[[#This Row],[DESCRIPCION]],'CAP26-28'!$H:$H) -> 0 | Q11: =SUMIF('CAP29'!$B:$H,Insumo[[#This Row],[DESCRIPCION]],'CAP29'!$H:$H) -> 0 | T11: 11908
A12: Abrazadera tipo mecanico 4" | B12: Un | C12: =T12*$T$3 -> 22732.5 | D12: {=IF(Insumo[[#This Row],[VALOR]]=0,Insumo[TOTAL],E12/C12)} -> 0 | E12: =SUM(Insumo[[#This Row],[CAP1-3]:[CAP29]]) -> 0 | F12: =SUMIF('CAP1-3'!$B:$H,Insumo[[#This Row],[DESCRIPCION]],'CAP1-3'!$H:$H) -> 0 | G12: =SUMIF('CAP4-5'!$B:$H,Insumo[[#This Row],[DESCRIPCION]],'CAP4-5'!$H:$H) -> 0 | H12: =SUMIF('CAP6-7'!$B:$H,Insumo[[#This Row],[DESCRIPCION]],'CAP6-7'!$H:$H) -> 0 | I12: =SUMIF('CAP8'!$B:$H,Insumo[[#This Row],[DESCRIPCION]],'CAP8'!$H:$H) -> 0 | J12: =SUMIF('CAP9-13'!$B:$H,Insumo[[#This Row],[DESCRIPCION]],'CAP9-13'!$H:$H) -> 0 | K12: =SUMIF('CAP14-15'!$B:$H,Insumo[[#This Row],[DESCRIPCION]],'CAP14-15'!$H:$H) -> 0 | L12: =SUMIF('CAP16-18'!$B:$H,Insumo[[#This Row],[DESCRIPCION]],'CAP16-18'!$H:$H) -> 0 | M12: =SUMIF('CAP19-22'!$B:$H,Insumo[[#This Row],[DESCRIPCION]],'CAP19-22'!$H:$H) -> 0 | N12: =SUMIF('CAP23-24'!$B:$H,Insumo[[#This Row],[DESCRIPCION]],'CAP23-24'!$H:$H) -> 0 | O12: =SUMIF('CAP25'!$B:$H,Insumo[[#This Row],[DESCRIPCION]],'CAP25'!$H:$H) -> 0 | P12: =SUMIF('CAP26-28'!$B:$H,Insumo[[#This Row],[DESCRIPCION]],'CAP26-28'!$H:$H) -> 0 | Q12: =SUMIF('CAP29'!$B:$H,Insumo[[#This Row],[DESCRIPCION]],'CAP29'!$H:$H) -> 0 | T12: 21650
A13: Accesorios bandeja portacables 10x8 (cruz, te, codo, reduccion) promedio | B13: Un | C13: =T13*$T$3 -> 75600 | D13: {=IF(Insumo[[#This Row],[VALOR]]=0,Insumo[TOTAL],E13/C13)} -> 0 | E13: =SUM(Insumo[[#This Row],[CAP1-3]:[CAP29]]) -> 0 | F13: =SUMIF('CAP1-3'!$B:$H,Insumo[[#This Row],[DESCRIPCION]],'CAP1-3'!$H:$H) -> 0 | G13: =SUMIF('CAP4-5'!$B:$H,Insumo[[#This Row],[DESCRIPCION]],'CAP4-5'!$H:$H) -> 0 | H13: =SUMIF('CAP6-7'!$B:$H,Insumo[[#This Row],[DESCRIPCION]],'CAP6-7'!$H:$H) -> 0 | I13: =SUMIF('CAP8'!$B:$H,Insumo[[#This Row],[DESCRIPCION]],'CAP8'!$H:$H) -> 0 | J13: =SUMIF('CAP9-13'!$B:$H,Insumo[[#This Row],[DESCRIPCION]],'CAP9-13'!$H:$H) -> 0 | K13: =SUMIF('CAP14-15'!$B:$H,Insumo[[#This Row],[DESCRIPCION]],'CAP14-15'!$H:$H) -> 0 | L13: =SUMIF('CAP16-18'!$B:$H,Insumo[[#This Row],[DESCRIPCION]],'CAP16-18'!$H:$H) -> 0 | M13: =SUMIF('CAP19-22'!$B:$H,Insumo[[#This Row],[DESCRIPCION]],'CAP19-22'!$H:$H) -> 0 | N13: =SUMIF('CAP23-24'!$B:$H,Insumo[[#This Row],[DESCRIPCION]],'CAP23-24'!$H:$H) -> 0 | O13: =SUMIF('CAP25'!$B:$H,Insumo[[#This Row],[DESCRIPCION]],'CAP25'!$H:$H) -> 0 | P13: =SUMIF('CAP26-28'!$B:$H,Insumo[[#This Row],[DESCRIPCION]],'CAP26-28'!$H:$H) -> 0 | Q13: =SUMIF('CAP29'!$B:$H,Insumo[[#This Row],[DESCRIPCION]],'CAP29'!$H:$H) -> 0 | T13: 72000
A14: Accesorios bandeja portacables 20x8 (cruz, te, codo, reduccion) promedio | B14: Un | C14: =T14*$T$3 -> 88200 | D14: {=IF(Insumo[[#This Row],[VALOR]]=0,Insumo[TOTAL],E14/C14)} -> 0 | E14: =SUM(Insumo[[#This Row],[CAP1-3]:[CAP29]]) -> 0 | F14: =SUMIF('CAP1-3'!$B:$H,Insumo[[#This Row],[DESCRIPCION]],'CAP1-3'!$H:$H) -> 0 | G14: =SUMIF('CAP4-5'!$B:$H,Insumo[[#This Row],[DESCRIPCION]],'CAP4-5'!$H:$H) -> 0 | H14: =SUMIF('CAP6-7'!$B:$H,Insumo[[#This Row],[DESCRIPCION]],'CAP6-7'!$H:$H) -> 0 | I14: =SUMIF('CAP8'!$B:$H,Insumo[[#This Row],[DESCRIPCION]],'CAP8'!$H:$H) -> 0 | J14: =SUMIF('CAP9-13'!$B:$H,Insumo[[#This Row],[DESCRIPCION]],'CAP9-13'!$H:$H) -> 0 | K14: =SUMIF('CAP14-15'!$B:$H,Insumo[[#This Row],[DESCRIPCION]],'CAP14-15'!$H:$H) -> 0 | L14: =SUMIF('CAP16-18'!$B:$H,Insumo[[#This Row],[DESCRIPCION]],'CAP16-18'!$H:$H) -> 0 | M14: =SUMIF('CAP19-22'!$B:$H,Insumo[[#This Row],[DESCRIPCION]],'CAP19-22'!$H:$H) -> 0 | N14: =SUMIF('CAP23-24'!$B:$H,Insumo[[#This Row],[DESCRIPCION]],'CAP23-24'!$H:$H) -> 0 | O14: =SUMIF('CAP25'!$B:$H,Insumo[[#This Row],[DESCRIPCION]],'CAP25'!$H:$H) -> 0 | P14: =SUMIF('CAP26-28'!$B:$H,Insumo[[#This Row],[DESCRIPCION]],'CAP26-28'!$H:$H) -> 0 | Q14: =SUMIF('CAP29'!$B:$H,Insumo[[#This Row],[DESCRIPCION]],'CAP29'!$H:$H) -> 0 | T14: 84000
A15: Accesorios bandeja portacables 30x8 (cruz, te, codo, reduccion) promedio | B15: Un | C15: =T15*$T$3 -> 98280 | D15: {=IF(Insumo[[#This Row],[VALOR]]=0,Insumo[TOTAL],E15/C15)} -> 0 | E15: =SUM(Insumo[[#This Row],[CAP1-3]:[CAP29]]) -> 0 | F15: =SUMIF('CAP1-3'!$B:$H,Insumo[[#This Row],[DESCRIPCION]],'CAP1-3'!$H:$H) -> 0 | G15: =SUMIF('CAP4-5'!$B:$H,Insumo[[#This Row],[DESCRIPCION]],'CAP4-5'!$H:$H) -> 0 | H15: =SUMIF('CAP6-7'!$B:$H,Insumo[[#This Row],[DESCRIPCION]],'CAP6-7'!$H:$H) -> 0 | I15: =SUMIF('CAP8'!$B:$H,Insumo[[#This Row],[DESCRIPCION]],'CAP8'!$H:$H) -> 0 | J15: =SUMIF('CAP9-13'!$B:$H,Insumo[[#This Row],[DESCRIPCION]],'CAP9-13'!$H:$H) -> 0 | K15: =SUMIF('CAP14-15'!$B:$H,Insumo[[#This Row],[DESCRIPCION]],'CAP14-15'!$H:$H) -> 0 | L15: =SUMIF('CAP16-18'!$B:$H,Insumo[[#This Row],[DESCRIPCION]],'CAP16-18'!$H:$H) -> 0 | M15: =SUMIF('CAP19-22'!$B:$H,Insumo[[#This Row],[DESCRIPCION]],'CAP19-22'!$H:$H) -> 0 | N15: =SUMIF('CAP23-24'!$B:$H,Insumo[[#This Row],[DESCRIPCION]],'CAP23-24'!$H:$H) -> 0 | O15: =SUMIF('CAP25'!$B:$H,Insumo[[#This Row],[DESCRIPCION]],'CAP25'!$H:$H) -> 0 | P15: =SUMIF('CAP26-28'!$B:$H,Insumo[[#This Row],[DESCRIPCION]],'CAP26-28'!$H:$H) -> 0 | Q15: =SUMIF('CAP29'!$B:$H,Insumo[[#This Row],[DESCRIPCION]],'CAP29'!$H:$H) -> 0 | T15: 93600
A16: Accesorios bandeja portacables 40x8 (cruz, te, codo, reduccion) promedio | B16: Un | C16: =T16*$T$3 -> 107100 | D16: {=IF(Insumo[[#This Row],[VALOR]]=0,Insumo[TOTAL],E16/C16)} -> 0 | E16: =SUM(Insumo[[#This Row],[CAP1-3]:[CAP29]]) -> 0 | F16: =SUMIF('CAP1-3'!$B:$H,Insumo[[#This Row],[DESCRIPCION]],'CAP1-3'!$H:$H) -> 0 | G16: =SUMIF('CAP4-5'!$B:$H,Insumo[[#This Row],[DESCRIPCION]],'CAP4-5'!$H:$H) -> 0 | H16: =SUMIF('CAP6-7'!$B:$H,Insumo[[#This Row],[DESCRIPCION]],'CAP6-7'!$H:$H) -> 0 | I16: =SUMIF('CAP8'!$B:$H,Insumo[[#This Row],[DESCRIPCION]],'CAP8'!$H:$H) -> 0 | J16: =SUMIF('CAP9-13'!$B:$H,Insumo[[#This Row],[DESCRIPCION]],'CAP9-13'!$H:$H) -> 0 | K16: =SUMIF('CAP14-15'!$B:$H,Insumo[[#This Row],[DESCRIPCION]],'CAP14-15'!$H:$H) -> 0 | L16: =SUMIF('CAP16-18'!$B:$H,Insumo[[#This Row],[DESCRIPCION]],'CAP16-18'!$H:$H) -> 0 | M16: =SUMIF('CAP19-22'!$B:$H,Insumo[[#This Row],[DESCRIPCION]],'CAP19-22'!$H:$H) -> 0 | N16: =SUMIF('CAP23-24'!$B:$H,Insumo[[#This Row],[DESCRIPCION]],'CAP23-24'!$H:$H) -> 0 | O16: =SUMIF('CAP25'!$B:$H,Insumo[[#This Row],[DESCRIPCION]],'CAP25'!$H:$H) -> 0 | P16: =SUMIF('CAP26-28'!$B:$H,Insumo[[#This Row],[DESCRIPCION]],'CAP26-28'!$H:$H) -> 0 | Q16: =SUMIF('CAP29'!$B:$H,Insumo[[#This Row],[DESCRIPCION]],'CAP29'!$H:$H) -> 0 | T16: 102000
... A22: Accesorios conduit PVC Ø=1 1/4" | B22: Un | C22: =T22*$T$3 -> 6238.05 | D22: {=IF(Insumo[[#This Row],[VALOR]]=0,Insumo[TOTAL],E22/C22)} -> 0 | E22: =SUM(Insumo[[#This Row],[CAP1-3]:[CAP29]]) -> 0 | F22: =SUMIF('CAP1-3'!$B:$H,Insumo[[#This Row],[DESCRIPCION]],'CAP1-3'!$H:$H) -> 0 | G22: =SUMIF('CAP4-5'!$B:$H,Insumo[[#This Row],[DESCRIPCION]],'CAP4-5'!$H:$H) -> 0 | H22: =SUMIF('CAP6-7'!$B:$H,Insumo[[#This Row],[DESCRIPCION]],'CAP6-7'!$H:$H) -> 0 | I22: =SUMIF('CAP8'!$B:$H,Insumo[[#This Row],[DESCRIPCION]],'CAP8'!$H:$H) -> 0 | J22: =SUMIF('CAP9-13'!$B:$H,Insumo[[#This Row],[DESCRIPCION]],'CAP9-13'!$H:$H) -> 0 | K22: =SUMIF('CAP14-15'!$B:$H,Insumo[[#This Row],[DESCRIPCION]],'CAP14-15'!$H:$H) -> 0 | L22: =SUMIF('CAP16-18'!$B:$H,Insumo[[#This Row],[DESCRIPCION]],'CAP16-18'!$H:$H) -> 0 | M22: =SUMIF('CAP19-22'!$B:$H,Insumo[[#This Row],[DESCRIPCION]],'CAP19-22'!$H:$H) -> 0 | N22: =SUMIF('CAP23-24'!$B:$H,Insumo[[#This Row],[DESCRIPCION]],'CAP23-24'!$H:$H) -> 0 | O22: =SUMIF('CAP25'!$B:$H,Insumo[[#This Row],[DESCRIPCION]],'CAP25'!$H:$H) -> 0 | P22: =SUMIF('CAP26-28'!$B:$H,Insumo[[#This Row],[DESCRIPCION]],'CAP26-28'!$H:$H) -> 0 | Q22: =SUMIF('CAP29'!$B:$H,Insumo[[#This Row],[DESCRIPCION]],'CAP29'!$H:$H) -> 0 | T22: 5941
A23: Accesorios conduit PVC Ø=1/2" | B23: Un | C23: =T23*$T$3 -> 2086.35 | D23: {=IF(Insumo[[#This Row],[VALOR]]=0,Insumo[TOTAL],E23/C23)} -> 0 | E23: =SUM(Insumo[[#This Row],[CAP1-3]:[CAP29]]) -> 0 | F23: =SUMIF('CAP1-3'!$B:$H,Insumo[[#This Row],[DESCRIPCION]],'CAP1-3'!$H:$H) -> 0 | G23: =SUMIF('CAP4-5'!$B:$H,Insumo[[#This Row],[DESCRIPCION]],'CAP4-5'!$H:$H) -> 0 | H23: =SUMIF('CAP6-7'!$B:$H,Insumo[[#This Row],[DESCRIPCION]],'CAP6-7'!$H:$H) -> 0 | I23: =SUMIF('CAP8'!$B:$H,Insumo[[#This Row],[DESCRIPCION]],'CAP8'!$H:$H) -> 0 | J23: =SUMIF('CAP9-13'!$B:$H,Insumo[[#This Row],[DESCRIPCION]],'CAP9-13'!$H:$H) -> 0 | K23: =SUMIF('CAP14-15'!$B:$H,Insumo[[#This Row],[DESCRIPCION]],'CAP14-15'!$H:$H) -> 0 | L23: =SUMIF('CAP16-18'!$B:$H,Insumo[[#This Row],[DESCRIPCION]],'CAP16-18'!$H:$H) -> 0 | M23: =SUMIF('CAP19-22'!$B:$H,Insumo[[#This Row],[DESCRIPCION]],'CAP19-22'!$H:$H) -> 0 | N23: =SUMIF('CAP23-24'!$B:$H,Insumo[[#This Row],[DESCRIPCION]],'CAP23-24'!$H:$H) -> 0 | O23: =SUMIF('CAP25'!$B:$H,Insumo[[#This Row],[DESCRIPCION]],'CAP25'!$H:$H) -> 0 | P23: =SUMIF('CAP26-28'!$B:$H,Insumo[[#This Row],[DESCRIPCION]],'CAP26-28'!$H:$H) -> 0 | Q23: =SUMIF('CAP29'!$B:$H,Insumo[[#This Row],[DESCRIPCION]],'CAP29'!$H:$H) -> 0 | R23: Gerfor Feb-2025 | T23: 1987
A24: Accesorios CPVC presión Ø=1" | B24: Un | C24: =T24*$T$3 -> 35906.85 | D24: {=IF(Insumo[[#This Row],[VALOR]]=0,Insumo[TOTAL],E24/C24)} -> 0 | E24: =SUM(Insumo[[#This Row],[CAP1-3]:[CAP29]]) -> 0 | F24: =SUMIF('CAP1-3'!$B:$H,Insumo[[#This Row],[DESCRIPCION]],'CAP1-3'!$H:$H) -> 0 | G24: =SUMIF('CAP4-5'!$B:$H,Insumo[[#This Row],[DESCRIPCION]],'CAP4-5'!$H:$H) -> 0 | H24: =SUMIF('CAP6-7'!$B:$H,Insumo[[#This Row],[DESCRIPCION]],'CAP6-7'!$H:$H) -> 0 | I24: =SUMIF('CAP8'!$B:$H,Insumo[[#This Row],[DESCRIPCION]],'CAP8'!$H:$H) -> 0 | J24: =SUMIF('CAP9-13'!$B:$H,Insumo[[#This Row],[DESCRIPCION]],'CAP9-13'!$H:$H) -> 0 | K24: =SUMIF('CAP14-15'!$B:$H,Insumo[[#This Row],[DESCRIPCION]],'CAP14-15'!$H:$H) -> 0 | L24: =SUMIF('CAP16-18'!$B:$H,Insumo[[#This Row],[DESCRIPCION]],'CAP16-18'!$H:$H) -> 0 | M24: =SUMIF('CAP19-22'!$B:$H,Insumo[[#This Row],[DESCRIPCION]],'CAP19-22'!$H:$H) -> 0 | N24: =SUMIF('CAP23-24'!$B:$H,Insumo[[#This Row],[DESCRIPCION]],'CAP23-24'!$H:$H) -> 0 | O24: =SUMIF('CAP25'!$B:$H,Insumo[[#This Row],[DESCRIPCION]],'CAP25'!$H:$H) -> 0 | P24: =SUMIF('CAP26-28'!$B:$H,Insumo[[#This Row],[DESCRIPCION]],'CAP26-28'!$H:$H) -> 0 | Q24: =SUMIF('CAP29'!$B:$H,Insumo[[#This Row],[DESCRIPCION]],'CAP29'!$H:$H) -> 0 | R24: Gerfor Feb-2025 | T24: 34197
A25: Accesorios CPVC presión Ø=1/2" | B25: Un | C25: =T25*$T$3 -> 3488.1 | D25: {=IF(Insumo[[#This Row],[VALOR]]=0,Insumo[TOTAL],E25/C25)} -> 0 | E25: =SUM(Insumo[[#This Row],[CAP1-3]:[CAP29]]) -> 0 | F25: =SUMIF('CAP1-3'!$B:$H,Insumo[[#This Row],[DESCRIPCION]],'CAP1-3'!$H:$H) -> 0 | G25: =SUMIF('CAP4-5'!$B:$H,Insumo[[#This Row],[DESCRIPCION]],'CAP4-5'!$H:$H) -> 0 | H25: =SUMIF('CAP6-7'!$B:$H,Insumo[[#This Row],[DESCRIPCION]],'CAP6-7'!$H:$H) -> 0 | I25: =SUMIF('CAP8'!$B:$H,Insumo[[#This Row],[DESCRIPCION]],'CAP8'!$H:$H) -> 0 | J25: =SUMIF('CAP9-13'!$B:$H,Insumo[[#This Row],[DESCRIPCION]],'CAP9-13'!$H:$H) -> 0 | K25: =SUMIF('CAP14-15'!$B:$H,Insumo[[#This Row],[DESCRIPCION]],'CAP14-15'!$H:$H) -> 0 | L25: =SUMIF('CAP16-18'!$B:$H,Insumo[[#This Row],[DESCRIPCION]],'CAP16-18'!$H:$H) -> 0 | M25: =SUMIF('CAP19-22'!$B:$H,Insumo[[#This Row],[DESCRIPCION]],'CAP19-22'!$H:$H) -> 0 | N25: =SUMIF('CAP23-24'!$B:$H,Insumo[[#This Row],[DESCRIPCION]],'CAP23-24'!$H:$H) -> 0 | O25: =SUMIF('CAP25'!$B:$H,Insumo[[#This Row],[DESCRIPCION]],'CAP25'!$H:$H) -> 0 | P25: =SUMIF('CAP26-28'!$B:$H,Insumo[[#This Row],[DESCRIPCION]],'CAP26-28'!$H:$H) -> 0 | Q25: =SUMIF('CAP29'!$B:$H,Insumo[[#This Row],[DESCRIPCION]],'CAP29'!$H:$H) -> 0 | R25: Gerfor Feb-2025 | T25: 3322
A26: Accesorios CPVC presión Ø=3/4" | B26: Un | C26: =T26*$T$3 -> 5551.35 | D26: {=IF(Insumo[[#This Row],[VALOR]]=0,Insumo[TOTAL],E26/C26)} -> 0 | E26: =SUM(Insumo[[#This Row],[CAP1-3]:[CAP29]]) -> 0 | F26: =SUMIF('CAP1-3'!$B:$H,Insumo[[#This Row],[DESCRIPCION]],'CAP1-3'!$H:$H) -> 0 | G26: =SUMIF('CAP4-5'!$B:$H,Insumo[[#This Row],[DESCRIPCION]],'CAP4-5'!$H:$H) -> 0 | H26: =SUMIF('CAP6-7'!$B:$H,Insumo[[#This Row],[DESCRIPCION]],'CAP6-7'!$H:$H) -> 0 | I26: =SUMIF('CAP8'!$B:$H,Insumo[[#This Row],[DESCRIPCION]],'CAP8'!$H:$H) -> 0 | J26: =SUMIF('CAP9-13'!$B:$H,Insumo[[#This Row],[DESCRIPCION]],'CAP9-13'!$H:$H) -> 0 | K26: =SUMIF('CAP14-15'!$B:$H,Insumo[[#This Row],[DESCRIPCION]],'CAP14-15'!$H:$H) -> 0 | L26: =SUMIF('CAP16-18'!$B:$H,Insumo[[#This Row],[DESCRIPCION]],'CAP16-18'!$H:$H) -> 0 | M26: =SUMIF('CAP19-22'!$B:$H,Insumo[[#This Row],[DESCRIPCION]],'CAP19-22'!$H:$H) -> 0 | N26: =SUMIF('CAP23-24'!$B:$H,Insumo[[#This Row],[DESCRIPCION]],'CAP23-24'!$H:$H) -> 0 | O26: =SUMIF('CAP25'!$B:$H,Insumo[[#This Row],[DESCRIPCION]],'CAP25'!$H:$H) -> 0 | P26: =SUMIF('CAP26-28'!$B:$H,Insumo[[#This Row],[DESCRIPCION]],'CAP26-28'!$H:$H) -> 0 | Q26: =SUMIF('CAP29'!$B:$H,Insumo[[#This Row],[DESCRIPCION]],'CAP29'!$H:$H) -> 0 | R26: Gerfor Feb-2025 | T26: 5287
A27: Accesorios HG 1 1/2" | B27: Un | C27: =T27*$T$3 -> 20459.25 | D27: {=IF(Insumo[[#This Row],[VALOR]]=0,Insumo[TOTAL],E27/C27)} -> 0 | E27: =SUM(Insumo[[#This Row],[CAP1-3]:[CAP29]]) -> 0 | F27: =SUMIF('CAP1-3'!$B:$H,Insumo[[#This Row],[DESCRIPCION]],'CAP1-3'!$H:$H) -> 0 | G27: =SUMIF('CAP4-5'!$B:$H,Insumo[[#This Row],[DESCRIPCION]],'CAP4-5'!$H:$H) -> 0 | H27: =SUMIF('CAP6-7'!$B:$H,Insumo[[#This Row],[DESCRIPCION]],'CAP6-7'!$H:$H) -> 0 | I27: =SUMIF('CAP8'!$B:$H,Insumo[[#This Row],[DESCRIPCION]],'CAP8'!$H:$H) -> 0 | J27: =SUMIF('CAP9-13'!$B:$H,Insumo[[#This Row],[DESCRIPCION]],'CAP9-13'!$H:$H) -> 0 | K27: =SUMIF('CAP14-15'!$B:$H,Insumo[[#This Row],[DESCRIPCION]],'CAP14-15'!$H:$H) -> 0 | L27: =SUMIF('CAP16-18'!$B:$H,Insumo[[#This Row],[DESCRIPCION]],'CAP16-18'!$H:$H) -> 0 | M27: =SUMIF('CAP19-22'!$B:$H,Insumo[[#This Row],[DESCRIPCION]],'CAP19-22'!$H:$H) -> 0 | N27: =SUMIF('CAP23-24'!$B:$H,Insumo[[#This Row],[DESCRIPCION]],'CAP23-24'!$H:$H) -> 0 | O27: =SUMIF('CAP25'!$B:$H,Insumo[[#This Row],[DESCRIPCION]],'CAP25'!$H:$H) -> 0 | P27: =SUMIF('CAP26-28'!$B:$H,Insumo[[#This Row],[DESCRIPCION]],'CAP26-28'!$H:$H) -> 0 | Q27: =SUMIF('CAP29'!$B:$H,Insumo[[#This Row],[DESCRIPCION]],'CAP29'!$H:$H) -> 0 | T27: 19485
A28: Accesorios HG 1 1/4" | B28: Un | C28: =T28*$T$3 -> 13639.5 | D28: {=IF(Insumo[[#This Row],[VALOR]]=0,Insumo[TOTAL],E28/C28)} -> 0 | E28: =SUM(Insumo[[#This Row],[CAP1-3]:[CAP29]]) -> 0 | F28: =SUMIF('CAP1-3'!$B:$H,Insumo[[#This Row],[DESCRIPCION]],'CAP1-3'!$H:$H) -> 0 | G28: =SUMIF('CAP4-5'!$B:$H,Insumo[[#This Row],[DESCRIPCION]],'CAP4-5'!$H:$H) -> 0 | H28: =SUMIF('CAP6-7'!$B:$H,Insumo[[#This Row],[DESCRIPCION]],'CAP6-7'!$H:$H) -> 0 | I28: =SUMIF('CAP8'!$B:$H,Insumo[[#This Row],[DESCRIPCION]],'CAP8'!$H:$H) -> 0 | J28: =SUMIF('CAP9-13'!$B:$H,Insumo[[#This Row],[DESCRIPCION]],'CAP9-13'!$H:$H) -> 0 | K28: =SUMIF('CAP14-15'!$B:$H,Insumo[[#This Row],[DESCRIPCION]],'CAP14-15'!$H:$H) -> 0 | L28: =SUMIF('CAP16-18'!$B:$H,Insumo[[#This Row],[DESCRIPCION]],'CAP16-18'!$H:$H) -> 0 | M28: =SUMIF('CAP19-22'!$B:$H,Insumo[[#This Row],[DESCRIPCION]],'CAP19-22'!$H:$H) -> 0 | N28: =SUMIF('CAP23-24'!$B:$H,Insumo[[#This Row],[DESCRIPCION]],'CAP23-24'!$H:$H) -> 0 | O28: =SUMIF('CAP25'!$B:$H,Insumo[[#This Row],[DESCRIPCION]],'CAP25'!$H:$H) -> 0 | P28: =SUMIF('CAP26-28'!$B:$H,Insumo[[#This Row],[DESCRIPCION]],'CAP26-28'!$H:$H) -> 0 | Q28: =SUMIF('CAP29'!$B:$H,Insumo[[#This Row],[DESCRIPCION]],'CAP29'!$H:$H) -> 0 | T28: 12990
A29: Accesorios HG 1" | B29: Un | C29: =T29*$T$3 -> 9093 | D29: {=IF(Insumo[[#This Row],[VALOR]]=0,Insumo[TOTAL],E29/C29)} -> 0 | E29: =SUM(Insumo[[#This Row],[CAP1-3]:[CAP29]]) -> 0 | F29: =SUMIF('CAP1-3'!$B:$H,Insumo[[#This Row],[DESCRIPCION]],'CAP1-3'!$H:$H) -> 0 | G29: =SUMIF('CAP4-5'!$B:$H,Insumo[[#This Row],[DESCRIPCION]],'CAP4-5'!$H:$H) -> 0 | H29: =SUMIF('CAP6-7'!$B:$H,Insumo[[#This Row],[DESCRIPCION]],'CAP6-7'!$H:$H) -> 0 | I29: =SUMIF('CAP8'!$B:$H,Insumo[[#This Row],[DESCRIPCION]],'CAP8'!$H:$H) -> 0 | J29: =SUMIF('CAP9-13'!$B:$H,Insumo[[#This Row],[DESCRIPCION]],'CAP9-13'!$H:$H) -> 0 | K29: =SUMIF('CAP14-15'!$B:$H,Insumo[[#This Row],[DESCRIPCION]],'CAP14-15'!$H:$H) -> 0 | L29: =SUMIF('CAP16-18'!$B:$H,Insumo[[#This Row],[DESCRIPCION]],'CAP16-18'!$H:$H) -> 0 | M29: =SUMIF('CAP19-22'!$B:$H,Insumo[[#This Row],[DESCRIPCION]],'CAP19-22'!$H:$H) -> 0 | N29: =SUMIF('CAP23-24'!$B:$H,Insumo[[#This Row],[DESCRIPCION]],'CAP23-24'!$H:$H) -> 0 | O29: =SUMIF('CAP25'!$B:$H,Insumo[[#This Row],[DESCRIPCION]],'CAP25'!$H:$H) -> 0 | P29: =SUMIF('CAP26-28'!$B:$H,Insumo[[#This Row],[DESCRIPCION]],'CAP26-28'!$H:$H) -> 0 | Q29: =SUMIF('CAP29'!$B:$H,Insumo[[#This Row],[DESCRIPCION]],'CAP29'!$H:$H) -> 0 | T29: 8660
A30: Accesorios HG 1/2" | B30: Un | C30: =T30*$T$3 -> 3978.45 | D30: {=IF(Insumo[[#This Row],[VALOR]]=0,Insumo[TOTAL],E30/C30)} -> 0 | E30: =SUM(Insumo[[#This Row],[CAP1-3]:[CAP29]]) -> 0 | F30: =SUMIF('CAP1-3'!$B:$H,Insumo[[#This Row],[DESCRIPCION]],'CAP1-3'!$H:$H) -> 0 | G30: =SUMIF('CAP4-5'!$B:$H,Insumo[[#This Row],[DESCRIPCION]],'CAP4-5'!$H:$H) -> 0 | H30: =SUMIF('CAP6-7'!$B:$H,Insumo[[#This Row],[DESCRIPCION]],'CAP6-7'!$H:$H) -> 0 | I30: =SUMIF('CAP8'!$B:$H,Insumo[[#This Row],[DESCRIPCION]],'CAP8'!$H:$H) -> 0 | J30: =SUMIF('CAP9-13'!$B:$H,Insumo[[#This Row],[DESCRIPCION]],'CAP9-13'!$H:$H) -> 0 | K30: =SUMIF('CAP14-15'!$B:$H,Insumo[[#This Row],[DESCRIPCION]],'CAP14-15'!$H:$H) -> 0 | L30: =SUMIF('CAP16-18'!$B:$H,Insumo[[#This Row],[DESCRIPCION]],'CAP16-18'!$H:$H) -> 0 | M30: =SUMIF('CAP19-22'!$B:$H,Insumo[[#This Row],[DESCRIPCION]],'CAP19-22'!$H:$H) -> 0 | N30: =SUMIF('CAP23-24'!$B:$H,Insumo[[#This Row],[DESCRIPCION]],'CAP23-24'!$H:$H) -> 0 | O30: =SUMIF('CAP25'!$B:$H,Insumo[[#This Row],[DESCRIPCION]],'CAP25'!$H:$H) -> 0 | P30: =SUMIF('CAP26-28'!$B:$H,Insumo[[#This Row],[DESCRIPCION]],'CAP26-28'!$H:$H) -> 0 | Q30: =SUMIF('CAP29'!$B:$H,Insumo[[#This Row],[DESCRIPCION]],'CAP29'!$H:$H) -> 0 | T30: 3789
A31: Accesorios HG 2 1/2" | B31: Un | C31: =T31*$T$3 -> 36372 | D31: {=IF(Insumo[[#This Row],[VALOR]]=0,Insumo[TOTAL],E31/C31)} -> 0 | E31: =SUM(Insumo[[#This Row],[CAP1-3]:[CAP29]]) -> 0 | F31: =SUMIF('CAP1-3'!$B:$H,Insumo[[#This Row],[DESCRIPCION]],'CAP1-3'!$H:$H) -> 0 | G31: =SUMIF('CAP4-5'!$B:$H,Insumo[[#This Row],[DESCRIPCION]],'CAP4-5'!$H:$H) -> 0 | H31: =SUMIF('CAP6-7'!$B:$H,Insumo[[#This Row],[DESCRIPCION]],'CAP6-7'!$H:$H) -> 0 | I31: =SUMIF('CAP8'!$B:$H,Insumo[[#This Row],[DESCRIPCION]],'CAP8'!$H:$H) -> 0 | J31: =SUMIF('CAP9-13'!$B:$H,Insumo[[#This Row],[DESCRIPCION]],'CAP9-13'!$H:$H) -> 0 | K31: =SUMIF('CAP14-15'!$B:$H,Insumo[[#This Row],[DESCRIPCION]],'CAP14-15'!$H:$H) -> 0 | L31: =SUMIF('CAP16-18'!$B:$H,Insumo[[#This Row],[DESCRIPCION]],'CAP16-18'!$H:$H) -> 0 | M31: =SUMIF('CAP19-22'!$B:$H,Insumo[[#This Row],[DESCRIPCION]],'CAP19-22'!$H:$H) -> 0 | N31: =SUMIF('CAP23-24'!$B:$H,Insumo[[#This Row],[DESCRIPCION]],'CAP23-24'!$H:$H) -> 0 | O31: =SUMIF('CAP25'!$B:$H,Insumo[[#This Row],[DESCRIPCION]],'CAP25'!$H:$H) -> 0 | P31: =SUMIF('CAP26-28'!$B:$H,Insumo[[#This Row],[DESCRIPCION]],'CAP26-28'!$H:$H) -> 0 | Q31: =SUMIF('CAP29'!$B:$H,Insumo[[#This Row],[DESCRIPCION]],'CAP29'!$H:$H) -> 0 | T31: 34640
A32: Accesorios HG 2" | B32: Un | C32: =T32*$T$3 -> 28416.15 | D32: {=IF(Insumo[[#This Row],[VALOR]]=0,Insumo[TOTAL],E32/C32)} -> 0 | E32: =SUM(Insumo[[#This Row],[CAP1-3]:[CAP29]]) -> 0 | F32: =SUMIF('CAP1-3'!$B:$H,Insumo[[#This Row],[DESCRIPCION]],'CAP1-3'!$H:$H) -> 0 | G32: =SUMIF('CAP4-5'!$B:$H,Insumo[[#This Row],[DESCRIPCION]],'CAP4-5'!$H:$H) -> 0 | H32: =SUMIF('CAP6-7'!$B:$H,Insumo[[#This Row],[DESCRIPCION]],'CAP6-7'!$H:$H) -> 0 | I32: =SUMIF('CAP8'!$B:$H,Insumo[[#This Row],[DESCRIPCION]],'CAP8'!$H:$H) -> 0 | J32: =SUMIF('CAP9-13'!$B:$H,Insumo[[#This Row],[DESCRIPCION]],'CAP9-13'!$H:$H) -> 0 | K32: =SUMIF('CAP14-15'!$B:$H,Insumo[[#This Row],[DESCRIPCION]],'CAP14-15'!$H:$H) -> 0 | L32: =SUMIF('CAP16-18'!$B:$H,Insumo[[#This Row],[DESCRIPCION]],'CAP16-18'!$H:$H) -> 0 | M32: =SUMIF('CAP19-22'!$B:$H,Insumo[[#This Row],[DESCRIPCION]],'CAP19-22'!$H:$H) -> 0 | N32: =SUMIF('CAP23-24'!$B:$H,Insumo[[#This Row],[DESCRIPCION]],'CAP23-24'!$H:$H) -> 0 | O32: =SUMIF('CAP25'!$B:$H,Insumo[[#This Row],[DESCRIPCION]],'CAP25'!$H:$H) -> 0 | P32: =SUMIF('CAP26-28'!$B:$H,Insumo[[#This Row],[DESCRIPCION]],'CAP26-28'!$H:$H) -> 0 | Q32: =SUMIF('CAP29'!$B:$H,Insumo[[#This Row],[DESCRIPCION]],'CAP29'!$H:$H) -> 0 | T32: 27063
A33: Accesorios HG 3" | B33: Un | C33: =T33*$T$3 -> 45465 | D33: {=IF(Insumo[[#This Row],[VALOR]]=0,Insumo[TOTAL],E33/C33)} -> 0 | E33: =SUM(Insumo[[#This Row],[CAP1-3]:[CAP29]]) -> 0 | F33: =SUMIF('CAP1-3'!$B:$H,Insumo[[#This Row],[DESCRIPCION]],'CAP1-3'!$H:$H) -> 0 | G33: =SUMIF('CAP4-5'!$B:$H,Insumo[[#This Row],[DESCRIPCION]],'CAP4-5'!$H:$H) -> 0 | H33: =SUMIF('CAP6-7'!$B:$H,Insumo[[#This Row],[DESCRIPCION]],'CAP6-7'!$H:$H) -> 0 | I33: =SUMIF('CAP8'!$B:$H,Insumo[[#This Row],[DESCRIPCION]],'CAP8'!$H:$H) -> 0 | J33: =SUMIF('CAP9-13'!$B:$H,Insumo[[#This Row],[DESCRIPCION]],'CAP9-13'!$H:$H) -> 0 | K33: =SUMIF('CAP14-15'!$B:$H,Insumo[[#This Row],[DESCRIPCION]],'CAP14-15'!$H:$H) -> 0 | L33: =SUMIF('CAP16-18'!$B:$H,Insumo[[#This Row],[DESCRIPCION]],'CAP16-18'!$H:$H) -> 0 | M33: =SUMIF('CAP19-22'!$B:$H,Insumo[[#This Row],[DESCRIPCION]],'CAP19-22'!$H:$H) -> 0 | N33: =SUMIF('CAP23-24'!$B:$H,Insumo[[#This Row],[DESCRIPCION]],'CAP23-24'!$H:$H) -> 0 | O33: =SUMIF('CAP25'!$B:$H,Insumo[[#This Row],[DESCRIPCION]],'CAP25'!$H:$H) -> 0 | P33: =SUMIF('CAP26-28'!$B:$H,Insumo[[#This Row],[DESCRIPCION]],'CAP26-28'!$H:$H) -> 0 | Q33: =SUMIF('CAP29'!$B:$H,Insumo[[#This Row],[DESCRIPCION]],'CAP29'!$H:$H) -> 0 | T33: 43300
A34: Accesorios HG 3/4" | B34: Un | C34: =T34*$T$3 -> 6251.7 | D34: {=IF(Insumo[[#This Row],[VALOR]]=0,Insumo[TOTAL],E34/C34)} -> 0 | E34: =SUM(Insumo[[#This Row],[CAP1-3]:[CAP29]]) -> 0 | F34: =SUMIF('CAP1-3'!$B:$H,Insumo[[#This Row],[DESCRIPCION]],'CAP1-3'!$H:$H) -> 0 | G34: =SUMIF('CAP4-5'!$B:$H,Insumo[[#This Row],[DESCRIPCION]],'CAP4-5'!$H:$H) -> 0 | H34: =SUMIF('CAP6-7'!$B:$H,Insumo[[#This Row],[DESCRIPCION]],'CAP6-7'!$H:$H) -> 0 | I34: =SUMIF('CAP8'!$B:$H,Insumo[[#This Row],[DESCRIPCION]],'CAP8'!$H:$H) -> 0 | J34: =SUMIF('CAP9-13'!$B:$H,Insumo[[#This Row],[DESCRIPCION]],'CAP9-13'!$H:$H) -> 0 | K34: =SUMIF('CAP14-15'!$B:$H,Insumo[[#This Row],[DESCRIPCION]],'CAP14-15'!$H:$H) -> 0 | L34: =SUMIF('CAP16-18'!$B:$H,Insumo[[#This Row],[DESCRIPCION]],'CAP16-18'!$H:$H) -> 0 | M34: =SUMIF('CAP19-22'!$B:$H,Insumo[[#This Row],[DESCRIPCION]],'CAP19-22'!$H:$H) -> 0 | N34: =SUMIF('CAP23-24'!$B:$H,Insumo[[#This Row],[DESCRIPCION]],'CAP23-24'!$H:$H) -> 0 | O34: =SUMIF('CAP25'!$B:$H,Insumo[[#This Row],[DESCRIPCION]],'CAP25'!$H:$H) -> 0 | P34: =SUMIF('CAP26-28'!$B:$H,Insumo[[#This Row],[DESCRIPCION]],'CAP26-28'!$H:$H) -> 0 | Q34: =SUMIF('CAP29'!$B:$H,Insumo[[#This Row],[DESCRIPCION]],'CAP29'!$H:$H) -> 0 | T34: 5954
A35: Accesorios HG 3/8" | B35: Un | C35: =T35*$T$3 -> 2841.3 | D35: {=IF(Insumo[[#This Row],[VALOR]]=0,Insumo[TOTAL],E35/C35)} -> 0 | E35: =SUM(Insumo[[#This Row],[CAP1-3]:[CAP29]]) -> 0 | F35: =SUMIF('CAP1-3'!$B:$H,Insumo[[#This Row],[DESCRIPCION]],'CAP1-3'!$H:$H) -> 0 | G35: =SUMIF('CAP4-5'!$B:$H,Insumo[[#This Row],[DESCRIPCION]],'CAP4-5'!$H:$H) -> 0 | H35: =SUMIF('CAP6-7'!$B:$H,Insumo[[#This Row],[DESCRIPCION]],'CAP6-7'!$H:$H) -> 0 | I35: =SUMIF('CAP8'!$B:$H,Insumo[[#This Row],[DESCRIPCION]],'CAP8'!$H:$H) -> 0 | J35: =SUMIF('CAP9-13'!$B:$H,Insumo[[#This Row],[DESCRIPCION]],'CAP9-13'!$H:$H) -> 0 | K35: =SUMIF('CAP14-15'!$B:$H,Insumo[[#This Row],[DESCRIPCION]],'CAP14-15'!$H:$H) -> 0 | L35: =SUMIF('CAP16-18'!$B:$H,Insumo[[#This Row],[DESCRIPCION]],'CAP16-18'!$H:$H) -> 0 | M35: =SUMIF('CAP19-22'!$B:$H,Insumo[[#This Row],[DESCRIPCION]],'CAP19-22'!$H:$H) -> 0 | N35: =SUMIF('CAP23-24'!$B:$H,Insumo[[#This Row],[DESCRIPCION]],'CAP23-24'!$H:$H) -> 0 | O35: =SUMIF('CAP25'!$B:$H,Insumo[[#This Row],[DESCRIPCION]],'CAP25'!$H:$H) -> 0 | P35: =SUMIF('CAP26-28'!$B:$H,Insumo[[#This Row],[DESCRIPCION]],'CAP26-28'!$H:$H) -> 0 | Q35: =SUMIF('CAP29'!$B:$H,Insumo[[#This Row],[DESCRIPCION]],'CAP29'!$H:$H) -> 0 | T35: 2706
A36: Accesorios para guarda escoba 1/2" PVC | B36: Un | C36: =T36*$T$3 -> 7956.9 | D36: {=IF(Insumo[[#This Row],[VALOR]]=0,Insumo[TOTAL],E36/C36)} -> 0 | E36: =SUM(Insumo[[#This Row],[CAP1-3]:[CAP29]]) -> 0 | F36: =SUMIF('CAP1-3'!$B:$H,Insumo[[#This Row],[DESCRIPCION]],'CAP1-3'!$H:$H) -> 0 | G36: =SUMIF('CAP4-5'!$B:$H,Insumo[[#This Row],[DESCRIPCION]],'CAP4-5'!$H:$H) -> 0 | H36: =SUMIF('CAP6-7'!$B:$H,Insumo[[#This Row],[DESCRIPCION]],'CAP6-7'!$H:$H) -> 0 | I36: =SUMIF('CAP8'!$B:$H,Insumo[[#This Row],[DESCRIPCION]],'CAP8'!$H:$H) -> 0 | J36: =SUMIF('CAP9-13'!$B:$H,Insumo[[#This Row],[DESCRIPCION]],'CAP9-13'!$H:$H) -> 0 | K36: =SUMIF('CAP14-15'!$B:$H,Insumo[[#This Row],[DESCRIPCION]],'CAP14-15'!$H:$H) -> 0 | L36: =SUMIF('CAP16-18'!$B:$H,Insumo[[#This Row],[DESCRIPCION]],'CAP16-18'!$H:$H) -> 0 | M36: =SUMIF('CAP19-22'!$B:$H,Insumo[[#This Row],[DESCRIPCION]],'CAP19-22'!$H:$H) -> 0 | N36: =SUMIF('CAP23-24'!$B:$H,Insumo[[#This Row],[DESCRIPCION]],'CAP23-24'!$H:$H) -> 0 | O36: =SUMIF('CAP25'!$B:$H,Insumo[[#This Row],[DESCRIPCION]],'CAP25'!$H:$H) -> 0 | P36: =SUMIF('CAP26-28'!$B:$H,Insumo[[#This Row],[DESCRIPCION]],'CAP26-28'!$H:$H) -> 0 | Q36: =SUMIF('CAP29'!$B:$H,Insumo[[#This Row],[DESCRIPCION]],'CAP29'!$H:$H) -> 0 | T36: 7578
A37: Accesorios PVC presión Ø=1 1/2" | B37: Un | C37: =T37*$T$3 -> 15990.45 | D37: {=IF(Insumo[[#This Row],[VALOR]]=0,Insumo[TOTAL],E37/C37)} -> 0 | E37: =SUM(Insumo[[#This Row],[CAP1-3]:[CAP29]]) -> 0 | F37: =SUMIF('CAP1-3'!$B:$H,Insumo[[#This Row],[DESCRIPCION]],'CAP1-3'!$H:$H) -> 0 | G37: =SUMIF('CAP4-5'!$B:$H,Insumo[[#This Row],[DESCRIPCION]],'CAP4-5'!$H:$H) -> 0 | H37: =SUMIF('CAP6-7'!$B:$H,Insumo[[#This Row],[DESCRIPCION]],'CAP6-7'!$H:$H) -> 0 | I37: =SUMIF('CAP8'!$B:$H,Insumo[[#This Row],[DESCRIPCION]],'CAP8'!$H:$H) -> 0 | J37: =SUMIF('CAP9-13'!$B:$H,Insumo[[#This Row],[DESCRIPCION]],'CAP9-13'!$H:$H) -> 0 | K37: =SUMIF('CAP14-15'!$B:$H,Insumo[[#This Row],[DESCRIPCION]],'CAP14-15'!$H:$H) -> 0 | L37: =SUMIF('CAP16-18'!$B:$H,Insumo[[#This Row],[DESCRIPCION]],'CAP16-18'!$H:$H) -> 0 | M37: =SUMIF('CAP19-22'!$B:$H,Insumo[[#This Row],[DESCRIPCION]],'CAP19-22'!$H:$H) -> 0 | N37: =SUMIF('CAP23-24'!$B:$H,Insumo[[#This Row],[DESCRIPCION]],'CAP23-24'!$H:$H) -> 0 | O37: =SUMIF('CAP25'!$B:$H,Insumo[[#This Row],[DESCRIPCION]],'CAP25'!$H:$H) -> 0 | P37: =SUMIF('CAP26-28'!$B:$H,Insumo[[#This Row],[DESCRIPCION]],'CAP26-28'!$H:$H) -> 0 | Q37: =SUMIF('CAP29'!$B:$H,Insumo[[#This Row],[DESCRIPCION]],'CAP29'!$H:$H) -> 0 | R37: Gerfor Feb-2025 | T37: 15229
A38: Accesorios PVC presión Ø=1 1/4" | B38: Un | C38: =T38*$T$3 -> 12164.25 | D38: {=IF(Insumo[[#This Row],[VALOR]]=0,Insumo[TOTAL],E38/C38)} -> 0 | E38: =SUM(Insumo[[#This Row],[CAP1-3]:[CAP29]]) -> 0 | F38: =SUMIF('CAP1-3'!$B:$H,Insumo[[#This Row],[DESCRIPCION]],'CAP1-3'!$H:$H) -> 0 | G38: =SUMIF('CAP4-5'!$B:$H,Insumo[[#This Row],[DESCRIPCION]],'CAP4-5'!$H:$H) -> 0 | H38: =SUMIF('CAP6-7'!$B:$H,Insumo[[#This Row],[DESCRIPCION]],'CAP6-7'!$H:$H) -> 0 | I38: =SUMIF('CAP8'!$B:$H,Insumo[[#This Row],[DESCRIPCION]],'CAP8'!$H:$H) -> 0 | J38: =SUMIF('CAP9-13'!$B:$H,Insumo[[#This Row],[DESCRIPCION]],'CAP9-13'!$H:$H) -> 0 | K38: =SUMIF('CAP14-15'!$B:$H,Insumo[[#This Row],[DESCRIPCION]],'CAP14-15'!$H:$H) -> 0 | L38: =SUMIF('CAP16-18'!$B:$H,Insumo[[#This Row],[DESCRIPCION]],'CAP16-18'!$H:$H) -> 0 | M38: =SUMIF('CAP19-22'!$B:$H,Insumo[[#This Row],[DESCRIPCION]],'CAP19-22'!$H:$H) -> 0 | N38: =SUMIF('CAP23-24'!$B:$H,Insumo[[#This Row],[DESCRIPCION]],'CAP23-24'!$H:$H) -> 0 | O38: =SUMIF('CAP25'!$B:$H,Insumo[[#This Row],[DESCRIPCION]],'CAP25'!$H:$H) -> 0 | P38: =SUMIF('CAP26-28'!$B:$H,Insumo[[#This Row],[DESCRIPCION]],'CAP26-28'!$H:$H) -> 0 | Q38: =SUMIF('CAP29'!$B:$H,Insumo[[#This Row],[DESCRIPCION]],'CAP29'!$H:$H) -> 0 | R38: Gerfor Feb-2025 | T38: 11585
A39: Accesorios PVC presión Ø=1" | B39: Un | C39: =T39*$T$3 -> 4688.25 | D39: {=IF(Insumo[[#This Row],[VALOR]]=0,Insumo[TOTAL],E39/C39)} -> 0 | E39: =SUM(Insumo[[#This Row],[CAP1-3]:[CAP29]]) -> 0 | F39: =SUMIF('CAP1-3'!$B:$H,Insumo[[#This Row],[DESCRIPCION]],'CAP1-3'!$H:$H) -> 0 | G39: =SUMIF('CAP4-5'!$B:$H,Insumo[[#This Row],[DESCRIPCION]],'CAP4-5'!$H:$H) -> 0 | H39: =SUMIF('CAP6-7'!$B:$H,Insumo[[#This Row],[DESCRIPCION]],'CAP6-7'!$H:$H) -> 0 | I39: =SUMIF('CAP8'!$B:$H,Insumo[[#This Row],[DESCRIPCION]],'CAP8'!$H:$H) -> 0 | J39: =SUMIF('CAP9-13'!$B:$H,Insumo[[#This Row],[DESCRIPCION]],'CAP9-13'!$H:$H) -> 0 | K39: =SUMIF('CAP14-15'!$B:$H,Insumo[[#This Row],[DESCRIPCION]],'CAP14-15'!$H:$H) -> 0 | L39: =SUMIF('CAP16-18'!$B:$H,Insumo[[#This Row],[DESCRIPCION]],'CAP16-18'!$H:$H) -> 0 | M39: =SUMIF('CAP19-22'!$B:$H,Insumo[[#This Row],[DESCRIPCION]],'CAP19-22'!$H:$H) -> 0 | N39: =SUMIF('CAP23-24'!$B:$H,Insumo[[#This Row],[DESCRIPCION]],'CAP23-24'!$H:$H) -> 0 | O39: =SUMIF('CAP25'!$B:$H,Insumo[[#This Row],[DESCRIPCION]],'CAP25'!$H:$H) -> 0 | P39: =SUMIF('CAP26-28'!$B:$H,Insumo[[#This Row],[DESCRIPCION]],'CAP26-28'!$H:$H) -> 0 | Q39: =SUMIF('CAP29'!$B:$H,Insumo[[#This Row],[DESCRIPCION]],'CAP29'!$H:$H) -> 0 | R39: Gerfor Feb-2025 | T39: 4465
A40: Accesorios PVC presión Ø=1/2" | B40: Un | C40: =T40*$T$3 -> 1423.8 | D40: {=IF(Insumo[[#This Row],[VALOR]]=0,Insumo[TOTAL],E40/C40)} -> 0 | E40: =SUM(Insumo[[#This Row],[CAP1-3]:[CAP29]]) -> 0 | F40: =SUMIF('CAP1-3'!$B:$H,Insumo[[#This Row],[DESCRIPCION]],'CAP1-3'!$H:$H) -> 0 | G40: =SUMIF('CAP4-5'!$B:$H,Insumo[[#This Row],[DESCRIPCION]],'CAP4-5'!$H:$H) -> 0 | H40: =SUMIF('CAP6-7'!$B:$H,Insumo[[#This Row],[DESCRIPCION]],'CAP6-7'!$H:$H) -> 0 | I40: =SUMIF('CAP8'!$B:$H,Insumo[[#This Row],[DESCRIPCION]],'CAP8'!$H:$H) -> 0 | J40: =SUMIF('CAP9-13'!$B:$H,Insumo[[#This Row],[DESCRIPCION]],'CAP9-13'!$H:$H) -> 0 | K40: =SUMIF('CAP14-15'!$B:$H,Insumo[[#This Row],[DESCRIPCION]],'CAP14-15'!$H:$H) -> 0 | L40: =SUMIF('CAP16-18'!$B:$H,Insumo[[#This Row],[DESCRIPCION]],'CAP16-18'!$H:$H) -> 0 | M40: =SUMIF('CAP19-22'!$B:$H,Insumo[[#This Row],[DESCRIPCION]],'CAP19-22'!$H:$H) -> 0 | N40: =SUMIF('CAP23-24'!$B:$H,Insumo[[#This Row],[DESCRIPCION]],'CAP23-24'!$H:$H) -> 0 | O40: =SUMIF('CAP25'!$B:$H,Insumo[[#This Row],[DESCRIPCION]],'CAP25'!$H:$H) -> 0 | P40: =SUMIF('CAP26-28'!$B:$H,Insumo[[#This Row],[DESCRIPCION]],'CAP26-28'!$H:$H) -> 0 | Q40: =SUMIF('CAP29'!$B:$H,Insumo[[#This Row],[DESCRIPCION]],'CAP29'!$H:$H) -> 0 | R40: Gerfor Feb-2025 | T40: 1356
A41: Accesorios PVC presión Ø=2 1/2" | B41: Un | C41: =T41*$T$3 -> 70897.05 | D41: {=IF(Insumo[[#This Row],[VALOR]]=0,Insumo[TOTAL],E41/C41)} -> 0 | E41: =SUM(Insumo[[#This Row],[CAP1-3]:[CAP29]]) -> 0 | F41: =SUMIF('CAP1-3'!$B:$H,Insumo[[#This Row],[DESCRIPCION]],'CAP1-3'!$H:$H) -> 0 | G41: =SUMIF('CAP4-5'!$B:$H,Insumo[[#This Row],[DESCRIPCION]],'CAP4-5'!$H:$H) -> 0 | H41: =SUMIF('CAP6-7'!$B:$H,Insumo[[#This Row],[DESCRIPCION]],'CAP6-7'!$H:$H) -> 0 | I41: =SUMIF('CAP8'!$B:$H,Insumo[[#This Row],[DESCRIPCION]],'CAP8'!$H:$H) -> 0 | J41: =SUMIF('CAP9-13'!$B:$H,Insumo[[#This Row],[DESCRIPCION]],'CAP9-13'!$H:$H) -> 0 | K41: =SUMIF('CAP14-15'!$B:$H,Insumo[[#This Row],[DESCRIPCION]],'CAP14-15'!$H:$H) -> 0 | L41: =SUMIF('CAP16-18'!$B:$H,Insumo[[#This Row],[DESCRIPCION]],'CAP16-18'!$H:$H) -> 0 | M41: =SUMIF('CAP19-22'!$B:$H,Insumo[[#This Row],[DESCRIPCION]],'CAP19-22'!$H:$H) -> 0 | N41: =SUMIF('CAP23-24'!$B:$H,Insumo[[#This Row],[DESCRIPCION]],'CAP23-24'!$H:$H) -> 0 | O41: =SUMIF('CAP25'!$B:$H,Insumo[[#This Row],[DESCRIPCION]],'CAP25'!$H:$H) -> 0 | P41: =SUMIF('CAP26-28'!$B:$H,Insumo[[#This Row],[DESCRIPCION]],'CAP26-28'!$H:$H) -> 0 | Q41: =SUMIF('CAP29'!$B:$H,Insumo[[#This Row],[DESCRIPCION]],'CAP29'!$H:$H) -> 0 | R41: Gerfor Feb-2025 | T41: 67521
A42: Accesorios PVC presión Ø=2" | B42: Un | C42: =T42*$T$3 -> 25366.95 | D42: {=IF(Insumo[[#This Row],[VALOR]]=0,Insumo[TOTAL],E42/C42)} -> 0 | E42: =SUM(Insumo[[#This Row],[CAP1-3]:[CAP29]]) -> 0 | F42: =SUMIF('CAP1-3'!$B:$H,Insumo[[#This Row],[DESCRIPCION]],'CAP1-3'!$H:$H) -> 0 | G42: =SUMIF('CAP4-5'!$B:$H,Insumo[[#This Row],[DESCRIPCION]],'CAP4-5'!$H:$H) -> 0 | H42: =SUMIF('CAP6-7'!$B:$H,Insumo[[#This Row],[DESCRIPCION]],'CAP6-7'!$H:$H) -> 0 | I42: =SUMIF('CAP8'!$B:$H,Insumo[[#This Row],[DESCRIPCION]],'CAP8'!$H:$H) -> 0 | J42: =SUMIF('CAP9-13'!$B:$H,Insumo[[#This Row],[DESCRIPCION]],'CAP9-13'!$H:$H) -> 0 | K42: =SUMIF('CAP14-15'!$B:$H,Insumo[[#This Row],[DESCRIPCION]],'CAP14-15'!$H:$H) -> 0 | L42: =SUMIF('CAP16-18'!$B:$H,Insumo[[#This Row],[DESCRIPCION]],'CAP16-18'!$H:$H) -> 0 | M42: =SUMIF('CAP19-22'!$B:$H,Insumo[[#This Row],[DESCRIPCION]],'CAP19-22'!$H:$H) -> 0 | N42: =SUMIF('CAP23-24'!$B:$H,Insumo[[#This Row],[DESCRIPCION]],'CAP23-24'!$H:$H) -> 0 | O42: =SUMIF('CAP25'!$B:$H,Insumo[[#This Row],[DESCRIPCION]],'CAP25'!$H:$H) -> 0 | P42: =SUMIF('CAP26-28'!$B:$H,Insumo[[#This Row],[DESCRIPCION]],'CAP26-28'!$H:$H) -> 0 | Q42: =SUMIF('CAP29'!$B:$H,Insumo[[#This Row],[DESCRIPCION]],'CAP29'!$H:$H) -> 0 | R42: Gerfor Feb-2025 | T42: 24159
A43: Accesorios PVC presión Ø=3" | B43: Un | C43: =T43*$T$3 -> 95646.6 | D43: {=IF(Insumo[[#This Row],[VALOR]]=0,Insumo[TOTAL],E43/C43)} -> 0 | E43: =SUM(Insumo[[#This Row],[CAP1-3]:[CAP29]]) -> 0 | F43: =SUMIF('CAP1-3'!$B:$H,Insumo[[#This Row],[DESCRIPCION]],'CAP1-3'!$H:$H) -> 0 | G43: =SUMIF('CAP4-5'!$B:$H,Insumo[[#This Row],[DESCRIPCION]],'CAP4-5'!$H:$H) -> 0 | H43: =SUMIF('CAP6-7'!$B:$H,Insumo[[#This Row],[DESCRIPCION]],'CAP6-7'!$H:$H) -> 0 | I43: =SUMIF('CAP8'!$B:$H,Insumo[[#This Row],[DESCRIPCION]],'CAP8'!$H:$H) -> 0 | J43: =SUMIF('CAP9-13'!$B:$H,Insumo[[#This Row],[DESCRIPCION]],'CAP9-13'!$H:$H) -> 0 | K43: =SUMIF('CAP14-15'!$B:$H,Insumo[[#This Row],[DESCRIPCION]],'CAP14-15'!$H:$H) -> 0 | L43: =SUMIF('CAP16-18'!$B:$H,Insumo[[#This Row],[DESCRIPCION]],'CAP16-18'!$H:$H) -> 0 | M43: =SUMIF('CAP19-22'!$B:$H,Insumo[[#This Row],[DESCRIPCION]],'CAP19-22'!$H:$H) -> 0 | N43: =SUMIF('CAP23-24'!$B:$H,Insumo[[#This Row],[DESCRIPCION]],'CAP23-24'!$H:$H) -> 0 | O43: =SUMIF('CAP25'!$B:$H,Insumo[[#This Row],[DESCRIPCION]],'CAP25'!$H:$H) -> 0 | P43: =SUMIF('CAP26-28'!$B:$H,Insumo[[#This Row],[DESCRIPCION]],'CAP26-28'!$H:$H) -> 0 | Q43: =SUMIF('CAP29'!$B:$H,Insumo[[#This Row],[DESCRIPCION]],'CAP29'!$H:$H) -> 0 | R43: Gerfor Feb-2025 | T43: 91092
A44: Accesorios PVC presión Ø=3/4" | B44: Un | C44: =T44*$T$3 -> 2399.25 | D44: {=IF(Insumo[[#This Row],[VALOR]]=0,Insumo[TOTAL],E44/C44)} -> 0 | E44: =SUM(Insumo[[#This Row],[CAP1-3]:[CAP29]]) -> 0 | F44: =SUMIF('CAP1-3'!$B:$H,Insumo[[#This Row],[DESCRIPCION]],'CAP1-3'!$H:$H) -> 0 | G44: =SUMIF('CAP4-5'!$B:$H,Insumo[[#This Row],[DESCRIPCION]],'CAP4-5'!$H:$H) -> 0 | H44: =SUMIF('CAP6-7'!$B:$H,Insumo[[#This Row],[DESCRIPCION]],'CAP6-7'!$H:$H) -> 0 | I44: =SUMIF('CAP8'!$B:$H,Insumo[[#This Row],[DESCRIPCION]],'CAP8'!$H:$H) -> 0 | J44: =SUMIF('CAP9-13'!$B:$H,Insumo[[#This Row],[DESCRIPCION]],'CAP9-13'!$H:$H) -> 0 | K44: =SUMIF('CAP14-15'!$B:$H,Insumo[[#This Row],[DESCRIPCION]],'CAP14-15'!$H:$H) -> 0 | L44: =SUMIF('CAP16-18'!$B:$H,Insumo[[#This Row],[DESCRIPCION]],'CAP16-18'!$H:$H) -> 0 | M44: =SUMIF('CAP19-22'!$B:$H,Insumo[[#This Row],[DESCRIPCION]],'CAP19-22'!$H:$H) -> 0 | N44: =SUMIF('CAP23-24'!$B:$H,Insumo[[#This Row],[DESCRIPCION]],'CAP23-24'!$H:$H) -> 0 | O44: =SUMIF('CAP25'!$B:$H,Insumo[[#This Row],[DESCRIPCION]],'CAP25'!$H:$H) -> 0 | P44: =SUMIF('CAP26-28'!$B:$H,Insumo[[#This Row],[DESCRIPCION]],'CAP26-28'!$H:$H) -> 0 | Q44: =SUMIF('CAP29'!$B:$H,Insumo[[#This Row],[DESCRIPCION]],'CAP29'!$H:$H) -> 0 | R44: Gerfor Feb-2025 | T44: 2285
A45: Accesorios PVC presión Ø=4" | B45: Un | C45: =T45*$T$3 -> 208672.8 | D45: {=IF(Insumo[[#This Row],[VALOR]]=0,Insumo[TOTAL],E45/C45)} -> 0 | E45: =SUM(Insumo[[#This Row],[CAP1-3]:[CAP29]]) -> 0 | F45: =SUMIF('CAP1-3'!$B:$H,Insumo[[#This Row],[DESCRIPCION]],'CAP1-3'!$H:$H) -> 0 | G45: =SUMIF('CAP4-5'!$B:$H,Insumo[[#This Row],[DESCRIPCION]],'CAP4-5'!$H:$H) -> 0 | H45: =SUMIF('CAP6-7'!$B:$H,Insumo[[#This Row],[DESCRIPCION]],'CAP6-7'!$H:$H) -> 0 | I45: =SUMIF('CAP8'!$B:$H,Insumo[[#This Row],[DESCRIPCION]],'CAP8'!$H:$H) -> 0 | J45: =SUMIF('CAP9-13'!$B:$H,Insumo[[#This Row],[DESCRIPCION]],'CAP9-13'!$H:$H) -> 0 | K45: =SUMIF('CAP14-15'!$B:$H,Insumo[[#This Row],[DESCRIPCION]],'CAP14-15'!$H:$H) -> 0 | L45: =SUMIF('CAP16-18'!$B:$H,Insumo[[#This Row],[DESCRIPCION]],'CAP16-18'!$H:$H) -> 0 | M45: =SUMIF('CAP19-22'!$B:$H,Insumo[[#This Row],[DESCRIPCION]],'CAP19-22'!$H:$H) -> 0 | N45: =SUMIF('CAP23-24'!$B:$H,Insumo[[#This Row],[DESCRIPCION]],'CAP23-24'!$H:$H) -> 0 | O45: =SUMIF('CAP25'!$B:$H,Insumo[[#This Row],[DESCRIPCION]],'CAP25'!$H:$H) -> 0 | P45: =SUMIF('CAP26-28'!$B:$H,Insumo[[#This Row],[DESCRIPCION]],'CAP26-28'!$H:$H) -> 0 | Q45: =SUMIF('CAP29'!$B:$H,Insumo[[#This Row],[DESCRIPCION]],'CAP29'!$H:$H) -> 0 | R45: Gerfor Feb-2025 | T45: 198736
A46: Accesorios PVC presión Ø=6" | B46: Un | C46: =T46*$T$3 -> 351672.3 | D46: {=IF(Insumo[[#This Row],[VALOR]]=0,Insumo[TOTAL],E46/C46)} -> 0 | E46: =SUM(Insumo[[#This Row],[CAP1-3]:[CAP29]]) -> 0 | F46: =SUMIF('CAP1-3'!$B:$H,Insumo[[#This Row],[DESCRIPCION]],'CAP1-3'!$H:$H) -> 0 | G46: =SUMIF('CAP4-5'!$B:$H,Insumo[[#This Row],[DESCRIPCION]],'CAP4-5'!$H:$H) -> 0 | H46: =SUMIF('CAP6-7'!$B:$H,Insumo[[#This Row],[DESCRIPCION]],'CAP6-7'!$H:$H) -> 0 | I46: =SUMIF('CAP8'!$B:$H,Insumo[[#This Row],[DESCRIPCION]],'CAP8'!$H:$H) -> 0 | J46: =SUMIF('CAP9-13'!$B:$H,Insumo[[#This Row],[DESCRIPCION]],'CAP9-13'!$H:$H) -> 0 | K46: =SUMIF('CAP14-15'!$B:$H,Insumo[[#This Row],[DESCRIPCION]],'CAP14-15'!$H:$H) -> 0 | L46: =SUMIF('CAP16-18'!$B:$H,Insumo[[#This Row],[DESCRIPCION]],'CAP16-18'!$H:$H) -> 0 | M46: =SUMIF('CAP19-22'!$B:$H,Insumo[[#This Row],[DESCRIPCION]],'CAP19-22'!$H:$H) -> 0 | N46: =SUMIF('CAP23-24'!$B:$H,Insumo[[#This Row],[DESCRIPCION]],'CAP23-24'!$H:$H) -> 0 | O46: =SUMIF('CAP25'!$B:$H,Insumo[[#This Row],[DESCRIPCION]],'CAP25'!$H:$H) -> 0 | P46: =SUMIF('CAP26-28'!$B:$H,Insumo[[#This Row],[DESCRIPCION]],'CAP26-28'!$H:$H) -> 0 | Q46: =SUMIF('CAP29'!$B:$H,Insumo[[#This Row],[DESCRIPCION]],'CAP29'!$H:$H) -> 0 | T46: 334926
A47: Accesorios PVC sanitarios Ø=1 1/2" | B47: Un | C47: =T47*$T$3 -> 4725 | D47: {=IF(Insumo[[#This Row],[VALOR]]=0,Insumo[TOTAL],E47/C47)} -> 0 | E47: =SUM(Insumo[[#This Row],[CAP1-3]:[CAP29]]) -> 0 | F47: =SUMIF('CAP1-3'!$B:$H,Insumo[[#This Row],[DESCRIPCION]],'CAP1-3'!$H:$H) -> 0 | G47: =SUMIF('CAP4-5'!$B:$H,Insumo[[#This Row],[DESCRIPCION]],'CAP4-5'!$H:$H) -> 0 | H47: =SUMIF('CAP6-7'!$B:$H,Insumo[[#This Row],[DESCRIPCION]],'CAP6-7'!$H:$H) -> 0 | I47: =SUMIF('CAP8'!$B:$H,Insumo[[#This Row],[DESCRIPCION]],'CAP8'!$H:$H) -> 0 | J47: =SUMIF('CAP9-13'!$B:$H,Insumo[[#This Row],[DESCRIPCION]],'CAP9-13'!$H:$H) -> 0 | K47: =SUMIF('CAP14-15'!$B:$H,Insumo[[#This Row],[DESCRIPCION]],'CAP14-15'!$H:$H) -> 0 | L47: =SUMIF('CAP16-18'!$B:$H,Insumo[[#This Row],[DESCRIPCION]],'CAP16-18'!$H:$H) -> 0 | M47: =SUMIF('CAP19-22'!$B:$H,Insumo[[#This Row],[DESCRIPCION]],'CAP19-22'!$H:$H) -> 0 | N47: =SUMIF('CAP23-24'!$B:$H,Insumo[[#This Row],[DESCRIPCION]],'CAP23-24'!$H:$H) -> 0 | O47: =SUMIF('CAP25'!$B:$H,Insumo[[#This Row],[DESCRIPCION]],'CAP25'!$H:$H) -> 0 | P47: =SUMIF('CAP26-28'!$B:$H,Insumo[[#This Row],[DESCRIPCION]],'CAP26-28'!$H:$H) -> 0 | Q47: =SUMIF('CAP29'!$B:$H,Insumo[[#This Row],[DESCRIPCION]],'CAP29'!$H:$H) -> 0 | R47: Gerfor Feb-2025 | T47: 4500
A48: Accesorios PVC sanitarios Ø=2" | B48: Un | C48: =T48*$T$3 -> 5561.85 | D48: {=IF(Insumo[[#This Row],[VALOR]]=0,Insumo[TOTAL],E48/C48)} -> 0 | E48: =SUM(Insumo[[#This Row],[CAP1-3]:[CAP29]]) -> 0 | F48: =SUMIF('CAP1-3'!$B:$H,Insumo[[#This Row],[DESCRIPCION]],'CAP1-3'!$H:$H) -> 0 | G48: =SUMIF('CAP4-5'!$B:$H,Insumo[[#This Row],[DESCRIPCION]],'CAP4-5'!$H:$H) -> 0 | H48: =SUMIF('CAP6-7'!$B:$H,Insumo[[#This Row],[DESCRIPCION]],'CAP6-7'!$H:$H) -> 0 | I48: =SUMIF('CAP8'!$B:$H,Insumo[[#This Row],[DESCRIPCION]],'CAP8'!$H:$H) -> 0 | J48: =SUMIF('CAP9-13'!$B:$H,Insumo[[#This Row],[DESCRIPCION]],'CAP9-13'!$H:$H) -> 0 | K48: =SUMIF('CAP14-15'!$B:$H,Insumo[[#This Row],[DESCRIPCION]],'CAP14-15'!$H:$H) -> 0 | L48: =SUMIF('CAP16-18'!$B:$H,Insumo[[#This Row],[DESCRIPCION]],'CAP16-18'!$H:$H) -> 0 | M48: =SUMIF('CAP19-22'!$B:$H,Insumo[[#This Row],[DESCRIPCION]],'CAP19-22'!$H:$H) -> 0 | N48: =SUMIF('CAP23-24'!$B:$H,Insumo[[#This Row],[DESCRIPCION]],'CAP23-24'!$H:$H) -> 0 | O48: =SUMIF('CAP25'!$B:$H,Insumo[[#This Row],[DESCRIPCION]],'CAP25'!$H:$H) -> 0 | P48: =SUMIF('CAP26-28'!$B:$H,Insumo[[#This Row],[DESCRIPCION]],'CAP26-28'!$H:$H) -> 0 | Q48: =SUMIF('CAP29'!$B:$H,Insumo[[#This Row],[DESCRIPCION]],'CAP29'!$H:$H) -> 0 | R48: Gerfor Feb-2025 | T48: 5297
A49: Accesorios PVC sanitarios Ø=3" | B49: Un | C49: =T49*$T$3 -> 12877.2 | D49: {=IF(Insumo[[#This Row],[VALOR]]=0,Insumo[TOTAL],E49/C49)} -> 0 | E49: =SUM(Insumo[[#This Row],[CAP1-3]:[CAP29]]) -> 0 | F49: =SUMIF('CAP1-3'!$B:$H,Insumo[[#This Row],[DESCRIPCION]],'CAP1-3'!$H:$H) -> 0 | G49: =SUMIF('CAP4-5'!$B:$H,Insumo[[#This Row],[DESCRIPCION]],'CAP4-5'!$H:$H) -> 0 | H49: =SUMIF('CAP6-7'!$B:$H,Insumo[[#This Row],[DESCRIPCION]],'CAP6-7'!$H:$H) -> 0 | I49: =SUMIF('CAP8'!$B:$H,Insumo[[#This Row],[DESCRIPCION]],'CAP8'!$H:$H) -> 0 | J49: =SUMIF('CAP9-13'!$B:$H,Insumo[[#This Row],[DESCRIPCION]],'CAP9-13'!$H:$H) -> 0 | K49: =SUMIF('CAP14-15'!$B:$H,Insumo[[#This Row],[DESCRIPCION]],'CAP14-15'!$H:$H) -> 0 | L49: =SUMIF('CAP16-18'!$B:$H,Insumo[[#This Row],[DESCRIPCION]],'CAP16-18'!$H:$H) -> 0 | M49: =SUMIF('CAP19-22'!$B:$H,Insumo[[#This Row],[DESCRIPCION]],'CAP19-22'!$H:$H) -> 0 | N49: =SUMIF('CAP23-24'!$B:$H,Insumo[[#This Row],[DESCRIPCION]],'CAP23-24'!$H:$H) -> 0 | O49: =SUMIF('CAP25'!$B:$H,Insumo[[#This Row],[DESCRIPCION]],'CAP25'!$H:$H) -> 0 | P49: =SUMIF('CAP26-28'!$B:$H,Insumo[[#This Row],[DESCRIPCION]],'CAP26-28'!$H:$H) -> 0 | Q49: =SUMIF('CAP29'!$B:$H,Insumo[[#This Row],[DESCRIPCION]],'CAP29'!$H:$H) -> 0 | R49: Gerfor Feb-2025 | T49: 12264
A50: Accesorios PVC sanitarios Ø=4" | B50: Un | C50: =T50*$T$3 -> 22253.7 | D50: {=IF(Insumo[[#This Row],[VALOR]]=0,Insumo[TOTAL],E50/C50)} -> 0 | E50: =SUM(Insumo[[#This Row],[CAP1-3]:[CAP29]]) -> 0 | F50: =SUMIF('CAP1-3'!$B:$H,Insumo[[#This Row],[DESCRIPCION]],'CAP1-3'!$H:$H) -> 0 | G50: =SUMIF('CAP4-5'!$B:$H,Insumo[[#This Row],[DESCRIPCION]],'CAP4-5'!$H:$H) -> 0 | H50: =SUMIF('CAP6-7'!$B:$H,Insumo[[#This Row],[DESCRIPCION]],'CAP6-7'!$H:$H) -> 0 | I50: =SUMIF('CAP8'!$B:$H,Insumo[[#This Row],[DESCRIPCION]],'CAP8'!$H:$H) -> 0 | J50: =SUMIF('CAP9-13'!$B:$H,Insumo[[#This Row],[DESCRIPCION]],'CAP9-13'!$H:$H) -> 0 | K50: =SUMIF('CAP14-15'!$B:$H,Insumo[[#This Row],[DESCRIPCION]],'CAP14-15'!$H:$H) -> 0 | L50: =SUMIF('CAP16-18'!$B:$H,Insumo[[#This Row],[DESCRIPCION]],'CAP16-18'!$H:$H) -> 0 | M50: =SUMIF('CAP19-22'!$B:$H,Insumo[[#This Row],[DESCRIPCION]],'CAP19-22'!$H:$H) -> 0 | N50: =SUMIF('CAP23-24'!$B:$H,Insumo[[#This Row],[DESCRIPCION]],'CAP23-24'!$H:$H) -> 0 | O50: =SUMIF('CAP25'!$B:$H,Insumo[[#This Row],[DESCRIPCION]],'CAP25'!$H:$H) -> 0 | P50: =SUMIF('CAP26-28'!$B:$H,Insumo[[#This Row],[DESCRIPCION]],'CAP26-28'!$H:$H) -> 0 | Q50: =SUMIF('CAP29'!$B:$H,Insumo[[#This Row],[DESCRIPCION]],'CAP29'!$H:$H) -> 0 | R50: Gerfor Feb-2025 | T50: 21194
A51: Accesorios PVC sanitarios Ø=6" | B51: Un | C51: =T51*$T$3 -> 188779.5 | D51: {=IF(Insumo[[#This Row],[VALOR]]=0,Insumo[TOTAL],E51/C51)} -> 0 | E51: =SUM(Insumo[[#This Row],[CAP1-3]:[CAP29]]) -> 0 | F51: =SUMIF('CAP1-3'!$B:$H,Insumo[[#This Row],[DESCRIPCION]],'CAP1-3'!$H:$H) -> 0 | G51: =SUMIF('CAP4-5'!$B:$H,Insumo[[#This Row],[DESCRIPCION]],'CAP4-5'!$H:$H) -> 0 | H51: =SUMIF('CAP6-7'!$B:$H,Insumo[[#This Row],[DESCRIPCION]],'CAP6-7'!$H:$H) -> 0 | I51: =SUMIF('CAP8'!$B:$H,Insumo[[#This Row],[DESCRIPCION]],'CAP8'!$H:$H) -> 0 | J51: =SUMIF('CAP9-13'!$B:$H,Insumo[[#This Row],[DESCRIPCION]],'CAP9-13'!$H:$H) -> 0 | K51: =SUMIF('CAP14-15'!$B:$H,Insumo[[#This Row],[DESCRIPCION]],'CAP14-15'!$H:$H) -> 0 | L51: =SUMIF('CAP16-18'!$B:$H,Insumo[[#This Row],[DESCRIPCION]],'CAP16-18'!$H:$H) -> 0 | M51: =SUMIF('CAP19-22'!$B:$H,Insumo[[#This Row],[DESCRIPCION]],'CAP19-22'!$H:$H) -> 0 | N51: =SUMIF('CAP23-24'!$B:$H,Insumo[[#This Row],[DESCRIPCION]],'CAP23-24'!$H:$H) -> 0 | O51: =SUMIF('CAP25'!$B:$H,Insumo[[#This Row],[DESCRIPCION]],'CAP25'!$H:$H) -> 0 | P51: =SUMIF('CAP26-28'!$B:$H,Insumo[[#This Row],[DESCRIPCION]],'CAP26-28'!$H:$H) -> 0 | Q51: =SUMIF('CAP29'!$B:$H,Insumo[[#This Row],[DESCRIPCION]],'CAP29'!$H:$H) -> 0 | R51: Gerfor Feb-2025 | T51: 179790
A52: Accesorios y empaques canal PVC promedio de U y soporte | B52: Un | C52: =T52*$T$3 -> 9149.7 | D52: {=IF(Insumo[[#This Row],[VALOR]]=0,Insumo[TOTAL],E52/C52)} -> 0 | E52: =SUM(Insumo[[#This Row],[CAP1-3]:[CAP29]]) -> 0 | F52: =SUMIF('CAP1-3'!$B:$H,Insumo[[#This Row],[DESCRIPCION]],'CAP1-3'!$H:$H) -> 0 | G52: =SUMIF('CAP4-5'!$B:$H,Insumo[[#This Row],[DESCRIPCION]],'CAP4-5'!$H:$H) -> 0 | H52: =SUMIF('CAP6-7'!$B:$H,Insumo[[#This Row],[DESCRIPCION]],'CAP6-7'!$H:$H) -> 0 | I52: =SUMIF('CAP8'!$B:$H,Insumo[[#This Row],[DESCRIPCION]],'CAP8'!$H:$H) -> 0 | J52: =SUMIF('CAP9-13'!$B:$H,Insumo[[#This Row],[DESCRIPCION]],'CAP9-13'!$H:$H) -> 0 | K52: =SUMIF('CAP14-15'!$B:$H,Insumo[[#This Row],[DESCRIPCION]],'CAP14-15'!$H:$H) -> 0 | L52: =SUMIF('CAP16-18'!$B:$H,Insumo[[#This Row],[DESCRIPCION]],'CAP16-18'!$H:$H) -> 0 | M52: =SUMIF('CAP19-22'!$B:$H,Insumo[[#This Row],[DESCRIPCION]],'CAP19-22'!$H:$H) -> 0 | N52: =SUMIF('CAP23-24'!$B:$H,Insumo[[#This Row],[DESCRIPCION]],'CAP23-24'!$H:$H) -> 0 | O52: =SUMIF('CAP25'!$B:$H,Insumo[[#This Row],[DESCRIPCION]],'CAP25'!$H:$H) -> 0 | P52: =SUMIF('CAP26-28'!$B:$H,Insumo[[#This Row],[DESCRIPCION]],'CAP26-28'!$H:$H) -> 0 | Q52: =SUMIF('CAP29'!$B:$H,Insumo[[#This Row],[DESCRIPCION]],'CAP29'!$H:$H) -> 0 | T52: 8714
A53: Acero de Fy = 60.000 psi d>1/4 | B53: Kg | C53: =T53*$T$3 -> 5686.8 | D53: {=IF(Insumo[[#This Row],[VALOR]]=0,Insumo[TOTAL],E53/C53)} -> 0 | E53: =SUM(Insumo[[#This Row],[CAP1-3]:[CAP29]]) -> 0 | F53: =SUMIF('CAP1-3'!$B:$H,Insumo[[#This Row],[DESCRIPCION]],'CAP1-3'!$H:$H) -> 0 | G53: =SUMIF('CAP4-5'!$B:$H,Insumo[[#This Row],[DESCRIPCION]],'CAP4-5'!$H:$H) -> 0 | H53: =SUMIF('CAP6-7'!$B:$H,Insumo[[#This Row],[DESCRIPCION]],'CAP6-7'!$H:$H) -> 0 | I53: =SUMIF('CAP8'!$B:$H,Insumo[[#This Row],[DESCRIPCION]],'CAP8'!$H:$H) -> 0 | J53: =SUMIF('CAP9-13'!$B:$H,Insumo[[#This Row],[DESCRIPCION]],'CAP9-13'!$H:$H) -> 0 | K53: =SUMIF('CAP14-15'!$B:$H,Insumo[[#This Row],[DESCRIPCION]],'CAP14-15'!$H:$H) -> 0 | L53: =SUMIF('CAP16-18'!$B:$H,Insumo[[#This Row],[DESCRIPCION]],'CAP16-18'!$H:$H) -> 0 | M53: =SUMIF('CAP19-22'!$B:$H,Insumo[[#This Row],[DESCRIPCION]],'CAP19-22'!$H:$H) -> 0 | N53: =SUMIF('CAP23-24'!$B:$H,Insumo[[#This Row],[DESCRIPCION]],'CAP23-24'!$H:$H) -> 0 | O53: =SUMIF('CAP25'!$B:$H,Insumo[[#This Row],[DESCRIPCION]],'CAP25'!$H:$H) -> 0 | P53: =SUMIF('CAP26-28'!$B:$H,Insumo[[#This Row],[DESCRIPCION]],'CAP26-28'!$H:$H) -> 0 | Q53: =SUMIF('CAP29'!$B:$H,Insumo[[#This Row],[DESCRIPCION]],'CAP29'!$H:$H) -> 0 | T53: 5416
A54: Acero Estructural A36 | B54: Kg | C54: =T54*$T$3 -> 8524.95 | D54: {=IF(Insumo[[#This Row],[VALOR]]=0,Insumo[TOTAL],E54/C54)} -> 0 | E54: =SUM(Insumo[[#This Row],[CAP1-3]:[CAP29]]) -> 0 | F54: =SUMIF('CAP1-3'!$B:$H,Insumo[[#This Row],[DESCRIPCION]],'CAP1-3'!$H:$H) -> 0 | G54: =SUMIF('CAP4-5'!$B:$H,Insumo[[#This Row],[DESCRIPCION]],'CAP4-5'!$H:$H) -> 0 | H54: =SUMIF('CAP6-7'!$B:$H,Insumo[[#This Row],[DESCRIPCION]],'CAP6-7'!$H:$H) -> 0 | I54: =SUMIF('CAP8'!$B:$H,Insumo[[#This Row],[DESCRIPCION]],'CAP8'!$H:$H) -> 0 | J54: =SUMIF('CAP9-13'!$B:$H,Insumo[[#This Row],[DESCRIPCION]],'CAP9-13'!$H:$H) -> 0 | K54: =SUMIF('CAP14-15'!$B:$H,Insumo[[#This Row],[DESCRIPCION]],'CAP14-15'!$H:$H) -> 0 | L54: =SUMIF('CAP16-18'!$B:$H,Insumo[[#This Row],[DESCRIPCION]],'CAP16-18'!$H:$H) -> 0 | M54: =SUMIF('CAP19-22'!$B:$H,Insumo[[#This Row],[DESCRIPCION]],'CAP19-22'!$H:$H) -> 0 | N54: =SUMIF('CAP23-24'!$B:$H,Insumo[[#This Row],[DESCRIPCION]],'CAP23-24'!$H:$H) -> 0 | O54: =SUMIF('CAP25'!$B:$H,Insumo[[#This Row],[DESCRIPCION]],'CAP25'!$H:$H) -> 0 | P54: =SUMIF('CAP26-28'!$B:$H,Insumo[[#This Row],[DESCRIPCION]],'CAP26-28'!$H:$H) -> 0 | Q54: =SUMIF('CAP29'!$B:$H,Insumo[[#This Row],[DESCRIPCION]],'CAP29'!$H:$H) -> 0 | T54: 8119
A55: Acople ranurado hierro ductil sch 40 1 1/2" | B55: Un | C55: =T55*$T$3 -> 2501.1 | D55: {=IF(Insumo[[#This Row],[VALOR]]=0,Insumo[TOTAL],E55/C55)} -> 0 | E55: =SUM(Insumo[[#This Row],[CAP1-3]:[CAP29]]) -> 0 | F55: =SUMIF('CAP1-3'!$B:$H,Insumo[[#This Row],[DESCRIPCION]],'CAP1-3'!$H:$H) -> 0 | G55: =SUMIF('CAP4-5'!$B:$H,Insumo[[#This Row],[DESCRIPCION]],'CAP4-5'!$H:$H) -> 0 | H55: =SUMIF('CAP6-7'!$B:$H,Insumo[[#This Row],[DESCRIPCION]],'CAP6-7'!$H:$H) -> 0 | I55: =SUMIF('CAP8'!$B:$H,Insumo[[#This Row],[DESCRIPCION]],'CAP8'!$H:$H) -> 0 | J55: =SUMIF('CAP9-13'!$B:$H,Insumo[[#This Row],[DESCRIPCION]],'CAP9-13'!$H:$H) -> 0 | K55: =SUMIF('CAP14-15'!$B:$H,Insumo[[#This Row],[DESCRIPCION]],'CAP14-15'!$H:$H) -> 0 | L55: =SUMIF('CAP16-18'!$B:$H,Insumo[[#This Row],[DESCRIPCION]],'CAP16-18'!$H:$H) -> 0 | M55: =SUMIF('CAP19-22'!$B:$H,Insumo[[#This Row],[DESCRIPCION]],'CAP19-22'!$H:$H) -> 0 | N55: =SUMIF('CAP23-24'!$B:$H,Insumo[[#This Row],[DESCRIPCION]],'CAP23-24'!$H:$H) -> 0 | O55: =SUMIF('CAP25'!$B:$H,Insumo[[#This Row],[DESCRIPCION]],'CAP25'!$H:$H) -> 0 | P55: =SUMIF('CAP26-28'!$B:$H,Insumo[[#This Row],[DESCRIPCION]],'CAP26-28'!$H:$H) -> 0 | Q55: =SUMIF('CAP29'!$B:$H,Insumo[[#This Row],[DESCRIPCION]],'CAP29'!$H:$H) -> 0 | T55: 2382
A56: Acople ranurado hierro ductil sch 40 1 1/4" | B56: Un | C56: =T56*$T$3 -> 3295.95 | D56: {=IF(Insumo[[#This Row],[VALOR]]=0,Insumo[TOTAL],E56/C56)} -> 0 | E56: =SUM(Insumo[[#This Row],[CAP1-3]:[CAP29]]) -> 0 | F56: =SUMIF('CAP1-3'!$B:$H,Insumo[[#This Row],[DESCRIPCION]],'CAP1-3'!$H:$H) -> 0 | G56: =SUMIF('CAP4-5'!$B:$H,Insumo[[#This Row],[DESCRIPCION]],'CAP4-5'!$H:$H) -> 0 | H56: =SUMIF('CAP6-7'!$B:$H,Insumo[[#This Row],[DESCRIPCION]],'CAP6-7'!$H:$H) -> 0 | I56: =SUMIF('CAP8'!$B:$H,Insumo[[#This Row],[DESCRIPCION]],'CAP8'!$H:$H) -> 0 | J56: =SUMIF('CAP9-13'!$B:$H,Insumo[[#This Row],[DESCRIPCION]],'CAP9-13'!$H:$H) -> 0 | K56: =SUMIF('CAP14-15'!$B:$H,Insumo[[#This Row],[DESCRIPCION]],'CAP14-15'!$H:$H) -> 0 | L56: =SUMIF('CAP16-18'!$B:$H,Insumo[[#This Row],[DESCRIPCION]],'CAP16-18'!$H:$H) -> 0 | M56: =SUMIF('CAP19-22'!$B:$H,Insumo[[#This Row],[DESCRIPCION]],'CAP19-22'!$H:$H) -> 0 | N56: =SUMIF('CAP23-24'!$B:$H,Insumo[[#This Row],[DESCRIPCION]],'CAP23-24'!$H:$H) -> 0 | O56: =SUMIF('CAP25'!$B:$H,Insumo[[#This Row],[DESCRIPCION]],'CAP25'!$H:$H) -> 0 | P56: =SUMIF('CAP26-28'!$B:$H,Insumo[[#This Row],[DESCRIPCION]],'CAP26-28'!$H:$H) -> 0 | Q56: =SUMIF('CAP29'!$B:$H,Insumo[[#This Row],[DESCRIPCION]],'CAP29'!$H:$H) -> 0 | T56: 3139
A57: Acople ranurado hierro ductil sch 40 1" | B57: Un | C57: =T57*$T$3 -> 2727.9 | D57: {=IF(Insumo[[#This Row],[VALOR]]=0,Insumo[TOTAL],E57/C57)} -> 0 | E57: =SUM(Insumo[[#This Row],[CAP1-3]:[CAP29]]) -> 0 | F57: =SUMIF('CAP1-3'!$B:$H,Insumo[[#This Row],[DESCRIPCION]],'CAP1-3'!$H:$H) -> 0 | G57: =SUMIF('CAP4-5'!$B:$H,Insumo[[#This Row],[DESCRIPCION]],'CAP4-5'!$H:$H) -> 0 | H57: =SUMIF('CAP6-7'!$B:$H,Insumo[[#This Row],[DESCRIPCION]],'CAP6-7'!$H:$H) -> 0 | I57: =SUMIF('CAP8'!$B:$H,Insumo[[#This Row],[DESCRIPCION]],'CAP8'!$H:$H) -> 0 | J57: =SUMIF('CAP9-13'!$B:$H,Insumo[[#This Row],[DESCRIPCION]],'CAP9-13'!$H:$H) -> 0 | K57: =SUMIF('CAP14-15'!$B:$H,Insumo[[#This Row],[DESCRIPCION]],'CAP14-15'!$H:$H) -> 0 | L57: =SUMIF('CAP16-18'!$B:$H,Insumo[[#This Row],[DESCRIPCION]],'CAP16-18'!$H:$H) -> 0 | M57: =SUMIF('CAP19-22'!$B:$H,Insumo[[#This Row],[DESCRIPCION]],'CAP19-22'!$H:$H) -> 0 | N57: =SUMIF('CAP23-24'!$B:$H,Insumo[[#This Row],[DESCRIPCION]],'CAP23-24'!$H:$H) -> 0 | O57: =SUMIF('CAP25'!$B:$H,Insumo[[#This Row],[DESCRIPCION]],'CAP25'!$H:$H) -> 0 | P57: =SUMIF('CAP26-28'!$B:$H,Insumo[[#This Row],[DESCRIPCION]],'CAP26-28'!$H:$H) -> 0 | Q57: =SUMIF('CAP29'!$B:$H,Insumo[[#This Row],[DESCRIPCION]],'CAP29'!$H:$H) -> 0 | T57: 2598
A58: Acople ranurado hierro ductil sch 40 2 1/2" | B58: Un | C58: =T58*$T$3 -> 2273.25 | D58: {=IF(Insumo[[#This Row],[VALOR]]=0,Insumo[TOTAL],E58/C58)} -> 0 | E58: =SUM(Insumo[[#This Row],[CAP1-3]:[CAP29]]) -> 0 | F58: =SUMIF('CAP1-3'!$B:$H,Insumo[[#This Row],[DESCRIPCION]],'CAP1-3'!$H:$H) -> 0 | G58: =SUMIF('CAP4-5'!$B:$H,Insumo[[#This Row],[DESCRIPCION]],'CAP4-5'!$H:$H) -> 0 | H58: =SUMIF('CAP6-7'!$B:$H,Insumo[[#This Row],[DESCRIPCION]],'CAP6-7'!$H:$H) -> 0 | I58: =SUMIF('CAP8'!$B:$H,Insumo[[#This Row],[DESCRIPCION]],'CAP8'!$H:$H) -> 0 | J58: =SUMIF('CAP9-13'!$B:$H,Insumo[[#This Row],[DESCRIPCION]],'CAP9-13'!$H:$H) -> 0 | K58: =SUMIF('CAP14-15'!$B:$H,Insumo[[#This Row],[DESCRIPCION]],'CAP14-15'!$H:$H) -> 0 | L58: =SUMIF('CAP16-18'!$B:$H,Insumo[[#This Row],[DESCRIPCION]],'CAP16-18'!$H:$H) -> 0 | M58: =SUMIF('CAP19-22'!$B:$H,Insumo[[#This Row],[DESCRIPCION]],'CAP19-22'!$H:$H) -> 0 | N58: =SUMIF('CAP23-24'!$B:$H,Insumo[[#This Row],[DESCRIPCION]],'CAP23-24'!$H:$H) -> 0 | O58: =SUMIF('CAP25'!$B:$H,Insumo[[#This Row],[DESCRIPCION]],'CAP25'!$H:$H) -> 0 | P58: =SUMIF('CAP26-28'!$B:$H,Insumo[[#This Row],[DESCRIPCION]],'CAP26-28'!$H:$H) -> 0 | Q58: =SUMIF('CAP29'!$B:$H,Insumo[[#This Row],[DESCRIPCION]],'CAP29'!$H:$H) -> 0 | T58: 2165
A59: Acople ranurado hierro ductil sch 40 2" | B59: Un | C59: =T59*$T$3 -> 3978.45 | D59: {=IF(Insumo[[#This Row],[VALOR]]=0,Insumo[TOTAL],E59/C59)} -> 0 | E59: =SUM(Insumo[[#This Row],[CAP1-3]:[CAP29]]) -> 0 | F59: =SUMIF('CAP1-3'!$B:$H,Insumo[[#This Row],[DESCRIPCION]],'CAP1-3'!$H:$H) -> 0 | G59: =SUMIF('CAP4-5'!$B:$H,Insumo[[#This Row],[DESCRIPCION]],'CAP4-5'!$H:$H) -> 0 | H59: =SUMIF('CAP6-7'!$B:$H,Insumo[[#This Row],[DESCRIPCION]],'CAP6-7'!$H:$H) -> 0 | I59: =SUMIF('CAP8'!$B:$H,Insumo[[#This Row],[DESCRIPCION]],'CAP8'!$H:$H) -> 0 | J59: =SUMIF('CAP9-13'!$B:$H,Insumo[[#This Row],[DESCRIPCION]],'CAP9-13'!$H:$H) -> 0 | K59: =SUMIF('CAP14-15'!$B:$H,Insumo[[#This Row],[DESCRIPCION]],'CAP14-15'!$H:$H) -> 0 | L59: =SUMIF('CAP16-18'!$B:$H,Insumo[[#This Row],[DESCRIPCION]],'CAP16-18'!$H:$H) -> 0 | M59: =SUMIF('CAP19-22'!$B:$H,Insumo[[#This Row],[DESCRIPCION]],'CAP19-22'!$H:$H) -> 0 | N59: =SUMIF('CAP23-24'!$B:$H,Insumo[[#This Row],[DESCRIPCION]],'CAP23-24'!$H:$H) -> 0 | O59: =SUMIF('CAP25'!$B:$H,Insumo[[#This Row],[DESCRIPCION]],'CAP25'!$H:$H) -> 0 | P59: =SUMIF('CAP26-28'!$B:$H,Insumo[[#This Row],[DESCRIPCION]],'CAP26-28'!$H:$H) -> 0 | Q59: =SUMIF('CAP29'!$B:$H,Insumo[[#This Row],[DESCRIPCION]],'CAP29'!$H:$H) -> 0 | T59: 3789
A60: Acople ranurado hierro ductil sch 40 4" | B60: Un | C60: =T60*$T$3 -> 3750.6 | D60: {=IF(Insumo[[#This Row],[VALOR]]=0,Insumo[TOTAL],E60/C60)} -> 0 | E60: =SUM(Insumo[[#This Row],[CAP1-3]:[CAP29]]) -> 0 | F60: =SUMIF('CAP1-3'!$B:$H,Insumo[[#This Row],[DESCRIPCION]],'CAP1-3'!$H:$H) -> 0 | G60: =SUMIF('CAP4-5'!$B:$H,Insumo[[#This Row],[DESCRIPCION]],'CAP4-5'!$H:$H) -> 0 | H60: =SUMIF('CAP6-7'!$B:$H,Insumo[[#This Row],[DESCRIPCION]],'CAP6-7'!$H:$H) -> 0 | I60: =SUMIF('CAP8'!$B:$H,Insumo[[#This Row],[DESCRIPCION]],'CAP8'!$H:$H) -> 0 | J60: =SUMIF('CAP9-13'!$B:$H,Insumo[[#This Row],[DESCRIPCION]],'CAP9-13'!$H:$H) -> 0 | K60: =SUMIF('CAP14-15'!$B:$H,Insumo[[#This Row],[DESCRIPCION]],'CAP14-15'!$H:$H) -> 0 | L60: =SUMIF('CAP16-18'!$B:$H,Insumo[[#This Row],[DESCRIPCION]],'CAP16-18'!$H:$H) -> 0 | M60: =SUMIF('CAP19-22'!$B:$H,Insumo[[#This Row],[DESCRIPCION]],'CAP19-22'!$H:$H) -> 0 | N60: =SUMIF('CAP23-24'!$B:$H,Insumo[[#This Row],[DESCRIPCION]],'CAP23-24'!$H:$H) -> 0 | O60: =SUMIF('CAP25'!$B:$H,Insumo[[#This Row],[DESCRIPCION]],'CAP25'!$H:$H) -> 0 | P60: =SUMIF('CAP26-28'!$B:$H,Insumo[[#This Row],[DESCRIPCION]],'CAP26-28'!$H:$H) -> 0 | Q60: =SUMIF('CAP29'!$B:$H,Insumo[[#This Row],[DESCRIPCION]],'CAP29'!$H:$H) -> 0 | T60: 3572
A61: Acronal | B61: galón | C61: =T61*$T$3 -> 56717.85 | D61: {=IF(Insumo[[#This Row],[VALOR]]=0,Insumo[TOTAL],E61/C61)} -> 0 | E61: =SUM(Insumo[[#This Row],[CAP1-3]:[CAP29]]) -> 0 | F61: =SUMIF('CAP1-3'!$B:$H,Insumo[[#This Row],[DESCRIPCION]],'CAP1-3'!$H:$H) -> 0 | G61: =SUMIF('CAP4-5'!$B:$H,Insumo[[#This Row],[DESCRIPCION]],'CAP4-5'!$H:$H) -> 0 | H61: =SUMIF('CAP6-7'!$B:$H,Insumo[[#This Row],[DESCRIPCION]],'CAP6-7'!$H:$H) -> 0 | I61: =SUMIF('CAP8'!$B:$H,Insumo[[#This Row],[DESCRIPCION]],'CAP8'!$H:$H) -> 0 | J61: =SUMIF('CAP9-13'!$B:$H,Insumo[[#This Row],[DESCRIPCION]],'CAP9-13'!$H:$H) -> 0 | K61: =SUMIF('CAP14-15'!$B:$H,Insumo[[#This Row],[DESCRIPCION]],'CAP14-15'!$H:$H) -> 0 | L61: =SUMIF('CAP16-18'!$B:$H,Insumo[[#This Row],[DESCRIPCION]],'CAP16-18'!$H:$H) -> 0 | M61: =SUMIF('CAP19-22'!$B:$H,Insumo[[#This Row],[DESCRIPCION]],'CAP19-22'!$H:$H) -> 0 | N61: =SUMIF('CAP23-24'!$B:$H,Insumo[[#This Row],[DESCRIPCION]],'CAP23-24'!$H:$H) -> 0 | O61: =SUMIF('CAP25'!$B:$H,Insumo[[#This Row],[DESCRIPCION]],'CAP25'!$H:$H) -> 0 | P61: =SUMIF('CAP26-28'!$B:$H,Insumo[[#This Row],[DESCRIPCION]],'CAP26-28'!$H:$H) -> 0 | Q61: =SUMIF('CAP29'!$B:$H,Insumo[[#This Row],[DESCRIPCION]],'CAP29'!$H:$H) -> 0 | R61: Homecenter abr 2025 | T61: 54017
A62: Adaptador macho PVC presión de Ø=1/2" PF+UAD | B62: Un | C62: =T62*$T$3 -> 744.45 | D62: {=IF(Insumo[[#This Row],[VALOR]]=0,Insumo[TOTAL],E62/C62)} -> 0 | E62: =SUM(Insumo[[#This Row],[CAP1-3]:[CAP29]]) -> 0 | F62: =SUMIF('CAP1-3'!$B:$H,Insumo[[#This Row],[DESCRIPCION]],'CAP1-3'!$H:$H) -> 0 | G62: =SUMIF('CAP4-5'!$B:$H,Insumo[[#This Row],[DESCRIPCION]],'CAP4-5'!$H:$H) -> 0 | H62: =SUMIF('CAP6-7'!$B:$H,Insumo[[#This Row],[DESCRIPCION]],'CAP6-7'!$H:$H) -> 0 | I62: =SUMIF('CAP8'!$B:$H,Insumo[[#This Row],[DESCRIPCION]],'CAP8'!$H:$H) -> 0 | J62: =SUMIF('CAP9-13'!$B:$H,Insumo[[#This Row],[DESCRIPCION]],'CAP9-13'!$H:$H) -> 0 | K62: =SUMIF('CAP14-15'!$B:$H,Insumo[[#This Row],[DESCRIPCION]],'CAP14-15'!$H:$H) -> 0 | L62: =SUMIF('CAP16-18'!$B:$H,Insumo[[#This Row],[DESCRIPCION]],'CAP16-18'!$H:$H) -> 0 | M62: =SUMIF('CAP19-22'!$B:$H,Insumo[[#This Row],[DESCRIPCION]],'CAP19-22'!$H:$H) -> 0 | N62: =SUMIF('CAP23-24'!$B:$H,Insumo[[#This Row],[DESCRIPCION]],'CAP23-24'!$H:$H) -> 0 | O62: =SUMIF('CAP25'!$B:$H,Insumo[[#This Row],[DESCRIPCION]],'CAP25'!$H:$H) -> 0 | P62: =SUMIF('CAP26-28'!$B:$H,Insumo[[#This Row],[DESCRIPCION]],'CAP26-28'!$H:$H) -> 0 | Q62: =SUMIF('CAP29'!$B:$H,Insumo[[#This Row],[DESCRIPCION]],'CAP29'!$H:$H) -> 0 | R62: Gerfor Feb-2025 | T62: 709
A63: Adaptador macho PVC presión de Ø=3" | B63: Un | C63: =T63*$T$3 -> 45993.15 | D63: {=IF(Insumo[[#This Row],[VALOR]]=0,Insumo[TOTAL],E63/C63)} -> 0 | E63: =SUM(Insumo[[#This Row],[CAP1-3]:[CAP29]]) -> 0 | F63: =SUMIF('CAP1-3'!$B:$H,Insumo[[#This Row],[DESCRIPCION]],'CAP1-3'!$H:$H) -> 0 | G63: =SUMIF('CAP4-5'!$B:$H,Insumo[[#This Row],[DESCRIPCION]],'CAP4-5'!$H:$H) -> 0 | H63: =SUMIF('CAP6-7'!$B:$H,Insumo[[#This Row],[DESCRIPCION]],'CAP6-7'!$H:$H) -> 0 | I63: =SUMIF('CAP8'!$B:$H,Insumo[[#This Row],[DESCRIPCION]],'CAP8'!$H:$H) -> 0 | J63: =SUMIF('CAP9-13'!$B:$H,Insumo[[#This Row],[DESCRIPCION]],'CAP9-13'!$H:$H) -> 0 | K63: =SUMIF('CAP14-15'!$B:$H,Insumo[[#This Row],[DESCRIPCION]],'CAP14-15'!$H:$H) -> 0 | L63: =SUMIF('CAP16-18'!$B:$H,Insumo[[#This Row],[DESCRIPCION]],'CAP16-18'!$H:$H) -> 0 | M63: =SUMIF('CAP19-22'!$B:$H,Insumo[[#This Row],[DESCRIPCION]],'CAP19-22'!$H:$H) -> 0 | N63: =SUMIF('CAP23-24'!$B:$H,Insumo[[#This Row],[DESCRIPCION]],'CAP23-24'!$H:$H) -> 0 | O63: =SUMIF('CAP25'!$B:$H,Insumo[[#This Row],[DESCRIPCION]],'CAP25'!$H:$H) -> 0 | P63: =SUMIF('CAP26-28'!$B:$H,Insumo[[#This Row],[DESCRIPCION]],'CAP26-28'!$H:$H) -> 0 | Q63: =SUMIF('CAP29'!$B:$H,Insumo[[#This Row],[DESCRIPCION]],'CAP29'!$H:$H) -> 0 | R63: Gerfor Feb-2025 | T63: 43803
A64: Adaptador Terminal EMT de 1/2" | B64: Un | C64: =T64*$T$3 -> 1207.5 | D64: {=IF(Insumo[[#This Row],[VALOR]]=0,Insumo[TOTAL],E64/C64)} -> 0 | E64: =SUM(Insumo[[#This Row],[CAP1-3]:[CAP29]]) -> 0 | F64: =SUMIF('CAP1-3'!$B:$H,Insumo[[#This Row],[DESCRIPCION]],'CAP1-3'!$H:$H) -> 0 | G64: =SUMIF('CAP4-5'!$B:$H,Insumo[[#This Row],[DESCRIPCION]],'CAP4-5'!$H:$H) -> 0 | H64: =SUMIF('CAP6-7'!$B:$H,Insumo[[#This Row],[DESCRIPCION]],'CAP6-7'!$H:$H) -> 0 | I64: =SUMIF('CAP8'!$B:$H,Insumo[[#This Row],[DESCRIPCION]],'CAP8'!$H:$H) -> 0 | J64: =SUMIF('CAP9-13'!$B:$H,Insumo[[#This Row],[DESCRIPCION]],'CAP9-13'!$H:$H) -> 0 | K64: =SUMIF('CAP14-15'!$B:$H,Insumo[[#This Row],[DESCRIPCION]],'CAP14-15'!$H:$H) -> 0 | L64: =SUMIF('CAP16-18'!$B:$H,Insumo[[#This Row],[DESCRIPCION]],'CAP16-18'!$H:$H) -> 0 | M64: =SUMIF('CAP19-22'!$B:$H,Insumo[[#This Row],[DESCRIPCION]],'CAP19-22'!$H:$H) -> 0 | N64: =SUMIF('CAP23-24'!$B:$H,Insumo[[#This Row],[DESCRIPCION]],'CAP23-24'!$H:$H) -> 0 | O64: =SUMIF('CAP25'!$B:$H,Insumo[[#This Row],[DESCRIPCION]],'CAP25'!$H:$H) -> 0 | P64: =SUMIF('CAP26-28'!$B:$H,Insumo[[#This Row],[DESCRIPCION]],'CAP26-28'!$H:$H) -> 0 | Q64: =SUMIF('CAP29'!$B:$H,Insumo[[#This Row],[DESCRIPCION]],'CAP29'!$H:$H) -> 0 | T64: 1150
A65: Adaptador Terminal EMT de 3/4" | B65: Un | C65: =T65*$T$3 -> 2310 | D65: {=IF(Insumo[[#This Row],[VALOR]]=0,Insumo[TOTAL],E65/C65)} -> 0 | E65: =SUM(Insumo[[#This Row],[CAP1-3]:[CAP29]]) -> 0 | F65: =SUMIF('CAP1-3'!$B:$H,Insumo[[#This Row],[DESCRIPCION]],'CAP1-3'!$H:$H) -> 0 | G65: =SUMIF('CAP4-5'!$B:$H,Insumo[[#This Row],[DESCRIPCION]],'CAP4-5'!$H:$H) -> 0 | H65: =SUMIF('CAP6-7'!$B:$H,Insumo[[#This Row],[DESCRIPCION]],'CAP6-7'!$H:$H) -> 0 | I65: =SUMIF('CAP8'!$B:$H,Insumo[[#This Row],[DESCRIPCION]],'CAP8'!$H:$H) -> 0 | J65: =SUMIF('CAP9-13'!$B:$H,Insumo[[#This Row],[DESCRIPCION]],'CAP9-13'!$H:$H) -> 0 | K65: =SUMIF('CAP14-15'!$B:$H,Insumo[[#This Row],[DESCRIPCION]],'CAP14-15'!$H:$H) -> 0 | L65: =SUMIF('CAP16-18'!$B:$H,Insumo[[#This Row],[DESCRIPCION]],'CAP16-18'!$H:$H) -> 0 | M65: =SUMIF('CAP19-22'!$B:$H,Insumo[[#This Row],[DESCRIPCION]],'CAP19-22'!$H:$H) -> 0 | N65: =SUMIF('CAP23-24'!$B:$H,Insumo[[#This Row],[DESCRIPCION]],'CAP23-24'!$H:$H) -> 0 | O65: =SUMIF('CAP25'!$B:$H,Insumo[[#This Row],[DESCRIPCION]],'CAP25'!$H:$H) -> 0 | P65: =SUMIF('CAP26-28'!$B:$H,Insumo[[#This Row],[DESCRIPCION]],'CAP26-28'!$H:$H) -> 0 | Q65: =SUMIF('CAP29'!$B:$H,Insumo[[#This Row],[DESCRIPCION]],'CAP29'!$H:$H) -> 0 | T65: 2200
A66: Adaptador Terminal EMT de 1" | B66: Un | C66: =T66*$T$3 -> 3412.5 | D66: {=IF(Insumo[[#This Row],[VALOR]]=0,Insumo[TOTAL],E66/C66)} -> 0 | E66: =SUM(Insumo[[#This Row],[CAP1-3]:[CAP29]]) -> 0 | F66: =SUMIF('CAP1-3'!$B:$H,Insumo[[#This Row],[DESCRIPCION]],'CAP1-3'!$H:$H) -> 0 | G66: =SUMIF('CAP4-5'!$B:$H,Insumo[[#This Row],[DESCRIPCION]],'CAP4-5'!$H:$H) -> 0 | H66: =SUMIF('CAP6-7'!$B:$H,Insumo[[#This Row],[DESCRIPCION]],'CAP6-7'!$H:$H) -> 0 | I66: =SUMIF('CAP8'!$B:$H,Insumo[[#This Row],[DESCRIPCION]],'CAP8'!$H:$H) -> 0 | J66: =SUMIF('CAP9-13'!$B:$H,Insumo[[#This Row],[DESCRIPCION]],'CAP9-13'!$H:$H) -> 0 | K66: =SUMIF('CAP14-15'!$B:$H,Insumo[[#This Row],[DESCRIPCION]],'CAP14-15'!$H:$H) -> 0 | L66: =SUMIF('CAP16-18'!$B:$H,Insumo[[#This Row],[DESCRIPCION]],'CAP16-18'!$H:$H) -> 0 | M66: =SUMIF('CAP19-22'!$B:$H,Insumo[[#This Row],[DESCRIPCION]],'CAP19-22'!$H:$H) -> 0 | N66: =SUMIF('CAP23-24'!$B:$H,Insumo[[#This Row],[DESCRIPCION]],'CAP23-24'!$H:$H) -> 0 | O66: =SUMIF('CAP25'!$B:$H,Insumo[[#This Row],[DESCRIPCION]],'CAP25'!$H:$H) -> 0 | P66: =SUMIF('CAP26-28'!$B:$H,Insumo[[#This Row],[DESCRIPCION]],'CAP26-28'!$H:$H) -> 0 | Q66: =SUMIF('CAP29'!$B:$H,Insumo[[#This Row],[DESCRIPCION]],'CAP29'!$H:$H) -> 0 | T66: 3250
A67: Adaptador Terminal EMT de 2" | B67: Un | C67: =T67*$T$3 -> 6825 | D67: {=IF(Insumo[[#This Row],[VALOR]]=0,Insumo[TOTAL],E67/C67)} -> 0 | E67: =SUM(Insumo[[#This Row],[CAP1-3]:[CAP29]]) -> 0 | F67: =SUMIF('CAP1-3'!$B:$H,Insumo[[#This Row],[DESCRIPCION]],'CAP1-3'!$H:$H) -> 0 | G67: =SUMIF('CAP4-5'!$B:$H,Insumo[[#This Row],[DESCRIPCION]],'CAP4-5'!$H:$H) -> 0 | H67: =SUMIF('CAP6-7'!$B:$H,Insumo[[#This Row],[DESCRIPCION]],'CAP6-7'!$H:$H) -> 0 | I67: =SUMIF('CAP8'!$B:$H,Insumo[[#This Row],[DESCRIPCION]],'CAP8'!$H:$H) -> 0 | J67: =SUMIF('CAP9-13'!$B:$H,Insumo[[#This Row],[DESCRIPCION]],'CAP9-13'!$H:$H) -> 0 | K67: =SUMIF('CAP14-15'!$B:$H,Insumo[[#This Row],[DESCRIPCION]],'CAP14-15'!$H:$H) -> 0 | L67: =SUMIF('CAP16-18'!$B:$H,Insumo[[#This Row],[DESCRIPCION]],'CAP16-18'!$H:$H) -> 0 | M67: =SUMIF('CAP19-22'!$B:$H,Insumo[[#This Row],[DESCRIPCION]],'CAP19-22'!$H:$H) -> 0 | N67: =SUMIF('CAP23-24'!$B:$H,Insumo[[#This Row],[DESCRIPCION]],'CAP23-24'!$H:$H) -> 0 | O67: =SUMIF('CAP25'!$B:$H,Insumo[[#This Row],[DESCRIPCION]],'CAP25'!$H:$H) -> 0 | P67: =SUMIF('CAP26-28'!$B:$H,Insumo[[#This Row],[DESCRIPCION]],'CAP26-28'!$H:$H) -> 0 | Q67: =SUMIF('CAP29'!$B:$H,Insumo[[#This Row],[DESCRIPCION]],'CAP29'!$H:$H) -> 0 | T67: 6500
A68: Adaptador Terminal EMT de 3" | B68: Un | C68: =T68*$T$3 -> 19530 | D68: {=IF(Insumo[[#This Row],[VALOR]]=0,Insumo[TOTAL],E68/C68)} -> 0 | E68: =SUM(Insumo[[#This Row],[CAP1-3]:[CAP29]]) -> 0 | F68: =SUMIF('CAP1-3'!$B:$H,Insumo[[#This Row],[DESCRIPCION]],'CAP1-3'!$H:$H) -> 0 | G68: =SUMIF('CAP4-5'!$B:$H,Insumo[[#This Row],[DESCRIPCION]],'CAP4-5'!$H:$H) -> 0 | H68: =SUMIF('CAP6-7'!$B:$H,Insumo[[#This Row],[DESCRIPCION]],'CAP6-7'!$H:$H) -> 0 | I68: =SUMIF('CAP8'!$B:$H,Insumo[[#This Row],[DESCRIPCION]],'CAP8'!$H:$H) -> 0 | J68: =SUMIF('CAP9-13'!$B:$H,Insumo[[#This Row],[DESCRIPCION]],'CAP9-13'!$H:$H) -> 0 | K68: =SUMIF('CAP14-15'!$B:$H,Insumo[[#This Row],[DESCRIPCION]],'CAP14-15'!$H:$H) -> 0 | L68: =SUMIF('CAP16-18'!$B:$H,Insumo[[#This Row],[DESCRIPCION]],'CAP16-18'!$H:$H) -> 0 | M68: =SUMIF('CAP19-22'!$B:$H,Insumo[[#This Row],[DESCRIPCION]],'CAP19-22'!$H:$H) -> 0 | N68: =SUMIF('CAP23-24'!$B:$H,Insumo[[#This Row],[DESCRIPCION]],'CAP23-24'!$H:$H) -> 0 | O68: =SUMIF('CAP25'!$B:$H,Insumo[[#This Row],[DESCRIPCION]],'CAP25'!$H:$H) -> 0 | P68: =SUMIF('CAP26-28'!$B:$H,Insumo[[#This Row],[DESCRIPCION]],'CAP26-28'!$H:$H) -> 0 | Q68: =SUMIF('CAP29'!$B:$H,Insumo[[#This Row],[DESCRIPCION]],'CAP29'!$H:$H) -> 0 | T68: 18600
A69: Adaptador Terminal PVC de 1/2" | B69: Un | C69: =T69*$T$3 -> 1575 | D69: {=IF(Insumo[[#This Row],[VALOR]]=0,Insumo[TOTAL],E69/C69)} -> 0 | E69: =SUM(Insumo[[#This Row],[CAP1-3]:[CAP29]]) -> 0 | F69: =SUMIF('CAP1-3'!$B:$H,Insumo[[#This Row],[DESCRIPCION]],'CAP1-3'!$H:$H) -> 0 | G69: =SUMIF('CAP4-5'!$B:$H,Insumo[[#This Row],[DESCRIPCION]],'CAP4-5'!$H:$H) -> 0 | H69: =SUMIF('CAP6-7'!$B:$H,Insumo[[#This Row],[DESCRIPCION]],'CAP6-7'!$H:$H) -> 0 | I69: =SUMIF('CAP8'!$B:$H,Insumo[[#This Row],[DESCRIPCION]],'CAP8'!$H:$H) -> 0 | J69: =SUMIF('CAP9-13'!$B:$H,Insumo[[#This Row],[DESCRIPCION]],'CAP9-13'!$H:$H) -> 0 | K69: =SUMIF('CAP14-15'!$B:$H,Insumo[[#This Row],[DESCRIPCION]],'CAP14-15'!$H:$H) -> 0 | L69: =SUMIF('CAP16-18'!$B:$H,Insumo[[#This Row],[DESCRIPCION]],'CAP16-18'!$H:$H) -> 0 | M69: =SUMIF('CAP19-22'!$B:$H,Insumo[[#This Row],[DESCRIPCION]],'CAP19-22'!$H:$H) -> 0 | N69: =SUMIF('CAP23-24'!$B:$H,Insumo[[#This Row],[DESCRIPCION]],'CAP23-24'!$H:$H) -> 0 | O69: =SUMIF('CAP25'!$B:$H,Insumo[[#This Row],[DESCRIPCION]],'CAP25'!$H:$H) -> 0 | P69: =SUMIF('CAP26-28'!$B:$H,Insumo[[#This Row],[DESCRIPCION]],'CAP26-28'!$H:$H) -> 0 | Q69: =SUMIF('CAP29'!$B:$H,Insumo[[#This Row],[DESCRIPCION]],'CAP29'!$H:$H) -> 0 | T69: 1500
A70: Adaptador Terminal PVC de 3/4" | B70: Un | C70: =T70*$T$3 -> 1890 | D70: {=IF(Insumo[[#This Row],[VALOR]]=0,Insumo[TOTAL],E70/C70)} -> 0 | E70: =SUM(Insumo[[#This Row],[CAP1-3]:[CAP29]]) -> 0 | F70: =SUMIF('CAP1-3'!$B:$H,Insumo[[#This Row],[DESCRIPCION]],'CAP1-3'!$H:$H) -> 0 | G70: =SUMIF('CAP4-5'!$B:$H,Insumo[[#This Row],[DESCRIPCION]],'CAP4-5'!$H:$H) -> 0 | H70: =SUMIF('CAP6-7'!$B:$H,Insumo[[#This Row],[DESCRIPCION]],'CAP6-7'!$H:$H) -> 0 | I70: =SUMIF('CAP8'!$B:$H,Insumo[[#This Row],[DESCRIPCION]],'CAP8'!$H:$H) -> 0 | J70: =SUMIF('CAP9-13'!$B:$H,Insumo[[#This Row],[DESCRIPCION]],'CAP9-13'!$H:$H) -> 0 | K70: =SUMIF('CAP14-15'!$B:$H,Insumo[[#This Row],[DESCRIPCION]],'CAP14-15'!$H:$H) -> 0 | L70: =SUMIF('CAP16-18'!$B:$H,Insumo[[#This Row],[DESCRIPCION]],'CAP16-18'!$H:$H) -> 0 | M70: =SUMIF('CAP19-22'!$B:$H,Insumo[[#This Row],[DESCRIPCION]],'CAP19-22'!$H:$H) -> 0 | N70: =SUMIF('CAP23-24'!$B:$H,Insumo[[#This Row],[DESCRIPCION]],'CAP23-24'!$H:$H) -> 0 | O70: =SUMIF('CAP25'!$B:$H,Insumo[[#This Row],[DESCRIPCION]],'CAP25'!$H:$H) -> 0 | P70: =SUMIF('CAP26-28'!$B:$H,Insumo[[#This Row],[DESCRIPCION]],'CAP26-28'!$H:$H) -> 0 | Q70: =SUMIF('CAP29'!$B:$H,Insumo[[#This Row],[DESCRIPCION]],'CAP29'!$H:$H) -> 0 | T70: 1800
A71: Adaptador Terminal PVC de 1" | B71: Un | C71: =T71*$T$3 -> 2625 | D71: {=IF(Insumo[[#This Row],[VALOR]]=0,Insumo[TOTAL],E71/C71)} -> 0 | E71: =SUM(Insumo[[#This Row],[CAP1-3]:[CAP29]]) -> 0 | F71: =SUMIF('CAP1-3'!$B:$H,Insumo[[#This Row],[DESCRIPCION]],'CAP1-3'!$H:$H) -> 0 | G71: =SUMIF('CAP4-5'!$B:$H,Insumo[[#This Row],[DESCRIPCION]],'CAP4-5'!$H:$H) -> 0 | H71: =SUMIF('CAP6-7'!$B:$H,Insumo[[#This Row],[DESCRIPCION]],'CAP6-7'!$H:$H) -> 0 | I71: =SUMIF('CAP8'!$B:$H,Insumo[[#This Row],[DESCRIPCION]],'CAP8'!$H:$H) -> 0 | J71: =SUMIF('CAP9-13'!$B:$H,Insumo[[#This Row],[DESCRIPCION]],'CAP9-13'!$H:$H) -> 0 | K71: =SUMIF('CAP14-15'!$B:$H,Insumo[[#This Row],[DESCRIPCION]],'CAP14-15'!$H:$H) -> 0 | L71: =SUMIF('CAP16-18'!$B:$H,Insumo[[#This Row],[DESCRIPCION]],'CAP16-18'!$H:$H) -> 0 | M71: =SUMIF('CAP19-22'!$B:$H,Insumo[[#This Row],[DESCRIPCION]],'CAP19-22'!$H:$H) -> 0 | N71: =SUMIF('CAP23-24'!$B:$H,Insumo[[#This Row],[DESCRIPCION]],'CAP23-24'!$H:$H) -> 0 | O71: =SUMIF('CAP25'!$B:$H,Insumo[[#This Row],[DESCRIPCION]],'CAP25'!$H:$H) -> 0 | P71: =SUMIF('CAP26-28'!$B:$H,Insumo[[#This Row],[DESCRIPCION]],'CAP26-28'!$H:$H) -> 0 | Q71: =SUMIF('CAP29'!$B:$H,Insumo[[#This Row],[DESCRIPCION]],'CAP29'!$H:$H) -> 0 | T71: 2500
A72: Adaptador Terminal PVC de 1 1/2" | B72: Un | C72: =T72*$T$3 -> 3780 | D72: {=IF(Insumo[[#This Row],[VALOR]]=0,Insumo[TOTAL],E72/C72)} -> 0 | E72: =SUM(Insumo[[#This Row],[CAP1-3]:[CAP29]]) -> 0 | F72: =SUMIF('CAP1-3'!$B:$H,Insumo[[#This Row],[DESCRIPCION]],'CAP1-3'!$H:$H) -> 0 | G72: =SUMIF('CAP4-5'!$B:$H,Insumo[[#This Row],[DESCRIPCION]],'CAP4-5'!$H:$H) -> 0 | H72: =SUMIF('CAP6-7'!$B:$H,Insumo[[#This Row],[DESCRIPCION]],'CAP6-7'!$H:$H) -> 0 | I72: =SUMIF('CAP8'!$B:$H,Insumo[[#This Row],[DESCRIPCION]],'CAP8'!$H:$H) -> 0 | J72: =SUMIF('CAP9-13'!$B:$H,Insumo[[#This Row],[DESCRIPCION]],'CAP9-13'!$H:$H) -> 0 | K72: =SUMIF('CAP14-15'!$B:$H,Insumo[[#This Row],[DESCRIPCION]],'CAP14-15'!$H:$H) -> 0 | L72: =SUMIF('CAP16-18'!$B:$H,Insumo[[#This Row],[DESCRIPCION]],'CAP16-18'!$H:$H) -> 0 | M72: =SUMIF('CAP19-22'!$B:$H,Insumo[[#This Row],[DESCRIPCION]],'CAP19-22'!$H:$H) -> 0 | N72: =SUMIF('CAP23-24'!$B:$H,Insumo[[#This Row],[DESCRIPCION]],'CAP23-24'!$H:$H) -> 0 | O72: =SUMIF('CAP25'!$B:$H,Insumo[[#This Row],[DESCRIPCION]],'CAP25'!$H:$H) -> 0 | P72: =SUMIF('CAP26-28'!$B:$H,Insumo[[#This Row],[DESCRIPCION]],'CAP26-28'!$H:$H) -> 0 | Q72: =SUMIF('CAP29'!$B:$H,Insumo[[#This Row],[DESCRIPCION]],'CAP29'!$H:$H) -> 0 | T72: 3600
A73: Adaptador Terminal PVC de 2" | B73: Un | C73: =T73*$T$3 -> 4725 | D73: {=IF(Insumo[[#This Row],[VALOR]]=0,Insumo[TOTAL],E73/C73)} -> 0 | E73: =SUM(Insumo[[#This Row],[CAP1-3]:[CAP29]]) -> 0 | F73: =SUMIF('CAP1-3'!$B:$H,Insumo[[#This Row],[DESCRIPCION]],'CAP1-3'!$H:$H) -> 0 | G73: =SUMIF('CAP4-5'!$B:$H,Insumo[[#This Row],[DESCRIPCION]],'CAP4-5'!$H:$H) -> 0 | H73: =SUMIF('CAP6-7'!$B:$H,Insumo[[#This Row],[DESCRIPCION]],'CAP6-7'!$H:$H) -> 0 | I73: =SUMIF('CAP8'!$B:$H,Insumo[[#This Row],[DESCRIPCION]],'CAP8'!$H:$H) -> 0 | J73: =SUMIF('CAP9-13'!$B:$H,Insumo[[#This Row],[DESCRIPCION]],'CAP9-13'!$H:$H) -> 0 | K73: =SUMIF('CAP14-15'!$B:$H,Insumo[[#This Row],[DESCRIPCION]],'CAP14-15'!$H:$H) -> 0 | L73: =SUMIF('CAP16-18'!$B:$H,Insumo[[#This Row],[DESCRIPCION]],'CAP16-18'!$H:$H) -> 0 | M73: =SUMIF('CAP19-22'!$B:$H,Insumo[[#This Row],[DESCRIPCION]],'CAP19-22'!$H:$H) -> 0 | N73: =SUMIF('CAP23-24'!$B:$H,Insumo[[#This Row],[DESCRIPCION]],'CAP23-24'!$H:$H) -> 0 | O73: =SUMIF('CAP25'!$B:$H,Insumo[[#This Row],[DESCRIPCION]],'CAP25'!$H:$H) -> 0 | P73: =SUMIF('CAP26-28'!$B:$H,Insumo[[#This Row],[DESCRIPCION]],'CAP26-28'!$H:$H) -> 0 | Q73: =SUMIF('CAP29'!$B:$H,Insumo[[#This Row],[DESCRIPCION]],'CAP29'!$H:$H) -> 0 | T73: 4500
A74: Adaptador Terminal PVC de 3" | B74: Un | C74: =T74*$T$3 -> 7875 | D74: {=IF(Insumo[[#This Row],[VALOR]]=0,Insumo[TOTAL],E74/C74)} -> 0 | E74: =SUM(Insumo[[#This Row],[CAP1-3]:[CAP29]]) -> 0 | F74: =SUMIF('CAP1-3'!$B:$H,Insumo[[#This Row],[DESCRIPCION]],'CAP1-3'!$H:$H) -> 0 | G74: =SUMIF('CAP4-5'!$B:$H,Insumo[[#This Row],[DESCRIPCION]],'CAP4-5'!$H:$H) -> 0 | H74: =SUMIF('CAP6-7'!$B:$H,Insumo[[#This Row],[DESCRIPCION]],'CAP6-7'!$H:$H) -> 0 | I74: =SUMIF('CAP8'!$B:$H,Insumo[[#This Row],[DESCRIPCION]],'CAP8'!$H:$H) -> 0 | J74: =SUMIF('CAP9-13'!$B:$H,Insumo[[#This Row],[DESCRIPCION]],'CAP9-13'!$H:$H) -> 0 | K74: =SUMIF('CAP14-15'!$B:$H,Insumo[[#This Row],[DESCRIPCION]],'CAP14-15'!$H:$H) -> 0 | L74: =SUMIF('CAP16-18'!$B:$H,Insumo[[#This Row],[DESCRIPCION]],'CAP16-18'!$H:$H) -> 0 | M74: =SUMIF('CAP19-22'!$B:$H,Insumo[[#This Row],[DESCRIPCION]],'CAP19-22'!$H:$H) -> 0 | N74: =SUMIF('CAP23-24'!$B:$H,Insumo[[#This Row],[DESCRIPCION]],'CAP23-24'!$H:$H) -> 0 | O74: =SUMIF('CAP25'!$B:$H,Insumo[[#This Row],[DESCRIPCION]],'CAP25'!$H:$H) -> 0 | P74: =SUMIF('CAP26-28'!$B:$H,Insumo[[#This Row],[DESCRIPCION]],'CAP26-28'!$H:$H) -> 0 | Q74: =SUMIF('CAP29'!$B:$H,Insumo[[#This Row],[DESCRIPCION]],'CAP29'!$H:$H) -> 0 | T74: 7500
A75: Adhesivo para piso de vinilo | B75: galón | C75: =T75*$T$3 -> 142493.4 | D75: {=IF(Insumo[[#This Row],[VALOR]]=0,Insumo[TOTAL],E75/C75)} -> 0 | E75: =SUM(Insumo[[#This Row],[CAP1-3]:[CAP29]]) -> 0 | F75: =SUMIF('CAP1-3'!$B:$H,Insumo[[#This Row],[DESCRIPCION]],'CAP1-3'!$H:$H) -> 0 | G75: =SUMIF('CAP4-5'!$B:$H,Insumo[[#This Row],[DESCRIPCION]],'CAP4-5'!$H:$H) -> 0 | H75: =SUMIF('CAP6-7'!$B:$H,Insumo[[#This Row],[DESCRIPCION]],'CAP6-7'!$H:$H) -> 0 | I75: =SUMIF('CAP8'!$B:$H,Insumo[[#This Row],[DESCRIPCION]],'CAP8'!$H:$H) -> 0 | J75: =SUMIF('CAP9-13'!$B:$H,Insumo[[#This Row],[DESCRIPCION]],'CAP9-13'!$H:$H) -> 0 | K75: =SUMIF('CAP14-15'!$B:$H,Insumo[[#This Row],[DESCRIPCION]],'CAP14-15'!$H:$H) -> 0 | L75: =SUMIF('CAP16-18'!$B:$H,Insumo[[#This Row],[DESCRIPCION]],'CAP16-18'!$H:$H) -> 0 | M75: =SUMIF('CAP19-22'!$B:$H,Insumo[[#This Row],[DESCRIPCION]],'CAP19-22'!$H:$H) -> 0 | N75: =SUMIF('CAP23-24'!$B:$H,Insumo[[#This Row],[DESCRIPCION]],'CAP23-24'!$H:$H) -> 0 | O75: =SUMIF('CAP25'!$B:$H,Insumo[[#This Row],[DESCRIPCION]],'CAP25'!$H:$H) -> 0 | P75: =SUMIF('CAP26-28'!$B:$H,Insumo[[#This Row],[DESCRIPCION]],'CAP26-28'!$H:$H) -> 0 | Q75: =SUMIF('CAP29'!$B:$H,Insumo[[#This Row],[DESCRIPCION]],'CAP29'!$H:$H) -> 0 | T75: 135708
... A91: Alambre de púas Cal 14 | B91: M | C91: =T91*$T$3 -> 865.2 | D91: {=IF(Insumo[[#This Row],[VALOR]]=0,Insumo[TOTAL],E91/C91)} -> 0 | E91: =SUM(Insumo[[#This Row],[CAP1-3]:[CAP29]]) -> 0 | F91: =SUMIF('CAP1-3'!$B:$H,Insumo[[#This Row],[DESCRIPCION]],'CAP1-3'!$H:$H) -> 0 | G91: =SUMIF('CAP4-5'!$B:$H,Insumo[[#This Row],[DESCRIPCION]],'CAP4-5'!$H:$H) -> 0 | H91: =SUMIF('CAP6-7'!$B:$H,Insumo[[#This Row],[DESCRIPCION]],'CAP6-7'!$H:$H) -> 0 | I91: =SUMIF('CAP8'!$B:$H,Insumo[[#This Row],[DESCRIPCION]],'CAP8'!$H:$H) -> 0 | J91: =SUMIF('CAP9-13'!$B:$H,Insumo[[#This Row],[DESCRIPCION]],'CAP9-13'!$H:$H) -> 0 | K91: =SUMIF('CAP14-15'!$B:$H,Insumo[[#This Row],[DESCRIPCION]],'CAP14-15'!$H:$H) -> 0 | L91: =SUMIF('CAP16-18'!$B:$H,Insumo[[#This Row],[DESCRIPCION]],'CAP16-18'!$H:$H) -> 0 | M91: =SUMIF('CAP19-22'!$B:$H,Insumo[[#This Row],[DESCRIPCION]],'CAP19-22'!$H:$H) -> 0 | N91: =SUMIF('CAP23-24'!$B:$H,Insumo[[#This Row],[DESCRIPCION]],'CAP23-24'!$H:$H) -> 0 | O91: =SUMIF('CAP25'!$B:$H,Insumo[[#This Row],[DESCRIPCION]],'CAP25'!$H:$H) -> 0 | P91: =SUMIF('CAP26-28'!$B:$H,Insumo[[#This Row],[DESCRIPCION]],'CAP26-28'!$H:$H) -> 0 | Q91: =SUMIF('CAP29'!$B:$H,Insumo[[#This Row],[DESCRIPCION]],'CAP29'!$H:$H) -> 0 | T91: 824
A92: Alambre galvanizado Cal 12 | B92: Kg | C92: =T92*$T$3 -> 11353.65 | D92: {=IF(Insumo[[#This Row],[VALOR]]=0,Insumo[TOTAL],E92/C92)} -> 0 | E92: =SUM(Insumo[[#This Row],[CAP1-3]:[CAP29]]) -> 0 | F92: =SUMIF('CAP1-3'!$B:$H,Insumo[[#This Row],[DESCRIPCION]],'CAP1-3'!$H:$H) -> 0 | G92: =SUMIF('CAP4-5'!$B:$H,Insumo[[#This Row],[DESCRIPCION]],'CAP4-5'!$H:$H) -> 0 | H92: =SUMIF('CAP6-7'!$B:$H,Insumo[[#This Row],[DESCRIPCION]],'CAP6-7'!$H:$H) -> 0 | I92: =SUMIF('CAP8'!$B:$H,Insumo[[#This Row],[DESCRIPCION]],'CAP8'!$H:$H) -> 0 | J92: =SUMIF('CAP9-13'!$B:$H,Insumo[[#This Row],[DESCRIPCION]],'CAP9-13'!$H:$H) -> 0 | K92: =SUMIF('CAP14-15'!$B:$H,Insumo[[#This Row],[DESCRIPCION]],'CAP14-15'!$H:$H) -> 0 | L92: =SUMIF('CAP16-18'!$B:$H,Insumo[[#This Row],[DESCRIPCION]],'CAP16-18'!$H:$H) -> 0 | M92: =SUMIF('CAP19-22'!$B:$H,Insumo[[#This Row],[DESCRIPCION]],'CAP19-22'!$H:$H) -> 0 | N92: =SUMIF('CAP23-24'!$B:$H,Insumo[[#This Row],[DESCRIPCION]],'CAP23-24'!$H:$H) -> 0 | O92: =SUMIF('CAP25'!$B:$H,Insumo[[#This Row],[DESCRIPCION]],'CAP25'!$H:$H) -> 0 | P92: =SUMIF('CAP26-28'!$B:$H,Insumo[[#This Row],[DESCRIPCION]],'CAP26-28'!$H:$H) -> 0 | Q92: =SUMIF('CAP29'!$B:$H,Insumo[[#This Row],[DESCRIPCION]],'CAP29'!$H:$H) -> 0 | R92: Proalco Feb 2025 | T92: 10813
A93: Alambre galvanizado Cal 13 | B93: Kg | C93: =T93*$T$3 -> 11461.8 | D93: {=IF(Insumo[[#This Row],[VALOR]]=0,Insumo[TOTAL],E93/C93)} -> 0 | E93: =SUM(Insumo[[#This Row],[CAP1-3]:[CAP29]]) -> 0 | F93: =SUMIF('CAP1-3'!$B:$H,Insumo[[#This Row],[DESCRIPCION]],'CAP1-3'!$H:$H) -> 0 | G93: =SUMIF('CAP4-5'!$B:$H,Insumo[[#This Row],[DESCRIPCION]],'CAP4-5'!$H:$H) -> 0 | H93: =SUMIF('CAP6-7'!$B:$H,Insumo[[#This Row],[DESCRIPCION]],'CAP6-7'!$H:$H) -> 0 | I93: =SUMIF('CAP8'!$B:$H,Insumo[[#This Row],[DESCRIPCION]],'CAP8'!$H:$H) -> 0 | J93: =SUMIF('CAP9-13'!$B:$H,Insumo[[#This Row],[DESCRIPCION]],'CAP9-13'!$H:$H) -> 0 | K93: =SUMIF('CAP14-15'!$B:$H,Insumo[[#This Row],[DESCRIPCION]],'CAP14-15'!$H:$H) -> 0 | L93: =SUMIF('CAP16-18'!$B:$H,Insumo[[#This Row],[DESCRIPCION]],'CAP16-18'!$H:$H) -> 0 | M93: =SUMIF('CAP19-22'!$B:$H,Insumo[[#This Row],[DESCRIPCION]],'CAP19-22'!$H:$H) -> 0 | N93: =SUMIF('CAP23-24'!$B:$H,Insumo[[#This Row],[DESCRIPCION]],'CAP23-24'!$H:$H) -> 0 | O93: =SUMIF('CAP25'!$B:$H,Insumo[[#This Row],[DESCRIPCION]],'CAP25'!$H:$H) -> 0 | P93: =SUMIF('CAP26-28'!$B:$H,Insumo[[#This Row],[DESCRIPCION]],'CAP26-28'!$H:$H) -> 0 | Q93: =SUMIF('CAP29'!$B:$H,Insumo[[#This Row],[DESCRIPCION]],'CAP29'!$H:$H) -> 0 | T93: 10916
A94: Alambre galvanizado Cal 14 | B94: Kg | C94: =T94*$T$3 -> 11569.95 | D94: {=IF(Insumo[[#This Row],[VALOR]]=0,Insumo[TOTAL],E94/C94)} -> 0 | E94: =SUM(Insumo[[#This Row],[CAP1-3]:[CAP29]]) -> 0 | F94: =SUMIF('CAP1-3'!$B:$H,Insumo[[#This Row],[DESCRIPCION]],'CAP1-3'!$H:$H) -> 0 | G94: =SUMIF('CAP4-5'!$B:$H,Insumo[[#This Row],[DESCRIPCION]],'CAP4-5'!$H:$H) -> 0 | H94: =SUMIF('CAP6-7'!$B:$H,Insumo[[#This Row],[DESCRIPCION]],'CAP6-7'!$H:$H) -> 0 | I94: =SUMIF('CAP8'!$B:$H,Insumo[[#This Row],[DESCRIPCION]],'CAP8'!$H:$H) -> 0 | J94: =SUMIF('CAP9-13'!$B:$H,Insumo[[#This Row],[DESCRIPCION]],'CAP9-13'!$H:$H) -> 0 | K94: =SUMIF('CAP14-15'!$B:$H,Insumo[[#This Row],[DESCRIPCION]],'CAP14-15'!$H:$H) -> 0 | L94: =SUMIF('CAP16-18'!$B:$H,Insumo[[#This Row],[DESCRIPCION]],'CAP16-18'!$H:$H) -> 0 | M94: =SUMIF('CAP19-22'!$B:$H,Insumo[[#This Row],[DESCRIPCION]],'CAP19-22'!$H:$H) -> 0 | N94: =SUMIF('CAP23-24'!$B:$H,Insumo[[#This Row],[DESCRIPCION]],'CAP23-24'!$H:$H) -> 0 | O94: =SUMIF('CAP25'!$B:$H,Insumo[[#This Row],[DESCRIPCION]],'CAP25'!$H:$H) -> 0 | P94: =SUMIF('CAP26-28'!$B:$H,Insumo[[#This Row],[DESCRIPCION]],'CAP26-28'!$H:$H) -> 0 | Q94: =SUMIF('CAP29'!$B:$H,Insumo[[#This Row],[DESCRIPCION]],'CAP29'!$H:$H) -> 0 | R94: Proalco Feb 2025 | T94: 11019
A95: Alambre negro calibre 18 | B95: Kg | C95: =T95*$T$3 -> 7665 | D95: {=IF(Insumo[[#This Row],[VALOR]]=0,Insumo[TOTAL],E95/C95)} -> 0 | E95: =SUM(Insumo[[#This Row],[CAP1-3]:[CAP29]]) -> 0 | F95: =SUMIF('CAP1-3'!$B:$H,Insumo[[#This Row],[DESCRIPCION]],'CAP1-3'!$H:$H) -> 0 | G95: =SUMIF('CAP4-5'!$B:$H,Insumo[[#This Row],[DESCRIPCION]],'CAP4-5'!$H:$H) -> 0 | H95: =SUMIF('CAP6-7'!$B:$H,Insumo[[#This Row],[DESCRIPCION]],'CAP6-7'!$H:$H) -> 0 | I95: =SUMIF('CAP8'!$B:$H,Insumo[[#This Row],[DESCRIPCION]],'CAP8'!$H:$H) -> 0 | J95: =SUMIF('CAP9-13'!$B:$H,Insumo[[#This Row],[DESCRIPCION]],'CAP9-13'!$H:$H) -> 0 | K95: =SUMIF('CAP14-15'!$B:$H,Insumo[[#This Row],[DESCRIPCION]],'CAP14-15'!$H:$H) -> 0 | L95: =SUMIF('CAP16-18'!$B:$H,Insumo[[#This Row],[DESCRIPCION]],'CAP16-18'!$H:$H) -> 0 | M95: =SUMIF('CAP19-22'!$B:$H,Insumo[[#This Row],[DESCRIPCION]],'CAP19-22'!$H:$H) -> 0 | N95: =SUMIF('CAP23-24'!$B:$H,Insumo[[#This Row],[DESCRIPCION]],'CAP23-24'!$H:$H) -> 0 | O95: =SUMIF('CAP25'!$B:$H,Insumo[[#This Row],[DESCRIPCION]],'CAP25'!$H:$H) -> 0 | P95: =SUMIF('CAP26-28'!$B:$H,Insumo[[#This Row],[DESCRIPCION]],'CAP26-28'!$H:$H) -> 0 | Q95: =SUMIF('CAP29'!$B:$H,Insumo[[#This Row],[DESCRIPCION]],'CAP29'!$H:$H) -> 0 | T95: 7300
A96: Alcorque para proteccion de raiz | B96: Un | C96: =T96*$T$3 -> 1363950 | D96: {=IF(Insumo[[#This Row],[VALOR]]=0,Insumo[TOTAL],E96/C96)} -> 0 | E96: =SUM(Insumo[[#This Row],[CAP1-3]:[CAP29]]) -> 0 | F96: =SUMIF('CAP1-3'!$B:$H,Insumo[[#This Row],[DESCRIPCION]],'CAP1-3'!$H:$H) -> 0 | G96: =SUMIF('CAP4-5'!$B:$H,Insumo[[#This Row],[DESCRIPCION]],'CAP4-5'!$H:$H) -> 0 | H96: =SUMIF('CAP6-7'!$B:$H,Insumo[[#This Row],[DESCRIPCION]],'CAP6-7'!$H:$H) -> 0 | I96: =SUMIF('CAP8'!$B:$H,Insumo[[#This Row],[DESCRIPCION]],'CAP8'!$H:$H) -> 0 | J96: =SUMIF('CAP9-13'!$B:$H,Insumo[[#This Row],[DESCRIPCION]],'CAP9-13'!$H:$H) -> 0 | K96: =SUMIF('CAP14-15'!$B:$H,Insumo[[#This Row],[DESCRIPCION]],'CAP14-15'!$H:$H) -> 0 | L96: =SUMIF('CAP16-18'!$B:$H,Insumo[[#This Row],[DESCRIPCION]],'CAP16-18'!$H:$H) -> 0 | M96: =SUMIF('CAP19-22'!$B:$H,Insumo[[#This Row],[DESCRIPCION]],'CAP19-22'!$H:$H) -> 0 | N96: =SUMIF('CAP23-24'!$B:$H,Insumo[[#This Row],[DESCRIPCION]],'CAP23-24'!$H:$H) -> 0 | O96: =SUMIF('CAP25'!$B:$H,Insumo[[#This Row],[DESCRIPCION]],'CAP25'!$H:$H) -> 0 | P96: =SUMIF('CAP26-28'!$B:$H,Insumo[[#This Row],[DESCRIPCION]],'CAP26-28'!$H:$H) -> 0 | Q96: =SUMIF('CAP29'!$B:$H,Insumo[[#This Row],[DESCRIPCION]],'CAP29'!$H:$H) -> 0 | T96: 1299000
A97: Amarra de nylon de 10 cm | B97: Un | C97: =T97*$T$3 -> 74.55 | D97: {=IF(Insumo[[#This Row],[VALOR]]=0,Insumo[TOTAL],E97/C97)} -> 0 | E97: =SUM(Insumo[[#This Row],[CAP1-3]:[CAP29]]) -> 0 | F97: =SUMIF('CAP1-3'!$B:$H,Insumo[[#This Row],[DESCRIPCION]],'CAP1-3'!$H:$H) -> 0 | G97: =SUMIF('CAP4-5'!$B:$H,Insumo[[#This Row],[DESCRIPCION]],'CAP4-5'!$H:$H) -> 0 | H97: =SUMIF('CAP6-7'!$B:$H,Insumo[[#This Row],[DESCRIPCION]],'CAP6-7'!$H:$H) -> 0 | I97: =SUMIF('CAP8'!$B:$H,Insumo[[#This Row],[DESCRIPCION]],'CAP8'!$H:$H) -> 0 | J97: =SUMIF('CAP9-13'!$B:$H,Insumo[[#This Row],[DESCRIPCION]],'CAP9-13'!$H:$H) -> 0 | K97: =SUMIF('CAP14-15'!$B:$H,Insumo[[#This Row],[DESCRIPCION]],'CAP14-15'!$H:$H) -> 0 | L97: =SUMIF('CAP16-18'!$B:$H,Insumo[[#This Row],[DESCRIPCION]],'CAP16-18'!$H:$H) -> 0 | M97: =SUMIF('CAP19-22'!$B:$H,Insumo[[#This Row],[DESCRIPCION]],'CAP19-22'!$H:$H) -> 0 | N97: =SUMIF('CAP23-24'!$B:$H,Insumo[[#This Row],[DESCRIPCION]],'CAP23-24'!$H:$H) -> 0 | O97: =SUMIF('CAP25'!$B:$H,Insumo[[#This Row],[DESCRIPCION]],'CAP25'!$H:$H) -> 0 | P97: =SUMIF('CAP26-28'!$B:$H,Insumo[[#This Row],[DESCRIPCION]],'CAP26-28'!$H:$H) -> 0 | Q97: =SUMIF('CAP29'!$B:$H,Insumo[[#This Row],[DESCRIPCION]],'CAP29'!$H:$H) -> 0 | T97: 71
A98: Amarras con tapa plástica | B98: Un | C98: =T98*$T$3 -> 443.1 | D98: {=IF(Insumo[[#This Row],[VALOR]]=0,Insumo[TOTAL],E98/C98)} -> 0 | E98: =SUM(Insumo[[#This Row],[CAP1-3]:[CAP29]]) -> 0 | F98: =SUMIF('CAP1-3'!$B:$H,Insumo[[#This Row],[DESCRIPCION]],'CAP1-3'!$H:$H) -> 0 | G98: =SUMIF('CAP4-5'!$B:$H,Insumo[[#This Row],[DESCRIPCION]],'CAP4-5'!$H:$H) -> 0 | H98: =SUMIF('CAP6-7'!$B:$H,Insumo[[#This Row],[DESCRIPCION]],'CAP6-7'!$H:$H) -> 0 | I98: =SUMIF('CAP8'!$B:$H,Insumo[[#This Row],[DESCRIPCION]],'CAP8'!$H:$H) -> 0 | J98: =SUMIF('CAP9-13'!$B:$H,Insumo[[#This Row],[DESCRIPCION]],'CAP9-13'!$H:$H) -> 0 | K98: =SUMIF('CAP14-15'!$B:$H,Insumo[[#This Row],[DESCRIPCION]],'CAP14-15'!$H:$H) -> 0 | L98: =SUMIF('CAP16-18'!$B:$H,Insumo[[#This Row],[DESCRIPCION]],'CAP16-18'!$H:$H) -> 0 | M98: =SUMIF('CAP19-22'!$B:$H,Insumo[[#This Row],[DESCRIPCION]],'CAP19-22'!$H:$H) -> 0 | N98: =SUMIF('CAP23-24'!$B:$H,Insumo[[#This Row],[DESCRIPCION]],'CAP23-24'!$H:$H) -> 0 | O98: =SUMIF('CAP25'!$B:$H,Insumo[[#This Row],[DESCRIPCION]],'CAP25'!$H:$H) -> 0 | P98: =SUMIF('CAP26-28'!$B:$H,Insumo[[#This Row],[DESCRIPCION]],'CAP26-28'!$H:$H) -> 0 | Q98: =SUMIF('CAP29'!$B:$H,Insumo[[#This Row],[DESCRIPCION]],'CAP29'!$H:$H) -> 0 | T98: 422
A99: Angulo 1 X 3/16" | B99: M | C99: =T99*$T$3 -> 11388.3 | D99: {=IF(Insumo[[#This Row],[VALOR]]=0,Insumo[TOTAL],E99/C99)} -> 0 | E99: =SUM(Insumo[[#This Row],[CAP1-3]:[CAP29]]) -> 0 | F99: =SUMIF('CAP1-3'!$B:$H,Insumo[[#This Row],[DESCRIPCION]],'CAP1-3'!$H:$H) -> 0 | G99: =SUMIF('CAP4-5'!$B:$H,Insumo[[#This Row],[DESCRIPCION]],'CAP4-5'!$H:$H) -> 0 | H99: =SUMIF('CAP6-7'!$B:$H,Insumo[[#This Row],[DESCRIPCION]],'CAP6-7'!$H:$H) -> 0 | I99: =SUMIF('CAP8'!$B:$H,Insumo[[#This Row],[DESCRIPCION]],'CAP8'!$H:$H) -> 0 | J99: =SUMIF('CAP9-13'!$B:$H,Insumo[[#This Row],[DESCRIPCION]],'CAP9-13'!$H:$H) -> 0 | K99: =SUMIF('CAP14-15'!$B:$H,Insumo[[#This Row],[DESCRIPCION]],'CAP14-15'!$H:$H) -> 0 | L99: =SUMIF('CAP16-18'!$B:$H,Insumo[[#This Row],[DESCRIPCION]],'CAP16-18'!$H:$H) -> 0 | M99: =SUMIF('CAP19-22'!$B:$H,Insumo[[#This Row],[DESCRIPCION]],'CAP19-22'!$H:$H) -> 0 | N99: =SUMIF('CAP23-24'!$B:$H,Insumo[[#This Row],[DESCRIPCION]],'CAP23-24'!$H:$H) -> 0 | O99: =SUMIF('CAP25'!$B:$H,Insumo[[#This Row],[DESCRIPCION]],'CAP25'!$H:$H) -> 0 | P99: =SUMIF('CAP26-28'!$B:$H,Insumo[[#This Row],[DESCRIPCION]],'CAP26-28'!$H:$H) -> 0 | Q99: =SUMIF('CAP29'!$B:$H,Insumo[[#This Row],[DESCRIPCION]],'CAP29'!$H:$H) -> 0 | R99: GyJ Web abr 2025 | T99: 10846
A100: Angulo 1/8" x 1 1/2" | B100: M | C100: =T100*$T$3 -> 10533.6 | D100: {=IF(Insumo[[#This Row],[VALOR]]=0,Insumo[TOTAL],E100/C100)} -> 0 | E100: =SUM(Insumo[[#This Row],[CAP1-3]:[CAP29]]) -> 0 | F100: =SUMIF('CAP1-3'!$B:$H,Insumo[[#This Row],[DESCRIPCION]],'CAP1-3'!$H:$H) -> 0 | G100: =SUMIF('CAP4-5'!$B:$H,Insumo[[#This Row],[DESCRIPCION]],'CAP4-5'!$H:$H) -> 0 | H100: =SUMIF('CAP6-7'!$B:$H,Insumo[[#This Row],[DESCRIPCION]],'CAP6-7'!$H:$H) -> 0 | I100: =SUMIF('CAP8'!$B:$H,Insumo[[#This Row],[DESCRIPCION]],'CAP8'!$H:$H) -> 0 | J100: =SUMIF('CAP9-13'!$B:$H,Insumo[[#This Row],[DESCRIPCION]],'CAP9-13'!$H:$H) -> 0 | K100: =SUMIF('CAP14-15'!$B:$H,Insumo[[#This Row],[DESCRIPCION]],'CAP14-15'!$H:$H) -> 0 | L100: =SUMIF('CAP16-18'!$B:$H,Insumo[[#This Row],[DESCRIPCION]],'CAP16-18'!$H:$H) -> 0 | M100: =SUMIF('CAP19-22'!$B:$H,Insumo[[#This Row],[DESCRIPCION]],'CAP19-22'!$H:$H) -> 0 | N100: =SUMIF('CAP23-24'!$B:$H,Insumo[[#This Row],[DESCRIPCION]],'CAP23-24'!$H:$H) -> 0 | O100: =SUMIF('CAP25'!$B:$H,Insumo[[#This Row],[DESCRIPCION]],'CAP25'!$H:$H) -> 0 | P100: =SUMIF('CAP26-28'!$B:$H,Insumo[[#This Row],[DESCRIPCION]],'CAP26-28'!$H:$H) -> 0 | Q100: =SUMIF('CAP29'!$B:$H,Insumo[[#This Row],[DESCRIPCION]],'CAP29'!$H:$H) -> 0 | T100: 10032
A101: Angulo 2 X 1/4" | B101: M | C101: =T101*$T$3 -> 31556.7 | D101: {=IF(Insumo[[#This Row],[VALOR]]=0,Insumo[TOTAL],E101/C101)} -> 0 | E101: =SUM(Insumo[[#This Row],[CAP1-3]:[CAP29]]) -> 0 | F101: =SUMIF('CAP1-3'!$B:$H,Insumo[[#This Row],[DESCRIPCION]],'CAP1-3'!$H:$H) -> 0 | G101: =SUMIF('CAP4-5'!$B:$H,Insumo[[#This Row],[DESCRIPCION]],'CAP4-5'!$H:$H) -> 0 | H101: =SUMIF('CAP6-7'!$B:$H,Insumo[[#This Row],[DESCRIPCION]],'CAP6-7'!$H:$H) -> 0 | I101: =SUMIF('CAP8'!$B:$H,Insumo[[#This Row],[DESCRIPCION]],'CAP8'!$H:$H) -> 0 | J101: =SUMIF('CAP9-13'!$B:$H,Insumo[[#This Row],[DESCRIPCION]],'CAP9-13'!$H:$H) -> 0 | K101: =SUMIF('CAP14-15'!$B:$H,Insumo[[#This Row],[DESCRIPCION]],'CAP14-15'!$H:$H) -> 0 | L101: =SUMIF('CAP16-18'!$B:$H,Insumo[[#This Row],[DESCRIPCION]],'CAP16-18'!$H:$H) -> 0 | M101: =SUMIF('CAP19-22'!$B:$H,Insumo[[#This Row],[DESCRIPCION]],'CAP19-22'!$H:$H) -> 0 | N101: =SUMIF('CAP23-24'!$B:$H,Insumo[[#This Row],[DESCRIPCION]],'CAP23-24'!$H:$H) -> 0 | O101: =SUMIF('CAP25'!$B:$H,Insumo[[#This Row],[DESCRIPCION]],'CAP25'!$H:$H) -> 0 | P101: =SUMIF('CAP26-28'!$B:$H,Insumo[[#This Row],[DESCRIPCION]],'CAP26-28'!$H:$H) -> 0 | Q101: =SUMIF('CAP29'!$B:$H,Insumo[[#This Row],[DESCRIPCION]],'CAP29'!$H:$H) -> 0 | R101: GyJ Web abr 2025 | T101: 30054
A102: Angulo 3/4 X 1/8" | B102: M | C102: =T102*$T$3 -> 3231.9 | D102: {=IF(Insumo[[#This Row],[VALOR]]=0,Insumo[TOTAL],E102/C102)} -> 0 | E102: =SUM(Insumo[[#This Row],[CAP1-3]:[CAP29]]) -> 0 | F102: =SUMIF('CAP1-3'!$B:$H,Insumo[[#This Row],[DESCRIPCION]],'CAP1-3'!$H:$H) -> 0 | G102: =SUMIF('CAP4-5'!$B:$H,Insumo[[#This Row],[DESCRIPCION]],'CAP4-5'!$H:$H) -> 0 | H102: =SUMIF('CAP6-7'!$B:$H,Insumo[[#This Row],[DESCRIPCION]],'CAP6-7'!$H:$H) -> 0 | I102: =SUMIF('CAP8'!$B:$H,Insumo[[#This Row],[DESCRIPCION]],'CAP8'!$H:$H) -> 0 | J102: =SUMIF('CAP9-13'!$B:$H,Insumo[[#This Row],[DESCRIPCION]],'CAP9-13'!$H:$H) -> 0 | K102: =SUMIF('CAP14-15'!$B:$H,Insumo[[#This Row],[DESCRIPCION]],'CAP14-15'!$H:$H) -> 0 | L102: =SUMIF('CAP16-18'!$B:$H,Insumo[[#This Row],[DESCRIPCION]],'CAP16-18'!$H:$H) -> 0 | M102: =SUMIF('CAP19-22'!$B:$H,Insumo[[#This Row],[DESCRIPCION]],'CAP19-22'!$H:$H) -> 0 | N102: =SUMIF('CAP23-24'!$B:$H,Insumo[[#This Row],[DESCRIPCION]],'CAP23-24'!$H:$H) -> 0 | O102: =SUMIF('CAP25'!$B:$H,Insumo[[#This Row],[DESCRIPCION]],'CAP25'!$H:$H) -> 0 | P102: =SUMIF('CAP26-28'!$B:$H,Insumo[[#This Row],[DESCRIPCION]],'CAP26-28'!$H:$H) -> 0 | Q102: =SUMIF('CAP29'!$B:$H,Insumo[[#This Row],[DESCRIPCION]],'CAP29'!$H:$H) -> 0 | R102: GyJ Web abr 2025 | T102: 3078
A103: Anticorrosivo | B103: galón | C103: =T103*$T$3 -> 97886.25 | D103: {=IF(Insumo[[#This Row],[VALOR]]=0,Insumo[TOTAL],E103/C103)} -> 0 | E103: =SUM(Insumo[[#This Row],[CAP1-3]:[CAP29]]) -> 0 | F103: =SUMIF('CAP1-3'!$B:$H,Insumo[[#This Row],[DESCRIPCION]],'CAP1-3'!$H:$H) -> 0 | G103: =SUMIF('CAP4-5'!$B:$H,Insumo[[#This Row],[DESCRIPCION]],'CAP4-5'!$H:$H) -> 0 | H103: =SUMIF('CAP6-7'!$B:$H,Insumo[[#This Row],[DESCRIPCION]],'CAP6-7'!$H:$H) -> 0 | I103: =SUMIF('CAP8'!$B:$H,Insumo[[#This Row],[DESCRIPCION]],'CAP8'!$H:$H) -> 0 | J103: =SUMIF('CAP9-13'!$B:$H,Insumo[[#This Row],[DESCRIPCION]],'CAP9-13'!$H:$H) -> 0 | K103: =SUMIF('CAP14-15'!$B:$H,Insumo[[#This Row],[DESCRIPCION]],'CAP14-15'!$H:$H) -> 0 | L103: =SUMIF('CAP16-18'!$B:$H,Insumo[[#This Row],[DESCRIPCION]],'CAP16-18'!$H:$H) -> 0 | M103: =SUMIF('CAP19-22'!$B:$H,Insumo[[#This Row],[DESCRIPCION]],'CAP19-22'!$H:$H) -> 0 | N103: =SUMIF('CAP23-24'!$B:$H,Insumo[[#This Row],[DESCRIPCION]],'CAP23-24'!$H:$H) -> 0 | O103: =SUMIF('CAP25'!$B:$H,Insumo[[#This Row],[DESCRIPCION]],'CAP25'!$H:$H) -> 0 | P103: =SUMIF('CAP26-28'!$B:$H,Insumo[[#This Row],[DESCRIPCION]],'CAP26-28'!$H:$H) -> 0 | Q103: =SUMIF('CAP29'!$B:$H,Insumo[[#This Row],[DESCRIPCION]],'CAP29'!$H:$H) -> 0 | T103: 93225
A104: Antisol blanco o similar | B104: Kg | C104: =T104*$T$3 -> 14812.35 | D104: {=IF(Insumo[[#This Row],[VALOR]]=0,Insumo[TOTAL],E104/C104)} -> 0 | E104: =SUM(Insumo[[#This Row],[CAP1-3]:[CAP29]]) -> 0 | F104: =SUMIF('CAP1-3'!$B:$H,Insumo[[#This Row],[DESCRIPCION]],'CAP1-3'!$H:$H) -> 0 | G104: =SUMIF('CAP4-5'!$B:$H,Insumo[[#This Row],[DESCRIPCION]],'CAP4-5'!$H:$H) -> 0 | H104: =SUMIF('CAP6-7'!$B:$H,Insumo[[#This Row],[DESCRIPCION]],'CAP6-7'!$H:$H) -> 0 | I104: =SUMIF('CAP8'!$B:$H,Insumo[[#This Row],[DESCRIPCION]],'CAP8'!$H:$H) -> 0 | J104: =SUMIF('CAP9-13'!$B:$H,Insumo[[#This Row],[DESCRIPCION]],'CAP9-13'!$H:$H) -> 0 | K104: =SUMIF('CAP14-15'!$B:$H,Insumo[[#This Row],[DESCRIPCION]],'CAP14-15'!$H:$H) -> 0 | L104: =SUMIF('CAP16-18'!$B:$H,Insumo[[#This Row],[DESCRIPCION]],'CAP16-18'!$H:$H) -> 0 | M104: =SUMIF('CAP19-22'!$B:$H,Insumo[[#This Row],[DESCRIPCION]],'CAP19-22'!$H:$H) -> 0 | N104: =SUMIF('CAP23-24'!$B:$H,Insumo[[#This Row],[DESCRIPCION]],'CAP23-24'!$H:$H) -> 0 | O104: =SUMIF('CAP25'!$B:$H,Insumo[[#This Row],[DESCRIPCION]],'CAP25'!$H:$H) -> 0 | P104: =SUMIF('CAP26-28'!$B:$H,Insumo[[#This Row],[DESCRIPCION]],'CAP26-28'!$H:$H) -> 0 | Q104: =SUMIF('CAP29'!$B:$H,Insumo[[#This Row],[DESCRIPCION]],'CAP29'!$H:$H) -> 0 | T104: 14107
A105: Arandela de Neopreno | B105: Un | C105: =T105*$T$3 -> 1137.15 | D105: {=IF(Insumo[[#This Row],[VALOR]]=0,Insumo[TOTAL],E105/C105)} -> 0 | E105: =SUM(Insumo[[#This Row],[CAP1-3]:[CAP29]]) -> 0 | F105: =SUMIF('CAP1-3'!$B:$H,Insumo[[#This Row],[DESCRIPCION]],'CAP1-3'!$H:$H) -> 0 | G105: =SUMIF('CAP4-5'!$B:$H,Insumo[[#This Row],[DESCRIPCION]],'CAP4-5'!$H:$H) -> 0 | H105: =SUMIF('CAP6-7'!$B:$H,Insumo[[#This Row],[DESCRIPCION]],'CAP6-7'!$H:$H) -> 0 | I105: =SUMIF('CAP8'!$B:$H,Insumo[[#This Row],[DESCRIPCION]],'CAP8'!$H:$H) -> 0 | J105: =SUMIF('CAP9-13'!$B:$H,Insumo[[#This Row],[DESCRIPCION]],'CAP9-13'!$H:$H) -> 0 | K105: =SUMIF('CAP14-15'!$B:$H,Insumo[[#This Row],[DESCRIPCION]],'CAP14-15'!$H:$H) -> 0 | L105: =SUMIF('CAP16-18'!$B:$H,Insumo[[#This Row],[DESCRIPCION]],'CAP16-18'!$H:$H) -> 0 | M105: =SUMIF('CAP19-22'!$B:$H,Insumo[[#This Row],[DESCRIPCION]],'CAP19-22'!$H:$H) -> 0 | N105: =SUMIF('CAP23-24'!$B:$H,Insumo[[#This Row],[DESCRIPCION]],'CAP23-24'!$H:$H) -> 0 | O105: =SUMIF('CAP25'!$B:$H,Insumo[[#This Row],[DESCRIPCION]],'CAP25'!$H:$H) -> 0 | P105: =SUMIF('CAP26-28'!$B:$H,Insumo[[#This Row],[DESCRIPCION]],'CAP26-28'!$H:$H) -> 0 | Q105: =SUMIF('CAP29'!$B:$H,Insumo[[#This Row],[DESCRIPCION]],'CAP29'!$H:$H) -> 0 | T105: 1083
A106: Arbol H>0,50 m y <3,00 m | B106: Un | C106: =T106*$T$3 -> 147761.25 | D106: {=IF(Insumo[[#This Row],[VALOR]]=0,Insumo[TOTAL],E106/C106)} -> 0 | E106: =SUM(Insumo[[#This Row],[CAP1-3]:[CAP29]]) -> 0 | F106: =SUMIF('CAP1-3'!$B:$H,Insumo[[#This Row],[DESCRIPCION]],'CAP1-3'!$H:$H) -> 0 | G106: =SUMIF('CAP4-5'!$B:$H,Insumo[[#This Row],[DESCRIPCION]],'CAP4-5'!$H:$H) -> 0 | H106: =SUMIF('CAP6-7'!$B:$H,Insumo[[#This Row],[DESCRIPCION]],'CAP6-7'!$H:$H) -> 0 | I106: =SUMIF('CAP8'!$B:$H,Insumo[[#This Row],[DESCRIPCION]],'CAP8'!$H:$H) -> 0 | J106: =SUMIF('CAP9-13'!$B:$H,Insumo[[#This Row],[DESCRIPCION]],'CAP9-13'!$H:$H) -> 0 | K106: =SUMIF('CAP14-15'!$B:$H,Insumo[[#This Row],[DESCRIPCION]],'CAP14-15'!$H:$H) -> 0 | L106: =SUMIF('CAP16-18'!$B:$H,Insumo[[#This Row],[DESCRIPCION]],'CAP16-18'!$H:$H) -> 0 | M106: =SUMIF('CAP19-22'!$B:$H,Insumo[[#This Row],[DESCRIPCION]],'CAP19-22'!$H:$H) -> 0 | N106: =SUMIF('CAP23-24'!$B:$H,Insumo[[#This Row],[DESCRIPCION]],'CAP23-24'!$H:$H) -> 0 | O106: =SUMIF('CAP25'!$B:$H,Insumo[[#This Row],[DESCRIPCION]],'CAP25'!$H:$H) -> 0 | P106: =SUMIF('CAP26-28'!$B:$H,Insumo[[#This Row],[DESCRIPCION]],'CAP26-28'!$H:$H) -> 0 | Q106: =SUMIF('CAP29'!$B:$H,Insumo[[#This Row],[DESCRIPCION]],'CAP29'!$H:$H) -> 0 | T106: 140725
A107: Arbol Hmin>=3,00 m | B107: Un | C107: =T107*$T$3 -> 170493.75 | D107: {=IF(Insumo[[#This Row],[VALOR]]=0,Insumo[TOTAL],E107/C107)} -> 0 | E107: =SUM(Insumo[[#This Row],[CAP1-3]:[CAP29]]) -> 0 | F107: =SUMIF('CAP1-3'!$B:$H,Insumo[[#This Row],[DESCRIPCION]],'CAP1-3'!$H:$H) -> 0 | G107: =SUMIF('CAP4-5'!$B:$H,Insumo[[#This Row],[DESCRIPCION]],'CAP4-5'!$H:$H) -> 0 | H107: =SUMIF('CAP6-7'!$B:$H,Insumo[[#This Row],[DESCRIPCION]],'CAP6-7'!$H:$H) -> 0 | I107: =SUMIF('CAP8'!$B:$H,Insumo[[#This Row],[DESCRIPCION]],'CAP8'!$H:$H) -> 0 | J107: =SUMIF('CAP9-13'!$B:$H,Insumo[[#This Row],[DESCRIPCION]],'CAP9-13'!$H:$H) -> 0 | K107: =SUMIF('CAP14-15'!$B:$H,Insumo[[#This Row],[DESCRIPCION]],'CAP14-15'!$H:$H) -> 0 | L107: =SUMIF('CAP16-18'!$B:$H,Insumo[[#This Row],[DESCRIPCION]],'CAP16-18'!$H:$H) -> 0 | M107: =SUMIF('CAP19-22'!$B:$H,Insumo[[#This Row],[DESCRIPCION]],'CAP19-22'!$H:$H) -> 0 | N107: =SUMIF('CAP23-24'!$B:$H,Insumo[[#This Row],[DESCRIPCION]],'CAP23-24'!$H:$H) -> 0 | O107: =SUMIF('CAP25'!$B:$H,Insumo[[#This Row],[DESCRIPCION]],'CAP25'!$H:$H) -> 0 | P107: =SUMIF('CAP26-28'!$B:$H,Insumo[[#This Row],[DESCRIPCION]],'CAP26-28'!$H:$H) -> 0 | Q107: =SUMIF('CAP29'!$B:$H,Insumo[[#This Row],[DESCRIPCION]],'CAP29'!$H:$H) -> 0 | T107: 162375
A108: Arena | B108: M3 | C108: =T108*$T$3 -> 81268.95 | D108: {=IF(Insumo[[#This Row],[VALOR]]=0,Insumo[TOTAL],E108/C108)} -> 0 | E108: =SUM(Insumo[[#This Row],[CAP1-3]:[CAP29]]) -> 0 | F108: =SUMIF('CAP1-3'!$B:$H,Insumo[[#This Row],[DESCRIPCION]],'CAP1-3'!$H:$H) -> 0 | G108: =SUMIF('CAP4-5'!$B:$H,Insumo[[#This Row],[DESCRIPCION]],'CAP4-5'!$H:$H) -> 0 | H108: =SUMIF('CAP6-7'!$B:$H,Insumo[[#This Row],[DESCRIPCION]],'CAP6-7'!$H:$H) -> 0 | I108: =SUMIF('CAP8'!$B:$H,Insumo[[#This Row],[DESCRIPCION]],'CAP8'!$H:$H) -> 0 | J108: =SUMIF('CAP9-13'!$B:$H,Insumo[[#This Row],[DESCRIPCION]],'CAP9-13'!$H:$H) -> 0 | K108: =SUMIF('CAP14-15'!$B:$H,Insumo[[#This Row],[DESCRIPCION]],'CAP14-15'!$H:$H) -> 0 | L108: =SUMIF('CAP16-18'!$B:$H,Insumo[[#This Row],[DESCRIPCION]],'CAP16-18'!$H:$H) -> 0 | M108: =SUMIF('CAP19-22'!$B:$H,Insumo[[#This Row],[DESCRIPCION]],'CAP19-22'!$H:$H) -> 0 | N108: =SUMIF('CAP23-24'!$B:$H,Insumo[[#This Row],[DESCRIPCION]],'CAP23-24'!$H:$H) -> 0 | O108: =SUMIF('CAP25'!$B:$H,Insumo[[#This Row],[DESCRIPCION]],'CAP25'!$H:$H) -> 0 | P108: =SUMIF('CAP26-28'!$B:$H,Insumo[[#This Row],[DESCRIPCION]],'CAP26-28'!$H:$H) -> 0 | Q108: =SUMIF('CAP29'!$B:$H,Insumo[[#This Row],[DESCRIPCION]],'CAP29'!$H:$H) -> 0 | T108: 77399
A109: Arena de Pega (Media de Rio) | B109: M3 | C109: =T109*$T$3 -> 81268.95 | D109: {=IF(Insumo[[#This Row],[VALOR]]=0,Insumo[TOTAL],E109/C109)} -> 0 | E109: =SUM(Insumo[[#This Row],[CAP1-3]:[CAP29]]) -> 0 | F109: =SUMIF('CAP1-3'!$B:$H,Insumo[[#This Row],[DESCRIPCION]],'CAP1-3'!$H:$H) -> 0 | G109: =SUMIF('CAP4-5'!$B:$H,Insumo[[#This Row],[DESCRIPCION]],'CAP4-5'!$H:$H) -> 0 | H109: =SUMIF('CAP6-7'!$B:$H,Insumo[[#This Row],[DESCRIPCION]],'CAP6-7'!$H:$H) -> 0 | I109: =SUMIF('CAP8'!$B:$H,Insumo[[#This Row],[DESCRIPCION]],'CAP8'!$H:$H) -> 0 | J109: =SUMIF('CAP9-13'!$B:$H,Insumo[[#This Row],[DESCRIPCION]],'CAP9-13'!$H:$H) -> 0 | K109: =SUMIF('CAP14-15'!$B:$H,Insumo[[#This Row],[DESCRIPCION]],'CAP14-15'!$H:$H) -> 0 | L109: =SUMIF('CAP16-18'!$B:$H,Insumo[[#This Row],[DESCRIPCION]],'CAP16-18'!$H:$H) -> 0 | M109: =SUMIF('CAP19-22'!$B:$H,Insumo[[#This Row],[DESCRIPCION]],'CAP19-22'!$H:$H) -> 0 | N109: =SUMIF('CAP23-24'!$B:$H,Insumo[[#This Row],[DESCRIPCION]],'CAP23-24'!$H:$H) -> 0 | O109: =SUMIF('CAP25'!$B:$H,Insumo[[#This Row],[DESCRIPCION]],'CAP25'!$H:$H) -> 0 | P109: =SUMIF('CAP26-28'!$B:$H,Insumo[[#This Row],[DESCRIPCION]],'CAP26-28'!$H:$H) -> 0 | Q109: =SUMIF('CAP29'!$B:$H,Insumo[[#This Row],[DESCRIPCION]],'CAP29'!$H:$H) -> 0 | T109: 77399
A110: Arena de río | B110: M3 | C110: =T110*$T$3 -> 81268.95 | D110: {=IF(Insumo[[#This Row],[VALOR]]=0,Insumo[TOTAL],E110/C110)} -> 0 | E110: =SUM(Insumo[[#This Row],[CAP1-3]:[CAP29]]) -> 0 | F110: =SUMIF('CAP1-3'!$B:$H,Insumo[[#This Row],[DESCRIPCION]],'CAP1-3'!$H:$H) -> 0 | G110: =SUMIF('CAP4-5'!$B:$H,Insumo[[#This Row],[DESCRIPCION]],'CAP4-5'!$H:$H) -> 0 | H110: =SUMIF('CAP6-7'!$B:$H,Insumo[[#This Row],[DESCRIPCION]],'CAP6-7'!$H:$H) -> 0 | I110: =SUMIF('CAP8'!$B:$H,Insumo[[#This Row],[DESCRIPCION]],'CAP8'!$H:$H) -> 0 | J110: =SUMIF('CAP9-13'!$B:$H,Insumo[[#This Row],[DESCRIPCION]],'CAP9-13'!$H:$H) -> 0 | K110: =SUMIF('CAP14-15'!$B:$H,Insumo[[#This Row],[DESCRIPCION]],'CAP14-15'!$H:$H) -> 0 | L110: =SUMIF('CAP16-18'!$B:$H,Insumo[[#This Row],[DESCRIPCION]],'CAP16-18'!$H:$H) -> 0 | M110: =SUMIF('CAP19-22'!$B:$H,Insumo[[#This Row],[DESCRIPCION]],'CAP19-22'!$H:$H) -> 0 | N110: =SUMIF('CAP23-24'!$B:$H,Insumo[[#This Row],[DESCRIPCION]],'CAP23-24'!$H:$H) -> 0 | O110: =SUMIF('CAP25'!$B:$H,Insumo[[#This Row],[DESCRIPCION]],'CAP25'!$H:$H) -> 0 | P110: =SUMIF('CAP26-28'!$B:$H,Insumo[[#This Row],[DESCRIPCION]],'CAP26-28'!$H:$H) -> 0 | Q110: =SUMIF('CAP29'!$B:$H,Insumo[[#This Row],[DESCRIPCION]],'CAP29'!$H:$H) -> 0 | T110: 77399
A111: Arenón | B111: M3 | C111: =T111*$T$3 -> 81268.95 | D111: {=IF(Insumo[[#This Row],[VALOR]]=0,Insumo[TOTAL],E111/C111)} -> 0 | E111: =SUM(Insumo[[#This Row],[CAP1-3]:[CAP29]]) -> 0 | F111: =SUMIF('CAP1-3'!$B:$H,Insumo[[#This Row],[DESCRIPCION]],'CAP1-3'!$H:$H) -> 0 | G111: =SUMIF('CAP4-5'!$B:$H,Insumo[[#This Row],[DESCRIPCION]],'CAP4-5'!$H:$H) -> 0 | H111: =SUMIF('CAP6-7'!$B:$H,Insumo[[#This Row],[DESCRIPCION]],'CAP6-7'!$H:$H) -> 0 | I111: =SUMIF('CAP8'!$B:$H,Insumo[[#This Row],[DESCRIPCION]],'CAP8'!$H:$H) -> 0 | J111: =SUMIF('CAP9-13'!$B:$H,Insumo[[#This Row],[DESCRIPCION]],'CAP9-13'!$H:$H) -> 0 | K111: =SUMIF('CAP14-15'!$B:$H,Insumo[[#This Row],[DESCRIPCION]],'CAP14-15'!$H:$H) -> 0 | L111: =SUMIF('CAP16-18'!$B:$H,Insumo[[#This Row],[DESCRIPCION]],'CAP16-18'!$H:$H) -> 0 | M111: =SUMIF('CAP19-22'!$B:$H,Insumo[[#This Row],[DESCRIPCION]],'CAP19-22'!$H:$H) -> 0 | N111: =SUMIF('CAP23-24'!$B:$H,Insumo[[#This Row],[DESCRIPCION]],'CAP23-24'!$H:$H) -> 0 | O111: =SUMIF('CAP25'!$B:$H,Insumo[[#This Row],[DESCRIPCION]],'CAP25'!$H:$H) -> 0 | P111: =SUMIF('CAP26-28'!$B:$H,Insumo[[#This Row],[DESCRIPCION]],'CAP26-28'!$H:$H) -> 0 | Q111: =SUMIF('CAP29'!$B:$H,Insumo[[#This Row],[DESCRIPCION]],'CAP29'!$H:$H) -> 0 | T111: 77399
A112: Arenón triturado de cantera | B112: M3 | C112: =T112*$T$3 -> 79563.75 | D112: {=IF(Insumo[[#This Row],[VALOR]]=0,Insumo[TOTAL],E112/C112)} -> 0 | E112: =SUM(Insumo[[#This Row],[CAP1-3]:[CAP29]]) -> 0 | F112: =SUMIF('CAP1-3'!$B:$H,Insumo[[#This Row],[DESCRIPCION]],'CAP1-3'!$H:$H) -> 0 | G112: =SUMIF('CAP4-5'!$B:$H,Insumo[[#This Row],[DESCRIPCION]],'CAP4-5'!$H:$H) -> 0 | H112: =SUMIF('CAP6-7'!$B:$H,Insumo[[#This Row],[DESCRIPCION]],'CAP6-7'!$H:$H) -> 0 | I112: =SUMIF('CAP8'!$B:$H,Insumo[[#This Row],[DESCRIPCION]],'CAP8'!$H:$H) -> 0 | J112: =SUMIF('CAP9-13'!$B:$H,Insumo[[#This Row],[DESCRIPCION]],'CAP9-13'!$H:$H) -> 0 | K112: =SUMIF('CAP14-15'!$B:$H,Insumo[[#This Row],[DESCRIPCION]],'CAP14-15'!$H:$H) -> 0 | L112: =SUMIF('CAP16-18'!$B:$H,Insumo[[#This Row],[DESCRIPCION]],'CAP16-18'!$H:$H) -> 0 | M112: =SUMIF('CAP19-22'!$B:$H,Insumo[[#This Row],[DESCRIPCION]],'CAP19-22'!$H:$H) -> 0 | N112: =SUMIF('CAP23-24'!$B:$H,Insumo[[#This Row],[DESCRIPCION]],'CAP23-24'!$H:$H) -> 0 | O112: =SUMIF('CAP25'!$B:$H,Insumo[[#This Row],[DESCRIPCION]],'CAP25'!$H:$H) -> 0 | P112: =SUMIF('CAP26-28'!$B:$H,Insumo[[#This Row],[DESCRIPCION]],'CAP26-28'!$H:$H) -> 0 | Q112: =SUMIF('CAP29'!$B:$H,Insumo[[#This Row],[DESCRIPCION]],'CAP29'!$H:$H) -> 0 | T112: 75775
A113: Aro base y aro tapa de H. F. d = 0,60 m | B113: Un | C113: =T113*$T$3 -> 284997.3 | D113: {=IF(Insumo[[#This Row],[VALOR]]=0,Insumo[TOTAL],E113/C113)} -> 0 | E113: =SUM(Insumo[[#This Row],[CAP1-3]:[CAP29]]) -> 0 | F113: =SUMIF('CAP1-3'!$B:$H,Insumo[[#This Row],[DESCRIPCION]],'CAP1-3'!$H:$H) -> 0 | G113: =SUMIF('CAP4-5'!$B:$H,Insumo[[#This Row],[DESCRIPCION]],'CAP4-5'!$H:$H) -> 0 | H113: =SUMIF('CAP6-7'!$B:$H,Insumo[[#This Row],[DESCRIPCION]],'CAP6-7'!$H:$H) -> 0 | I113: =SUMIF('CAP8'!$B:$H,Insumo[[#This Row],[DESCRIPCION]],'CAP8'!$H:$H) -> 0 | J113: =SUMIF('CAP9-13'!$B:$H,Insumo[[#This Row],[DESCRIPCION]],'CAP9-13'!$H:$H) -> 0 | K113: =SUMIF('CAP14-15'!$B:$H,Insumo[[#This Row],[DESCRIPCION]],'CAP14-15'!$H:$H) -> 0 | L113: =SUMIF('CAP16-18'!$B:$H,Insumo[[#This Row],[DESCRIPCION]],'CAP16-18'!$H:$H) -> 0 | M113: =SUMIF('CAP19-22'!$B:$H,Insumo[[#This Row],[DESCRIPCION]],'CAP19-22'!$H:$H) -> 0 | N113: =SUMIF('CAP23-24'!$B:$H,Insumo[[#This Row],[DESCRIPCION]],'CAP23-24'!$H:$H) -> 0 | O113: =SUMIF('CAP25'!$B:$H,Insumo[[#This Row],[DESCRIPCION]],'CAP25'!$H:$H) -> 0 | P113: =SUMIF('CAP26-28'!$B:$H,Insumo[[#This Row],[DESCRIPCION]],'CAP26-28'!$H:$H) -> 0 | Q113: =SUMIF('CAP29'!$B:$H,Insumo[[#This Row],[DESCRIPCION]],'CAP29'!$H:$H) -> 0 | T113: 271426
A114: Aro para baloncesto, incluye malla | B114: Un | C114: =T114*$T$3 -> 451245.9 | D114: {=IF(Insumo[[#This Row],[VALOR]]=0,Insumo[TOTAL],E114/C114)} -> 0 | E114: =SUM(Insumo[[#This Row],[CAP1-3]:[CAP29]]) -> 0 | F114: =SUMIF('CAP1-3'!$B:$H,Insumo[[#This Row],[DESCRIPCION]],'CAP1-3'!$H:$H) -> 0 | G114: =SUMIF('CAP4-5'!$B:$H,Insumo[[#This Row],[DESCRIPCION]],'CAP4-5'!$H:$H) -> 0 | H114: =SUMIF('CAP6-7'!$B:$H,Insumo[[#This Row],[DESCRIPCION]],'CAP6-7'!$H:$H) -> 0 | I114: =SUMIF('CAP8'!$B:$H,Insumo[[#This Row],[DESCRIPCION]],'CAP8'!$H:$H) -> 0 | J114: =SUMIF('CAP9-13'!$B:$H,Insumo[[#This Row],[DESCRIPCION]],'CAP9-13'!$H:$H) -> 0 | K114: =SUMIF('CAP14-15'!$B:$H,Insumo[[#This Row],[DESCRIPCION]],'CAP14-15'!$H:$H) -> 0 | L114: =SUMIF('CAP16-18'!$B:$H,Insumo[[#This Row],[DESCRIPCION]],'CAP16-18'!$H:$H) -> 0 | M114: =SUMIF('CAP19-22'!$B:$H,Insumo[[#This Row],[DESCRIPCION]],'CAP19-22'!$H:$H) -> 0 | N114: =SUMIF('CAP23-24'!$B:$H,Insumo[[#This Row],[DESCRIPCION]],'CAP23-24'!$H:$H) -> 0 | O114: =SUMIF('CAP25'!$B:$H,Insumo[[#This Row],[DESCRIPCION]],'CAP25'!$H:$H) -> 0 | P114: =SUMIF('CAP26-28'!$B:$H,Insumo[[#This Row],[DESCRIPCION]],'CAP26-28'!$H:$H) -> 0 | Q114: =SUMIF('CAP29'!$B:$H,Insumo[[#This Row],[DESCRIPCION]],'CAP29'!$H:$H) -> 0 | T114: 429758
... A165: Brocha 4" | B165: Un | C165: =T165*$T$3 -> 17049.9 | D165: {=IF(Insumo[[#This Row],[VALOR]]=0,Insumo[TOTAL],E165/C165)} -> 0 | E165: =SUM(Insumo[[#This Row],[CAP1-3]:[CAP29]]) -> 0 | F165: =SUMIF('CAP1-3'!$B:$H,Insumo[[#This Row],[DESCRIPCION]],'CAP1-3'!$H:$H) -> 0 | G165: =SUMIF('CAP4-5'!$B:$H,Insumo[[#This Row],[DESCRIPCION]],'CAP4-5'!$H:$H) -> 0 | H165: =SUMIF('CAP6-7'!$B:$H,Insumo[[#This Row],[DESCRIPCION]],'CAP6-7'!$H:$H) -> 0 | I165: =SUMIF('CAP8'!$B:$H,Insumo[[#This Row],[DESCRIPCION]],'CAP8'!$H:$H) -> 0 | J165: =SUMIF('CAP9-13'!$B:$H,Insumo[[#This Row],[DESCRIPCION]],'CAP9-13'!$H:$H) -> 0 | K165: =SUMIF('CAP14-15'!$B:$H,Insumo[[#This Row],[DESCRIPCION]],'CAP14-15'!$H:$H) -> 0 | L165: =SUMIF('CAP16-18'!$B:$H,Insumo[[#This Row],[DESCRIPCION]],'CAP16-18'!$H:$H) -> 0 | M165: =SUMIF('CAP19-22'!$B:$H,Insumo[[#This Row],[DESCRIPCION]],'CAP19-22'!$H:$H) -> 0 | N165: =SUMIF('CAP23-24'!$B:$H,Insumo[[#This Row],[DESCRIPCION]],'CAP23-24'!$H:$H) -> 0 | O165: =SUMIF('CAP25'!$B:$H,Insumo[[#This Row],[DESCRIPCION]],'CAP25'!$H:$H) -> 0 | P165: =SUMIF('CAP26-28'!$B:$H,Insumo[[#This Row],[DESCRIPCION]],'CAP26-28'!$H:$H) -> 0 | Q165: =SUMIF('CAP29'!$B:$H,Insumo[[#This Row],[DESCRIPCION]],'CAP29'!$H:$H) -> 0 | T165: 16238
A166: Caballete teja ondulada fibrocemento fijo l = 0,873 m | B166: Un | C166: =T166*$T$3 -> 45351.6 | D166: {=IF(Insumo[[#This Row],[VALOR]]=0,Insumo[TOTAL],E166/C166)} -> 0 | E166: =SUM(Insumo[[#This Row],[CAP1-3]:[CAP29]]) -> 0 | F166: =SUMIF('CAP1-3'!$B:$H,Insumo[[#This Row],[DESCRIPCION]],'CAP1-3'!$H:$H) -> 0 | G166: =SUMIF('CAP4-5'!$B:$H,Insumo[[#This Row],[DESCRIPCION]],'CAP4-5'!$H:$H) -> 0 | H166: =SUMIF('CAP6-7'!$B:$H,Insumo[[#This Row],[DESCRIPCION]],'CAP6-7'!$H:$H) -> 0 | I166: =SUMIF('CAP8'!$B:$H,Insumo[[#This Row],[DESCRIPCION]],'CAP8'!$H:$H) -> 0 | J166: =SUMIF('CAP9-13'!$B:$H,Insumo[[#This Row],[DESCRIPCION]],'CAP9-13'!$H:$H) -> 0 | K166: =SUMIF('CAP14-15'!$B:$H,Insumo[[#This Row],[DESCRIPCION]],'CAP14-15'!$H:$H) -> 0 | L166: =SUMIF('CAP16-18'!$B:$H,Insumo[[#This Row],[DESCRIPCION]],'CAP16-18'!$H:$H) -> 0 | M166: =SUMIF('CAP19-22'!$B:$H,Insumo[[#This Row],[DESCRIPCION]],'CAP19-22'!$H:$H) -> 0 | N166: =SUMIF('CAP23-24'!$B:$H,Insumo[[#This Row],[DESCRIPCION]],'CAP23-24'!$H:$H) -> 0 | O166: =SUMIF('CAP25'!$B:$H,Insumo[[#This Row],[DESCRIPCION]],'CAP25'!$H:$H) -> 0 | P166: =SUMIF('CAP26-28'!$B:$H,Insumo[[#This Row],[DESCRIPCION]],'CAP26-28'!$H:$H) -> 0 | Q166: =SUMIF('CAP29'!$B:$H,Insumo[[#This Row],[DESCRIPCION]],'CAP29'!$H:$H) -> 0 | R166: Homecenter febrero 2025 | T166: 43192
A167: Caballete teja ondulada fibrocemento tipo español articulado ambos | B167: Un | C167: =T167*$T$3 -> 45351.6 | D167: {=IF(Insumo[[#This Row],[VALOR]]=0,Insumo[TOTAL],E167/C167)} -> 0 | E167: =SUM(Insumo[[#This Row],[CAP1-3]:[CAP29]]) -> 0 | F167: =SUMIF('CAP1-3'!$B:$H,Insumo[[#This Row],[DESCRIPCION]],'CAP1-3'!$H:$H) -> 0 | G167: =SUMIF('CAP4-5'!$B:$H,Insumo[[#This Row],[DESCRIPCION]],'CAP4-5'!$H:$H) -> 0 | H167: =SUMIF('CAP6-7'!$B:$H,Insumo[[#This Row],[DESCRIPCION]],'CAP6-7'!$H:$H) -> 0 | I167: =SUMIF('CAP8'!$B:$H,Insumo[[#This Row],[DESCRIPCION]],'CAP8'!$H:$H) -> 0 | J167: =SUMIF('CAP9-13'!$B:$H,Insumo[[#This Row],[DESCRIPCION]],'CAP9-13'!$H:$H) -> 0 | K167: =SUMIF('CAP14-15'!$B:$H,Insumo[[#This Row],[DESCRIPCION]],'CAP14-15'!$H:$H) -> 0 | L167: =SUMIF('CAP16-18'!$B:$H,Insumo[[#This Row],[DESCRIPCION]],'CAP16-18'!$H:$H) -> 0 | M167: =SUMIF('CAP19-22'!$B:$H,Insumo[[#This Row],[DESCRIPCION]],'CAP19-22'!$H:$H) -> 0 | N167: =SUMIF('CAP23-24'!$B:$H,Insumo[[#This Row],[DESCRIPCION]],'CAP23-24'!$H:$H) -> 0 | O167: =SUMIF('CAP25'!$B:$H,Insumo[[#This Row],[DESCRIPCION]],'CAP25'!$H:$H) -> 0 | P167: =SUMIF('CAP26-28'!$B:$H,Insumo[[#This Row],[DESCRIPCION]],'CAP26-28'!$H:$H) -> 0 | Q167: =SUMIF('CAP29'!$B:$H,Insumo[[#This Row],[DESCRIPCION]],'CAP29'!$H:$H) -> 0 | T167: 43192
A168: Caballete teja ondulada transparente | B168: Un | C168: =T168*$T$3 -> 51148.65 | D168: {=IF(Insumo[[#This Row],[VALOR]]=0,Insumo[TOTAL],E168/C168)} -> 0 | E168: =SUM(Insumo[[#This Row],[CAP1-3]:[CAP29]]) -> 0 | F168: =SUMIF('CAP1-3'!$B:$H,Insumo[[#This Row],[DESCRIPCION]],'CAP1-3'!$H:$H) -> 0 | G168: =SUMIF('CAP4-5'!$B:$H,Insumo[[#This Row],[DESCRIPCION]],'CAP4-5'!$H:$H) -> 0 | H168: =SUMIF('CAP6-7'!$B:$H,Insumo[[#This Row],[DESCRIPCION]],'CAP6-7'!$H:$H) -> 0 | I168: =SUMIF('CAP8'!$B:$H,Insumo[[#This Row],[DESCRIPCION]],'CAP8'!$H:$H) -> 0 | J168: =SUMIF('CAP9-13'!$B:$H,Insumo[[#This Row],[DESCRIPCION]],'CAP9-13'!$H:$H) -> 0 | K168: =SUMIF('CAP14-15'!$B:$H,Insumo[[#This Row],[DESCRIPCION]],'CAP14-15'!$H:$H) -> 0 | L168: =SUMIF('CAP16-18'!$B:$H,Insumo[[#This Row],[DESCRIPCION]],'CAP16-18'!$H:$H) -> 0 | M168: =SUMIF('CAP19-22'!$B:$H,Insumo[[#This Row],[DESCRIPCION]],'CAP19-22'!$H:$H) -> 0 | N168: =SUMIF('CAP23-24'!$B:$H,Insumo[[#This Row],[DESCRIPCION]],'CAP23-24'!$H:$H) -> 0 | O168: =SUMIF('CAP25'!$B:$H,Insumo[[#This Row],[DESCRIPCION]],'CAP25'!$H:$H) -> 0 | P168: =SUMIF('CAP26-28'!$B:$H,Insumo[[#This Row],[DESCRIPCION]],'CAP26-28'!$H:$H) -> 0 | Q168: =SUMIF('CAP29'!$B:$H,Insumo[[#This Row],[DESCRIPCION]],'CAP29'!$H:$H) -> 0 | T168: 48713
A169: Caballete termoacustica | B169: Un | C169: =T169*$T$3 -> 56717.85 | D169: {=IF(Insumo[[#This Row],[VALOR]]=0,Insumo[TOTAL],E169/C169)} -> 0 | E169: =SUM(Insumo[[#This Row],[CAP1-3]:[CAP29]]) -> 0 | F169: =SUMIF('CAP1-3'!$B:$H,Insumo[[#This Row],[DESCRIPCION]],'CAP1-3'!$H:$H) -> 0 | G169: =SUMIF('CAP4-5'!$B:$H,Insumo[[#This Row],[DESCRIPCION]],'CAP4-5'!$H:$H) -> 0 | H169: =SUMIF('CAP6-7'!$B:$H,Insumo[[#This Row],[DESCRIPCION]],'CAP6-7'!$H:$H) -> 0 | I169: =SUMIF('CAP8'!$B:$H,Insumo[[#This Row],[DESCRIPCION]],'CAP8'!$H:$H) -> 0 | J169: =SUMIF('CAP9-13'!$B:$H,Insumo[[#This Row],[DESCRIPCION]],'CAP9-13'!$H:$H) -> 0 | K169: =SUMIF('CAP14-15'!$B:$H,Insumo[[#This Row],[DESCRIPCION]],'CAP14-15'!$H:$H) -> 0 | L169: =SUMIF('CAP16-18'!$B:$H,Insumo[[#This Row],[DESCRIPCION]],'CAP16-18'!$H:$H) -> 0 | M169: =SUMIF('CAP19-22'!$B:$H,Insumo[[#This Row],[DESCRIPCION]],'CAP19-22'!$H:$H) -> 0 | N169: =SUMIF('CAP23-24'!$B:$H,Insumo[[#This Row],[DESCRIPCION]],'CAP23-24'!$H:$H) -> 0 | O169: =SUMIF('CAP25'!$B:$H,Insumo[[#This Row],[DESCRIPCION]],'CAP25'!$H:$H) -> 0 | P169: =SUMIF('CAP26-28'!$B:$H,Insumo[[#This Row],[DESCRIPCION]],'CAP26-28'!$H:$H) -> 0 | Q169: =SUMIF('CAP29'!$B:$H,Insumo[[#This Row],[DESCRIPCION]],'CAP29'!$H:$H) -> 0 | R169: Homecenter febrero 2025 | T169: 54017
A170: Cable 1/2" Alta resistencia instalado | B170: M | C170: =T170*$T$3 -> 12503.4 | D170: {=IF(Insumo[[#This Row],[VALOR]]=0,Insumo[TOTAL],E170/C170)} -> 0 | E170: =SUM(Insumo[[#This Row],[CAP1-3]:[CAP29]]) -> 0 | F170: =SUMIF('CAP1-3'!$B:$H,Insumo[[#This Row],[DESCRIPCION]],'CAP1-3'!$H:$H) -> 0 | G170: =SUMIF('CAP4-5'!$B:$H,Insumo[[#This Row],[DESCRIPCION]],'CAP4-5'!$H:$H) -> 0 | H170: =SUMIF('CAP6-7'!$B:$H,Insumo[[#This Row],[DESCRIPCION]],'CAP6-7'!$H:$H) -> 0 | I170: =SUMIF('CAP8'!$B:$H,Insumo[[#This Row],[DESCRIPCION]],'CAP8'!$H:$H) -> 0 | J170: =SUMIF('CAP9-13'!$B:$H,Insumo[[#This Row],[DESCRIPCION]],'CAP9-13'!$H:$H) -> 0 | K170: =SUMIF('CAP14-15'!$B:$H,Insumo[[#This Row],[DESCRIPCION]],'CAP14-15'!$H:$H) -> 0 | L170: =SUMIF('CAP16-18'!$B:$H,Insumo[[#This Row],[DESCRIPCION]],'CAP16-18'!$H:$H) -> 0 | M170: =SUMIF('CAP19-22'!$B:$H,Insumo[[#This Row],[DESCRIPCION]],'CAP19-22'!$H:$H) -> 0 | N170: =SUMIF('CAP23-24'!$B:$H,Insumo[[#This Row],[DESCRIPCION]],'CAP23-24'!$H:$H) -> 0 | O170: =SUMIF('CAP25'!$B:$H,Insumo[[#This Row],[DESCRIPCION]],'CAP25'!$H:$H) -> 0 | P170: =SUMIF('CAP26-28'!$B:$H,Insumo[[#This Row],[DESCRIPCION]],'CAP26-28'!$H:$H) -> 0 | Q170: =SUMIF('CAP29'!$B:$H,Insumo[[#This Row],[DESCRIPCION]],'CAP29'!$H:$H) -> 0 | T170: 11908
...

Sheet Equipo
A1: =Presupuesto!A1 -> ALCALDIA DE PEREIRA
A2: =Presupuesto!A2 -> VERSION O BASE DE DATOS ALCALDIA DE PEREIRA 2026
A3: LISTA DE EQUIPOS
A4: DESCRIPCION | B4: UND | C4: VALOR | D4: CANTIDAD | E4: TOTAL | F4: CAP1 | G4: CAP4 | H4: CAP6 | I4: CAP8 | J4: CAP9 | K4: CAP14 | L4: CAP17 | M4: CAP19 | N4: CAP23 | O4: CAP25 | P4: CAP26 | Q4: CAP29 | R4: OBSERVACIONES | T4: 1.05
A5: Acarreo horizontal | B5: %MO | C5: =T5*$T$4 -> 0 | D5: =IF(Equipo[[#This Row],[VALOR]]=0,Equipo[[#This Row],[TOTAL]],E5/C5) -> 0 | E5: =SUM(Equipo[[#This Row],[CAP1]:[CAP29]]) -> 0 | F5: =SUMIF('CAP1-3'!$B:$H,Equipo[[#This Row],[DESCRIPCION]],'CAP1-3'!$H:$H) -> 0 | G5: =SUMIF('CAP4-5'!$B:$H,Equipo[[#This Row],[DESCRIPCION]],'CAP4-5'!$H:$H) -> 0 | H5: =SUMIF('CAP6-7'!$B:$H,Equipo[[#This Row],[DESCRIPCION]],'CAP6-7'!$H:$H) -> 0 | I5: =SUMIF('CAP8'!$B:$H,Equipo[[#This Row],[DESCRIPCION]],'CAP8'!$H:$H) -> 0 | J5: =SUMIF('CAP9-13'!$B:$H,Equipo[[#This Row],[DESCRIPCION]],'CAP9-13'!$H:$H) -> 0 | K5: =SUMIF('CAP14-15'!$B:$H,Equipo[[#This Row],[DESCRIPCION]],'CAP14-15'!$H:$H) -> 0 | L5: =SUMIF('CAP16-18'!$B:$H,Equipo[[#This Row],[DESCRIPCION]],'CAP16-18'!$H:$H) -> 0 | M5: =SUMIF('CAP19-22'!$B:$H,Equipo[[#This Row],[DESCRIPCION]],'CAP19-22'!$H:$H) -> 0 | N5: =SUMIF('CAP23-24'!$B:$H,Equipo[[#This Row],[DESCRIPCION]],'CAP23-24'!$H:$H) -> 0 | O5: =SUMIF('CAP25'!$B:$H,Equipo[[#This Row],[DESCRIPCION]],'CAP25'!$H:$H) -> 0 | P5: =SUMIF('CAP26-28'!$B:$H,Equipo[[#This Row],[DESCRIPCION]],'CAP26-28'!$H:$H) -> 0 | Q5: =SUMIF('CAP29'!$B:$H,Equipo[[#This Row],[DESCRIPCION]],'CAP29'!$H:$H) -> 0 | T5: 0
A6: Acarreo vertical | B6: %MO | C6: =T6*$T$4 -> 0 | D6: =IF(Equipo[[#This Row],[VALOR]]=0,Equipo[[#This Row],[TOTAL]],E6/C6) -> 0 | E6: =SUM(Equipo[[#This Row],[CAP1]:[CAP29]]) -> 0 | F6: =SUMIF('CAP1-3'!$B:$H,Equipo[[#This Row],[DESCRIPCION]],'CAP1-3'!$H:$H) -> 0 | G6: =SUMIF('CAP4-5'!$B:$H,Equipo[[#This Row],[DESCRIPCION]],'CAP4-5'!$H:$H) -> 0 | H6: =SUMIF('CAP6-7'!$B:$H,Equipo[[#This Row],[DESCRIPCION]],'CAP6-7'!$H:$H) -> 0 | I6: =SUMIF('CAP8'!$B:$H,Equipo[[#This Row],[DESCRIPCION]],'CAP8'!$H:$H) -> 0 | J6: =SUMIF('CAP9-13'!$B:$H,Equipo[[#This Row],[DESCRIPCION]],'CAP9-13'!$H:$H) -> 0 | K6: =SUMIF('CAP14-15'!$B:$H,Equipo[[#This Row],[DESCRIPCION]],'CAP14-15'!$H:$H) -> 0 | L6: =SUMIF('CAP16-18'!$B:$H,Equipo[[#This Row],[DESCRIPCION]],'CAP16-18'!$H:$H) -> 0 | M6: =SUMIF('CAP19-22'!$B:$H,Equipo[[#This Row],[DESCRIPCION]],'CAP19-22'!$H:$H) -> 0 | N6: =SUMIF('CAP23-24'!$B:$H,Equipo[[#This Row],[DESCRIPCION]],'CAP23-24'!$H:$H) -> 0 | O6: =SUMIF('CAP25'!$B:$H,Equipo[[#This Row],[DESCRIPCION]],'CAP25'!$H:$H) -> 0 | P6: =SUMIF('CAP26-28'!$B:$H,Equipo[[#This Row],[DESCRIPCION]],'CAP26-28'!$H:$H) -> 0 | Q6: =SUMIF('CAP29'!$B:$H,Equipo[[#This Row],[DESCRIPCION]],'CAP29'!$H:$H) -> 0 | T6: 0
A7: Andamio | B7: %MO | C7: =T7*$T$4 -> 2109.45 | D7: =IF(Equipo[[#This Row],[VALOR]]=0,Equipo[[#This Row],[TOTAL]],E7/C7) -> 0 | E7: =SUM(Equipo[[#This Row],[CAP1]:[CAP29]]) -> 0 | F7: =SUMIF('CAP1-3'!$B:$H,Equipo[[#This Row],[DESCRIPCION]],'CAP1-3'!$H:$H) -> 0 | G7: =SUMIF('CAP4-5'!$B:$H,Equipo[[#This Row],[DESCRIPCION]],'CAP4-5'!$H:$H) -> 0 | H7: =SUMIF('CAP6-7'!$B:$H,Equipo[[#This Row],[DESCRIPCION]],'CAP6-7'!$H:$H) -> 0 | I7: =SUMIF('CAP8'!$B:$H,Equipo[[#This Row],[DESCRIPCION]],'CAP8'!$H:$H) -> 0 | J7: =SUMIF('CAP9-13'!$B:$H,Equipo[[#This Row],[DESCRIPCION]],'CAP9-13'!$H:$H) -> 0 | K7: =SUMIF('CAP14-15'!$B:$H,Equipo[[#This Row],[DESCRIPCION]],'CAP14-15'!$H:$H) -> 0 | L7: =SUMIF('CAP16-18'!$B:$H,Equipo[[#This Row],[DESCRIPCION]],'CAP16-18'!$H:$H) -> 0 | M7: =SUMIF('CAP19-22'!$B:$H,Equipo[[#This Row],[DESCRIPCION]],'CAP19-22'!$H:$H) -> 0 | N7: =SUMIF('CAP23-24'!$B:$H,Equipo[[#This Row],[DESCRIPCION]],'CAP23-24'!$H:$H) -> 0 | O7: =SUMIF('CAP25'!$B:$H,Equipo[[#This Row],[DESCRIPCION]],'CAP25'!$H:$H) -> 0 | P7: =SUMIF('CAP26-28'!$B:$H,Equipo[[#This Row],[DESCRIPCION]],'CAP26-28'!$H:$H) -> 0 | Q7: =SUMIF('CAP29'!$B:$H,Equipo[[#This Row],[DESCRIPCION]],'CAP29'!$H:$H) -> 0 | R7: Equipos AMC Feb-2025 | T7: 2009
A8: Andamio certificado | B8: Día | C8: =T8*$T$4 -> 142078.65 | D8: =IF(Equipo[[#This Row],[VALOR]]=0,Equipo[[#This Row],[TOTAL]],E8/C8) -> 0 | E8: =SUM(Equipo[[#This Row],[CAP1]:[CAP29]]) -> 0 | F8: =SUMIF('CAP1-3'!$B:$H,Equipo[[#This Row],[DESCRIPCION]],'CAP1-3'!$H:$H) -> 0 | G8: =SUMIF('CAP4-5'!$B:$H,Equipo[[#This Row],[DESCRIPCION]],'CAP4-5'!$H:$H) -> 0 | H8: =SUMIF('CAP6-7'!$B:$H,Equipo[[#This Row],[DESCRIPCION]],'CAP6-7'!$H:$H) -> 0 | I8: =SUMIF('CAP8'!$B:$H,Equipo[[#This Row],[DESCRIPCION]],'CAP8'!$H:$H) -> 0 | J8: =SUMIF('CAP9-13'!$B:$H,Equipo[[#This Row],[DESCRIPCION]],'CAP9-13'!$H:$H) -> 0 | K8: =SUMIF('CAP14-15'!$B:$H,Equipo[[#This Row],[DESCRIPCION]],'CAP14-15'!$H:$H) -> 0 | L8: =SUMIF('CAP16-18'!$B:$H,Equipo[[#This Row],[DESCRIPCION]],'CAP16-18'!$H:$H) -> 0 | M8: =SUMIF('CAP19-22'!$B:$H,Equipo[[#This Row],[DESCRIPCION]],'CAP19-22'!$H:$H) -> 0 | N8: =SUMIF('CAP23-24'!$B:$H,Equipo[[#This Row],[DESCRIPCION]],'CAP23-24'!$H:$H) -> 0 | O8: =SUMIF('CAP25'!$B:$H,Equipo[[#This Row],[DESCRIPCION]],'CAP25'!$H:$H) -> 0 | P8: =SUMIF('CAP26-28'!$B:$H,Equipo[[#This Row],[DESCRIPCION]],'CAP26-28'!$H:$H) -> 0 | Q8: =SUMIF('CAP29'!$B:$H,Equipo[[#This Row],[DESCRIPCION]],'CAP29'!$H:$H) -> 0 | T8: 135313
A9: Baño portatil 2 aseos/semana | B9: Mes | C9: =T9*$T$4 -> 1022962.5 | D9: =IF(Equipo[[#This Row],[VALOR]]=0,Equipo[[#This Row],[TOTAL]],E9/C9) -> 5 | E9: =SUM(Equipo[[#This Row],[CAP1]:[CAP29]]) -> 5114812.5 | F9: =SUMIF('CAP1-3'!$B:$H,Equipo[[#This Row],[DESCRIPCION]],'CAP1-3'!$H:$H) -> 5114812.5 | G9: =SUMIF('CAP4-5'!$B:$H,Equipo[[#This Row],[DESCRIPCION]],'CAP4-5'!$H:$H) -> 0 | H9: =SUMIF('CAP6-7'!$B:$H,Equipo[[#This Row],[DESCRIPCION]],'CAP6-7'!$H:$H) -> 0 | I9: =SUMIF('CAP8'!$B:$H,Equipo[[#This Row],[DESCRIPCION]],'CAP8'!$H:$H) -> 0 | J9: =SUMIF('CAP9-13'!$B:$H,Equipo[[#This Row],[DESCRIPCION]],'CAP9-13'!$H:$H) -> 0 | K9: =SUMIF('CAP14-15'!$B:$H,Equipo[[#This Row],[DESCRIPCION]],'CAP14-15'!$H:$H) -> 0 | L9: =SUMIF('CAP16-18'!$B:$H,Equipo[[#This Row],[DESCRIPCION]],'CAP16-18'!$H:$H) -> 0 | M9: =SUMIF('CAP19-22'!$B:$H,Equipo[[#This Row],[DESCRIPCION]],'CAP19-22'!$H:$H) -> 0 | N9: =SUMIF('CAP23-24'!$B:$H,Equipo[[#This Row],[DESCRIPCION]],'CAP23-24'!$H:$H) -> 0 | O9: =SUMIF('CAP25'!$B:$H,Equipo[[#This Row],[DESCRIPCION]],'CAP25'!$H:$H) -> 0 | P9: =SUMIF('CAP26-28'!$B:$H,Equipo[[#This Row],[DESCRIPCION]],'CAP26-28'!$H:$H) -> 0 | Q9: =SUMIF('CAP29'!$B:$H,Equipo[[#This Row],[DESCRIPCION]],'CAP29'!$H:$H) -> 0 | R9: Rentabaños S.A.S Ene-2025 | T9: 974250
A10: Barreno manual (hélice, cucharón) | B10: Día | C10: =T10*$T$4 -> 107979.9 | D10: =IF(Equipo[[#This Row],[VALOR]]=0,Equipo[[#This Row],[TOTAL]],E10/C10) -> 0 | E10: =SUM(Equipo[[#This Row],[CAP1]:[CAP29]]) -> 0 | F10: =SUMIF('CAP1-3'!$B:$H,Equipo[[#This Row],[DESCRIPCION]],'CAP1-3'!$H:$H) -> 0 | G10: =SUMIF('CAP4-5'!$B:$H,Equipo[[#This Row],[DESCRIPCION]],'CAP4-5'!$H:$H) -> 0 | H10: =SUMIF('CAP6-7'!$B:$H,Equipo[[#This Row],[DESCRIPCION]],'CAP6-7'!$H:$H) -> 0 | I10: =SUMIF('CAP8'!$B:$H,Equipo[[#This Row],[DESCRIPCION]],'CAP8'!$H:$H) -> 0 | J10: =SUMIF('CAP9-13'!$B:$H,Equipo[[#This Row],[DESCRIPCION]],'CAP9-13'!$H:$H) -> 0 | K10: =SUMIF('CAP14-15'!$B:$H,Equipo[[#This Row],[DESCRIPCION]],'CAP14-15'!$H:$H) -> 0 | L10: =SUMIF('CAP16-18'!$B:$H,Equipo[[#This Row],[DESCRIPCION]],'CAP16-18'!$H:$H) -> 0 | M10: =SUMIF('CAP19-22'!$B:$H,Equipo[[#This Row],[DESCRIPCION]],'CAP19-22'!$H:$H) -> 0 | N10: =SUMIF('CAP23-24'!$B:$H,Equipo[[#This Row],[DESCRIPCION]],'CAP23-24'!$H:$H) -> 0 | O10: =SUMIF('CAP25'!$B:$H,Equipo[[#This Row],[DESCRIPCION]],'CAP25'!$H:$H) -> 0 | P10: =SUMIF('CAP26-28'!$B:$H,Equipo[[#This Row],[DESCRIPCION]],'CAP26-28'!$H:$H) -> 0 | Q10: =SUMIF('CAP29'!$B:$H,Equipo[[#This Row],[DESCRIPCION]],'CAP29'!$H:$H) -> 0 | T10: 102838
A11: Barreno para dren mecanico | B11: Día | C11: =T11*$T$4 -> 210276.15 | D11: =IF(Equipo[[#This Row],[VALOR]]=0,Equipo[[#This Row],[TOTAL]],E11/C11) -> 0 | E11: =SUM(Equipo[[#This Row],[CAP1]:[CAP29]]) -> 0 | F11: =SUMIF('CAP1-3'!$B:$H,Equipo[[#This Row],[DESCRIPCION]],'CAP1-3'!$H:$H) -> 0 | G11: =SUMIF('CAP4-5'!$B:$H,Equipo[[#This Row],[DESCRIPCION]],'CAP4-5'!$H:$H) -> 0 | H11: =SUMIF('CAP6-7'!$B:$H,Equipo[[#This Row],[DESCRIPCION]],'CAP6-7'!$H:$H) -> 0 | I11: =SUMIF('CAP8'!$B:$H,Equipo[[#This Row],[DESCRIPCION]],'CAP8'!$H:$H) -> 0 | J11: =SUMIF('CAP9-13'!$B:$H,Equipo[[#This Row],[DESCRIPCION]],'CAP9-13'!$H:$H) -> 0 | K11: =SUMIF('CAP14-15'!$B:$H,Equipo[[#This Row],[DESCRIPCION]],'CAP14-15'!$H:$H) -> 0 | L11: =SUMIF('CAP16-18'!$B:$H,Equipo[[#This Row],[DESCRIPCION]],'CAP16-18'!$H:$H) -> 0 | M11: =SUMIF('CAP19-22'!$B:$H,Equipo[[#This Row],[DESCRIPCION]],'CAP19-22'!$H:$H) -> 0 | N11: =SUMIF('CAP23-24'!$B:$H,Equipo[[#This Row],[DESCRIPCION]],'CAP23-24'!$H:$H) -> 0 | O11: =SUMIF('CAP25'!$B:$H,Equipo[[#This Row],[DESCRIPCION]],'CAP25'!$H:$H) -> 0 | P11: =SUMIF('CAP26-28'!$B:$H,Equipo[[#This Row],[DESCRIPCION]],'CAP26-28'!$H:$H) -> 0 | Q11: =SUMIF('CAP29'!$B:$H,Equipo[[#This Row],[DESCRIPCION]],'CAP29'!$H:$H) -> 0 | T11: 200263
A12: Bomba para concreto | B12: M3 | C12: =T12*$T$4 -> 82902.75 | D12: =IF(Equipo[[#This Row],[VALOR]]=0,Equipo[[#This Row],[TOTAL]],E12/C12) -> 0 | E12: =SUM(Equipo[[#This Row],[CAP1]:[CAP29]]) -> 0 | F12: =SUMIF('CAP1-3'!$B:$H,Equipo[[#This Row],[DESCRIPCION]],'CAP1-3'!$H:$H) -> 0 | G12: =SUMIF('CAP4-5'!$B:$H,Equipo[[#This Row],[DESCRIPCION]],'CAP4-5'!$H:$H) -> 0 | H12: =SUMIF('CAP6-7'!$B:$H,Equipo[[#This Row],[DESCRIPCION]],'CAP6-7'!$H:$H) -> 0 | I12: =SUMIF('CAP8'!$B:$H,Equipo[[#This Row],[DESCRIPCION]],'CAP8'!$H:$H) -> 0 | J12: =SUMIF('CAP9-13'!$B:$H,Equipo[[#This Row],[DESCRIPCION]],'CAP9-13'!$H:$H) -> 0 | K12: =SUMIF('CAP14-15'!$B:$H,Equipo[[#This Row],[DESCRIPCION]],'CAP14-15'!$H:$H) -> 0 | L12: =SUMIF('CAP16-18'!$B:$H,Equipo[[#This Row],[DESCRIPCION]],'CAP16-18'!$H:$H) -> 0 | M12: =SUMIF('CAP19-22'!$B:$H,Equipo[[#This Row],[DESCRIPCION]],'CAP19-22'!$H:$H) -> 0 | N12: =SUMIF('CAP23-24'!$B:$H,Equipo[[#This Row],[DESCRIPCION]],'CAP23-24'!$H:$H) -> 0 | O12: =SUMIF('CAP25'!$B:$H,Equipo[[#This Row],[DESCRIPCION]],'CAP25'!$H:$H) -> 0 | P12: =SUMIF('CAP26-28'!$B:$H,Equipo[[#This Row],[DESCRIPCION]],'CAP26-28'!$H:$H) -> 0 | Q12: =SUMIF('CAP29'!$B:$H,Equipo[[#This Row],[DESCRIPCION]],'CAP29'!$H:$H) -> 0 | T12: 78955
A13: Bomba para gato de tensionamiento | B13: Hr | C13: =T13*$T$4 -> 90174 | D13: =IF(Equipo[[#This Row],[VALOR]]=0,Equipo[[#This Row],[TOTAL]],E13/C13) -> 0 | E13: =SUM(Equipo[[#This Row],[CAP1]:[CAP29]]) -> 0 | F13: =SUMIF('CAP1-3'!$B:$H,Equipo[[#This Row],[DESCRIPCION]],'CAP1-3'!$H:$H) -> 0 | G13: =SUMIF('CAP4-5'!$B:$H,Equipo[[#This Row],[DESCRIPCION]],'CAP4-5'!$H:$H) -> 0 | H13: =SUMIF('CAP6-7'!$B:$H,Equipo[[#This Row],[DESCRIPCION]],'CAP6-7'!$H:$H) -> 0 | I13: =SUMIF('CAP8'!$B:$H,Equipo[[#This Row],[DESCRIPCION]],'CAP8'!$H:$H) -> 0 | J13: =SUMIF('CAP9-13'!$B:$H,Equipo[[#This Row],[DESCRIPCION]],'CAP9-13'!$H:$H) -> 0 | K13: =SUMIF('CAP14-15'!$B:$H,Equipo[[#This Row],[DESCRIPCION]],'CAP14-15'!$H:$H) -> 0 | L13: =SUMIF('CAP16-18'!$B:$H,Equipo[[#This Row],[DESCRIPCION]],'CAP16-18'!$H:$H) -> 0 | M13: =SUMIF('CAP19-22'!$B:$H,Equipo[[#This Row],[DESCRIPCION]],'CAP19-22'!$H:$H) -> 0 | N13: =SUMIF('CAP23-24'!$B:$H,Equipo[[#This Row],[DESCRIPCION]],'CAP23-24'!$H:$H) -> 0 | O13: =SUMIF('CAP25'!$B:$H,Equipo[[#This Row],[DESCRIPCION]],'CAP25'!$H:$H) -> 0 | P13: =SUMIF('CAP26-28'!$B:$H,Equipo[[#This Row],[DESCRIPCION]],'CAP26-28'!$H:$H) -> 0 | Q13: =SUMIF('CAP29'!$B:$H,Equipo[[#This Row],[DESCRIPCION]],'CAP29'!$H:$H) -> 0 | T13: 85880
A14: Bomba para inyectar | B14: Hr | C14: =T14*$T$4 -> 62514.9 | D14: =IF(Equipo[[#This Row],[VALOR]]=0,Equipo[[#This Row],[TOTAL]],E14/C14) -> 0 | E14: =SUM(Equipo[[#This Row],[CAP1]:[CAP29]]) -> 0 | F14: =SUMIF('CAP1-3'!$B:$H,Equipo[[#This Row],[DESCRIPCION]],'CAP1-3'!$H:$H) -> 0 | G14: =SUMIF('CAP4-5'!$B:$H,Equipo[[#This Row],[DESCRIPCION]],'CAP4-5'!$H:$H) -> 0 | H14: =SUMIF('CAP6-7'!$B:$H,Equipo[[#This Row],[DESCRIPCION]],'CAP6-7'!$H:$H) -> 0 | I14: =SUMIF('CAP8'!$B:$H,Equipo[[#This Row],[DESCRIPCION]],'CAP8'!$H:$H) -> 0 | J14: =SUMIF('CAP9-13'!$B:$H,Equipo[[#This Row],[DESCRIPCION]],'CAP9-13'!$H:$H) -> 0 | K14: =SUMIF('CAP14-15'!$B:$H,Equipo[[#This Row],[DESCRIPCION]],'CAP14-15'!$H:$H) -> 0 | L14: =SUMIF('CAP16-18'!$B:$H,Equipo[[#This Row],[DESCRIPCION]],'CAP16-18'!$H:$H) -> 0 | M14: =SUMIF('CAP19-22'!$B:$H,Equipo[[#This Row],[DESCRIPCION]],'CAP19-22'!$H:$H) -> 0 | N14: =SUMIF('CAP23-24'!$B:$H,Equipo[[#This Row],[DESCRIPCION]],'CAP23-24'!$H:$H) -> 0 | O14: =SUMIF('CAP25'!$B:$H,Equipo[[#This Row],[DESCRIPCION]],'CAP25'!$H:$H) -> 0 | P14: =SUMIF('CAP26-28'!$B:$H,Equipo[[#This Row],[DESCRIPCION]],'CAP26-28'!$H:$H) -> 0 | Q14: =SUMIF('CAP29'!$B:$H,Equipo[[#This Row],[DESCRIPCION]],'CAP29'!$H:$H) -> 0 | T14: 59538
A15: Bomba peristáltica manguera y kit de lanzado | B15: Hr | C15: =T15*$T$4 -> 56831.25 | D15: =IF(Equipo[[#This Row],[VALOR]]=0,Equipo[[#This Row],[TOTAL]],E15/C15) -> 0 | E15: =SUM(Equipo[[#This Row],[CAP1]:[CAP29]]) -> 0 | F15: =SUMIF('CAP1-3'!$B:$H,Equipo[[#This Row],[DESCRIPCION]],'CAP1-3'!$H:$H) -> 0 | G15: =SUMIF('CAP4-5'!$B:$H,Equipo[[#This Row],[DESCRIPCION]],'CAP4-5'!$H:$H) -> 0 | H15: =SUMIF('CAP6-7'!$B:$H,Equipo[[#This Row],[DESCRIPCION]],'CAP6-7'!$H:$H) -> 0 | I15: =SUMIF('CAP8'!$B:$H,Equipo[[#This Row],[DESCRIPCION]],'CAP8'!$H:$H) -> 0 | J15: =SUMIF('CAP9-13'!$B:$H,Equipo[[#This Row],[DESCRIPCION]],'CAP9-13'!$H:$H) -> 0 | K15: =SUMIF('CAP14-15'!$B:$H,Equipo[[#This Row],[DESCRIPCION]],'CAP14-15'!$H:$H) -> 0 | L15: =SUMIF('CAP16-18'!$B:$H,Equipo[[#This Row],[DESCRIPCION]],'CAP16-18'!$H:$H) -> 0 | M15: =SUMIF('CAP19-22'!$B:$H,Equipo[[#This Row],[DESCRIPCION]],'CAP19-22'!$H:$H) -> 0 | N15: =SUMIF('CAP23-24'!$B:$H,Equipo[[#This Row],[DESCRIPCION]],'CAP23-24'!$H:$H) -> 0 | O15: =SUMIF('CAP25'!$B:$H,Equipo[[#This Row],[DESCRIPCION]],'CAP25'!$H:$H) -> 0 | P15: =SUMIF('CAP26-28'!$B:$H,Equipo[[#This Row],[DESCRIPCION]],'CAP26-28'!$H:$H) -> 0 | Q15: =SUMIF('CAP29'!$B:$H,Equipo[[#This Row],[DESCRIPCION]],'CAP29'!$H:$H) -> 0 | T15: 54125
A16: Brilladora | B16: Día | C16: =T16*$T$4 -> 56831.25 | D16: =IF(Equipo[[#This Row],[VALOR]]=0,Equipo[[#This Row],[TOTAL]],E16/C16) -> 0 | E16: =SUM(Equipo[[#This Row],[CAP1]:[CAP29]]) -> 0 | F16: =SUMIF('CAP1-3'!$B:$H,Equipo[[#This Row],[DESCRIPCION]],'CAP1-3'!$H:$H) -> 0 | G16: =SUMIF('CAP4-5'!$B:$H,Equipo[[#This Row],[DESCRIPCION]],'CAP4-5'!$H:$H) -> 0 | H16: =SUMIF('CAP6-7'!$B:$H,Equipo[[#This Row],[DESCRIPCION]],'CAP6-7'!$H:$H) -> 0 | I16: =SUMIF('CAP8'!$B:$H,Equipo[[#This Row],[DESCRIPCION]],'CAP8'!$H:$H) -> 0 | J16: =SUMIF('CAP9-13'!$B:$H,Equipo[[#This Row],[DESCRIPCION]],'CAP9-13'!$H:$H) -> 0 | K16: =SUMIF('CAP14-15'!$B:$H,Equipo[[#This Row],[DESCRIPCION]],'CAP14-15'!$H:$H) -> 0 | L16: =SUMIF('CAP16-18'!$B:$H,Equipo[[#This Row],[DESCRIPCION]],'CAP16-18'!$H:$H) -> 0 | M16: =SUMIF('CAP19-22'!$B:$H,Equipo[[#This Row],[DESCRIPCION]],'CAP19-22'!$H:$H) -> 0 | N16: =SUMIF('CAP23-24'!$B:$H,Equipo[[#This Row],[DESCRIPCION]],'CAP23-24'!$H:$H) -> 0 | O16: =SUMIF('CAP25'!$B:$H,Equipo[[#This Row],[DESCRIPCION]],'CAP25'!$H:$H) -> 0 | P16: =SUMIF('CAP26-28'!$B:$H,Equipo[[#This Row],[DESCRIPCION]],'CAP26-28'!$H:$H) -> 0 | Q16: =SUMIF('CAP29'!$B:$H,Equipo[[#This Row],[DESCRIPCION]],'CAP29'!$H:$H) -> 0 | T16: 54125
A17: Buldózer D65-8 | B17: Hr | C17: =T17*$T$4 -> 244939.8 | D17: =IF(Equipo[[#This Row],[VALOR]]=0,Equipo[[#This Row],[TOTAL]],E17/C17) -> 0 | E17: =SUM(Equipo[[#This Row],[CAP1]:[CAP29]]) -> 0 | F17: =SUMIF('CAP1-3'!$B:$H,Equipo[[#This Row],[DESCRIPCION]],'CAP1-3'!$H:$H) -> 0 | G17: =SUMIF('CAP4-5'!$B:$H,Equipo[[#This Row],[DESCRIPCION]],'CAP4-5'!$H:$H) -> 0 | H17: =SUMIF('CAP6-7'!$B:$H,Equipo[[#This Row],[DESCRIPCION]],'CAP6-7'!$H:$H) -> 0 | I17: =SUMIF('CAP8'!$B:$H,Equipo[[#This Row],[DESCRIPCION]],'CAP8'!$H:$H) -> 0 | J17: =SUMIF('CAP9-13'!$B:$H,Equipo[[#This Row],[DESCRIPCION]],'CAP9-13'!$H:$H) -> 0 | K17: =SUMIF('CAP14-15'!$B:$H,Equipo[[#This Row],[DESCRIPCION]],'CAP14-15'!$H:$H) -> 0 | L17: =SUMIF('CAP16-18'!$B:$H,Equipo[[#This Row],[DESCRIPCION]],'CAP16-18'!$H:$H) -> 0 | M17: =SUMIF('CAP19-22'!$B:$H,Equipo[[#This Row],[DESCRIPCION]],'CAP19-22'!$H:$H) -> 0 | N17: =SUMIF('CAP23-24'!$B:$H,Equipo[[#This Row],[DESCRIPCION]],'CAP23-24'!$H:$H) -> 0 | O17: =SUMIF('CAP25'!$B:$H,Equipo[[#This Row],[DESCRIPCION]],'CAP25'!$H:$H) -> 0 | P17: =SUMIF('CAP26-28'!$B:$H,Equipo[[#This Row],[DESCRIPCION]],'CAP26-28'!$H:$H) -> 0 | Q17: =SUMIF('CAP29'!$B:$H,Equipo[[#This Row],[DESCRIPCION]],'CAP29'!$H:$H) -> 0 | T17: 233276
A18: Cargador 930 1,5 yd3 | B18: Hr | C18: =T18*$T$4 -> 237181.35 | D18: =IF(Equipo[[#This Row],[VALOR]]=0,Equipo[[#This Row],[TOTAL]],E18/C18) -> 0 | E18: =SUM(Equipo[[#This Row],[CAP1]:[CAP29]]) -> 0 | F18: =SUMIF('CAP1-3'!$B:$H,Equipo[[#This Row],[DESCRIPCION]],'CAP1-3'!$H:$H) -> 0 | G18: =SUMIF('CAP4-5'!$B:$H,Equipo[[#This Row],[DESCRIPCION]],'CAP4-5'!$H:$H) -> 0 | H18: =SUMIF('CAP6-7'!$B:$H,Equipo[[#This Row],[DESCRIPCION]],'CAP6-7'!$H:$H) -> 0 | I18: =SUMIF('CAP8'!$B:$H,Equipo[[#This Row],[DESCRIPCION]],'CAP8'!$H:$H) -> 0 | J18: =SUMIF('CAP9-13'!$B:$H,Equipo[[#This Row],[DESCRIPCION]],'CAP9-13'!$H:$H) -> 0 | K18: =SUMIF('CAP14-15'!$B:$H,Equipo[[#This Row],[DESCRIPCION]],'CAP14-15'!$H:$H) -> 0 | L18: =SUMIF('CAP16-18'!$B:$H,Equipo[[#This Row],[DESCRIPCION]],'CAP16-18'!$H:$H) -> 0 | M18: =SUMIF('CAP19-22'!$B:$H,Equipo[[#This Row],[DESCRIPCION]],'CAP19-22'!$H:$H) -> 0 | N18: =SUMIF('CAP23-24'!$B:$H,Equipo[[#This Row],[DESCRIPCION]],'CAP23-24'!$H:$H) -> 0 | O18: =SUMIF('CAP25'!$B:$H,Equipo[[#This Row],[DESCRIPCION]],'CAP25'!$H:$H) -> 0 | P18: =SUMIF('CAP26-28'!$B:$H,Equipo[[#This Row],[DESCRIPCION]],'CAP26-28'!$H:$H) -> 0 | Q18: =SUMIF('CAP29'!$B:$H,Equipo[[#This Row],[DESCRIPCION]],'CAP29'!$H:$H) -> 0 | T18: 225887
A19: Carrotanque agua | B19: Hr | C19: =T19*$T$4 -> 170493.75 | D19: =IF(Equipo[[#This Row],[VALOR]]=0,Equipo[[#This Row],[TOTAL]],E19/C19) -> 0 | E19: =SUM(Equipo[[#This Row],[CAP1]:[CAP29]]) -> 0 | F19: =SUMIF('CAP1-3'!$B:$H,Equipo[[#This Row],[DESCRIPCION]],'CAP1-3'!$H:$H) -> 0 | G19: =SUMIF('CAP4-5'!$B:$H,Equipo[[#This Row],[DESCRIPCION]],'CAP4-5'!$H:$H) -> 0 | H19: =SUMIF('CAP6-7'!$B:$H,Equipo[[#This Row],[DESCRIPCION]],'CAP6-7'!$H:$H) -> 0 | I19: =SUMIF('CAP8'!$B:$H,Equipo[[#This Row],[DESCRIPCION]],'CAP8'!$H:$H) -> 0 | J19: =SUMIF('CAP9-13'!$B:$H,Equipo[[#This Row],[DESCRIPCION]],'CAP9-13'!$H:$H) -> 0 | K19: =SUMIF('CAP14-15'!$B:$H,Equipo[[#This Row],[DESCRIPCION]],'CAP14-15'!$H:$H) -> 0 | L19: =SUMIF('CAP16-18'!$B:$H,Equipo[[#This Row],[DESCRIPCION]],'CAP16-18'!$H:$H) -> 0 | M19: =SUMIF('CAP19-22'!$B:$H,Equipo[[#This Row],[DESCRIPCION]],'CAP19-22'!$H:$H) -> 0 | N19: =SUMIF('CAP23-24'!$B:$H,Equipo[[#This Row],[DESCRIPCION]],'CAP23-24'!$H:$H) -> 0 | O19: =SUMIF('CAP25'!$B:$H,Equipo[[#This Row],[DESCRIPCION]],'CAP25'!$H:$H) -> 0 | P19: =SUMIF('CAP26-28'!$B:$H,Equipo[[#This Row],[DESCRIPCION]],'CAP26-28'!$H:$H) -> 0 | Q19: =SUMIF('CAP29'!$B:$H,Equipo[[#This Row],[DESCRIPCION]],'CAP29'!$H:$H) -> 0 | T19: 162375
A20: Carrotanque asfalto | B20: Hr | C20: =T20*$T$4 -> 170493.75 | D20: =IF(Equipo[[#This Row],[VALOR]]=0,Equipo[[#This Row],[TOTAL]],E20/C20) -> 0 | E20: =SUM(Equipo[[#This Row],[CAP1]:[CAP29]]) -> 0 | F20: =SUMIF('CAP1-3'!$B:$H,Equipo[[#This Row],[DESCRIPCION]],'CAP1-3'!$H:$H) -> 0 | G20: =SUMIF('CAP4-5'!$B:$H,Equipo[[#This Row],[DESCRIPCION]],'CAP4-5'!$H:$H) -> 0 | H20: =SUMIF('CAP6-7'!$B:$H,Equipo[[#This Row],[DESCRIPCION]],'CAP6-7'!$H:$H) -> 0 | I20: =SUMIF('CAP8'!$B:$H,Equipo[[#This Row],[DESCRIPCION]],'CAP8'!$H:$H) -> 0 | J20: =SUMIF('CAP9-13'!$B:$H,Equipo[[#This Row],[DESCRIPCION]],'CAP9-13'!$H:$H) -> 0 | K20: =SUMIF('CAP14-15'!$B:$H,Equipo[[#This Row],[DESCRIPCION]],'CAP14-15'!$H:$H) -> 0 | L20: =SUMIF('CAP16-18'!$B:$H,Equipo[[#This Row],[DESCRIPCION]],'CAP16-18'!$H:$H) -> 0 | M20: =SUMIF('CAP19-22'!$B:$H,Equipo[[#This Row],[DESCRIPCION]],'CAP19-22'!$H:$H) -> 0 | N20: =SUMIF('CAP23-24'!$B:$H,Equipo[[#This Row],[DESCRIPCION]],'CAP23-24'!$H:$H) -> 0 | O20: =SUMIF('CAP25'!$B:$H,Equipo[[#This Row],[DESCRIPCION]],'CAP25'!$H:$H) -> 0 | P20: =SUMIF('CAP26-28'!$B:$H,Equipo[[#This Row],[DESCRIPCION]],'CAP26-28'!$H:$H) -> 0 | Q20: =SUMIF('CAP29'!$B:$H,Equipo[[#This Row],[DESCRIPCION]],'CAP29'!$H:$H) -> 0 | T20: 162375
A21: Certificación Red Interna (Por un Organismo certificador Acreditado por la ONAC) | B21: Un | C21: =T21*$T$4 -> 185270.4 | D21: =IF(Equipo[[#This Row],[VALOR]]=0,Equipo[[#This Row],[TOTAL]],E21/C21) -> 0 | E21: =SUM(Equipo[[#This Row],[CAP1]:[CAP29]]) -> 0 | F21: =SUMIF('CAP1-3'!$B:$H,Equipo[[#This Row],[DESCRIPCION]],'CAP1-3'!$H:$H) -> 0 | G21: =SUMIF('CAP4-5'!$B:$H,Equipo[[#This Row],[DESCRIPCION]],'CAP4-5'!$H:$H) -> 0 | H21: =SUMIF('CAP6-7'!$B:$H,Equipo[[#This Row],[DESCRIPCION]],'CAP6-7'!$H:$H) -> 0 | I21: =SUMIF('CAP8'!$B:$H,Equipo[[#This Row],[DESCRIPCION]],'CAP8'!$H:$H) -> 0 | J21: =SUMIF('CAP9-13'!$B:$H,Equipo[[#This Row],[DESCRIPCION]],'CAP9-13'!$H:$H) -> 0 | K21: =SUMIF('CAP14-15'!$B:$H,Equipo[[#This Row],[DESCRIPCION]],'CAP14-15'!$H:$H) -> 0 | L21: =SUMIF('CAP16-18'!$B:$H,Equipo[[#This Row],[DESCRIPCION]],'CAP16-18'!$H:$H) -> 0 | M21: =SUMIF('CAP19-22'!$B:$H,Equipo[[#This Row],[DESCRIPCION]],'CAP19-22'!$H:$H) -> 0 | N21: =SUMIF('CAP23-24'!$B:$H,Equipo[[#This Row],[DESCRIPCION]],'CAP23-24'!$H:$H) -> 0 | O21: =SUMIF('CAP25'!$B:$H,Equipo[[#This Row],[DESCRIPCION]],'CAP25'!$H:$H) -> 0 | P21: =SUMIF('CAP26-28'!$B:$H,Equipo[[#This Row],[DESCRIPCION]],'CAP26-28'!$H:$H) -> 0 | Q21: =SUMIF('CAP29'!$B:$H,Equipo[[#This Row],[DESCRIPCION]],'CAP29'!$H:$H) -> 0 | T21: 176448
... A82: Tablero formaleta 70*140 | B82: Día | C82: =T82*$T$4 -> 981.75 | D82: =IF(Equipo[[#This Row],[VALOR]]=0,Equipo[[#This Row],[TOTAL]],E82/C82) -> 0 | E82: =SUM(Equipo[[#This Row],[CAP1]:[CAP29]]) -> 0 | F82: =SUMIF('CAP1-3'!$B:$H,Equipo[[#This Row],[DESCRIPCION]],'CAP1-3'!$H:$H) -> 0 | G82: =SUMIF('CAP4-5'!$B:$H,Equipo[[#This Row],[DESCRIPCION]],'CAP4-5'!$H:$H) -> 0 | H82: =SUMIF('CAP6-7'!$B:$H,Equipo[[#This Row],[DESCRIPCION]],'CAP6-7'!$H:$H) -> 0 | I82: =SUMIF('CAP8'!$B:$H,Equipo[[#This Row],[DESCRIPCION]],'CAP8'!$H:$H) -> 0 | J82: =SUMIF('CAP9-13'!$B:$H,Equipo[[#This Row],[DESCRIPCION]],'CAP9-13'!$H:$H) -> 0 | K82: =SUMIF('CAP14-15'!$B:$H,Equipo[[#This Row],[DESCRIPCION]],'CAP14-15'!$H:$H) -> 0 | L82: =SUMIF('CAP16-18'!$B:$H,Equipo[[#This Row],[DESCRIPCION]],'CAP16-18'!$H:$H) -> 0 | M82: =SUMIF('CAP19-22'!$B:$H,Equipo[[#This Row],[DESCRIPCION]],'CAP19-22'!$H:$H) -> 0 | N82: =SUMIF('CAP23-24'!$B:$H,Equipo[[#This Row],[DESCRIPCION]],'CAP23-24'!$H:$H) -> 0 | O82: =SUMIF('CAP25'!$B:$H,Equipo[[#This Row],[DESCRIPCION]],'CAP25'!$H:$H) -> 0 | P82: =SUMIF('CAP26-28'!$B:$H,Equipo[[#This Row],[DESCRIPCION]],'CAP26-28'!$H:$H) -> 0 | Q82: =SUMIF('CAP29'!$B:$H,Equipo[[#This Row],[DESCRIPCION]],'CAP29'!$H:$H) -> 0 | T82: 935
A83: Taco metálico de 2 - >3 m | B83: Día | C83: =T83*$T$4 -> 635.25 | D83: =IF(Equipo[[#This Row],[VALOR]]=0,Equipo[[#This Row],[TOTAL]],E83/C83) -> 0 | E83: =SUM(Equipo[[#This Row],[CAP1]:[CAP29]]) -> 0 | F83: =SUMIF('CAP1-3'!$B:$H,Equipo[[#This Row],[DESCRIPCION]],'CAP1-3'!$H:$H) -> 0 | G83: =SUMIF('CAP4-5'!$B:$H,Equipo[[#This Row],[DESCRIPCION]],'CAP4-5'!$H:$H) -> 0 | H83: =SUMIF('CAP6-7'!$B:$H,Equipo[[#This Row],[DESCRIPCION]],'CAP6-7'!$H:$H) -> 0 | I83: =SUMIF('CAP8'!$B:$H,Equipo[[#This Row],[DESCRIPCION]],'CAP8'!$H:$H) -> 0 | J83: =SUMIF('CAP9-13'!$B:$H,Equipo[[#This Row],[DESCRIPCION]],'CAP9-13'!$H:$H) -> 0 | K83: =SUMIF('CAP14-15'!$B:$H,Equipo[[#This Row],[DESCRIPCION]],'CAP14-15'!$H:$H) -> 0 | L83: =SUMIF('CAP16-18'!$B:$H,Equipo[[#This Row],[DESCRIPCION]],'CAP16-18'!$H:$H) -> 0 | M83: =SUMIF('CAP19-22'!$B:$H,Equipo[[#This Row],[DESCRIPCION]],'CAP19-22'!$H:$H) -> 0 | N83: =SUMIF('CAP23-24'!$B:$H,Equipo[[#This Row],[DESCRIPCION]],'CAP23-24'!$H:$H) -> 0 | O83: =SUMIF('CAP25'!$B:$H,Equipo[[#This Row],[DESCRIPCION]],'CAP25'!$H:$H) -> 0 | P83: =SUMIF('CAP26-28'!$B:$H,Equipo[[#This Row],[DESCRIPCION]],'CAP26-28'!$H:$H) -> 0 | Q83: =SUMIF('CAP29'!$B:$H,Equipo[[#This Row],[DESCRIPCION]],'CAP29'!$H:$H) -> 0 | R83: Equipos AMC Feb-2025 | T83: 605
A84: Taco metálico de 2,6 - >4 m | B84: Día | C84: =T84*$T$4 -> 750.75 | D84: =IF(Equipo[[#This Row],[VALOR]]=0,Equipo[[#This Row],[TOTAL]],E84/C84) -> 0 | E84: =SUM(Equipo[[#This Row],[CAP1]:[CAP29]]) -> 0 | F84: =SUMIF('CAP1-3'!$B:$H,Equipo[[#This Row],[DESCRIPCION]],'CAP1-3'!$H:$H) -> 0 | G84: =SUMIF('CAP4-5'!$B:$H,Equipo[[#This Row],[DESCRIPCION]],'CAP4-5'!$H:$H) -> 0 | H84: =SUMIF('CAP6-7'!$B:$H,Equipo[[#This Row],[DESCRIPCION]],'CAP6-7'!$H:$H) -> 0 | I84: =SUMIF('CAP8'!$B:$H,Equipo[[#This Row],[DESCRIPCION]],'CAP8'!$H:$H) -> 0 | J84: =SUMIF('CAP9-13'!$B:$H,Equipo[[#This Row],[DESCRIPCION]],'CAP9-13'!$H:$H) -> 0 | K84: =SUMIF('CAP14-15'!$B:$H,Equipo[[#This Row],[DESCRIPCION]],'CAP14-15'!$H:$H) -> 0 | L84: =SUMIF('CAP16-18'!$B:$H,Equipo[[#This Row],[DESCRIPCION]],'CAP16-18'!$H:$H) -> 0 | M84: =SUMIF('CAP19-22'!$B:$H,Equipo[[#This Row],[DESCRIPCION]],'CAP19-22'!$H:$H) -> 0 | N84: =SUMIF('CAP23-24'!$B:$H,Equipo[[#This Row],[DESCRIPCION]],'CAP23-24'!$H:$H) -> 0 | O84: =SUMIF('CAP25'!$B:$H,Equipo[[#This Row],[DESCRIPCION]],'CAP25'!$H:$H) -> 0 | P84: =SUMIF('CAP26-28'!$B:$H,Equipo[[#This Row],[DESCRIPCION]],'CAP26-28'!$H:$H) -> 0 | Q84: =SUMIF('CAP29'!$B:$H,Equipo[[#This Row],[DESCRIPCION]],'CAP29'!$H:$H) -> 0 | R84: Equipos AMC Feb-2025 | T84: 715
A85: Taladro | B85: Día | C85: =T85*$T$4 -> 101640 | D85: =IF(Equipo[[#This Row],[VALOR]]=0,Equipo[[#This Row],[TOTAL]],E85/C85) -> 0 | E85: =SUM(Equipo[[#This Row],[CAP1]:[CAP29]]) -> 0 | F85: =SUMIF('CAP1-3'!$B:$H,Equipo[[#This Row],[DESCRIPCION]],'CAP1-3'!$H:$H) -> 0 | G85: =SUMIF('CAP4-5'!$B:$H,Equipo[[#This Row],[DESCRIPCION]],'CAP4-5'!$H:$H) -> 0 | H85: =SUMIF('CAP6-7'!$B:$H,Equipo[[#This Row],[DESCRIPCION]],'CAP6-7'!$H:$H) -> 0 | I85: =SUMIF('CAP8'!$B:$H,Equipo[[#This Row],[DESCRIPCION]],'CAP8'!$H:$H) -> 0 | J85: =SUMIF('CAP9-13'!$B:$H,Equipo[[#This Row],[DESCRIPCION]],'CAP9-13'!$H:$H) -> 0 | K85: =SUMIF('CAP14-15'!$B:$H,Equipo[[#This Row],[DESCRIPCION]],'CAP14-15'!$H:$H) -> 0 | L85: =SUMIF('CAP16-18'!$B:$H,Equipo[[#This Row],[DESCRIPCION]],'CAP16-18'!$H:$H) -> 0 | M85: =SUMIF('CAP19-22'!$B:$H,Equipo[[#This Row],[DESCRIPCION]],'CAP19-22'!$H:$H) -> 0 | N85: =SUMIF('CAP23-24'!$B:$H,Equipo[[#This Row],[DESCRIPCION]],'CAP23-24'!$H:$H) -> 0 | O85: =SUMIF('CAP25'!$B:$H,Equipo[[#This Row],[DESCRIPCION]],'CAP25'!$H:$H) -> 0 | P85: =SUMIF('CAP26-28'!$B:$H,Equipo[[#This Row],[DESCRIPCION]],'CAP26-28'!$H:$H) -> 0 | Q85: =SUMIF('CAP29'!$B:$H,Equipo[[#This Row],[DESCRIPCION]],'CAP29'!$H:$H) -> 0 | T85: 96800
A86: Taladro percutor | B86: Día | C86: =T86*$T$4 -> 112455 | D86: =IF(Equipo[[#This Row],[VALOR]]=0,Equipo[[#This Row],[TOTAL]],E86/C86) -> 0 | E86: =SUM(Equipo[[#This Row],[CAP1]:[CAP29]]) -> 0 | F86: =SUMIF('CAP1-3'!$B:$H,Equipo[[#This Row],[DESCRIPCION]],'CAP1-3'!$H:$H) -> 0 | G86: =SUMIF('CAP4-5'!$B:$H,Equipo[[#This Row],[DESCRIPCION]],'CAP4-5'!$H:$H) -> 0 | H86: =SUMIF('CAP6-7'!$B:$H,Equipo[[#This Row],[DESCRIPCION]],'CAP6-7'!$H:$H) -> 0 | I86: =SUMIF('CAP8'!$B:$H,Equipo[[#This Row],[DESCRIPCION]],'CAP8'!$H:$H) -> 0 | J86: =SUMIF('CAP9-13'!$B:$H,Equipo[[#This Row],[DESCRIPCION]],'CAP9-13'!$H:$H) -> 0 | K86: =SUMIF('CAP14-15'!$B:$H,Equipo[[#This Row],[DESCRIPCION]],'CAP14-15'!$H:$H) -> 0 | L86: =SUMIF('CAP16-18'!$B:$H,Equipo[[#This Row],[DESCRIPCION]],'CAP16-18'!$H:$H) -> 0 | M86: =SUMIF('CAP19-22'!$B:$H,Equipo[[#This Row],[DESCRIPCION]],'CAP19-22'!$H:$H) -> 0 | N86: =SUMIF('CAP23-24'!$B:$H,Equipo[[#This Row],[DESCRIPCION]],'CAP23-24'!$H:$H) -> 0 | O86: =SUMIF('CAP25'!$B:$H,Equipo[[#This Row],[DESCRIPCION]],'CAP25'!$H:$H) -> 0 | P86: =SUMIF('CAP26-28'!$B:$H,Equipo[[#This Row],[DESCRIPCION]],'CAP26-28'!$H:$H) -> 0 | Q86: =SUMIF('CAP29'!$B:$H,Equipo[[#This Row],[DESCRIPCION]],'CAP29'!$H:$H) -> 0 | T86: 107100
A87: Toma de densidades | B87: Un | C87: =T87*$T$4 -> 41203.05 | D87: =IF(Equipo[[#This Row],[VALOR]]=0,Equipo[[#This Row],[TOTAL]],E87/C87) -> 0 | E87: =SUM(Equipo[[#This Row],[CAP1]:[CAP29]]) -> 0 | F87: =SUMIF('CAP1-3'!$B:$H,Equipo[[#This Row],[DESCRIPCION]],'CAP1-3'!$H:$H) -> 0 | G87: =SUMIF('CAP4-5'!$B:$H,Equipo[[#This Row],[DESCRIPCION]],'CAP4-5'!$H:$H) -> 0 | H87: =SUMIF('CAP6-7'!$B:$H,Equipo[[#This Row],[DESCRIPCION]],'CAP6-7'!$H:$H) -> 0 | I87: =SUMIF('CAP8'!$B:$H,Equipo[[#This Row],[DESCRIPCION]],'CAP8'!$H:$H) -> 0 | J87: =SUMIF('CAP9-13'!$B:$H,Equipo[[#This Row],[DESCRIPCION]],'CAP9-13'!$H:$H) -> 0 | K87: =SUMIF('CAP14-15'!$B:$H,Equipo[[#This Row],[DESCRIPCION]],'CAP14-15'!$H:$H) -> 0 | L87: =SUMIF('CAP16-18'!$B:$H,Equipo[[#This Row],[DESCRIPCION]],'CAP16-18'!$H:$H) -> 0 | M87: =SUMIF('CAP19-22'!$B:$H,Equipo[[#This Row],[DESCRIPCION]],'CAP19-22'!$H:$H) -> 0 | N87: =SUMIF('CAP23-24'!$B:$H,Equipo[[#This Row],[DESCRIPCION]],'CAP23-24'!$H:$H) -> 0 | O87: =SUMIF('CAP25'!$B:$H,Equipo[[#This Row],[DESCRIPCION]],'CAP25'!$H:$H) -> 0 | P87: =SUMIF('CAP26-28'!$B:$H,Equipo[[#This Row],[DESCRIPCION]],'CAP26-28'!$H:$H) -> 0 | Q87: =SUMIF('CAP29'!$B:$H,Equipo[[#This Row],[DESCRIPCION]],'CAP29'!$H:$H) -> 0 | T87: 39241
A88: Vibrador eléctrico o a gasolina | B88: Día | C88: =T88*$T$4 -> 56524.65 | D88: =IF(Equipo[[#This Row],[VALOR]]=0,Equipo[[#This Row],[TOTAL]],E88/C88) -> 0 | E88: =SUM(Equipo[[#This Row],[CAP1]:[CAP29]]) -> 0 | F88: =SUMIF('CAP1-3'!$B:$H,Equipo[[#This Row],[DESCRIPCION]],'CAP1-3'!$H:$H) -> 0 | G88: =SUMIF('CAP4-5'!$B:$H,Equipo[[#This Row],[DESCRIPCION]],'CAP4-5'!$H:$H) -> 0 | H88: =SUMIF('CAP6-7'!$B:$H,Equipo[[#This Row],[DESCRIPCION]],'CAP6-7'!$H:$H) -> 0 | I88: =SUMIF('CAP8'!$B:$H,Equipo[[#This Row],[DESCRIPCION]],'CAP8'!$H:$H) -> 0 | J88: =SUMIF('CAP9-13'!$B:$H,Equipo[[#This Row],[DESCRIPCION]],'CAP9-13'!$H:$H) -> 0 | K88: =SUMIF('CAP14-15'!$B:$H,Equipo[[#This Row],[DESCRIPCION]],'CAP14-15'!$H:$H) -> 0 | L88: =SUMIF('CAP16-18'!$B:$H,Equipo[[#This Row],[DESCRIPCION]],'CAP16-18'!$H:$H) -> 0 | M88: =SUMIF('CAP19-22'!$B:$H,Equipo[[#This Row],[DESCRIPCION]],'CAP19-22'!$H:$H) -> 0 | N88: =SUMIF('CAP23-24'!$B:$H,Equipo[[#This Row],[DESCRIPCION]],'CAP23-24'!$H:$H) -> 0 | O88: =SUMIF('CAP25'!$B:$H,Equipo[[#This Row],[DESCRIPCION]],'CAP25'!$H:$H) -> 0 | P88: =SUMIF('CAP26-28'!$B:$H,Equipo[[#This Row],[DESCRIPCION]],'CAP26-28'!$H:$H) -> 0 | Q88: =SUMIF('CAP29'!$B:$H,Equipo[[#This Row],[DESCRIPCION]],'CAP29'!$H:$H) -> 0 | T88: 53833
A89: Vibrocompactador manual | B89: Día | C89: =T89*$T$4 -> 82467 | D89: =IF(Equipo[[#This Row],[VALOR]]=0,Equipo[[#This Row],[TOTAL]],E89/C89) -> 0 | E89: =SUM(Equipo[[#This Row],[CAP1]:[CAP29]]) -> 0 | F89: =SUMIF('CAP1-3'!$B:$H,Equipo[[#This Row],[DESCRIPCION]],'CAP1-3'!$H:$H) -> 0 | G89: =SUMIF('CAP4-5'!$B:$H,Equipo[[#This Row],[DESCRIPCION]],'CAP4-5'!$H:$H) -> 0 | H89: =SUMIF('CAP6-7'!$B:$H,Equipo[[#This Row],[DESCRIPCION]],'CAP6-7'!$H:$H) -> 0 | I89: =SUMIF('CAP8'!$B:$H,Equipo[[#This Row],[DESCRIPCION]],'CAP8'!$H:$H) -> 0 | J89: =SUMIF('CAP9-13'!$B:$H,Equipo[[#This Row],[DESCRIPCION]],'CAP9-13'!$H:$H) -> 0 | K89: =SUMIF('CAP14-15'!$B:$H,Equipo[[#This Row],[DESCRIPCION]],'CAP14-15'!$H:$H) -> 0 | L89: =SUMIF('CAP16-18'!$B:$H,Equipo[[#This Row],[DESCRIPCION]],'CAP16-18'!$H:$H) -> 0 | M89: =SUMIF('CAP19-22'!$B:$H,Equipo[[#This Row],[DESCRIPCION]],'CAP19-22'!$H:$H) -> 0 | N89: =SUMIF('CAP23-24'!$B:$H,Equipo[[#This Row],[DESCRIPCION]],'CAP23-24'!$H:$H) -> 0 | O89: =SUMIF('CAP25'!$B:$H,Equipo[[#This Row],[DESCRIPCION]],'CAP25'!$H:$H) -> 0 | P89: =SUMIF('CAP26-28'!$B:$H,Equipo[[#This Row],[DESCRIPCION]],'CAP26-28'!$H:$H) -> 0 | Q89: =SUMIF('CAP29'!$B:$H,Equipo[[#This Row],[DESCRIPCION]],'CAP29'!$H:$H) -> 0 | T89: 78540
A90: Volqueta 7 m3 | B90: Hr | C90: =T90*$T$4 -> 89250 | D90: =IF(Equipo[[#This Row],[VALOR]]=0,Equipo[[#This Row],[TOTAL]],E90/C90) -> 0 | E90: =SUM(Equipo[[#This Row],[CAP1]:[CAP29]]) -> 0 | F90: =SUMIF('CAP1-3'!$B:$H,Equipo[[#This Row],[DESCRIPCION]],'CAP1-3'!$H:$H) -> 0 | G90: =SUMIF('CAP4-5'!$B:$H,Equipo[[#This Row],[DESCRIPCION]],'CAP4-5'!$H:$H) -> 0 | H90: =SUMIF('CAP6-7'!$B:$H,Equipo[[#This Row],[DESCRIPCION]],'CAP6-7'!$H:$H) -> 0 | I90: =SUMIF('CAP8'!$B:$H,Equipo[[#This Row],[DESCRIPCION]],'CAP8'!$H:$H) -> 0 | J90: =SUMIF('CAP9-13'!$B:$H,Equipo[[#This Row],[DESCRIPCION]],'CAP9-13'!$H:$H) -> 0 | K90: =SUMIF('CAP14-15'!$B:$H,Equipo[[#This Row],[DESCRIPCION]],'CAP14-15'!$H:$H) -> 0 | L90: =SUMIF('CAP16-18'!$B:$H,Equipo[[#This Row],[DESCRIPCION]],'CAP16-18'!$H:$H) -> 0 | M90: =SUMIF('CAP19-22'!$B:$H,Equipo[[#This Row],[DESCRIPCION]],'CAP19-22'!$H:$H) -> 0 | N90: =SUMIF('CAP23-24'!$B:$H,Equipo[[#This Row],[DESCRIPCION]],'CAP23-24'!$H:$H) -> 0 | O90: =SUMIF('CAP25'!$B:$H,Equipo[[#This Row],[DESCRIPCION]],'CAP25'!$H:$H) -> 0 | P90: =SUMIF('CAP26-28'!$B:$H,Equipo[[#This Row],[DESCRIPCION]],'CAP26-28'!$H:$H) -> 0 | Q90: =SUMIF('CAP29'!$B:$H,Equipo[[#This Row],[DESCRIPCION]],'CAP29'!$H:$H) -> 0 | T90: 85000
A91: Total | E91: =SUBTOTAL(109,Equipo[TOTAL]) -> 5114812.5 | F91: =SUBTOTAL(109,Equipo[CAP1]) -> 5114812.5 | G91: =SUBTOTAL(109,Equipo[CAP4]) -> 0 | H91: =SUBTOTAL(109,Equipo[CAP6]) -> 0 | I91: =SUBTOTAL(109,Equipo[CAP8]) -> 0 | J91: =SUBTOTAL(109,Equipo[CAP9]) -> 0 | K91: =SUBTOTAL(109,Equipo[CAP14]) -> 0 | L91: =SUBTOTAL(109,Equipo[CAP17]) -> 0 | M91: =SUBTOTAL(109,Equipo[CAP19]) -> 0 | N91: =SUBTOTAL(109,Equipo[CAP23]) -> 0 | O91: =SUBTOTAL(109,Equipo[CAP25]) -> 0 | P91: =SUBTOTAL(109,Equipo[CAP26]) -> 0 | Q91: =SUBTOTAL(109,Equipo[CAP29]) -> 0

Sheet Transporte
A1: =Presupuesto!A1 -> ALCALDIA DE PEREIRA
A2: =Presupuesto!A2 -> VERSION O BASE DE DATOS ALCALDIA DE PEREIRA 2026
A3: LISTA TARIFAS DE TRANSPORTE
A4: DESCRIPCION | B4: UND | C4: VALOR | D4: CANTIDAD | E4: TOTAL | F4: CAP1 | G4: CAP4 | H4: CAP6 | I4: CAP8 | J4: CAP9 | K4: CAP14 | L4: CAP17 | M4: CAP19 | N4: CAP23 | O4: CAP25 | P4: CAP26 | Q4: CAP29 | T4: 1.05
A5: Camabaja | B5: Hr | C5: =T5*$T$4 -> 266826 | D5: =IF(Transporte[[#This Row],[VALOR]]=0,0,E5/C5) -> 0 | E5: =SUM(Transporte[[#This Row],[CAP1]:[CAP29]]) -> 0 | F5: =SUMIF('CAP1-3'!$B:$H,Transporte[[#This Row],[DESCRIPCION]],'CAP1-3'!$H:$H) -> 0 | G5: =SUMIF('CAP4-5'!$B:$H,Transporte[[#This Row],[DESCRIPCION]],'CAP4-5'!$H:$H) -> 0 | H5: =SUMIF('CAP6-7'!$B:$H,Transporte[[#This Row],[DESCRIPCION]],'CAP6-7'!$H:$H) -> 0 | I5: =SUMIF('CAP8'!$B:$H,Transporte[[#This Row],[DESCRIPCION]],'CAP8'!$H:$H) -> 0 | J5: =SUMIF('CAP9-13'!$B:$H,Transporte[[#This Row],[DESCRIPCION]],'CAP9-13'!$H:$H) -> 0 | K5: =SUMIF('CAP14-15'!$B:$H,Transporte[[#This Row],[DESCRIPCION]],'CAP14-15'!$H:$H) -> 0 | L5: =SUMIF('CAP16-18'!$B:$H,Transporte[[#This Row],[DESCRIPCION]],'CAP16-18'!$H:$H) -> 0 | M5: =SUMIF('CAP19-22'!$B:$H,Transporte[[#This Row],[DESCRIPCION]],'CAP19-22'!$H:$H) -> 0 | N5: =SUMIF('CAP23-24'!$B:$H,Transporte[[#This Row],[DESCRIPCION]],'CAP23-24'!$H:$H) -> 0 | O5: =SUMIF('CAP25'!$B:$H,Transporte[[#This Row],[DESCRIPCION]],'CAP25'!$H:$H) -> 0 | P5: =SUMIF('CAP26-28'!$B:$H,Transporte[[#This Row],[DESCRIPCION]],'CAP26-28'!$H:$H) -> 0 | Q5: =SUMIF('CAP29'!$B:$H,Transporte[[#This Row],[DESCRIPCION]],'CAP29'!$H:$H) -> 0 | T5: 254120
A6: Camión 350 | B6: Hr | C6: =T6*$T$4 -> 79109.1 | D6: =IF(Transporte[[#This Row],[VALOR]]=0,0,E6/C6) -> 0 | E6: =SUM(Transporte[[#This Row],[CAP1]:[CAP29]]) -> 0 | F6: =SUMIF('CAP1-3'!$B:$H,Transporte[[#This Row],[DESCRIPCION]],'CAP1-3'!$H:$H) -> 0 | G6: =SUMIF('CAP4-5'!$B:$H,Transporte[[#This Row],[DESCRIPCION]],'CAP4-5'!$H:$H) -> 0 | H6: =SUMIF('CAP6-7'!$B:$H,Transporte[[#This Row],[DESCRIPCION]],'CAP6-7'!$H:$H) -> 0 | I6: =SUMIF('CAP8'!$B:$H,Transporte[[#This Row],[DESCRIPCION]],'CAP8'!$H:$H) -> 0 | J6: =SUMIF('CAP9-13'!$B:$H,Transporte[[#This Row],[DESCRIPCION]],'CAP9-13'!$H:$H) -> 0 | K6: =SUMIF('CAP14-15'!$B:$H,Transporte[[#This Row],[DESCRIPCION]],'CAP14-15'!$H:$H) -> 0 | L6: =SUMIF('CAP16-18'!$B:$H,Transporte[[#This Row],[DESCRIPCION]],'CAP16-18'!$H:$H) -> 0 | M6: =SUMIF('CAP19-22'!$B:$H,Transporte[[#This Row],[DESCRIPCION]],'CAP19-22'!$H:$H) -> 0 | N6: =SUMIF('CAP23-24'!$B:$H,Transporte[[#This Row],[DESCRIPCION]],'CAP23-24'!$H:$H) -> 0 | O6: =SUMIF('CAP25'!$B:$H,Transporte[[#This Row],[DESCRIPCION]],'CAP25'!$H:$H) -> 0 | P6: =SUMIF('CAP26-28'!$B:$H,Transporte[[#This Row],[DESCRIPCION]],'CAP26-28'!$H:$H) -> 0 | Q6: =SUMIF('CAP29'!$B:$H,Transporte[[#This Row],[DESCRIPCION]],'CAP29'!$H:$H) -> 0 | T6: 75342
A7: Camioneta | B7: Hr | C7: =T7*$T$4 -> 36118.95 | D7: =IF(Transporte[[#This Row],[VALOR]]=0,0,E7/C7) -> 0 | E7: =SUM(Transporte[[#This Row],[CAP1]:[CAP29]]) -> 0 | F7: =SUMIF('CAP1-3'!$B:$H,Transporte[[#This Row],[DESCRIPCION]],'CAP1-3'!$H:$H) -> 0 | G7: =SUMIF('CAP4-5'!$B:$H,Transporte[[#This Row],[DESCRIPCION]],'CAP4-5'!$H:$H) -> 0 | H7: =SUMIF('CAP6-7'!$B:$H,Transporte[[#This Row],[DESCRIPCION]],'CAP6-7'!$H:$H) -> 0 | I7: =SUMIF('CAP8'!$B:$H,Transporte[[#This Row],[DESCRIPCION]],'CAP8'!$H:$H) -> 0 | J7: =SUMIF('CAP9-13'!$B:$H,Transporte[[#This Row],[DESCRIPCION]],'CAP9-13'!$H:$H) -> 0 | K7: =SUMIF('CAP14-15'!$B:$H,Transporte[[#This Row],[DESCRIPCION]],'CAP14-15'!$H:$H) -> 0 | L7: =SUMIF('CAP16-18'!$B:$H,Transporte[[#This Row],[DESCRIPCION]],'CAP16-18'!$H:$H) -> 0 | M7: =SUMIF('CAP19-22'!$B:$H,Transporte[[#This Row],[DESCRIPCION]],'CAP19-22'!$H:$H) -> 0 | N7: =SUMIF('CAP23-24'!$B:$H,Transporte[[#This Row],[DESCRIPCION]],'CAP23-24'!$H:$H) -> 0 | O7: =SUMIF('CAP25'!$B:$H,Transporte[[#This Row],[DESCRIPCION]],'CAP25'!$H:$H) -> 0 | P7: =SUMIF('CAP26-28'!$B:$H,Transporte[[#This Row],[DESCRIPCION]],'CAP26-28'!$H:$H) -> 0 | Q7: =SUMIF('CAP29'!$B:$H,Transporte[[#This Row],[DESCRIPCION]],'CAP29'!$H:$H) -> 0 | T7: 34399
A8: Transporte materiales petreos | B8: M3-km | C8: =T8*$T$4 -> 1534.05 | D8: =IF(Transporte[[#This Row],[VALOR]]=0,0,E8/C8) -> 0 | E8: =SUM(Transporte[[#This Row],[CAP1]:[CAP29]]) -> 0 | F8: =SUMIF('CAP1-3'!$B:$H,Transporte[[#This Row],[DESCRIPCION]],'CAP1-3'!$H:$H) -> 0 | G8: =SUMIF('CAP4-5'!$B:$H,Transporte[[#This Row],[DESCRIPCION]],'CAP4-5'!$H:$H) -> 0 | H8: =SUMIF('CAP6-7'!$B:$H,Transporte[[#This Row],[DESCRIPCION]],'CAP6-7'!$H:$H) -> 0 | I8: =SUMIF('CAP8'!$B:$H,Transporte[[#This Row],[DESCRIPCION]],'CAP8'!$H:$H) -> 0 | J8: =SUMIF('CAP9-13'!$B:$H,Transporte[[#This Row],[DESCRIPCION]],'CAP9-13'!$H:$H) -> 0 | K8: =SUMIF('CAP14-15'!$B:$H,Transporte[[#This Row],[DESCRIPCION]],'CAP14-15'!$H:$H) -> 0 | L8: =SUMIF('CAP16-18'!$B:$H,Transporte[[#This Row],[DESCRIPCION]],'CAP16-18'!$H:$H) -> 0 | M8: =SUMIF('CAP19-22'!$B:$H,Transporte[[#This Row],[DESCRIPCION]],'CAP19-22'!$H:$H) -> 0 | N8: =SUMIF('CAP23-24'!$B:$H,Transporte[[#This Row],[DESCRIPCION]],'CAP23-24'!$H:$H) -> 0 | O8: =SUMIF('CAP25'!$B:$H,Transporte[[#This Row],[DESCRIPCION]],'CAP25'!$H:$H) -> 0 | P8: =SUMIF('CAP26-28'!$B:$H,Transporte[[#This Row],[DESCRIPCION]],'CAP26-28'!$H:$H) -> 0 | Q8: =SUMIF('CAP29'!$B:$H,Transporte[[#This Row],[DESCRIPCION]],'CAP29'!$H:$H) -> 0 | T8: 1461
A9: Transporte maquinaría pesada | B9: Km | C9: =T9*$T$4 -> 34010.55 | D9: =IF(Transporte[[#This Row],[VALOR]]=0,0,E9/C9) -> 0 | E9: =SUM(Transporte[[#This Row],[CAP1]:[CAP29]]) -> 0 | F9: =SUMIF('CAP1-3'!$B:$H,Transporte[[#This Row],[DESCRIPCION]],'CAP1-3'!$H:$H) -> 0 | G9: =SUMIF('CAP4-5'!$B:$H,Transporte[[#This Row],[DESCRIPCION]],'CAP4-5'!$H:$H) -> 0 | H9: =SUMIF('CAP6-7'!$B:$H,Transporte[[#This Row],[DESCRIPCION]],'CAP6-7'!$H:$H) -> 0 | I9: =SUMIF('CAP8'!$B:$H,Transporte[[#This Row],[DESCRIPCION]],'CAP8'!$H:$H) -> 0 | J9: =SUMIF('CAP9-13'!$B:$H,Transporte[[#This Row],[DESCRIPCION]],'CAP9-13'!$H:$H) -> 0 | K9: =SUMIF('CAP14-15'!$B:$H,Transporte[[#This Row],[DESCRIPCION]],'CAP14-15'!$H:$H) -> 0 | L9: =SUMIF('CAP16-18'!$B:$H,Transporte[[#This Row],[DESCRIPCION]],'CAP16-18'!$H:$H) -> 0 | M9: =SUMIF('CAP19-22'!$B:$H,Transporte[[#This Row],[DESCRIPCION]],'CAP19-22'!$H:$H) -> 0 | N9: =SUMIF('CAP23-24'!$B:$H,Transporte[[#This Row],[DESCRIPCION]],'CAP23-24'!$H:$H) -> 0 | O9: =SUMIF('CAP25'!$B:$H,Transporte[[#This Row],[DESCRIPCION]],'CAP25'!$H:$H) -> 0 | P9: =SUMIF('CAP26-28'!$B:$H,Transporte[[#This Row],[DESCRIPCION]],'CAP26-28'!$H:$H) -> 0 | Q9: =SUMIF('CAP29'!$B:$H,Transporte[[#This Row],[DESCRIPCION]],'CAP29'!$H:$H) -> 0 | T9: 32391
A10: Total | E10: =SUBTOTAL(109,Transporte[TOTAL]) -> 0 | F10: =SUBTOTAL(109,Transporte[CAP1]) -> 0 | G10: =SUBTOTAL(109,Transporte[CAP4]) -> 0 | H10: =SUBTOTAL(109,Transporte[CAP6]) -> 0 | I10: =SUBTOTAL(109,Transporte[CAP8]) -> 0 | J10: =SUBTOTAL(109,Transporte[CAP9]) -> 0 | K10: =SUBTOTAL(109,Transporte[CAP14]) -> 0 | L10: =SUBTOTAL(109,Transporte[CAP17]) -> 0 | M10: =SUBTOTAL(109,Transporte[CAP19]) -> 0 | N10: =SUBTOTAL(109,Transporte[CAP23]) -> 0 | O10: =SUBTOTAL(109,Transporte[CAP25]) -> 0 | P10: =SUBTOTAL(109,Transporte[CAP26]) -> 0 | Q10: =SUBTOTAL(109,Transporte[CAP29]) -> 0

Sheet Mano de obra
B1: =Presupuesto!A1 -> ALCALDIA DE PEREIRA
B2: =Presupuesto!A2 -> VERSION O BASE DE DATOS ALCALDIA DE PEREIRA 2026
B3: ANALISIS DE PRESTACIONES SOCIALES
B4: AÑOS | D4: 2026
B5: SMLMV: | D5: 1750905
B6: SUBSIDIO TRANSPORTE | D6: 249095
B7: DIAS LABORALES MES | D7: 25
B8: HORAS LABORALES POR DIA | D8: 7
B10: DETALLE | C10: Personal < 2 SMMV | D10: Personal > 2 SMMV
B11: SALARIO | C11: 1 | D11: 1
B12: CESANTIAS | C12: 0.0833 | D12: 0.0833
B13: VACACIONES | C13: 0.0417 | D13: 0.0417
B14: PRIMA DE SERVICIOS | C14: 0.0833 | D14: 0.0833
B15: INTERESES A LAS CESANTIAS | C15: 0.01 | D15: 0.01
B16: SUBSIDIO DE TRANSPORTE | C16: =ROUND(D6/D5,4) -> 0.1423
B17: APORTES SALUD | C17: 0.085 | D17: 0.085
B18: APORTES RIESGOS PROFESIONALES | C18: 0.0696 | D18: 0.0696
B19: APORTES PENSION | C19: 0.12 | D19: 0.12
B20: ICBF | C20: 0 | D20: 0
B21: SENA | C21: 0 | D21: 0
B22: APORTE CCF | C22: 0.04 | D22: 0.04
B23: FIC | C23: 0.025 | D23: 0.025
B24: DOTACION DE LABOR | C24: 0.0559
B25: INCREMENTO TEMPORAL POR EVENTO DEL SISMO | C25: 0.1 | D25: 0.1
B26: AJUSTE JORNADA LABORAL | C26: 0.1163 | D26: 0.1163
B27: SERVICIOS MEDICOS POR PRIMER MES | C27: 0.0017 | D27: 0.0017
B28: EXAMENES MEDICOS DE INGRESO | C28: 0.021 | D28: 0.021
B29: TOTAL PRESTACIONES SOCIALES | C29: =SUM(C11:C28) -> 1.9951 | D29: =SUM(D11:D28) -> 1.7969
B31: DESCRIPCION | C31: UN | D31: VALOR UNIT | E31: TOTAL | F31: CAP1 | G31: CAP4 | H31: CAP6 | I31: CAP8 | J31: CAP9 | K31: CAP14 | L31: CAP17 | M31: CAP19 | N31: CAP23 | O31: CAP25 | P31: CAP26 | Q31: CAP29
B32: VALORES INCLUYENDO PRESTACIONES | E32: =SUM(MObra[[#This Row],[CAP1]:[CAP29]]) -> 0
B33: Ayudante (jornal + prestaciones) | C33: día | D33: =$D$5*$C$29/30 -> 116441.02 | E33: =SUM(MObra[[#This Row],[CAP1]:[CAP29]]) -> 0 | F33: =SUMIF('CAP1-3'!$B:$H,MObra[[#This Row],[DESCRIPCION]],'CAP1-3'!$H:$H) -> 0 | G33: =SUMIF('CAP4-5'!$B:$H,MObra[[#This Row],[DESCRIPCION]],'CAP4-5'!$H:$H) -> 0 | H33: =SUMIF('CAP6-7'!$B:$H,MObra[[#This Row],[DESCRIPCION]],'CAP6-7'!$H:$H) -> 0 | I33: =SUMIF('CAP8'!$B:$H,MObra[[#This Row],[DESCRIPCION]],'CAP8'!$H:$H) -> 0 | J33: =SUMIF('CAP9-13'!$B:$H,MObra[[#This Row],[DESCRIPCION]],'CAP9-13'!$H:$H) -> 0 | K33: =SUMIF('CAP14-15'!$B:$H,MObra[[#This Row],[DESCRIPCION]],'CAP14-15'!$H:$H) -> 0 | L33: =SUMIF('CAP16-18'!$B:$H,MObra[[#This Row],[DESCRIPCION]],'CAP16-18'!$H:$H) -> 0 | M33: =SUMIF('CAP19-22'!$B:$H,MObra[[#This Row],[DESCRIPCION]],'CAP19-22'!$H:$H) -> 0 | N33: =SUMIF('CAP23-24'!$B:$H,MObra[[#This Row],[DESCRIPCION]],'CAP23-24'!$H:$H) -> 0 | O33: =SUMIF('CAP25'!$B:$H,MObra[[#This Row],[DESCRIPCION]],'CAP25'!$H:$H) -> 0 | P33: =SUMIF('CAP26-28'!$B:$H,MObra[[#This Row],[DESCRIPCION]],'CAP26-28'!$H:$H) -> 0 | Q33: =SUMIF('CAP29'!$B:$H,MObra[[#This Row],[DESCRIPCION]],'CAP29'!$H:$H) -> 0
B34: Ayudante eléctrico (jornal + prestaciones) | C34: día | D34: =$D$5*$C$29/30*1.1 -> 128085.12 | E34: =SUM(MObra[[#This Row],[CAP1]:[CAP29]]) -> 0 | F34: =SUMIF('CAP1-3'!$B:$H,MObra[[#This Row],[DESCRIPCION]],'CAP1-3'!$H:$H) -> 0 | G34: =SUMIF('CAP4-5'!$B:$H,MObra[[#This Row],[DESCRIPCION]],'CAP4-5'!$H:$H) -> 0 | H34: =SUMIF('CAP6-7'!$B:$H,MObra[[#This Row],[DESCRIPCION]],'CAP6-7'!$H:$H) -> 0 | I34: =SUMIF('CAP8'!$B:$H,MObra[[#This Row],[DESCRIPCION]],'CAP8'!$H:$H) -> 0 | J34: =SUMIF('CAP9-13'!$B:$H,MObra[[#This Row],[DESCRIPCION]],'CAP9-13'!$H:$H) -> 0 | K34: =SUMIF('CAP14-15'!$B:$H,MObra[[#This Row],[DESCRIPCION]],'CAP14-15'!$H:$H) -> 0 | L34: =SUMIF('CAP16-18'!$B:$H,MObra[[#This Row],[DESCRIPCION]],'CAP16-18'!$H:$H) -> 0 | M34: =SUMIF('CAP19-22'!$B:$H,MObra[[#This Row],[DESCRIPCION]],'CAP19-22'!$H:$H) -> 0 | N34: =SUMIF('CAP23-24'!$B:$H,MObra[[#This Row],[DESCRIPCION]],'CAP23-24'!$H:$H) -> 0 | O34: =SUMIF('CAP25'!$B:$H,MObra[[#This Row],[DESCRIPCION]],'CAP25'!$H:$H) -> 0 | P34: =SUMIF('CAP26-28'!$B:$H,MObra[[#This Row],[DESCRIPCION]],'CAP26-28'!$H:$H) -> 0 | Q34: =SUMIF('CAP29'!$B:$H,MObra[[#This Row],[DESCRIPCION]],'CAP29'!$H:$H) -> 0
B35: Ayudante práctico (jornal + prestaciones) | C35: día | D35: =$D$5*$C$29/30*1.1 -> 128085.12 | E35: =SUM(MObra[[#This Row],[CAP1]:[CAP29]]) -> 0 | F35: =SUMIF('CAP1-3'!$B:$H,MObra[[#This Row],[DESCRIPCION]],'CAP1-3'!$H:$H) -> 0 | G35: =SUMIF('CAP4-5'!$B:$H,MObra[[#This Row],[DESCRIPCION]],'CAP4-5'!$H:$H) -> 0 | H35: =SUMIF('CAP6-7'!$B:$H,MObra[[#This Row],[DESCRIPCION]],'CAP6-7'!$H:$H) -> 0 | I35: =SUMIF('CAP8'!$B:$H,MObra[[#This Row],[DESCRIPCION]],'CAP8'!$H:$H) -> 0 | J35: =SUMIF('CAP9-13'!$B:$H,MObra[[#This Row],[DESCRIPCION]],'CAP9-13'!$H:$H) -> 0 | K35: =SUMIF('CAP14-15'!$B:$H,MObra[[#This Row],[DESCRIPCION]],'CAP14-15'!$H:$H) -> 0 | L35: =SUMIF('CAP16-18'!$B:$H,MObra[[#This Row],[DESCRIPCION]],'CAP16-18'!$H:$H) -> 0 | M35: =SUMIF('CAP19-22'!$B:$H,MObra[[#This Row],[DESCRIPCION]],'CAP19-22'!$H:$H) -> 0 | N35: =SUMIF('CAP23-24'!$B:$H,MObra[[#This Row],[DESCRIPCION]],'CAP23-24'!$H:$H) -> 0 | O35: =SUMIF('CAP25'!$B:$H,MObra[[#This Row],[DESCRIPCION]],'CAP25'!$H:$H) -> 0 | P35: =SUMIF('CAP26-28'!$B:$H,MObra[[#This Row],[DESCRIPCION]],'CAP26-28'!$H:$H) -> 0 | Q35: =SUMIF('CAP29'!$B:$H,MObra[[#This Row],[DESCRIPCION]],'CAP29'!$H:$H) -> 0
B36: Cadenero 1o (jornal + prestaciones) | C36: día | D36: =$D$5*$C$29/30*1.1 -> 128085.12 | E36: =SUM(MObra[[#This Row],[CAP1]:[CAP29]]) -> 0 | F36: =SUMIF('CAP1-3'!$B:$H,MObra[[#This Row],[DESCRIPCION]],'CAP1-3'!$H:$H) -> 0 | G36: =SUMIF('CAP4-5'!$B:$H,MObra[[#This Row],[DESCRIPCION]],'CAP4-5'!$H:$H) -> 0 | H36: =SUMIF('CAP6-7'!$B:$H,MObra[[#This Row],[DESCRIPCION]],'CAP6-7'!$H:$H) -> 0 | I36: =SUMIF('CAP8'!$B:$H,MObra[[#This Row],[DESCRIPCION]],'CAP8'!$H:$H) -> 0 | J36: =SUMIF('CAP9-13'!$B:$H,MObra[[#This Row],[DESCRIPCION]],'CAP9-13'!$H:$H) -> 0 | K36: =SUMIF('CAP14-15'!$B:$H,MObra[[#This Row],[DESCRIPCION]],'CAP14-15'!$H:$H) -> 0 | L36: =SUMIF('CAP16-18'!$B:$H,MObra[[#This Row],[DESCRIPCION]],'CAP16-18'!$H:$H) -> 0 | M36: =SUMIF('CAP19-22'!$B:$H,MObra[[#This Row],[DESCRIPCION]],'CAP19-22'!$H:$H) -> 0 | N36: =SUMIF('CAP23-24'!$B:$H,MObra[[#This Row],[DESCRIPCION]],'CAP23-24'!$H:$H) -> 0 | O36: =SUMIF('CAP25'!$B:$H,MObra[[#This Row],[DESCRIPCION]],'CAP25'!$H:$H) -> 0 | P36: =SUMIF('CAP26-28'!$B:$H,MObra[[#This Row],[DESCRIPCION]],'CAP26-28'!$H:$H) -> 0 | Q36: =SUMIF('CAP29'!$B:$H,MObra[[#This Row],[DESCRIPCION]],'CAP29'!$H:$H) -> 0
B37: Cadenero 2o (jornal + prestaciones) | C37: día | D37: =$D$5*$C$29/30*1 -> 116441.02 | E37: =SUM(MObra[[#This Row],[CAP1]:[CAP29]]) -> 0 | F37: =SUMIF('CAP1-3'!$B:$H,MObra[[#This Row],[DESCRIPCION]],'CAP1-3'!$H:$H) -> 0 | G37: =SUMIF('CAP4-5'!$B:$H,MObra[[#This Row],[DESCRIPCION]],'CAP4-5'!$H:$H) -> 0 | H37: =SUMIF('CAP6-7'!$B:$H,MObra[[#This Row],[DESCRIPCION]],'CAP6-7'!$H:$H) -> 0 | I37: =SUMIF('CAP8'!$B:$H,MObra[[#This Row],[DESCRIPCION]],'CAP8'!$H:$H) -> 0 | J37: =SUMIF('CAP9-13'!$B:$H,MObra[[#This Row],[DESCRIPCION]],'CAP9-13'!$H:$H) -> 0 | K37: =SUMIF('CAP14-15'!$B:$H,MObra[[#This Row],[DESCRIPCION]],'CAP14-15'!$H:$H) -> 0 | L37: =SUMIF('CAP16-18'!$B:$H,MObra[[#This Row],[DESCRIPCION]],'CAP16-18'!$H:$H) -> 0 | M37: =SUMIF('CAP19-22'!$B:$H,MObra[[#This Row],[DESCRIPCION]],'CAP19-22'!$H:$H) -> 0 | N37: =SUMIF('CAP23-24'!$B:$H,MObra[[#This Row],[DESCRIPCION]],'CAP23-24'!$H:$H) -> 0 | O37: =SUMIF('CAP25'!$B:$H,MObra[[#This Row],[DESCRIPCION]],'CAP25'!$H:$H) -> 0 | P37: =SUMIF('CAP26-28'!$B:$H,MObra[[#This Row],[DESCRIPCION]],'CAP26-28'!$H:$H) -> 0 | Q37: =SUMIF('CAP29'!$B:$H,MObra[[#This Row],[DESCRIPCION]],'CAP29'!$H:$H) -> 0
B38: Controlador trafico (Mes + prestaciones) | C38: día | D38: =$D$5*$C$29/30*1.13 -> 131578.35 | E38: =SUM(MObra[[#This Row],[CAP1]:[CAP29]]) -> 0 | F38: =SUMIF('CAP1-3'!$B:$H,MObra[[#This Row],[DESCRIPCION]],'CAP1-3'!$H:$H) -> 0 | G38: =SUMIF('CAP4-5'!$B:$H,MObra[[#This Row],[DESCRIPCION]],'CAP4-5'!$H:$H) -> 0 | H38: =SUMIF('CAP6-7'!$B:$H,MObra[[#This Row],[DESCRIPCION]],'CAP6-7'!$H:$H) -> 0 | I38: =SUMIF('CAP8'!$B:$H,MObra[[#This Row],[DESCRIPCION]],'CAP8'!$H:$H) -> 0 | J38: =SUMIF('CAP9-13'!$B:$H,MObra[[#This Row],[DESCRIPCION]],'CAP9-13'!$H:$H) -> 0 | K38: =SUMIF('CAP14-15'!$B:$H,MObra[[#This Row],[DESCRIPCION]],'CAP14-15'!$H:$H) -> 0 | L38: =SUMIF('CAP16-18'!$B:$H,MObra[[#This Row],[DESCRIPCION]],'CAP16-18'!$H:$H) -> 0 | M38: =SUMIF('CAP19-22'!$B:$H,MObra[[#This Row],[DESCRIPCION]],'CAP19-22'!$H:$H) -> 0 | N38: =SUMIF('CAP23-24'!$B:$H,MObra[[#This Row],[DESCRIPCION]],'CAP23-24'!$H:$H) -> 0 | O38: =SUMIF('CAP25'!$B:$H,MObra[[#This Row],[DESCRIPCION]],'CAP25'!$H:$H) -> 0 | P38: =SUMIF('CAP26-28'!$B:$H,MObra[[#This Row],[DESCRIPCION]],'CAP26-28'!$H:$H) -> 0 | Q38: =SUMIF('CAP29'!$B:$H,MObra[[#This Row],[DESCRIPCION]],'CAP29'!$H:$H) -> 0
B39: Oficial (jornal + prestaciones) | C39: día | D39: =$D$5*$C$29/30*1.7 -> 197949.73 | E39: =SUM(MObra[[#This Row],[CAP1]:[CAP29]]) -> 0 | F39: =SUMIF('CAP1-3'!$B:$H,MObra[[#This Row],[DESCRIPCION]],'CAP1-3'!$H:$H) -> 0 | G39: =SUMIF('CAP4-5'!$B:$H,MObra[[#This Row],[DESCRIPCION]],'CAP4-5'!$H:$H) -> 0 | H39: =SUMIF('CAP6-7'!$B:$H,MObra[[#This Row],[DESCRIPCION]],'CAP6-7'!$H:$H) -> 0 | I39: =SUMIF('CAP8'!$B:$H,MObra[[#This Row],[DESCRIPCION]],'CAP8'!$H:$H) -> 0 | J39: =SUMIF('CAP9-13'!$B:$H,MObra[[#This Row],[DESCRIPCION]],'CAP9-13'!$H:$H) -> 0 | K39: =SUMIF('CAP14-15'!$B:$H,MObra[[#This Row],[DESCRIPCION]],'CAP14-15'!$H:$H) -> 0 | L39: =SUMIF('CAP16-18'!$B:$H,MObra[[#This Row],[DESCRIPCION]],'CAP16-18'!$H:$H) -> 0 | M39: =SUMIF('CAP19-22'!$B:$H,MObra[[#This Row],[DESCRIPCION]],'CAP19-22'!$H:$H) -> 0 | N39: =SUMIF('CAP23-24'!$B:$H,MObra[[#This Row],[DESCRIPCION]],'CAP23-24'!$H:$H) -> 0 | O39: =SUMIF('CAP25'!$B:$H,MObra[[#This Row],[DESCRIPCION]],'CAP25'!$H:$H) -> 0 | P39: =SUMIF('CAP26-28'!$B:$H,MObra[[#This Row],[DESCRIPCION]],'CAP26-28'!$H:$H) -> 0 | Q39: =SUMIF('CAP29'!$B:$H,MObra[[#This Row],[DESCRIPCION]],'CAP29'!$H:$H) -> 0
B40: Oficial electrico (Jornal + prestaciones) | C40: día | D40: =$D$5*$C$29/30*1.8 -> 209593.83 | E40: =SUM(MObra[[#This Row],[CAP1]:[CAP29]]) -> 0 | F40: =SUMIF('CAP1-3'!$B:$H,MObra[[#This Row],[DESCRIPCION]],'CAP1-3'!$H:$H) -> 0 | G40: =SUMIF('CAP4-5'!$B:$H,MObra[[#This Row],[DESCRIPCION]],'CAP4-5'!$H:$H) -> 0 | H40: =SUMIF('CAP6-7'!$B:$H,MObra[[#This Row],[DESCRIPCION]],'CAP6-7'!$H:$H) -> 0 | I40: =SUMIF('CAP8'!$B:$H,MObra[[#This Row],[DESCRIPCION]],'CAP8'!$H:$H) -> 0 | J40: =SUMIF('CAP9-13'!$B:$H,MObra[[#This Row],[DESCRIPCION]],'CAP9-13'!$H:$H) -> 0 | K40: =SUMIF('CAP14-15'!$B:$H,MObra[[#This Row],[DESCRIPCION]],'CAP14-15'!$H:$H) -> 0 | L40: =SUMIF('CAP16-18'!$B:$H,MObra[[#This Row],[DESCRIPCION]],'CAP16-18'!$H:$H) -> 0 | M40: =SUMIF('CAP19-22'!$B:$H,MObra[[#This Row],[DESCRIPCION]],'CAP19-22'!$H:$H) -> 0 | N40: =SUMIF('CAP23-24'!$B:$H,MObra[[#This Row],[DESCRIPCION]],'CAP23-24'!$H:$H) -> 0 | O40: =SUMIF('CAP25'!$B:$H,MObra[[#This Row],[DESCRIPCION]],'CAP25'!$H:$H) -> 0 | P40: =SUMIF('CAP26-28'!$B:$H,MObra[[#This Row],[DESCRIPCION]],'CAP26-28'!$H:$H) -> 0 | Q40: =SUMIF('CAP29'!$B:$H,MObra[[#This Row],[DESCRIPCION]],'CAP29'!$H:$H) -> 0
B41: Oficial soldador (Jornal + prestaciones) | C41: día | D41: =$D$5*$C$29/30*2.5 -> 291102.55 | E41: =SUM(MObra[[#This Row],[CAP1]:[CAP29]]) -> 0 | F41: =SUMIF('CAP1-3'!$B:$H,MObra[[#This Row],[DESCRIPCION]],'CAP1-3'!$H:$H) -> 0 | G41: =SUMIF('CAP4-5'!$B:$H,MObra[[#This Row],[DESCRIPCION]],'CAP4-5'!$H:$H) -> 0 | H41: =SUMIF('CAP6-7'!$B:$H,MObra[[#This Row],[DESCRIPCION]],'CAP6-7'!$H:$H) -> 0 | I41: =SUMIF('CAP8'!$B:$H,MObra[[#This Row],[DESCRIPCION]],'CAP8'!$H:$H) -> 0 | J41: =SUMIF('CAP9-13'!$B:$H,MObra[[#This Row],[DESCRIPCION]],'CAP9-13'!$H:$H) -> 0 | K41: =SUMIF('CAP14-15'!$B:$H,MObra[[#This Row],[DESCRIPCION]],'CAP14-15'!$H:$H) -> 0 | L41: =SUMIF('CAP16-18'!$B:$H,MObra[[#This Row],[DESCRIPCION]],'CAP16-18'!$H:$H) -> 0 | M41: =SUMIF('CAP19-22'!$B:$H,MObra[[#This Row],[DESCRIPCION]],'CAP19-22'!$H:$H) -> 0 | N41: =SUMIF('CAP23-24'!$B:$H,MObra[[#This Row],[DESCRIPCION]],'CAP23-24'!$H:$H) -> 0 | O41: =SUMIF('CAP25'!$B:$H,MObra[[#This Row],[DESCRIPCION]],'CAP25'!$H:$H) -> 0 | P41: =SUMIF('CAP26-28'!$B:$H,MObra[[#This Row],[DESCRIPCION]],'CAP26-28'!$H:$H) -> 0 | Q41: =SUMIF('CAP29'!$B:$H,MObra[[#This Row],[DESCRIPCION]],'CAP29'!$H:$H) -> 0
B42: Topógrafo (jornal + prestaciones) | C42: día | D42: =$D$5*$C$29/30*2 -> 232882.04 | E42: =SUM(MObra[[#This Row],[CAP1]:[CAP29]]) -> 0 | F42: =SUMIF('CAP1-3'!$B:$H,MObra[[#This Row],[DESCRIPCION]],'CAP1-3'!$H:$H) -> 0 | G42: =SUMIF('CAP4-5'!$B:$H,MObra[[#This Row],[DESCRIPCION]],'CAP4-5'!$H:$H) -> 0 | H42: =SUMIF('CAP6-7'!$B:$H,MObra[[#This Row],[DESCRIPCION]],'CAP6-7'!$H:$H) -> 0 | I42: =SUMIF('CAP8'!$B:$H,MObra[[#This Row],[DESCRIPCION]],'CAP8'!$H:$H) -> 0 | J42: =SUMIF('CAP9-13'!$B:$H,MObra[[#This Row],[DESCRIPCION]],'CAP9-13'!$H:$H) -> 0 | K42: =SUMIF('CAP14-15'!$B:$H,MObra[[#This Row],[DESCRIPCION]],'CAP14-15'!$H:$H) -> 0 | L42: =SUMIF('CAP16-18'!$B:$H,MObra[[#This Row],[DESCRIPCION]],'CAP16-18'!$H:$H) -> 0 | M42: =SUMIF('CAP19-22'!$B:$H,MObra[[#This Row],[DESCRIPCION]],'CAP19-22'!$H:$H) -> 0 | N42: =SUMIF('CAP23-24'!$B:$H,MObra[[#This Row],[DESCRIPCION]],'CAP23-24'!$H:$H) -> 0 | O42: =SUMIF('CAP25'!$B:$H,MObra[[#This Row],[DESCRIPCION]],'CAP25'!$H:$H) -> 0 | P42: =SUMIF('CAP26-28'!$B:$H,MObra[[#This Row],[DESCRIPCION]],'CAP26-28'!$H:$H) -> 0 | Q42: =SUMIF('CAP29'!$B:$H,MObra[[#This Row],[DESCRIPCION]],'CAP29'!$H:$H) -> 0
B43: Comisión topografía (topógrafo + Cadenero 1 + 2 Cadeneros 2) | C43: día | D43: =D42+D36+D37*2 -> 593849.2 | E43: =SUM(MObra[[#This Row],[CAP1]:[CAP29]]) -> 0 | F43: =SUMIF('CAP1-3'!$B:$H,MObra[[#This Row],[DESCRIPCION]],'CAP1-3'!$H:$H) -> 0 | G43: =SUMIF('CAP4-5'!$B:$H,MObra[[#This Row],[DESCRIPCION]],'CAP4-5'!$H:$H) -> 0 | H43: =SUMIF('CAP6-7'!$B:$H,MObra[[#This Row],[DESCRIPCION]],'CAP6-7'!$H:$H) -> 0 | I43: =SUMIF('CAP8'!$B:$H,MObra[[#This Row],[DESCRIPCION]],'CAP8'!$H:$H) -> 0 | J43: =SUMIF('CAP9-13'!$B:$H,MObra[[#This Row],[DESCRIPCION]],'CAP9-13'!$H:$H) -> 0 | K43: =SUMIF('CAP14-15'!$B:$H,MObra[[#This Row],[DESCRIPCION]],'CAP14-15'!$H:$H) -> 0 | L43: =SUMIF('CAP16-18'!$B:$H,MObra[[#This Row],[DESCRIPCION]],'CAP16-18'!$H:$H) -> 0 | M43: =SUMIF('CAP19-22'!$B:$H,MObra[[#This Row],[DESCRIPCION]],'CAP19-22'!$H:$H) -> 0 | N43: =SUMIF('CAP23-24'!$B:$H,MObra[[#This Row],[DESCRIPCION]],'CAP23-24'!$H:$H) -> 0 | O43: =SUMIF('CAP25'!$B:$H,MObra[[#This Row],[DESCRIPCION]],'CAP25'!$H:$H) -> 0 | P43: =SUMIF('CAP26-28'!$B:$H,MObra[[#This Row],[DESCRIPCION]],'CAP26-28'!$H:$H) -> 0 | Q43: =SUMIF('CAP29'!$B:$H,MObra[[#This Row],[DESCRIPCION]],'CAP29'!$H:$H) -> 0
B44: Cuadrilla 1 Of + 1 Ay (jornal + prestaciones) | C44: día | D44: =$D$33*1+$D$39*1 -> 314390.75 | E44: =SUM(MObra[[#This Row],[CAP1]:[CAP29]]) -> 0 | F44: =SUMIF('CAP1-3'!$B:$H,MObra[[#This Row],[DESCRIPCION]],'CAP1-3'!$H:$H) -> 0 | G44: =SUMIF('CAP4-5'!$B:$H,MObra[[#This Row],[DESCRIPCION]],'CAP4-5'!$H:$H) -> 0 | H44: =SUMIF('CAP6-7'!$B:$H,MObra[[#This Row],[DESCRIPCION]],'CAP6-7'!$H:$H) -> 0 | I44: =SUMIF('CAP8'!$B:$H,MObra[[#This Row],[DESCRIPCION]],'CAP8'!$H:$H) -> 0 | J44: =SUMIF('CAP9-13'!$B:$H,MObra[[#This Row],[DESCRIPCION]],'CAP9-13'!$H:$H) -> 0 | K44: =SUMIF('CAP14-15'!$B:$H,MObra[[#This Row],[DESCRIPCION]],'CAP14-15'!$H:$H) -> 0 | L44: =SUMIF('CAP16-18'!$B:$H,MObra[[#This Row],[DESCRIPCION]],'CAP16-18'!$H:$H) -> 0 | M44: =SUMIF('CAP19-22'!$B:$H,MObra[[#This Row],[DESCRIPCION]],'CAP19-22'!$H:$H) -> 0 | N44: =SUMIF('CAP23-24'!$B:$H,MObra[[#This Row],[DESCRIPCION]],'CAP23-24'!$H:$H) -> 0 | O44: =SUMIF('CAP25'!$B:$H,MObra[[#This Row],[DESCRIPCION]],'CAP25'!$H:$H) -> 0 | P44: =SUMIF('CAP26-28'!$B:$H,MObra[[#This Row],[DESCRIPCION]],'CAP26-28'!$H:$H) -> 0 | Q44: =SUMIF('CAP29'!$B:$H,MObra[[#This Row],[DESCRIPCION]],'CAP29'!$H:$H) -> 0
B45: Cuadrilla 1 Of + 2 Ay (jornal + prestaciones) | C45: día | D45: =$D$33*2+$D$39*1 -> 430831.77 | E45: =SUM(MObra[[#This Row],[CAP1]:[CAP29]]) -> 0 | F45: =SUMIF('CAP1-3'!$B:$H,MObra[[#This Row],[DESCRIPCION]],'CAP1-3'!$H:$H) -> 0 | G45: =SUMIF('CAP4-5'!$B:$H,MObra[[#This Row],[DESCRIPCION]],'CAP4-5'!$H:$H) -> 0 | H45: =SUMIF('CAP6-7'!$B:$H,MObra[[#This Row],[DESCRIPCION]],'CAP6-7'!$H:$H) -> 0 | I45: =SUMIF('CAP8'!$B:$H,MObra[[#This Row],[DESCRIPCION]],'CAP8'!$H:$H) -> 0 | J45: =SUMIF('CAP9-13'!$B:$H,MObra[[#This Row],[DESCRIPCION]],'CAP9-13'!$H:$H) -> 0 | K45: =SUMIF('CAP14-15'!$B:$H,MObra[[#This Row],[DESCRIPCION]],'CAP14-15'!$H:$H) -> 0 | L45: =SUMIF('CAP16-18'!$B:$H,MObra[[#This Row],[DESCRIPCION]],'CAP16-18'!$H:$H) -> 0 | M45: =SUMIF('CAP19-22'!$B:$H,MObra[[#This Row],[DESCRIPCION]],'CAP19-22'!$H:$H) -> 0 | N45: =SUMIF('CAP23-24'!$B:$H,MObra[[#This Row],[DESCRIPCION]],'CAP23-24'!$H:$H) -> 0 | O45: =SUMIF('CAP25'!$B:$H,MObra[[#This Row],[DESCRIPCION]],'CAP25'!$H:$H) -> 0 | P45: =SUMIF('CAP26-28'!$B:$H,MObra[[#This Row],[DESCRIPCION]],'CAP26-28'!$H:$H) -> 0 | Q45: =SUMIF('CAP29'!$B:$H,MObra[[#This Row],[DESCRIPCION]],'CAP29'!$H:$H) -> 0
B46: Cuadrilla 1 Of + 3 Ay (jornal + prestaciones) | C46: día | D46: =$D$33*3+$D$39*1 -> 547272.79 | E46: =SUM(MObra[[#This Row],[CAP1]:[CAP29]]) -> 0 | F46: =SUMIF('CAP1-3'!$B:$H,MObra[[#This Row],[DESCRIPCION]],'CAP1-3'!$H:$H) -> 0 | G46: =SUMIF('CAP4-5'!$B:$H,MObra[[#This Row],[DESCRIPCION]],'CAP4-5'!$H:$H) -> 0 | H46: =SUMIF('CAP6-7'!$B:$H,MObra[[#This Row],[DESCRIPCION]],'CAP6-7'!$H:$H) -> 0 | I46: =SUMIF('CAP8'!$B:$H,MObra[[#This Row],[DESCRIPCION]],'CAP8'!$H:$H) -> 0 | J46: =SUMIF('CAP9-13'!$B:$H,MObra[[#This Row],[DESCRIPCION]],'CAP9-13'!$H:$H) -> 0 | K46: =SUMIF('CAP14-15'!$B:$H,MObra[[#This Row],[DESCRIPCION]],'CAP14-15'!$H:$H) -> 0 | L46: =SUMIF('CAP16-18'!$B:$H,MObra[[#This Row],[DESCRIPCION]],'CAP16-18'!$H:$H) -> 0 | M46: =SUMIF('CAP19-22'!$B:$H,MObra[[#This Row],[DESCRIPCION]],'CAP19-22'!$H:$H) -> 0 | N46: =SUMIF('CAP23-24'!$B:$H,MObra[[#This Row],[DESCRIPCION]],'CAP23-24'!$H:$H) -> 0 | O46: =SUMIF('CAP25'!$B:$H,MObra[[#This Row],[DESCRIPCION]],'CAP25'!$H:$H) -> 0 | P46: =SUMIF('CAP26-28'!$B:$H,MObra[[#This Row],[DESCRIPCION]],'CAP26-28'!$H:$H) -> 0 | Q46: =SUMIF('CAP29'!$B:$H,MObra[[#This Row],[DESCRIPCION]],'CAP29'!$H:$H) -> 0
B47: Cuadrilla 1 Of + 4 Ay (jornal + prestaciones) | C47: día | D47: =$D$33*4+$D$39*1 -> 663713.81 | E47: =SUM(MObra[[#This Row],[CAP1]:[CAP29]]) -> 0 | F47: =SUMIF('CAP1-3'!$B:$H,MObra[[#This Row],[DESCRIPCION]],'CAP1-3'!$H:$H) -> 0 | G47: =SUMIF('CAP4-5'!$B:$H,MObra[[#This Row],[DESCRIPCION]],'CAP4-5'!$H:$H) -> 0 | H47: =SUMIF('CAP6-7'!$B:$H,MObra[[#This Row],[DESCRIPCION]],'CAP6-7'!$H:$H) -> 0 | I47: =SUMIF('CAP8'!$B:$H,MObra[[#This Row],[DESCRIPCION]],'CAP8'!$H:$H) -> 0 | J47: =SUMIF('CAP9-13'!$B:$H,MObra[[#This Row],[DESCRIPCION]],'CAP9-13'!$H:$H) -> 0 | K47: =SUMIF('CAP14-15'!$B:$H,MObra[[#This Row],[DESCRIPCION]],'CAP14-15'!$H:$H) -> 0 | L47: =SUMIF('CAP16-18'!$B:$H,MObra[[#This Row],[DESCRIPCION]],'CAP16-18'!$H:$H) -> 0 | M47: =SUMIF('CAP19-22'!$B:$H,MObra[[#This Row],[DESCRIPCION]],'CAP19-22'!$H:$H) -> 0 | N47: =SUMIF('CAP23-24'!$B:$H,MObra[[#This Row],[DESCRIPCION]],'CAP23-24'!$H:$H) -> 0 | O47: =SUMIF('CAP25'!$B:$H,MObra[[#This Row],[DESCRIPCION]],'CAP25'!$H:$H) -> 0 | P47: =SUMIF('CAP26-28'!$B:$H,MObra[[#This Row],[DESCRIPCION]],'CAP26-28'!$H:$H) -> 0 | Q47: =SUMIF('CAP29'!$B:$H,MObra[[#This Row],[DESCRIPCION]],'CAP29'!$H:$H) -> 0
B48: Cuadrilla 1 Of + 7 Ay (jornal + prestaciones) | C48: día | D48: =$D$33*7+$D$39*1 -> 1013036.9 | E48: =SUM(MObra[[#This Row],[CAP1]:[CAP29]]) -> 0 | F48: =SUMIF('CAP1-3'!$B:$H,MObra[[#This Row],[DESCRIPCION]],'CAP1-3'!$H:$H) -> 0 | G48: =SUMIF('CAP4-5'!$B:$H,MObra[[#This Row],[DESCRIPCION]],'CAP4-5'!$H:$H) -> 0 | H48: =SUMIF('CAP6-7'!$B:$H,MObra[[#This Row],[DESCRIPCION]],'CAP6-7'!$H:$H) -> 0 | I48: =SUMIF('CAP8'!$B:$H,MObra[[#This Row],[DESCRIPCION]],'CAP8'!$H:$H) -> 0 | J48: =SUMIF('CAP9-13'!$B:$H,MObra[[#This Row],[DESCRIPCION]],'CAP9-13'!$H:$H) -> 0 | K48: =SUMIF('CAP14-15'!$B:$H,MObra[[#This Row],[DESCRIPCION]],'CAP14-15'!$H:$H) -> 0 | L48: =SUMIF('CAP16-18'!$B:$H,MObra[[#This Row],[DESCRIPCION]],'CAP16-18'!$H:$H) -> 0 | M48: =SUMIF('CAP19-22'!$B:$H,MObra[[#This Row],[DESCRIPCION]],'CAP19-22'!$H:$H) -> 0 | N48: =SUMIF('CAP23-24'!$B:$H,MObra[[#This Row],[DESCRIPCION]],'CAP23-24'!$H:$H) -> 0 | O48: =SUMIF('CAP25'!$B:$H,MObra[[#This Row],[DESCRIPCION]],'CAP25'!$H:$H) -> 0 | P48: =SUMIF('CAP26-28'!$B:$H,MObra[[#This Row],[DESCRIPCION]],'CAP26-28'!$H:$H) -> 0 | Q48: =SUMIF('CAP29'!$B:$H,MObra[[#This Row],[DESCRIPCION]],'CAP29'!$H:$H) -> 0
B49: Cuadrilla 1 Of Electr. + 1 Ay (jornal + prestaciones) | C49: día | D49: =$D$34*1+$D$40*1 -> 337678.95 | E49: =SUM(MObra[[#This Row],[CAP1]:[CAP29]]) -> 0 | F49: =SUMIF('CAP1-3'!$B:$H,MObra[[#This Row],[DESCRIPCION]],'CAP1-3'!$H:$H) -> 0 | G49: =SUMIF('CAP4-5'!$B:$H,MObra[[#This Row],[DESCRIPCION]],'CAP4-5'!$H:$H) -> 0 | H49: =SUMIF('CAP6-7'!$B:$H,MObra[[#This Row],[DESCRIPCION]],'CAP6-7'!$H:$H) -> 0 | I49: =SUMIF('CAP8'!$B:$H,MObra[[#This Row],[DESCRIPCION]],'CAP8'!$H:$H) -> 0 | J49: =SUMIF('CAP9-13'!$B:$H,MObra[[#This Row],[DESCRIPCION]],'CAP9-13'!$H:$H) -> 0 | K49: =SUMIF('CAP14-15'!$B:$H,MObra[[#This Row],[DESCRIPCION]],'CAP14-15'!$H:$H) -> 0 | L49: =SUMIF('CAP16-18'!$B:$H,MObra[[#This Row],[DESCRIPCION]],'CAP16-18'!$H:$H) -> 0 | M49: =SUMIF('CAP19-22'!$B:$H,MObra[[#This Row],[DESCRIPCION]],'CAP19-22'!$H:$H) -> 0 | N49: =SUMIF('CAP23-24'!$B:$H,MObra[[#This Row],[DESCRIPCION]],'CAP23-24'!$H:$H) -> 0 | O49: =SUMIF('CAP25'!$B:$H,MObra[[#This Row],[DESCRIPCION]],'CAP25'!$H:$H) -> 0 | P49: =SUMIF('CAP26-28'!$B:$H,MObra[[#This Row],[DESCRIPCION]],'CAP26-28'!$H:$H) -> 0 | Q49: =SUMIF('CAP29'!$B:$H,MObra[[#This Row],[DESCRIPCION]],'CAP29'!$H:$H) -> 0
