Workbook
Name Analis: #REF!
Name Analis: #REF!
Name Andres123: #REF!
Name CompanyAddress: #REF!
Name CompanyAddress: #REF!
Name CompanyAddress: #REF!
Name CompanyAddress: #REF!
Name CompanyCity: #REF!
Name CompanyCity: #REF!
Name CompanyCity: #REF!
Name CompanyCity: #REF!
Name CompanyContactsHeader: #REF!
Name CompanyCountry: #REF!
Name CompanyCountry: #REF!
Name CompanyCountry: #REF!
Name CompanyCountry: #REF!
Name CompanyName: #REF!
Name CompanyName: #REF!
Name CompanyName: #REF!
Name CompanyName: #REF!
Name CompanyState: #REF!
Name CompanyState: #REF!
Name CompanyState: #REF!
Name CompanyState: #REF!
Name CompanyZip: #REF!
Name CompanyZip: #REF!
Name CompanyZip: #REF!
Name CompanyZip: #REF!
Name DataDisplayed: "Ejemplo"
Name Slicer_Contact_Type: #N/A
Name tablonx: 'BASE DE DATOS'!#REF!
Name tablonx: 'BASE DE DATOS'!#REF!
Name tablonx: 'BASE DE DATOS'!#REF!
Name xt: #REF!

Sheet BASE DE DATOS
A1: Base de Datos Gobernación de Risaralda
A3: MANO DE OBRA
A4: CÓDIGO | B4: DESCRIPCIÓN | C4: UNIDAD | E4: VALOR UNITARIO 2025
A5: MOB011 | B5: Acarreo Horizontal | C5: % MO | E5: 0
A6: MOB003 | B6: Ayudante (jornal + prestaciones) | C6: Día | E6: ='ANÁLISIS MANO DE OBRA'!F32 -> 88679
A7: MOB019 | B7: Ayudante eléctrico (jornal + prestaciones) | C7: Día | E7: =+'ANÁLISIS MANO DE OBRA'!F47 -> 141887
A8: MOB004 | B8: Ayudante práctico (jornal + prestaciones) | C8: Día | E8: ='ANÁLISIS MANO DE OBRA'!F33 -> 124151
A9: MOB010 | B9: Comisión topografía (Topógrafo + Cadenero 1 + Cadeneros 2) | C9: Día | E9: ='ANÁLISIS MANO DE OBRA'!F56 -> 375244
A10: MOB005 | B10: Cuadrilla A 1 Of + 4 Ay (jornal + prestaciones) | C10: Día | E10: ='ANÁLISIS MANO DE OBRA'!F52 -> 514339
A11: MOB006 | B11: Cuadrilla B 1 Min + 2 Ay (jornal + prestaciones) | C11: Día | E11: ='ANÁLISIS MANO DE OBRA'!F54 -> 372899
A12: MOB013 | B12: Cuadrilla C 1 Of + 7 Ay (jornal + prestaciones) | C12: Día | E12: ='ANÁLISIS MANO DE OBRA'!F57 -> 780376
A13: MOB001 | B13: =+'ANÁLISIS MANO DE OBRA'!B58 -> Cuadrilla CE (1 Of E + 7 Ay E) (jornal + prestaciones) | C13: Día | E13: =+'ANÁLISIS MANO DE OBRA'!F58 -> 1170568
A14: MOB014 | B14: Cuadrilla D 2 Of + 4 Ay (jornal + prestaciones) | C14: Día | E14: ='ANÁLISIS MANO DE OBRA'!F59 -> 673962
A15: MOB015 | B15: Cuadrilla E 1 Of + 1 Ay (jornal + prestaciones) | C15: Día | E15: ='ANÁLISIS MANO DE OBRA'!F48 -> 248302
A16: MOB009 | B16: =+'ANÁLISIS MANO DE OBRA'!B49 -> Cuadrilla EE 1 Of E + 1 Ay E (jornal + prestaciones) | C16: Día | E16: =+'ANÁLISIS MANO DE OBRA'!F49 -> 319246
A17: MOB016 | B17: Cuadrilla F 6 Of + 4 Ay (jornal + prestaciones) | C17: Día | E17: ='ANÁLISIS MANO DE OBRA'!F60 -> 1312454
A18: MOB017 | B18: Cuadrilla G 1 Of + 2 Ay (jornal + prestaciones) | C18: Día | E18: ='ANÁLISIS MANO DE OBRA'!F50 -> 336981
A19: MOB023 | B19: Cuadrilla GE 1 Of E + 2 A y E (jornal + prestaciones) | C19: Día | E19: ='ANÁLISIS MANO DE OBRA'!F41+2*'ANÁLISIS MANO DE OBRA'!F33 -> 425661
A20: MOB018 | B20: Cuadrilla H 4 Ay (jornal + prestaciones) | C20: Día | E20: ='ANÁLISIS MANO DE OBRA'!F61 -> 354716
A21: MOB020 | B21: Cuadrilla J (1 Of eléctrico + 1 Ay eléctrico) (jornal + prestaciones) | C21: Día | E21: ='ANÁLISIS MANO DE OBRA'!F62 -> 319246
A22: MOB021 | B22: Cuadrilla K (1 Of eléctrico + 2 Ay eléctricos) (jornal + prestaciones) | C22: Día | E22: ='ANÁLISIS MANO DE OBRA'!F63 -> 461133
A23: MOB022 | B23: Cuadrilla L 2 Of + 8 Ay (jornal + prestaciones) | C23: Día | E23: ='ANÁLISIS MANO DE OBRA'!F65 -> 1028678
A24: MOB008 | B24: Cuadrilla S (1 Sold.+1 Ay práctico) (jornal + prestaciones) | C24: Día | E24: ='ANÁLISIS MANO DE OBRA'!F64 -> 283774
A25: MOB024 | B25: Cuadrilla N 1 Min + 1 Ay (jornal + prestaciones) | C25: Día | E25: ='ANÁLISIS MANO DE OBRA'!F55 -> 284220
A26: MOB002 | B26: Oficial (jornal + prestaciones) | C26: Día | E26: ='ANÁLISIS MANO DE OBRA'!F34 -> 159623
A27: MOB007 | B27: Oficial eléctrico (jornal + prestaciones) | C27: Día | E27: ='ANÁLISIS MANO DE OBRA'!F41 -> 177359
A28: MOB012 | B28: Profesional en salud ocupacional | C28: Mes | E28: =+'ANÁLISIS MANO DE OBRA'!E46 -> 6570193
A29: MATERIALES
A31: CÓDIGO | B31: DESCRIPCIÓN | C31: UNIDAD | E31: VALOR UNITARIO 2025
A32: MAT,056 | B32: Abrazadera UNISTRUT para tubo ø 1 ½" zincada | C32: Un | E32: 1300
A33: MAT,004 | B33: Abrazadera UNISTRUT para tubo ø 2" zincada | C33: Un | E33: 1600
A34: MAT,058 | B34: Abrazadera UNISTRUT para tubo ø 3" zincada | C34: Un | E34: 2250
A35: MAT,003 | B35: Abrazadera UNISTRUT para tubo ø 3/4" zincada | C35: Un | E35: 850
A36: MAT,083 | B36: Abrazadera UNISTRUT para tubo ø 4" zincada | C36: Un | E36: 5734
A37: MAT,797 | B37: Accesorio esquina externa PVC media caña 60 mm blanco | C37: Un | E37: 8845
A38: MAT,796 | B38: Accesorio esquina interna PVC media caña 60 mm blanco | C38: Un | E38: 8845
A39: MAT,795 | B39: Accesorio esquina interna PVC media caña 90 mm blanco | C39: Un | E39: 12345
A40: MAT,791 | B40: Accesorio estrella PVC media caña 60 mm blanco | C40: Un | E40: 8845
A41: MAT,793 | B41: Accesorio estrella PVC media caña 90 mm blanco | C41: Un | E41: 12495
A42: MAT,794 | B42: Accesorio tapa PVC media caña 60 mm blanco | C42: Un | E42: 8845
A43: MAT,792 | B43: Accesorio tapa PVC media caña 90 mm blanco | C43: Un | E43: 12495
... A54: MAT,005 | B54: Accesorios PVC sanitaria 2" promedio (U + codo 90º) | C54: Un | E54: 7950
A55: MAT,006 | B55: Accesorios PVC sanitaria 3" promedio (U + codo 90º) | C55: Un | E55: =2900+7700 -> 10600
A56: MAT,007 | B56: Accesorios PVC sanitaria 4" promedio (U + codo 90º) | C56: Un | E56: =5650+10600 -> 16250
A57: MAT,009 | B57: Acelerante para concreto tipo Sika set | C57: Kg | E57: 20348
A58: MAT,010 | B58: Acero Fy = 37.000 PSI (2.601 kg/cm2) d ≤ ¼" | C58: Kg | E58: 4500
A59: MAT,011 | B59: Acero Fy = 60.000 PSI (40218 kg/cm2) d > ¼" | C59: Kg | E59: 4545
A60: MAT,641 | B60: Acero laminado A 36, para correa formada por pieza simple, de perfiles laminados en caliente, según ASTM A 36, acabado con imprimación antioxidante, trabajado en taller, para colocar en obra mediante soldadura | C60: Kg | E60: 2414
A61: MAT,534 | B61: Acople flexible para lavamanos de 1/2" 150 cm | C61: Un | E61: 14900
A62: MAT,045 | B62: Acople flexible para sanitario, conexión rosca 7/8" | C62: Un | E62: 5300
A63: MAT,012 | B63: ACPM | C63: Gl | E63: 10959
A64: MAT,014 | B64: Adaptador bajante PVC agua lluvia cuadrada 3" | C64: Un | E64: =203900/50 -> 4078
A65: MAT,015 | B65: Adaptador macho PF + UAD ½" | C65: Un | E65: 5400
A66: MAT,018 | B66: Adaptador PVC macho de ½" presión | C66: Un | E66: 350
A67: MAT,016 | B67: Adaptador PVC macho de 1 ½" presión | C67: Un | E67: 5500
A68: MAT,017 | B68: Adaptador PVC macho de 1" presión | C68: Un | E68: 2150
A69: MAT,019 | B69: Adaptador PVC macho de 2" presión | C69: Un | E69: 7200
A70: MAT,020 | B70: Adaptador PVC macho de 3/4" presión | C70: Un | E70: 1100
A71: MAT,931 | B71: Adaptador terminal conduit EMT 1/2" | C71: Un | E71: 4500
A72: MAT,618 | B72: Adaptador terminal conduit PVC ½" | C72: Un | E72: 400
A73: MAT,084 | B73: Adaptador terminal conduit PVC 3/4" | C73: Un | E73: =46900/100 -> 469
A74: MAT,607 | B74: Adaptador terminal EMT 3/4" | C74: Un | E74: 2200
A75: MAT,021 | B75: Adhesivo epóxico para pegar concreto fresco con endurecido de curado lento (tipo Sikadur v32 Primer) | C75: Kg | E75: 195900
A76: MAT,258 | B76: Adhesivo epóxico tipo IV grado 3 (ASTM C-881-02) para anclar barras de acero al concreto x 600 m (Sikadur® AnchorFix®-4 tubo x 600 m) o similar | C76: Un | E76: 99900
A77: MAT,022 | B77: Adhesivo para piso de vinilo | C77: Kg | E77: 25745
A78: MAT,023 | B78: Adhesivo para tubería de pared estructural 310 ml | C78: Un | E78: 90900
A79: MAT,630 | B79: Aditivo acelerante para concreto tipo Sikaset L o similar | C79: Kg | E79: =97900/5 -> 19580
A80: MAT,817 | B80: Aditivo curador (antisol o similar) | C80: Kg | E80: 13045
A81: MAT,024 | B81: Adoquín en gres peatonal (5 x 10 x 20 cm) | C81: M2 | E81: 75000
A82: MAT,025 | B82: Adoquín peatonal gris de concreto e = 0,06 m (5 Mpa) | C82: M2 | E82: =1100*50 -> 55000
A83: MAT,552 | B83: Adoquín vehicular gris de concreto e = 0,08 m | C83: M2 | E83: =800*50 -> 40000
A84: MAT,026 | B84: Afirmado para mantenimiento vial y elementos no estructurales | C84: M3 | E84: 26610
A85: MAT,027 | B85: Agua | C85: Lt | E85: 19
A86: MAT,578 | B86: Aislador tipo carrete 3" ANSI 53-2 | C86: Un | E86: 4000
A87: MAT,234 | B87: Ajustador alifático (varsol) 21132 o similar | C87: Gl | E87: 50182
A88: MAT,788 | B88: Ajustador para epóxicas 21209 o similar (usar solo siguiendo las recomendaciones del Fabricante Pintuco) | C88: Gl | E88: 74724
A89: MAT,028 | B89: Alambre de púas C 14 | C89: M | E89: 584
A90: MAT,029 | B90: Alambre galvanizado C 12 | C90: Kg | E90: 11400
A91: MAT,030 | B91: Alambre negro calibre 18 - 19 | C91: Kg | E91: 7790
A92: MAT,806 | B92: Alambre Nº 6 de aluminio para amarre | C92: M | E92: 3000
A93: MAT,598 | B93: Alambrón de aluminio 8 mm | C93: M | E93: =(4700+13950*1.19/3+5067)/3 -> 5100.1667
A94: MAT,001 | B94: Alas para cerámica (wings o piraguas) en Al x 2,5 m | C94: M | E94: =44900/2.5 -> 17960
A95: MAT,031 | B95: Alas para cerámica (wings o piraguas) en PVC x 2,4 m | C95: M | E95: =8900/2.4 -> 3708.3333
A96: MAT,032 | B96: Amarra con tapa plástica para techos | C96: Un | E96: =9900/20 -> 495
A97: MAT,496 | B97: Amarra de nylon de 10 cm | C97: Un | E97: 149
A98: MAT,903 | B98: Amarre plástico 10 cm bolsa tipo DEXON | C98: Un | E98: =3600/100 -> 36
A99: MAT,827 | B99: Anclaje mecánico tipo tornillo de cabeza avellanada con estrella interior de seis puntas para llave Torx, de acero galvanizado | C99: Un | E99: 4274
A100: MAT,087 | B100: Anclaje multipropósito de ø 3/8" (tipo hembra) | C100: Un | E100: 900
A101: MAT,088 | B101: Anclaje tipo cuña 3/8" x 2 ¼" | C101: Un | E101: 3700
A102: MAT,037 | B102: Ángulo C 26 perimetral de 20 x 30 x 2.40 m | C102: Un | E102: =ROUND(1105.74*2.44,0) -> 2698
A103: MAT,034 | B103: Ángulo de 1 ½" x 1/8" | C103: M | E103: 9383
A104: MAT,035 | B104: Ángulo de 1" x 1/8" | C104: M | E104: 6817
A105: MAT,516 | B105: Ángulo de 2" x 1/8" | C105: M | E105: 15817
A106: MAT,036 | B106: Ángulo de 2" x 3/16" (puente) | C106: M | E106: 22617
A107: MAT,902 | B107: Anillo marcación 12 - 6 AWG AR2 #0 tipo DEXSON DXN21R20 | C107: Un | E107: =5557/100 -> 55.57
A108: MAT,924 | B108: Anillo marcador para ablee AR2 UN tipo DEXSON | C108: Un | E108: =4323*1.19/100 -> 51.4437
A109: MAT,038 | B109: Anticorrosivo tipo 1 gris | C109: Gl | E109: 69900
A110: MAT,039 | B110: Antisol blanco o similar | C110: Kg | E110: 13045
A111: MAT,089 | B111: Arandela cuadrada 2" x 2" x ¼", ø 5/8" | C111: Un | E111: 800
A112: MAT,536 | B112: Arandela galvanizada de 3/8" | C112: Un | E112: 250
...

Sheet CONSTRUCCION
A1: IMPORTANTE: Los presentes precios unitarios de referencia fueron calculados en la ciudad de Pereira (zona urbana), por tanto deben ser modificados (incrementados) para las áreas rurales de los municipios de Pereira, Dosquebradas y La Virginia y en las áreas urbanas y rurales de los demás municipios, según el caso. Por estar basados en precios del mercado están sujetos a las variaciones del mismo, las cuales se aplicarán sin previo aviso. Pueden presentar inconsistencias, que se corregirán en el momento de ser detectadas.
A2: El presente listado es una simple guía para el Evaluador, no se constituye en camisa de fuerza, ni es obligatoria su aplicación, quien los utilice, deberá estudiarlos y estar consiente de sus bondades y limitaciones, y será su buen juicio el que prime al final, en cada caso. Dadas las variaciones del precio del dólar que influye principalmente en los insumos derivados del petróleo, el cobre, el cemento e insumos derivados, el PVC, etc., es importante que el Evaluador verifique el costo básico de estos insumos cada vez que pretenda hacer una evaluación o cotización.
A3: Los presente análisis incluyen para la mano de obra los ítems de salud e I.C.B.F., será responsabilidad del Evaluador mantenerlos o suprimirlos según la normatividad existente vigente y el caso particular en donde se aplicarán.
A4: De todos los Ítems posibles se ha suprimido el transporte de materiales, por tanto el evaluador deberá considerarlo como ítems aparte en cada evaluación o cotización. Por favor leer la Introducción.
A6: Análisis Unitarios de Referencia Gobernación de Risaralda
A7: G- ÍTEMS GENERALES
A8: G - 01 CONCRETOS Y MORTEROS
A9: ÍTEM | B9: CÓDIGO | C9: DESCRIPCIÓN | D9: UN | E9: CANT | F9: VR. UN. | G9: RENDIMIENTO, USOS, DESPEDICIOS | H9: VR. PARCIAL
A10: G-01-01 | C10: Concreto de 10,3 Mpa (1500 PSI) (Producción) | D10: M3 | F10: =ROUND(SUM(H10:H17),0) -> 374067
A11: MAT | B11: MAT,027 | C11: Agua | D11: Lt | E11: 160 | F11: =VLOOKUP(B11,'BASE DE DATOS'!$A$5:$E$997,5,FALSE) -> 19 | G11: 1.03 | H11: =IF(G11>0,(G11*F11*E11),(F11*E11)) -> 3131.2
B12: MAT,040 | C12: Arena | D12: M3 | E12: 0.56 | F12: =VLOOKUP(B12,'BASE DE DATOS'!$A$5:$E$997,5,FALSE) -> 71990 | G12: 1.03 | H12: =IF(G12>0,(G12*F12*E12),(F12*E12)) -> 41523.832
B13: MAT,068 | C13: Cemento gris saco por 50 kilos | D13: Sc | E13: 3.5 | F13: =VLOOKUP(B13,'BASE DE DATOS'!$A$5:$E$997,5,FALSE) -> 32900 | G13: 1.03 | H13: =IF(G13>0,(G13*F13*E13),(F13*E13)) -> 118604.5
B14: MAT,410 | C14: Triturado 3/4" para concreto | D14: M3 | E14: 0.97 | F14: =VLOOKUP(B14,'BASE DE DATOS'!$A$5:$E$997,5,FALSE) -> 74972.5 | G14: 1.03 | H14: =IF(G14>0,(G14*F14*E14),(F14*E14)) -> 74905.025
A15: M. O. | B15: MOB013 | C15: Cuadrilla C 1 Of + 7 Ay (jornal + prestaciones) | D15: Día | E15: 1 | F15: =VLOOKUP(B15,'BASE DE DATOS'!$A$5:$E$997,5,FALSE) -> 780376 | G15: =1/6.66667 -> 0.14999993 | H15: =IF(G15>0,(G15*F15*E15),(F15*E15)) -> 117056.34
A16: EQUIPO | B16: EQU003 | C16: Concretadora gasolina de 1 o 1 1/2 sacos | D16: Día | E16: 1 | F16: =VLOOKUP(B16,'BASE DE DATOS'!$A$5:$E$997,5,FALSE) -> 71400 | G16: =1/10 -> 0.1 | H16: =IF(G16>0,(G16*F16*E16),(F16*E16)) -> 7140
B17: EQU002 | C17: Herramienta menor (% mano obra) | D17: %MO | E17: 0.1 | F17: =H15 -> 117056.34 | G17: 0 | H17: =IF(G17>0,(G17*F17*E17),(F17*E17)) -> 11705.634
A18: G-01-02 | C18: Concreto de 13,8 Mpa (2000 PSI) (Producción) | D18: M3 | F18: =ROUND(SUM(H18:H25),0) -> 421463
A19: MAT | B19: MAT,027 | C19: Agua | D19: Lt | E19: 185 | F19: =VLOOKUP(B19,'BASE DE DATOS'!$A$5:$E$997,5,FALSE) -> 19 | G19: 1.03 | H19: =IF(G19>0,(G19*F19*E19),(F19*E19)) -> 3620.45
B20: MAT,040 | C20: Arena | D20: M3 | E20: 0.63 | F20: =VLOOKUP(B20,'BASE DE DATOS'!$A$5:$E$997,5,FALSE) -> 71990 | G20: 1.03 | H20: =IF(G20>0,(G20*F20*E20),(F20*E20)) -> 46714.311
B21: MAT,068 | C21: Cemento gris saco por 50 kilos | D21: Sc | E21: 5.2 | F21: =VLOOKUP(B21,'BASE DE DATOS'!$A$5:$E$997,5,FALSE) -> 32900 | G21: 1.03 | H21: =IF(G21>0,(G21*F21*E21),(F21*E21)) -> 176212.4
B22: MAT,410 | C22: Triturado 3/4" para concreto | D22: M3 | E22: 0.84 | F22: =VLOOKUP(B22,'BASE DE DATOS'!$A$5:$E$997,5,FALSE) -> 74972.5 | G22: 1.03 | H22: =IF(G22>0,(G22*F22*E22),(F22*E22)) -> 64866.207
A23: M. O. | B23: MOB013 | C23: Cuadrilla C 1 Of + 7 Ay (jornal + prestaciones) | D23: Día | E23: 1 | F23: =VLOOKUP(B23,'BASE DE DATOS'!$A$5:$E$997,5,FALSE) -> 780376 | G23: =1/6.66667 -> 0.14999993 | H23: =IF(G23>0,(G23*F23*E23),(F23*E23)) -> 117056.34
A24: EQUIPO | B24: EQU003 | C24: Concretadora gasolina de 1 o 1 1/2 sacos | D24: Día | E24: 1 | F24: =VLOOKUP(B24,'BASE DE DATOS'!$A$5:$E$997,5,FALSE) -> 71400 | G24: =1/10 -> 0.1 | H24: =IF(G24>0,(G24*F24*E24),(F24*E24)) -> 7140
B25: EQU002 | C25: Herramienta menor (% mano obra) | D25: %MO | E25: 0.05 | F25: =H23 -> 117056.34 | G25: 0 | H25: =IF(G25>0,(G25*F25*E25),(F25*E25)) -> 5852.8171
A26: G-01-03 | C26: Concreto de 17,2 Mpa (2500 PSI) (Producción) | D26: M3 | F26: =ROUND(SUM(H26:H33),0) -> 456694
A27: MAT | B27: MAT,027 | C27: Agua | D27: Lt | E27: 170 | F27: =VLOOKUP(B27,'BASE DE DATOS'!$A$5:$E$997,5,FALSE) -> 19 | G27: 1.03 | H27: =IF(G27>0,(G27*F27*E27),(F27*E27)) -> 3326.9
B28: MAT,040 | C28: Arena | D28: M3 | E28: 0.55 | F28: =VLOOKUP(B28,'BASE DE DATOS'!$A$5:$E$997,5,FALSE) -> 71990 | G28: 1.03 | H28: =IF(G28>0,(G28*F28*E28),(F28*E28)) -> 40782.335
B29: MAT,068 | C29: Cemento gris saco por 50 kilos | D29: Sc | E29: 6 | F29: =VLOOKUP(B29,'BASE DE DATOS'!$A$5:$E$997,5,FALSE) -> 32900 | G29: 1.03 | H29: =IF(G29>0,(G29*F29*E29),(F29*E29)) -> 203322
B30: MAT,410 | C30: Triturado 3/4" para concreto | D30: M3 | E30: 0.95 | F30: =VLOOKUP(B30,'BASE DE DATOS'!$A$5:$E$997,5,FALSE) -> 74972.5 | G30: 1.03 | H30: =IF(G30>0,(G30*F30*E30),(F30*E30)) -> 73360.591
A31: M. O. | B31: MOB013 | C31: Cuadrilla C 1 Of + 7 Ay (jornal + prestaciones) | D31: Día | E31: 1 | F31: =VLOOKUP(B31,'BASE DE DATOS'!$A$5:$E$997,5,FALSE) -> 780376 | G31: =1/6.66667 -> 0.14999993 | H31: =IF(G31>0,(G31*F31*E31),(F31*E31)) -> 117056.34
A32: EQUIPO | B32: EQU003 | C32: Concretadora gasolina de 1 o 1 1/2 sacos | D32: Día | E32: 1 | F32: =VLOOKUP(B32,'BASE DE DATOS'!$A$5:$E$997,5,FALSE) -> 71400 | G32: =1/10 -> 0.1 | H32: =IF(G32>0,(G32*F32*E32),(F32*E32)) -> 7140
B33: EQU002 | C33: Herramienta menor (% mano obra) | D33: %MO | E33: 0.1 | F33: =H31 -> 117056.34 | G33: 0 | H33: =IF(G33>0,(G33*F33*E33),(F33*E33)) -> 11705.634
A34: G-01-04 | C34: Concreto de 20,7 Mpa (3000 PSI) (Producción) | D34: M3 | F34: =ROUND(SUM(H34:H41),0) -> 482282
A35: MAT | B35: MAT,027 | C35: Agua | D35: Lt | E35: 180 | F35: =VLOOKUP(B35,'BASE DE DATOS'!$A$5:$E$997,5,FALSE) -> 19 | G35: 1.03 | H35: =IF(G35>0,(G35*F35*E35),(F35*E35)) -> 3522.6
B36: MAT,040 | C36: Arena | D36: M3 | E36: 0.55 | F36: =VLOOKUP(B36,'BASE DE DATOS'!$A$5:$E$997,5,FALSE) -> 71990 | G36: 1.03 | H36: =IF(G36>0,(G36*F36*E36),(F36*E36)) -> 40782.335
B37: MAT,068 | C37: Cemento gris saco por 50 kilos | D37: Sc | E37: 7 | F37: =VLOOKUP(B37,'BASE DE DATOS'!$A$5:$E$997,5,FALSE) -> 32900 | G37: 1.03 | H37: =IF(G37>0,(G37*F37*E37),(F37*E37)) -> 237209
B38: MAT,410 | C38: Triturado 3/4" para concreto | D38: M3 | E38: 0.84 | F38: =VLOOKUP(B38,'BASE DE DATOS'!$A$5:$E$997,5,FALSE) -> 74972.5 | G38: 1.03 | H38: =IF(G38>0,(G38*F38*E38),(F38*E38)) -> 64866.207
A39: M. O. | B39: MOB013 | C39: Cuadrilla C 1 Of + 7 Ay (jornal + prestaciones) | D39: Día | E39: 1 | F39: =VLOOKUP(B39,'BASE DE DATOS'!$A$5:$E$997,5,FALSE) -> 780376 | G39: =1/6.66667 -> 0.14999993 | H39: =IF(G39>0,(G39*F39*E39),(F39*E39)) -> 117056.34
A40: EQUIPO | B40: EQU003 | C40: Concretadora gasolina de 1 o 1 1/2 sacos | D40: Día | E40: 1 | F40: =VLOOKUP(B40,'BASE DE DATOS'!$A$5:$E$997,5,FALSE) -> 71400 | G40: =1/10 -> 0.1 | H40: =IF(G40>0,(G40*F40*E40),(F40*E40)) -> 7140
B41: EQU002 | C41: Herramienta menor (% mano obra) | D41: %MO | E41: 0.1 | F41: =H39 -> 117056.34 | G41: 0 | H41: =IF(G41>0,(G41*F41*E41),(F41*E41)) -> 11705.634
A42: G-01-05 | C42: Concreto de 24,5 Mpa (3500 PSI) (Producción) | D42: M3 | F42: =ROUND(SUM(H42:H49),0) -> 533927
A43: MAT | B43: MAT,027 | C43: Agua | D43: Lt | E43: 190 | F43: =VLOOKUP(B43,'BASE DE DATOS'!$A$5:$E$997,5,FALSE) -> 19 | G43: 1.03 | H43: =IF(G43>0,(G43*F43*E43),(F43*E43)) -> 3718.3
B44: MAT,040 | C44: Arena | D44: M3 | E44: 0.6 | F44: =VLOOKUP(B44,'BASE DE DATOS'!$A$5:$E$997,5,FALSE) -> 71990 | G44: 1.03 | H44: =IF(G44>0,(G44*F44*E44),(F44*E44)) -> 44489.82
B45: MAT,068 | C45: Cemento gris saco por 50 kilos | D45: Sc | E45: 8.5 | F45: =VLOOKUP(B45,'BASE DE DATOS'!$A$5:$E$997,5,FALSE) -> 32900 | G45: 1.03 | H45: =IF(G45>0,(G45*F45*E45),(F45*E45)) -> 288039.5
B46: MAT,410 | C46: Triturado 3/4" para concreto | D46: M3 | E46: 0.8 | F46: =VLOOKUP(B46,'BASE DE DATOS'!$A$5:$E$997,5,FALSE) -> 74972.5 | G46: 1.03 | H46: =IF(G46>0,(G46*F46*E46),(F46*E46)) -> 61777.34
A47: M. O. | B47: MOB013 | C47: Cuadrilla C 1 Of + 7 Ay (jornal + prestaciones) | D47: Día | E47: 1 | F47: =VLOOKUP(B47,'BASE DE DATOS'!$A$5:$E$997,5,FALSE) -> 780376 | G47: =1/6.66667 -> 0.14999993 | H47: =IF(G47>0,(G47*F47*E47),(F47*E47)) -> 117056.34
A48: EQUIPO | B48: EQU003 | C48: Concretadora gasolina de 1 o 1 1/2 sacos | D48: Día | E48: 1 | F48: =VLOOKUP(B48,'BASE DE DATOS'!$A$5:$E$997,5,FALSE) -> 71400 | G48: =1/10 -> 0.1 | H48: =IF(G48>0,(G48*F48*E48),(F48*E48)) -> 7140
B49: EQU002 | C49: Herramienta menor (% mano obra) | D49: %MO | E49: 0.1 | F49: =H47 -> 117056.34 | G49: 0 | H49: =IF(G49>0,(G49*F49*E49),(F49*E49)) -> 11705.634
A50: G-01-06 | C50: Concreto de 27,6 Mpa (4000 PSI) (Producción) | D50: M3 | F50: =ROUND(SUM(H50:H57),0) -> 563161
A51: MAT | B51: MAT,027 | C51: Agua | D51: Lt | E51: 200 | F51: =VLOOKUP(B51,'BASE DE DATOS'!$A$5:$E$997,5,FALSE) -> 19 | G51: 1.03 | H51: =IF(G51>0,(G51*F51*E51),(F51*E51)) -> 3914
B52: MAT,040 | C52: Arena | D52: M3 | E52: 0.67 | F52: =VLOOKUP(B52,'BASE DE DATOS'!$A$5:$E$997,5,FALSE) -> 71990 | G52: 1.03 | H52: =IF(G52>0,(G52*F52*E52),(F52*E52)) -> 49680.299
B53: MAT,068 | C53: Cemento gris saco por 50 kilos | D53: Sc | E53: 9.5 | F53: =VLOOKUP(B53,'BASE DE DATOS'!$A$5:$E$997,5,FALSE) -> 32900 | G53: 1.03 | H53: =IF(G53>0,(G53*F53*E53),(F53*E53)) -> 321926.5
B54: MAT,410 | C54: Triturado 3/4" para concreto | D54: M3 | E54: 0.67 | F54: =VLOOKUP(B54,'BASE DE DATOS'!$A$5:$E$997,5,FALSE) -> 74972.5 | G54: 1.03 | H54: =IF(G54>0,(G54*F54*E54),(F54*E54)) -> 51738.522
A55: M. O. | B55: MOB013 | C55: Cuadrilla C 1 Of + 7 Ay (jornal + prestaciones) | D55: Día | E55: 1 | F55: =VLOOKUP(B55,'BASE DE DATOS'!$A$5:$E$997,5,FALSE) -> 780376 | G55: =1/6.66667 -> 0.14999993 | H55: =IF(G55>0,(G55*F55*E55),(F55*E55)) -> 117056.34
A56: EQUIPO | B56: EQU003 | C56: Concretadora gasolina de 1 o 1 1/2 sacos | D56: Día | E56: 1 | F56: =VLOOKUP(B56,'BASE DE DATOS'!$A$5:$E$997,5,FALSE) -> 71400 | G56: =1/10 -> 0.1 | H56: =IF(G56>0,(G56*F56*E56),(F56*E56)) -> 7140
B57: EQU002 | C57: Herramienta menor (% mano obra) | D57: %MO | E57: 0.1 | F57: =H55 -> 117056.34 | G57: 0 | H57: =IF(G57>0,(G57*F57*E57),(F57*E57)) -> 11705.634
A58: G-01-07 | C58: Concreto de 20,7 Mpa (3000 PSI) impermeabilizado (Producción) | D58: M3 | F58: =SUM(H58:H60) -> 523640.36
A59: MAT | B59: MAT,187 | C59: Impermeabilizante para concreto | D59: Kg | E59: 1.75 | F59: =VLOOKUP(B59,'BASE DE DATOS'!$A$5:$E$997,5,FALSE) -> 22945 | G59: 1.03 | H59: =IF(G59>0,(G59*F59*E59),(F59*E59)) -> 41358.363
A60: ÍTEMS | B60: G-01-04 | C60: Concreto de 20,7 Mpa (Producción) | D60: M3 | E60: 1 | F60: =F34 -> 482282 | G60: 0 | H60: =IF(G60>0,(G60*F60*E60),(F60*E60)) -> 482282
A61: G-01-08 | C61: Concreto de 20,7 Mpa (3000 PSI) acelerado (Producción) | D61: M3 | F61: =ROUND(SUM(H61:H63),0) -> 628991
A62: MAT | B62: MAT,009 | C62: Acelerante para concreto tipo Sikaset | D62: Kg | E62: 7 | F62: =VLOOKUP(B62,'BASE DE DATOS'!$A$5:$E$997,5,FALSE) -> 20348 | G62: 1.03 | H62: =IF(G62>0,(G62*F62*E62),(F62*E62)) -> 146709.08
A63: ÍTEMS | B63: G-01-04 | C63: Concreto de 20,7 Mpa (Producción) | D63: M3 | E63: 1 | F63: =F34 -> 482282 | G63: 0 | H63: =IF(G63>0,(G63*F63*E63),(F63*E63)) -> 482282
A64: G-01-09 | C64: Concreto de 27,6 Mpa (4000 PSI) impermeabilizado (Producción) | D64: M3 | F64: =ROUND(SUM(H64:H66),0) -> 604519
A65: MAT | B65: MAT,187 | C65: Impermeabilizante para concreto | D65: Kg | E65: 1.75 | F65: =VLOOKUP(B65,'BASE DE DATOS'!$A$5:$E$997,5,FALSE) -> 22945 | G65: 1.03 | H65: =IF(G65>0,(G65*F65*E65),(F65*E65)) -> 41358.363
A66: ÍTEMS | B66: G-01-06 | C66: Concreto de 27,6 Mpa (Producción) | D66: M3 | E66: 1 | F66: =F50 -> 563161 | G66: 0 | H66: =IF(G66>0,(G66*F66*E66),(F66*E66)) -> 563161
A67: G-01-10 | C67: Concreto de 27,6 Mpa (4000 PSI) acelerado (Producción) | D67: M3 | F67: =ROUND(SUM(H67:H69),0) -> 730829
A68: MAT | B68: MAT,009 | C68: Acelerante para concreto tipo Sikaset | D68: Kg | E68: 8 | F68: =VLOOKUP(B68,'BASE DE DATOS'!$A$5:$E$997,5,FALSE) -> 20348 | G68: 1.03 | H68: =IF(G68>0,(G68*F68*E68),(F68*E68)) -> 167667.52
A69: ÍTEMS | B69: G-01-06 | C69: Concreto de 27,6 Mpa (Producción) | D69: M3 | E69: 1 | F69: =F50 -> 563161 | G69: 0 | H69: =IF(G69>0,(G69*F69*E69),(F69*E69)) -> 563161
A70: G-01-11 | C70: Concreto ciclópeo (Producción) | D70: M3 | F70: =ROUND(SUM(H70:H73),0) -> 475537
A71: MAT | B71: MAT,296 | C71: Piedra media songa | D71: M3 | E71: 0.4 | F71: =VLOOKUP(B71,'BASE DE DATOS'!$A$5:$E$997,5,FALSE) -> 77345 | G71: 1.03 | H71: =IF(G71>0,(G71*F71*E71),(F71*E71)) -> 31866.14
A72: ÍTEMS | B72: G-01-04 | C72: Concreto de 20,7 Mpa (Producción) | D72: M3 | E72: 0.6 | F72: =F34 -> 482282 | G72: 0 | H72: =IF(G72>0,(G72*F72*E72),(F72*E72)) -> 289369.2
A73: M. O. | B73: MOB005 | C73: Cuadrilla A 1 Of + 4 Ay (jornal + prestaciones) | D73: Día | E73: 1 | F73: =VLOOKUP(B73,'BASE DE DATOS'!$A$5:$E$997,5,FALSE) -> 514339 | G73: =1/4*1.2 -> 0.3 | H73: =IF(G73>0,(G73*F73*E73),(F73*E73)) -> 154301.7
A74: G-01-12 | C74: Concreto fluido 13,8 Mpa (2000 PSI) tamaño máximo 1/2" | D74: M3 | F74: =ROUND(SUM(H74:H78),0) -> 537482
A75: MAT | B75: MAT,145 | C75: Fluidificante para concretos | D75: Kg | E75: 3.5 | F75: =VLOOKUP(B75,'BASE DE DATOS'!$A$5:$E$997,5,FALSE) -> 20276 | G75: 1.03 | H75: =IF(G75>0,(G75*F75*E75),(F75*E75)) -> 73094.98
A76: ÍTEMS | B76: G-01-02 | C76: Concreto de 13,8 Mpa (Producción) | D76: M3 | E76: 1 | F76: =F18 -> 421463 | G76: 1.05 | H76: =IF(G76>0,(G76*F76*E76),(F76*E76)) -> 442536.15
A77: M. O. | B77: MOB015 | C77: Cuadrilla E 1 Of + 1 Ay (jornal + prestaciones) | D77: Día | E77: 1 | F77: =VLOOKUP(B77,'BASE DE DATOS'!$A$5:$E$997,5,FALSE) -> 248302 | G77: =1/12.5 -> 0.08 | H77: =IF(G77>0,(G77*F77*E77),(F77*E77)) -> 19864.16
A78: EQUIPO | B78: EQU002 | C78: Herramienta menor (% mano obra) | D78: %MO | E78: 0.1 | F78: =H77 -> 19864.16 | G78: 0 | H78: =IF(G78>0,(G78*F78*E78),(F78*E78)) -> 1986.416
A79: G-01-13 | C79: Concreto fluido 17,2 Mpa (2500 PSI) (Producción) | D79: M3 | F79: =ROUND(SUM(H79:H83),0) -> 548852
A80: MAT | B80: MAT,145 | C80: Fluidificante para concretos | D80: Kg | E80: 1.75 | F80: =VLOOKUP(B80,'BASE DE DATOS'!$A$5:$E$997,5,FALSE) -> 20276 | G80: 1.03 | H80: =IF(G80>0,(G80*F80*E80),(F80*E80)) -> 36547.49
A81: ÍTEMS | B81: G-01-03 | C81: Concreto de 17,2 Mpa (Producción) | D81: M3 | E81: 1 | F81: =F26 -> 456694 | G81: 1.05 | H81: =IF(G81>0,(G81*F81*E81),(F81*E81)) -> 479528.7
A82: M. O. | B82: MOB015 | C82: Cuadrilla E 1 Of + 1 Ay (jornal + prestaciones) | D82: Día | E82: 1 | F82: =VLOOKUP(B82,'BASE DE DATOS'!$A$5:$E$997,5,FALSE) -> 248302 | G82: =1/8.3333 -> 0.12000048 | H82: =IF(G82>0,(G82*F82*E82),(F82*E82)) -> 29796.359
A83: EQUIPO | B83: EQU002 | C83: Herramienta menor (% mano obra) | D83: %MO | E83: 0.1 | F83: =H82 -> 29796.359 | G83: 0 | H83: =IF(G83>0,(G83*F83*E83),(F83*E83)) -> 2979.6359
A84: G-01-14 | C84: Mortero 1:2 (Producción) | D84: M3 | F84: =ROUND(SUM(H84:H89),0) -> 636191
A85: MAT | B85: MAT,027 | C85: Agua | D85: Lt | E85: 250 | F85: =VLOOKUP(B85,'BASE DE DATOS'!$A$5:$E$997,5,FALSE) -> 19 | G85: 1.03 | H85: =IF(G85>0,(G85*F85*E85),(F85*E85)) -> 4892.5
B86: MAT,040 | C86: Arena | D86: M3 | E86: 0.97 | F86: =VLOOKUP(B86,'BASE DE DATOS'!$A$5:$E$997,5,FALSE) -> 71990 | G86: 1.03 | H86: =IF(G86>0,(G86*F86*E86),(F86*E86)) -> 71925.209
B87: MAT,068 | C87: Cemento gris saco por 50 kilos | D87: Sc | E87: 12.5 | F87: =VLOOKUP(B87,'BASE DE DATOS'!$A$5:$E$997,5,FALSE) -> 32900 | G87: 1.03 | H87: =IF(G87>0,(G87*F87*E87),(F87*E87)) -> 423587.5
A88: M. O. | B88: MOB005 | C88: Cuadrilla A 1 Of + 4 Ay (jornal + prestaciones) | D88: Día | E88: 1 | F88: =VLOOKUP(B88,'BASE DE DATOS'!$A$5:$E$997,5,FALSE) -> 514339 | G88: =1/4.16667 -> 0.23999981 | H88: =IF(G88>0,(G88*F88*E88),(F88*E88)) -> 123441.26
A89: EQUIPO | B89: EQU002 | C89: Herramienta menor (% mano obra) | D89: %MO | E89: 0.1 | F89: =H88 -> 123441.26 | G89: 0 | H89: =IF(G89>0,(G89*F89*E89),(F89*E89)) -> 12344.126
A90: G-01-15 | C90: Mortero 1:3 (Producción) | D90: M3 | F90: =ROUND(SUM(H90:H95),0) -> 525897
A91: MAT | B91: MAT,027 | C91: Agua | D91: Lt | E91: 220 | F91: =VLOOKUP(B91,'BASE DE DATOS'!$A$5:$E$997,5,FALSE) -> 19 | G91: 1.03 | H91: =IF(G91>0,(G91*F91*E91),(F91*E91)) -> 4305.4
B92: MAT,040 | C92: Arena | D92: M3 | E92: 1.09 | F92: =VLOOKUP(B92,'BASE DE DATOS'!$A$5:$E$997,5,FALSE) -> 71990 | G92: 1.03 | H92: =IF(G92>0,(G92*F92*E92),(F92*E92)) -> 80823.173
B93: MAT,068 | C93: Cemento gris saco por 50 kilos | D93: Sc | E93: 9 | F93: =VLOOKUP(B93,'BASE DE DATOS'!$A$5:$E$997,5,FALSE) -> 32900 | G93: 1.03 | H93: =IF(G93>0,(G93*F93*E93),(F93*E93)) -> 304983
A94: M. O. | B94: MOB005 | C94: Cuadrilla A 1 Of + 4 Ay (jornal + prestaciones) | D94: Día | E94: 1 | F94: =VLOOKUP(B94,'BASE DE DATOS'!$A$5:$E$997,5,FALSE) -> 514339 | G94: =1/4.16667 -> 0.23999981 | H94: =IF(G94>0,(G94*F94*E94),(F94*E94)) -> 123441.26
A95: EQUIPO | B95: EQU002 | C95: Herramienta menor (% mano obra) | D95: %MO | E95: 0.1 | F95: =H94 -> 123441.26 | G95: 0 | H95: =IF(G95>0,(G95*F95*E95),(F95*E95)) -> 12344.126
A96: G-01-16 | C96: Mortero 1:4 (Producción) | D96: M3 | F96: =ROUND(SUM(H96:H101),0) -> 471394
A97: MAT | B97: MAT,027 | C97: Agua | D97: Lt | E97: 200 | F97: =VLOOKUP(B97,'BASE DE DATOS'!$A$5:$E$997,5,FALSE) -> 19 | G97: 1.03 | H97: =IF(G97>0,(G97*F97*E97),(F97*E97)) -> 3914
B98: MAT,040 | C98: Arena | D98: M3 | E98: 1.16 | F98: =VLOOKUP(B98,'BASE DE DATOS'!$A$5:$E$997,5,FALSE) -> 71990 | G98: 1.03 | H98: =IF(G98>0,(G98*F98*E98),(F98*E98)) -> 86013.652
B99: MAT,068 | C99: Cemento gris saco por 50 kilos | D99: Sc | E99: 7.25 | F99: =VLOOKUP(B99,'BASE DE DATOS'!$A$5:$E$997,5,FALSE) -> 32900 | G99: 1.03 | H99: =IF(G99>0,(G99*F99*E99),(F99*E99)) -> 245680.75
A100: M. O. | B100: MOB005 | C100: Cuadrilla A 1 Of + 4 Ay (jornal + prestaciones) | D100: Día | E100: 1 | F100: =VLOOKUP(B100,'BASE DE DATOS'!$A$5:$E$997,5,FALSE) -> 514339 | G100: =1/4.16667 -> 0.23999981 | H100: =IF(G100>0,(G100*F100*E100),(F100*E100)) -> 123441.26
A101: EQUIPO | B101: EQU002 | C101: Herramienta menor (% mano obra) | D101: %MO | E101: 0.1 | F101: =H100 -> 123441.26 | G101: 0 | H101: =IF(G101>0,(G101*F101*E101),(F101*E101)) -> 12344.126
...

Sheet  VÍAS
A1: IMPORTANTE: Los presentes precios unitarios de referencia fueron calculados en la ciudad de Pereira (zona urbana), por tanto deben ser modificados (incrementados) para las áreas rurales de los municipios de Pereira, Dosquebradas y La Virginia y en las áreas urbanas y rurales de los demás municipios, según el caso. Por estar basados en precios del mercado están sujetos a las variaciones del mismo, las cuales se aplicarán sin previo aviso. Pueden presentar inconsistencias, que se corregirán en el momento de ser detectadas.
A2: El presente listado es una simple guía para el Evaluador, no se constituye en camisa de fuerza, ni es obligatoria su aplicación, quien los utilice, deberá estudiarlos y estar consiente de sus bondades y limitaciones, y será su buen juicio el que prime al final, en cada caso. Dadas las variaciones del precio del dólar que influye principalmente en los insumos derivados del petróleo, el cobre, el cemento e insumos derivados, el PVC, etc., es importante que el Evaluador verifique el costo básico de estos insumos cada vez que pretenda hacer una evaluación o cotización.
A3: Los presente análisis incluyen para la mano de obra los ítems de salud e I.C.B.F., será responsabilidad del Evaluador mantenerlos o suprimirlos según la normatividad existente vigente y el caso particular en donde se aplicarán.
A4: De todos los Ítems posibles se ha suprimido el transporte de materiales, por tanto el evaluador deberá considerarlo como ítems aparte en cada evaluación o cotización. Por favor leer la Introducción.
A6: 2.- CONSTRUCCIÓN, MANTENIMIENTO Y MEJORAMIENTO DE VÍAS
A7: 2 - 01 PRELIMINARES
A8: ÍTEM | B8: CÓDIGO | C8: DESCRIPCIÓN | D8: UN | E8: CANT | F8: VR. UN. | G8: RENDIMIENTO, USOS, DESPEDICIOS | H8: VR. PARCIAL
A9: 2-01-01 | C9: Localización y replanteo para pavimentación de vías (3 líneas, 3 instancias) | D9: M | F9: =ROUND(SUM(H9:H15),0) -> 5395
A10: MAT | B10: MAT,830 | C10: Manutención y gastos asociados comisión de topografía | D10: M | E10: 1 | F10: =VLOOKUP(B10,'BASE DE DATOS'!$A$5:$E$997,5,FALSE) -> 35000 | G10: =1/175 -> 0.0057142857 | H10: =IF(G10>0,(G10*F10*E10),(F10*E10)) -> 200
A11: M. O. | B11: MOB010 | C11: Comisión topografía (Topógrafo + Cadenero 1 + Cadenero 2) | D11: Día | E11: 1 | F11: =VLOOKUP(B11,'BASE DE DATOS'!$A$5:$E$997,5,FALSE) -> 375244 | G11: =1/175 -> 0.0057142857 | H11: =IF(G11>0,(G11*F11*E11),(F11*E11)) -> 2144.2514
A12: EQUIPO | B12: EQU070 | C12: Administración comisión de topografía | D12: Día | E12: 1 | F12: =VLOOKUP(B12,'BASE DE DATOS'!$A$5:$E$997,5,FALSE) -> 98462 | G12: =1/175 -> 0.0057142857 | H12: =IF(G12>0,(G12*F12*E12),(F12*E12)) -> 562.64
B13: EQU033 | C13: Alquiler de campero o camioneta modelo > 2016 de 2.600 o más C. C., con conductor | D13: Día | E13: 1 | F13: =VLOOKUP(B13,'BASE DE DATOS'!$A$5:$E$997,5,FALSE) -> 378333.33 | G13: =1/175 -> 0.0057142857 | H13: =IF(G13>0,(G13*F13*E13),(F13*E13)) -> 2161.9048
B14: EQU069 | C14: Computador y gastos de papeleria comisión de topografía | D14: Día | E14: 1 | F14: =VLOOKUP(B14,'BASE DE DATOS'!$A$5:$E$997,5,FALSE) -> 7000 | G14: =1/175 -> 0.0057142857 | H14: =IF(G14>0,(G14*F14*E14),(F14*E14)) -> 40
B15: EQU011 | C15: Equipo de topografía: Estación total, nivel de precisión y herramientas | D15: Día | E15: 1 | F15: =VLOOKUP(B15,'BASE DE DATOS'!$A$5:$E$997,5,FALSE) -> 50000 | G15: =1/175 -> 0.0057142857 | H15: =IF(G15>0,(G15*F15*E15),(F15*E15)) -> 285.71429
A16: 2-01-02 | C16: Levantamiento georreferenciado con dron | D16: Ha | F16: =ROUND(SUM(H16:H17),0) -> 1300000
A17: EQUIPO | B17: EQU071 | C17: Equipo dron LIDAR o similar con GNSS doble fecuencia, incluye levantamiento de nube de datos georreferenciados a vétices del IGAC, procesamiento de información en sotfware fotogramétrico especializado, en coordenadas MAGNA-SIRGAS para los siguientes entregables: Informe de procesamiento, superficie clasificada ortomosaicos en formato DWG tanto de terreno como de superficie y RGB, curvas de nivel - model digital del terreno (DTM), planos. Incluye un Ingeniero Coordinador del levantamiento, piloto certificado del dron, Auxiliar y/o Dibujante Topográfico cumpliendo toda su cargas prestacional, desplazamientos, registro fotográfico, mínimo 1 hectarea y 4 puntos de control | D17: Ha | E17: 1 | F17: =VLOOKUP(B17,'BASE DE DATOS'!$A$5:$E$997,5,FALSE) -> 1300000 | G17: 0 | H17: =IF(G17>0,(G17*F17*E17),(F17*E17)) -> 1300000
A18: 2-01-04 | C18: Remoción de derrumbes y disposición final | D18: M3 | F18: =ROUND(SUM(H18:H22),0) -> 22738
A19: ÍTEMS | B19: G-03-05 | C19: Disposición en botadero | D19: M3 | E19: 1 | F19: =CONSTRUCCION!F137 -> 17143 | G19: 1 | H19: =IF(G19>0,(G19*F19*E19),(F19*E19)) -> 17143
A20: M. O. | B20: MOB003 | C20: Ayudante (jornal + prestaciones) | D20: Día | E20: 1 | F20: =VLOOKUP(B20,'BASE DE DATOS'!$A$5:$E$997,5,FALSE) -> 88679 | G20: =1/264 -> 0.0037878788 | H20: =IF(G20>0,(G20*F20*E20),(F20*E20)) -> 335.9053
A21: EQUIPO | B21: EQU004 | C21: Buldócer D65-8 | D21: Hr | E21: 1 | F21: =VLOOKUP(B21,'BASE DE DATOS'!$A$5:$E$997,5,FALSE) -> 238000 | G21: =1/100 -> 0.01 | H21: =IF(G21>0,(G21*F21*E21),(F21*E21)) -> 2380
B22: EQU009 | C22: Cargador 930 1,5 yd3 | D22: Hr | E22: 1 | F22: =VLOOKUP(B22,'BASE DE DATOS'!$A$5:$E$997,5,FALSE) -> 190000 | G22: =1/66 -> 0.015151515 | H22: =IF(G22>0,(G22*F22*E22),(F22*E22)) -> 2878.7879
A23: 2-01-03 | C23: Rocería manual para cooperativas, incluye limpieza de obras de arte, retiro de sobrantes | D23: Km | F23: =ROUND(SUM(H23:H40),0) -> 1841109
A24: MATERIALES | B24: MAT,654 | C24: Azadones con cabo | D24: Un | E24: 5 | F24: =VLOOKUP(B24,'BASE DE DATOS'!$A$5:$E$997,5,FALSE) -> 44900 | G24: =1/50 -> 0.02 | H24: =IF(G24>0,(G24*F24*E24),(F24*E24)) -> 4490
B25: MAT,057 | C25: Buggy liviano antipinchazo 6 pies3 | D25: Un | E25: 2 | F25: =VLOOKUP(B25,'BASE DE DATOS'!$A$5:$E$997,5,FALSE) -> 299900 | G25: =1/50 -> 0.02 | H25: =IF(G25>0,(G25*F25*E25),(F25*E25)) -> 11996
B26: MAT,064 | C26: Capa en PVC para adulto contra lluvia | D26: Un | E26: 9 | F26: =VLOOKUP(B26,'BASE DE DATOS'!$A$5:$E$997,5,FALSE) -> 34900 | G26: =1/50 -> 0.02 | H26: =IF(G26>0,(G26*F26*E26),(F26*E26)) -> 6282
B27: MAT,066 | C27: Casco construcción cremallera colores blanco, rojo, amarillo, azul, dieléctrico | D27: Un | E27: 9 | F27: =VLOOKUP(B27,'BASE DE DATOS'!$A$5:$E$997,5,FALSE) -> 31900 | G27: =1/50 -> 0.02 | H27: =IF(G27>0,(G27*F27*E27),(F27*E27)) -> 5742
B28: MAT,080 | C28: Chaleco fluorescente con cinta reflectiva para obras | D28: Un | E28: 9 | F28: =VLOOKUP(B28,'BASE DE DATOS'!$A$5:$E$997,5,FALSE) -> 24325 | G28: =1/50 -> 0.02 | H28: =IF(G28>0,(G28*F28*E28),(F28*E28)) -> 4378.5
B29: MAT,095 | C29: Cinta de señalización C 6 | D29: M | E29: 1000 | F29: =VLOOKUP(B29,'BASE DE DATOS'!$A$5:$E$997,5,FALSE) -> 68 | G29: =1/2 -> 0.5 | H29: =IF(G29>0,(G29*F29*E29),(F29*E29)) -> 34000
B30: MAT,111 | C30: Conos viales de 70 cm Norma Invías Cap IV cinta reflectiva | D30: Un | E30: 6 | F30: =VLOOKUP(B30,'BASE DE DATOS'!$A$5:$E$997,5,FALSE) -> 74900 | G30: =1/50 -> 0.02 | H30: =IF(G30>0,(G30*F30*E30),(F30*E30)) -> 8988
B31: MAT,219 | C31: Lima plana con mango de 8" | D31: Un | E31: 18 | F31: =VLOOKUP(B31,'BASE DE DATOS'!$A$5:$E$997,5,FALSE) -> 25900 | G31: =1/50 -> 0.02 | H31: =IF(G31>0,(G31*F31*E31),(F31*E31)) -> 9324
B32: MAT,231 | C32: Machete mínimo de 22" | D32: Un | E32: 18 | F32: =VLOOKUP(B32,'BASE DE DATOS'!$A$5:$E$997,5,FALSE) -> 24900 | G32: =1/50 -> 0.02 | H32: =IF(G32>0,(G32*F32*E32),(F32*E32)) -> 8964
B33: MAT,277 | C33: Pala redonda con cabo | D33: Un | E33: 5 | F33: =VLOOKUP(B33,'BASE DE DATOS'!$A$5:$E$997,5,FALSE) -> 76900 | G33: =1/50 -> 0.02 | H33: =IF(G33>0,(G33*F33*E33),(F33*E33)) -> 7690
B34: MAT,278 | C34: Paleta pare - siga en polietileno y texto reflectivo, de 45 cm | D34: Un | E34: 2 | F34: =VLOOKUP(B34,'BASE DE DATOS'!$A$5:$E$997,5,FALSE) -> 55340 | G34: =1/50 -> 0.02 | H34: =IF(G34>0,(G34*F34*E34),(F34*E34)) -> 2213.6
B35: MAT,280 | C35: Papelería, fotografías, fotocopias - rocerías | D35: Mes | E35: 1 | F35: =VLOOKUP(B35,'BASE DE DATOS'!$A$5:$E$997,5,FALSE) -> 63997 | G35: 0 | H35: =IF(G35>0,(G35*F35*E35),(F35*E35)) -> 63997
B36: MAT,281 | C36: Par de botas lisa dieléctrico con puntera en acero de caucho, cinta amarilla, puntera y plantilla de acero | D36: Un | E36: 9 | F36: =VLOOKUP(B36,'BASE DE DATOS'!$A$5:$E$997,5,FALSE) -> 169900 | G36: =1/50 -> 0.02 | H36: =IF(G36>0,(G36*F36*E36),(F36*E36)) -> 30582
B37: MAT,295 | C37: Pica con cabo | D37: Un | E37: 5 | F37: =VLOOKUP(B37,'BASE DE DATOS'!$A$5:$E$997,5,FALSE) -> 84900 | G37: =1/50 -> 0.02 | H37: =IF(G37>0,(G37*F37*E37),(F37*E37)) -> 8490
B38: MAT,348 | C38: Señal (grupo1). Tablero en lámina galvanizada de 75 cm x 75 cm C 16 reflectivo tipo III | D38: Un | E38: 4 | F38: =VLOOKUP(B38,'BASE DE DATOS'!$A$5:$E$997,5,FALSE) -> 313200 | G38: =1/100 -> 0.01 | H38: =IF(G38>0,(G38*F38*E38),(F38*E38)) -> 12528
A39: M. O. | B39: MOB003 | C39: Ayudante (jornal + prestaciones) | D39: Día | E39: 1 | F39: =VLOOKUP(B39,'BASE DE DATOS'!$A$5:$E$997,5,FALSE) -> 88679 | G39: 18 | H39: =IF(G39>0,(G39*F39*E39),(F39*E39)) -> 1596222
A40: EQUIPO | B40: EQU033 | C40: Alquiler de campero o camioneta Mod. > 2016 de 2.600 o más C. C., con conductor | D40: Mes | E40: 1 | F40: =VLOOKUP(B40,'BASE DE DATOS'!$A$5:$E$997,5,FALSE) -> 378333.33 | G40: =1/15 -> 0.066666667 | H40: =IF(G40>0,(G40*F40*E40),(F40*E40)) -> 25222.222
A41: 2-01-05 | C41: Rocería de taludes a = 3 m, incluye conformación de cunetas en tierra o limpieza de cunetas en contrato y retiro manual de sobrantes | D41: Km | F41: =ROUND(SUM(H41:H45),0) -> 1219867
A42: MAT | B42: MAT,180 | C42: Herbicida | D42: Lt | E42: 0.2 | F42: =VLOOKUP(B42,'BASE DE DATOS'!$A$5:$E$997,5,FALSE) -> 32900 | G42: 1.03 | H42: =IF(G42>0,(G42*F42*E42),(F42*E42)) -> 6777.4
A43: M. O. | B43: MOB013 | C43: Cuadrilla C 1 Of + 7 Ay (jornal + prestaciones) | D43: Día | E43: 1 | F43: =VLOOKUP(B43,'BASE DE DATOS'!$A$5:$E$997,5,FALSE) -> 780376 | G43: 1.33 | H43: =IF(G43>0,(G43*F43*E43),(F43*E43)) -> 1037900.1
A44: EQUIPO | B44: EQU014 | C44: Guadaña | D44: Día | E44: 1 | F44: =VLOOKUP(B44,'BASE DE DATOS'!$A$5:$E$997,5,FALSE) -> 35700 | G44: 2 | H44: =IF(G44>0,(G44*F44*E44),(F44*E44)) -> 71400
B45: EQU002 | C45: Herramienta menor (% mano obra) | D45: %MO | E45: 0.1 | F45: =H43 -> 1037900.1 | G45: 0 | H45: =IF(G45>0,(G45*F45*E45),(F45*E45)) -> 103790.01
A46: 2-01-06 | C46: Desmonte y limpieza en bosque | D46: Ha | F46: =ROUND(SUM(H46:H50),0) -> 3328930
A47: M. O. | B47: MOB018 | C47: Cuadrilla H 4 Ay (jornal + prestaciones) | D47: Día | E47: 1 | F47: =VLOOKUP(B47,'BASE DE DATOS'!$A$5:$E$997,5,FALSE) -> 354716 | G47: =1/1.2 -> 0.83333333 | H47: =IF(G47>0,(G47*F47*E47),(F47*E47)) -> 295596.67
A48: EQUIPO | B48: EQU004 | C48: Andamio tubular certificado incluye arnés y línea de vida | D48: Hr | E48: 1 | F48: =VLOOKUP(B48,'BASE DE DATOS'!$A$5:$E$997,5,FALSE) -> 238000 | G48: =1/0.15 -> 6.6666667 | H48: =IF(G48>0,(G48*F48*E48),(F48*E48)) -> 1586666.7
B49: EQU009 | C49: Cargador 930 1,5 yd3 | D49: Hr | E49: 1 | F49: =VLOOKUP(B49,'BASE DE DATOS'!$A$5:$E$997,5,FALSE) -> 190000 | G49: =1/0.15 -> 6.6666667 | H49: =IF(G49>0,(G49*F49*E49),(F49*E49)) -> 1266666.7
B50: EQU059 | C50: Motosierra, 93.6 cm3 - 7.1 HP, 45-90 cm - 7.9 kg | D50: Día | E50: 1 | F50: =VLOOKUP(B50,'BASE DE DATOS'!$A$5:$E$997,5,FALSE) -> 27000 | G50: =1/0.15 -> 6.6666667 | H50: =IF(G50>0,(G50*F50*E50),(F50*E50)) -> 180000
A51: 2-01-07 | C51: Desmonte y limpieza en zonas no boscosas | D51: Ha | F51: =ROUND(SUM(H51:H54),0) -> 124283
A52: M. O. | B52: MOB003 | C52: Ayudante (jornal + prestaciones) | D52: Día | E52: 2 | F52: =VLOOKUP(B52,'BASE DE DATOS'!$A$5:$E$997,5,FALSE) -> 88679 | G52: =1/2.88 -> 0.34722222 | H52: =IF(G52>0,(G52*F52*E52),(F52*E52)) -> 61582.639
A53: EQUIPO | B53: EQU014 | C53: Guadaña | D53: Día | E53: 1 | F53: =VLOOKUP(B53,'BASE DE DATOS'!$A$5:$E$997,5,FALSE) -> 35700 | G53: 1 | H53: =IF(G53>0,(G53*F53*E53),(F53*E53)) -> 35700
B54: EQU059 | C54: Motosierra, 93.6 cm3 - 7.1 HP, 45-90 cm - 7.9 kg | D54: Día | E54: 1 | F54: =VLOOKUP(B54,'BASE DE DATOS'!$A$5:$E$997,5,FALSE) -> 27000 | G54: 1 | H54: =IF(G54>0,(G54*F54*E54),(F54*E54)) -> 27000
A55: 2-01-08 | C55: Corte de pavimento rígido con cortadora autopropulsada | D55: M | F55: =ROUND(SUM(H55:H59),0) -> 6712
A56: MAT | B56: MAT,027 | C56: Agua | D56: Lt | E56: 1 | F56: =VLOOKUP(B56,'BASE DE DATOS'!$A$5:$E$997,5,FALSE) -> 19 | G56: =1 -> 1 | H56: =IF(G56>0,(G56*F56*E56),(F56*E56)) -> 19
B57: MAT,153 | C57: Gasolina | D57: Gl | E57: 1 | F57: =VLOOKUP(B57,'BASE DE DATOS'!$A$5:$E$997,5,FALSE) -> 16241 | G57: =1/70 -> 0.014285714 | H57: =IF(G57>0,(G57*F57*E57),(F57*E57)) -> 232.01429
A58: M. O. | B58: MOB004 | C58: Ayudante práctico (jornal + prestaciones) | D58: Día | E58: 1 | F58: =VLOOKUP(B58,'BASE DE DATOS'!$A$5:$E$997,5,FALSE) -> 124151 | G58: =1/45 -> 0.022222222 | H58: =IF(G58>0,(G58*F58*E58),(F58*E58)) -> 2758.9111
A59: EQUIPO | B59: EQU031 | C59: Cortadora de concreto con disco | D59: Día | E59: 1 | F59: =VLOOKUP(B59,'BASE DE DATOS'!$A$5:$E$997,5,FALSE) -> 166600 | G59: =1/45 -> 0.022222222 | H59: =IF(G59>0,(G59*F59*E59),(F59*E59)) -> 3702.2222
A60: 2-01-09 | C60: Corte de pavimento flexible con cortadora autopropulsada | D60: M | F60: =ROUND(SUM(H60:H64),0) -> 4683
A61: MAT | B61: MAT,027 | C61: Agua | D61: Lt | E61: 1 | F61: =VLOOKUP(B61,'BASE DE DATOS'!$A$5:$E$997,5,FALSE) -> 19 | G61: =1 -> 1 | H61: =IF(G61>0,(G61*F61*E61),(F61*E61)) -> 19
B62: MAT,153 | C62: Gasolina | D62: Gl | E62: 1 | F62: =VLOOKUP(B62,'BASE DE DATOS'!$A$5:$E$997,5,FALSE) -> 16241 | G62: =1/70 -> 0.014285714 | H62: =IF(G62>0,(G62*F62*E62),(F62*E62)) -> 232.01429
A63: M. O. | B63: MOB004 | C63: Ayudante práctico (jornal + prestaciones) | D63: Día | E63: 1 | F63: =VLOOKUP(B63,'BASE DE DATOS'!$A$5:$E$997,5,FALSE) -> 124151 | G63: =1/75 -> 0.013333333 | H63: =IF(G63>0,(G63*F63*E63),(F63*E63)) -> 1655.3467
A64: EQUIPO | B64: EQU031 | C64: Cortadora de concreto con disco | D64: Día | E64: 1 | F64: =VLOOKUP(B64,'BASE DE DATOS'!$A$5:$E$997,5,FALSE) -> 166600 | G64: =1/60 -> 0.016666667 | H64: =IF(G64>0,(G64*F64*E64),(F64*E64)) -> 2776.6667
A65: 2-01-10 | C65: Demolición cono cámara | D65: Un | F65: =ROUND(SUM(H65:H68),0) -> 161396
A66: M. O. | B66: MOB004 | C66: Ayudante práctico (jornal + prestaciones) | D66: Día | E66: 1 | F66: =VLOOKUP(B66,'BASE DE DATOS'!$A$5:$E$997,5,FALSE) -> 124151 | G66: =1 -> 1 | H66: =IF(G66>0,(G66*F66*E66),(F66*E66)) -> 124151
B67: MOB011 | C67: Acarreo horizontal | D67: %MO | E67: 0.1 | F67: =H66 -> 124151 | G67: 0 | H67: =IF(G67>0,(G67*F67*E67),(F67*E67)) -> 12415.1
A68: EQUIPO | B68: EQU002 | C68: Herramienta menor (% mano obra) | D68: %MO | E68: 0.2 | F68: =H66 -> 124151 | G68: 0 | H68: =IF(G68>0,(G68*F68*E68),(F68*E68)) -> 24830.2
A69: 2-01-11 | C69: Demolición cuerpo cámara | D69: M | F69: =ROUND(SUM(H69:H72),0) -> 192138
A70: M. O. | B70: MOB003 | C70: Ayudante (jornal + prestaciones) | D70: Día | E70: 1 | F70: =VLOOKUP(B70,'BASE DE DATOS'!$A$5:$E$997,5,FALSE) -> 88679 | G70: =1/0.6 -> 1.6666667 | H70: =IF(G70>0,(G70*F70*E70),(F70*E70)) -> 147798.33
B71: MOB011 | C71: Acarreo horizontal | D71: %MO | E71: 0.1 | F71: =H70 -> 147798.33 | G71: 0 | H71: =IF(G71>0,(G71*F71*E71),(F71*E71)) -> 14779.833
A72: EQUIPO | B72: EQU002 | C72: Herramienta menor (% mano obra) | D72: %MO | E72: 0.2 | F72: =H70 -> 147798.33 | G72: 0 | H72: =IF(G72>0,(G72*F72*E72),(F72*E72)) -> 29559.667
A73: 2-01-12 | C73: Demolición con compresor de sardinel | D73: M | F73: =ROUND(SUM(H73:H77),0) -> 6090
A74: M. O. | B74: MOB003 | C74: Ayudante (jornal + prestaciones) | D74: Día | E74: 2 | F74: =VLOOKUP(B74,'BASE DE DATOS'!$A$5:$E$997,5,FALSE) -> 88679 | G74: =1/160 -> 0.00625 | H74: =IF(G74>0,(G74*F74*E74),(F74*E74)) -> 1108.4875
B75: MOB011 | C75: Acarreo horizontal | D75: %MO | E75: 0.1 | F75: =H74 -> 1108.4875 | G75: 0 | H75: =IF(G75>0,(G75*F75*E75),(F75*E75)) -> 110.84875
A76: EQUIPO | B76: EQU005 | C76: Compresor 185 pies3 CFM de 2 martillos, incluye 2 operarios y combustible | D76: Hr | E76: 1 | F76: =VLOOKUP(B76,'BASE DE DATOS'!$A$5:$E$997,5,FALSE) -> 95200 | G76: =1/20 -> 0.05 | H76: =IF(G76>0,(G76*F76*E76),(F76*E76)) -> 4760
B77: EQU002 | C77: Herramienta menor (% mano obra) | D77: %MO | E77: 0.1 | F77: =H74 -> 1108.4875 | G77: 0 | H77: =IF(G77>0,(G77*F77*E77),(F77*E77)) -> 110.84875
A78: 2-01-13 | C78: Demolición sumidero | D78: Un | F78: =ROUND(SUM(H78:H80),0) -> 142774
A79: M. O. | B79: MOB004 | C79: Ayudante práctico (jornal + prestaciones) | D79: Día | E79: 1 | F79: =VLOOKUP(B79,'BASE DE DATOS'!$A$5:$E$997,5,FALSE) -> 124151 | G79: =1/1 -> 1 | H79: =IF(G79>0,(G79*F79*E79),(F79*E79)) -> 124151
A80: EQUIPO | B80: EQU002 | C80: Herramienta menor (% mano obra) | D80: %MO | E80: 0.15 | F80: =H79 -> 124151 | G80: 0 | H80: =IF(G80>0,(G80*F80*E80),(F80*E80)) -> 18622.65
A81: 2-01-14 | C81: Demolición de pavimento rígido (no incluye Derechos de Disposición Final) | D81: M2 | F81: =ROUND(SUM(H81:H86),0) -> 15543
A82: M. O. | B82: MOB015 | C82: Cuadrilla G 1 Of + 2 Ay (jornal + prestaciones) | D82: Día | E82: 1 | F82: =VLOOKUP(B82,'BASE DE DATOS'!$A$5:$E$997,5,FALSE) -> 248302 | G82: =1/60 -> 0.016666667 | H82: =IF(G82>0,(G82*F82*E82),(F82*E82)) -> 4138.3667
B83: MOB011 | C83: Acarreo horizontal | D83: %MO | E83: 0.02 | F83: =H82 -> 4138.3667 | G83: 0 | H83: =IF(G83>0,(G83*F83*E83),(F83*E83)) -> 82.767333
A84: EQUIPO | B84: EQU064 | C84: Retroexcavadora A25C a similar | D84: Hr | E84: 1 | F84: =VLOOKUP(B84,'BASE DE DATOS'!$A$5:$E$997,5,FALSE) -> 261800 | G84: =1/32 -> 0.03125 | H84: =IF(G84>0,(G84*F84*E84),(F84*E84)) -> 8181.25
B85: EQU005 | C85: Compresor 185 pies3 CFM de 2 martillos, incluye 2 operarios y combustible | D85: Hr | E85: 1 | F85: =VLOOKUP(B85,'BASE DE DATOS'!$A$5:$E$997,5,FALSE) -> 95200 | G85: =1/32 -> 0.03125 | H85: =IF(G85>0,(G85*F85*E85),(F85*E85)) -> 2975
B86: EQU002 | C86: Herramienta menor (% mano obra) | D86: %MO | E86: 0.04 | F86: =H82 -> 4138.3667 | G86: 0 | H86: =IF(G86>0,(G86*F86*E86),(F86*E86)) -> 165.53467
A87: 2-01-15 | C87: Demolición pavimento flexible manual e > 0,07 m | D87: M2 | F87: =ROUND(SUM(H87:H90),0) -> 14780
A88: M. O. | B88: MOB018 | C88: Cuadrilla H 4 Ay (jornal + prestaciones) | D88: Día | E88: 1 | F88: =VLOOKUP(B88,'BASE DE DATOS'!$A$5:$E$997,5,FALSE) -> 354716 | G88: =1/30 -> 0.033333333 | H88: =IF(G88>0,(G88*F88*E88),(F88*E88)) -> 11823.867
B89: MOB011 | C89: Acarreo horizontal | D89: %MO | E89: 0.1 | F89: =+H88 -> 11823.867 | G89: 0 | H89: =IF(G89>0,(G89*F89*E89),(F89*E89)) -> 1182.3867
A90: EQUIPO | B90: EQU002 | C90: Herramienta menor (% mano obra) | D90: %MO | E90: 0.15 | F90: =+H88 -> 11823.867 | G90: 0 | H90: =IF(G90>0,(G90*F90*E90),(F90*E90)) -> 1773.58
A91: 2-01-16 | C91: Desarme de gaviones | D91: M3 | F91: =ROUND(SUM(H91:H94),0) -> 43808
A92: M. O. | B92: MOB017 | C92: Cuadrilla G 1 Of + 2 Ay (jornal + prestaciones) | D92: Día | E92: 1 | F92: =VLOOKUP(B92,'BASE DE DATOS'!$A$5:$E$997,5,FALSE) -> 336981 | G92: =1/10 -> 0.1 | H92: =IF(G92>0,(G92*F92*E92),(F92*E92)) -> 33698.1
B93: MOB011 | C93: Acarreo horizontal | D93: %MO | E93: 0.25 | F93: =+H92 -> 33698.1 | G93: 0 | H93: =IF(G93>0,(G93*F93*E93),(F93*E93)) -> 8424.525
A94: EQUIPO | B94: EQU002 | C94: Herramienta menor (% mano obra) | D94: %MO | E94: 0.05 | F94: =+H92 -> 33698.1 | G94: 0 | H94: =IF(G94>0,(G94*F94*E94),(F94*E94)) -> 1684.905
A95: 2-01-17 | C95: Limpieza de alcantarillas (circular o de cajón), incluye descole y retiro manual | D95: Un | F95: =ROUND(SUM(H95:H98),0) -> 141886
A96: M. O. | B96: MOB003 | C96: Ayudante (jornal + prestaciones) | D96: Día | E96: 2 | F96: =VLOOKUP(B96,'BASE DE DATOS'!$A$5:$E$997,5,FALSE) -> 88679 | G96: =1/1.5 -> 0.66666667 | H96: =IF(G96>0,(G96*F96*E96),(F96*E96)) -> 118238.67
B97: MOB011 | C97: Acarreo horizontal | D97: %MO | E97: 0.1 | F97: =+H96 -> 118238.67 | G97: 0 | H97: =IF(G97>0,(G97*F97*E97),(F97*E97)) -> 11823.867
A98: EQUIPO | B98: EQU002 | C98: Herramienta menor (% mano obra) | D98: %MO | E98: 0.1 | F98: =+H96 -> 118238.67 | G98: 0 | H98: =IF(G98>0,(G98*F98*E98),(F98*E98)) -> 11823.867
A99: 2-01-18 | C99: Limpieza manual de cunetas revestidas y canales en concreto (disipador, zanjas de coronación), incluye retiro manual | D99: M | F99: =ROUND(SUM(H99:H102),0) -> 4257
A100: M. O. | B100: MOB018 | C100: Cuadrilla H 4 Ay (jornal + prestaciones) | D100: Día | E100: 1 | F100: =VLOOKUP(B100,'BASE DE DATOS'!$A$5:$E$997,5,FALSE) -> 354716 | G100: =1/100 -> 0.01 | H100: =IF(G100>0,(G100*F100*E100),(F100*E100)) -> 3547.16
B101: MOB011 | C101: Acarreo horizontal | D101: %MO | E101: 0.1 | F101: =+H100 -> 3547.16 | G101: 0 | H101: =IF(G101>0,(G101*F101*E101),(F101*E101)) -> 354.716
...

Sheet ANÁLISIS MANO DE OBRA
B2: Análisis Mano de Obra Gobernación de Risaralda
B5: ANÁLISIS MANO DE OBRA
B6: Salario Mínimo Mensual Legal Vigente año 2025 | C6: 1423500 | D6: =C6*2 -> 2847000 | E6: (Dos salarios mínimos)
B7: Subsidio de Transporte (salario <= 2 SMMLV) | C7: 200000
B9: FACTOR PRESTACIONAL
B10: DESCRIPCIÓN | C10: SALARIO <= 2 SMMLV | D10: SALARIO > 2 SMMLV | E10: SALARIO <= 2 SMMLV
C11: PERSONAL TÉCNICO, OPERATIVO Riesgo Clase V | D11: PERSONAL TÉCNICO, OPERATIVO Riesgo Clase V | E11: PERSONAL TÉCNICO, OPERATIVO Riesgo Clase II
B12: PRESTACIONES SOCIALES
B13: Cesantías | C13: 0.0833 | D13: 0.0833 | E13: 0.0833
B14: Intereses cesantías | C14: 0.01 | D14: 0.01 | E14: 0.01
B15: Vacaciones | C15: 0.0472 | D15: 0.0472 | E15: 0.0472
B16: Prima | C16: 0.0833 | D16: 0.0833 | E16: 0.0833
B17: Dotación | C17: 0.08 | E17: 0.08
B18: SEGURIDAD SOCIAL
B19: Aportes régimen general de pensiones (I.V.M.) | C19: 0.12 | D19: 0.12 | E19: 0.12
B20: Aporte riesgos profesionales A.R.L. | C20: 0.0696 | D20: 0.0696 | E20: 0.01
B21: Aportes régimen contributivo de salud | C21: 0.085 | D21: 0.085 | E21: 0.085
B22: OTROS APORTES
B23: Aportes FIC | C23: 0.025 | D23: 0.025 | E23: 0.025
B24: SENA | C24: 0.04 | D24: 0.04 | E24: 0.04
B25: I.C.B.F. | C25: 0.03 | D25: 0.03 | E25: 0.03
B26: Comfamiliar | C26: 0.04 | D26: 0.04 | E26: 0.04
B27: Subsidio de transporte | C27: =C7/C6 -> 0.14049877 | E27: =C7/C6 -> 0.14049877
B28: Exámenes médicos de ingreso y egreso y certificado de trabajo seguro en alturas | C28: 0.015 | D28: 0.015 | E28: 0.015
C29: =SUM(C12:C28) -> 0.86889877 | D29: =SUM(D12:D28) -> 0.6484 | E29: =SUM(E12:E28) -> 0.80929877
B31: NOMBRE | C31: SALARIO MENSUAL | D31: PRESTACIONES Y APORTES | E31: SALARIO + PRESTACIONES | F31: SALARIO DÍA
B32: Ayudante | C32: =C6 -> 1423500 | D32: =ROUND((C32*$C$29),0) -> 1236877 | E32: =C32+D32 -> 2660377 | F32: =ROUND((E32/30),0) -> 88679
B33: Ayudante práctico | C33: =C32*1.4 -> 1992900 | D33: =ROUND((C33*$C$29),0) -> 1731628 | E33: =C33+D33 -> 3724528 | F33: =ROUND((E33/30),0) -> 124151 | G33: RESOLUCIÓN POR TABLA
B34: Oficial | C34: =C32*1.8 -> 2562300 | D34: =ROUND((C34*$C$29),0) -> 2226379 | E34: =C34+D34 -> 4788679 | F34: =ROUND((E34/30),0) -> 159623 | G34: ANALIZAR EL PORCENTAJE
B35: Cadenero 1 | C35: 1800000 | D35: =ROUND((C35*$C$29),0) -> 1564018 | E35: =C35+D35 -> 3364018 | F35: =ROUND((E35/30),0) -> 112134
B36: Cadenero 2 | C36: =C32 -> 1423500 | D36: =ROUND((C36*$C$29),0) -> 1236877 | E36: =C36+D36 -> 2660377 | F36: =ROUND((E36/30),0) -> 88679
B37: Liniero categoría 1 | C37: =C32*2.8 -> 3985800 | D37: =ROUND((C37*D29),0) -> 2584393 | E37: =C37+D37 -> 6570193 | F37: =ROUND((E37/30),0) -> 219006
B38: Liniero categoría 2 | C38: =C32*1.8 -> 2562300 | D38: =ROUND((C38*$C$29),0) -> 2226379 | E38: =C38+D38 -> 4788679 | F38: =ROUND((E38/30),0) -> 159623
B39: Maestro de obra | C39: =C32*2.6 -> 3701100 | D39: =ROUND((C39*$D$29),0) -> 2399793 | E39: =C39+D39 -> 6100893 | F39: =ROUND((E39/30),0) -> 203363
B40: Minero | C40: =C32*2.5 -> 3558750 | D40: =ROUND((C40*$D$29),0) -> 2307494 | E40: =C40+D40 -> 5866244 | F40: =ROUND((E40/30),0) -> 195541
B41: Oficial eléctrico | C41: =C32*2 -> 2847000 | D41: =ROUND((C41*$C$29),0) -> 2473755 | E41: =C41+D41 -> 5320755 | F41: =ROUND((E41/30),0) -> 177359
B42: Oficial pintor | C42: =C32*1.6 -> 2277600 | D42: =ROUND((C42*$C$29),0) -> 1979004 | E42: =C42+D42 -> 4256604 | F42: =ROUND((E42/30),0) -> 141887
B43: Operador de maquinaria | C43: =C32*1.8 -> 2562300 | D43: =ROUND((C43*$C$29),0) -> 2226379 | E43: =C43+D43 -> 4788679 | F43: =ROUND((E43/30),0) -> 159623
B44: Soldador | C44: =C32*1.8 -> 2562300 | D44: =ROUND((C44*$C$29),0) -> 2226379 | E44: =C44+D44 -> 4788679 | F44: =ROUND((E44/30),0) -> 159623
B45: Topógrafo | C45: 2800000 | D45: =ROUND((C45*$C$29),0) -> 2432917 | E45: =C45+D45 -> 5232917 | F45: =ROUND((E45/30),0) -> 174431
B46: Profesional en salud ocupacional | C46: =C32*2.8 -> 3985800 | D46: =ROUND((C46*$D$29),0) -> 2584393 | E46: =C46+D46 -> 6570193 | F46: =ROUND((E46/30),0) -> 219006
B47: Ayudante eléctrico | C47: =C32*1.6 -> 2277600 | D47: =ROUND((C47*$C$29),0) -> 1979004 | E47: =C47+D47 -> 4256604 | F47: =ROUND((E47/30),0) -> 141887
B48: Cuadrilla E 1 Of + 1 Ay (jornal + prestaciones) | F48: =F34+F32 -> 248302
B49: Cuadrilla EE 1 Of E + 1 Ay E (jornal + prestaciones) | F49: =F41+F47 -> 319246
B50: Cuadrilla G 1 Of + 2 Ay (jornal + prestaciones) | F50: =F34+(2*F32) -> 336981
B51: Cuadrilla GE 1 Of E + 2 Ay E (jornal + prestaciones) | F51: =F41+(2*F47) -> 461133
B52: Cuadrilla A 1 Of + 4 Ay (jornal + prestaciones) | F52: =F34+(4*F32) -> 514339
B53: Cuadrilla AE 1E Of + 4 Ay E (jornal + prestaciones) | F53: =F41+4*F47 -> 744907
B54: Cuadrilla B 1 Min + 2 Ay (jornal + prestaciones) | F54: =F40+(2*F32) -> 372899
B55: Cuadrilla N 1 Min + 1 Ay (jornal + prestaciones) | F55: =F40+F32 -> 284220
B56: Comisión topografía (Topógrafo + Cadenero 1 + Cadenero 2) | F56: =F45+F35+F36 -> 375244
B57: Cuadrilla C 1 Of + 7 Ay (jornal + prestaciones) | F57: =$F$34+(7*$F$32) -> 780376
B58: Cuadrilla CE (1 Of E + 7 Ay E) (jornal + prestaciones) | F58: =$F$41+(7*$F$47) -> 1170568
B59: Cuadrilla D 2 Of + 4 Ay (jornal + prestaciones) | F59: =(2*F34)+(4*F32) -> 673962
B60: Cuadrilla F 6 Of + 4 Ay (jornal + prestaciones) | F60: =(6*F34)+(4*F32) -> 1312454
B61: Cuadrilla H 4 Ay (jornal + prestaciones) | F61: =4*F32 -> 354716
B62: Cuadrilla J (1 Of eléctrico + 1Ay eléctrico) (jornal + prestaciones) | F62: =F41+F47 -> 319246
B63: Cuadrilla K (1Of eléctrico + 2Ay eléctricos) (jornal + prestaciones) | F63: =F41+(2*F47) -> 461133
B64: Cuadrilla S (1 Soldador + 1 Ay práctico) (jornal + prestaciones) | F64: =F44+F33 -> 283774
B65: Cuadrilla L 2 Of + 8 Ay (jornal + prestaciones) | F65: =F34*2+F32*8 -> 1028678
B66: Cuadrilla M 1 Of + 3 Ay (jornal + prestaciones) | F66: =F34+(3*F32) -> 425660

Sheet ELÉCTRICOS NUEVOS
A1: IMPORTANTE: Los presentes precios unitarios de referencia fueron calculados en la ciudad de Pereira (zona urbana), por tanto deben ser modificados (incrementados) para las áreas rurales de los municipios de Pereira, Dosquebradas y La Virginia y en las áreas urbanas y rurales de los demás municipios, según el caso. Por estar basados en precios del mercado están sujetos a las variaciones del mismo, las cuales se aplicarán sin previo aviso. Pueden presentar inconsistencias, que se corregirán en el momento de ser detectadas.
A2: El presente listado es una simple guía para el Evaluador, no se constituye en camisa de fuerza, ni es obligatoria su aplicación, quien los utilice, deberá estudiarlos y estar consiente de sus bondades y limitaciones, y será su buen juicio el que prime al final, en cada caso. Dadas las variaciones del precio del dólar que influye principalmente en los insumos derivados del petróleo, el cobre, el cemento e insumos derivados, el PVC, etc., es importante que el Evaluador verifique el costo básico de estos insumos cada vez que pretenda hacer una evaluación o cotización.
A3: Los presente análisis incluyen para la mano de obra los ítems de salud e I.C.B.F., será responsabilidad del Evaluador mantenerlos o suprimirlos según la normatividad existente vigente y el caso particular en donde se aplicarán.
A4: De todos los Ítems posibles se ha suprimido el transporte de materiales, por tanto el evaluador deberá considerarlo como ítems aparte en cada evaluación o cotización. Por favor leer la Introducción.
A6: 3 - INSTALACIONES ELÉCTRICAS: MEDIA TENSIÓN E INTERIOR EDIFICACIONES
A7: 3 - 01 RED DE MEDIA TENSIÓN
A8: ÍTEM | B8: CÓDIGO | C8: DESCRIPCIÓN | D8: UN | E8: CANT. | F8: VR. UN. | G8: RENDIMIENTO, USOS, DESPEDICIOS | H8: VR. PARCIAL
A9: 03.01.01 | C9: Punto transformador 3 ø instalación en camilla - 13.2 kv. Incluye poste auxiliar de 14 x 750 m x Kg | D9: Un | F9: =ROUND(SUM(H9:H30),0) -> 7524228
A10: MATERIALES | B10: MAT,089 | C10: Arandela cuadrada 2" x 2" x ¼", ø 5/8" | D10: Un | E10: 22 | F10: =VLOOKUP(B10,'[1]BASE DE DATOS'!$A$5:$E$964,5,FALSE) -> 800 | G10: 0 | H10: =IF(G10>0,(G10*F10*E10),(F10*E10)) -> 17600
B11: MAT,108 | C11: Arandela presión ø 5/8" | D11: Un | E11: 6 | F11: =VLOOKUP(B11,'[1]BASE DE DATOS'!$A$5:$E$964,5,FALSE) -> 250 | G11: 0 | H11: =IF(G11>0,(G11*F11*E11),(F11*E11)) -> 1500
B12: MAT,269 | C12: Cable cobre # 4 AWG HF FR LS - (EXZHELLENT BW) | D12: M | E12: 22 | F12: =VLOOKUP(B12,'[1]BASE DE DATOS'!$A$5:$E$964,5,FALSE) -> 16800 | G12: 1.03 | H12: =IF(G12>0,(G12*F12*E12),(F12*E12)) -> 380688
B13: MAT,373 | C13: Camilla de transformador ¼" x 2.5 m | D13: Un | E13: 1 | F13: =VLOOKUP(B13,'[1]BASE DE DATOS'!$A$5:$E$964,5,FALSE) -> 1354000 | G13: 0 | H13: =IF(G13>0,(G13*F13*E13),(F13*E13)) -> 1354000
B14: MAT,396 | C14: Cinta bandit 5/8" | D14: M | E14: 3 | F14: =VLOOKUP(B14,'[1]BASE DE DATOS'!$A$5:$E$964,5,FALSE) -> 4033 | G14: 1.05 | H14: =IF(G14>0,(G14*F14*E14),(F14*E14)) -> 12703.95
B15: MAT,402 | C15: Collarín doble 7" - 8" | D15: Un | E15: 2 | F15: =VLOOKUP(B15,'[1]BASE DE DATOS'!$A$5:$E$964,5,FALSE) -> 19550 | G15: 0 | H15: =IF(G15>0,(G15*F15*E15),(F15*E15)) -> 39100
B16: MAT,404 | C16: Collarín sencillo 7" - 8" | D16: Un | E16: 2 | F16: =VLOOKUP(B16,'[1]BASE DE DATOS'!$A$5:$E$964,5,FALSE) -> 19750 | G16: 0 | H16: =IF(G16>0,(G16*F16*E16),(F16*E16)) -> 39500
B17: MAT,530 | C17: Cortacircuitos 15 KV - 100 A | D17: Un | E17: 3 | F17: =VLOOKUP(B17,'[1]BASE DE DATOS'!$A$5:$E$964,5,FALSE) -> 176550 | G17: 0 | H17: =IF(G17>0,(G17*F17*E17),(F17*E17)) -> 529650
B18: MAT,545 | C18: Cruceta metálica 2 ½" x 2 ½" x 3/16" x 2 m | D18: Un | E18: 1 | F18: =VLOOKUP(B18,'[1]BASE DE DATOS'!$A$5:$E$964,5,FALSE) -> 90726 | G18: 0 | H18: =IF(G18>0,(G18*F18*E18),(F18*E18)) -> 90726
B19: MAT,608 | C19: Dado galvanizado 3" x 3" x ¼" | D19: Un | E19: 3 | F19: =VLOOKUP(B19,'[1]BASE DE DATOS'!$A$5:$E$964,5,FALSE) -> 17500 | G19: 0 | H19: =IF(G19>0,(G19*F19*E19),(F19*E19)) -> 52500
B20: MAT,656 | C20: Fusible primario tipo H de 5 A - 13.2 KV | D20: Un | E20: 3 | F20: =VLOOKUP(B20,'[1]BASE DE DATOS'!$A$5:$E$964,5,FALSE) -> 6500 | G20: 0 | H20: =IF(G20>0,(G20*F20*E20),(F20*E20)) -> 19500
B21: MAT,660 | C21: Grapa bandit 5/8" | D21: Un | E21: 2 | F21: =VLOOKUP(B21,'[1]BASE DE DATOS'!$A$5:$E$964,5,FALSE) -> 750 | G21: 0 | H21: =IF(G21>0,(G21*F21*E21),(F21*E21)) -> 1500
B22: MAT,703 | C22: Pararrayos polimérico 12 KV - 10 KA | D22: Un | E22: 3 | F22: =VLOOKUP(B22,'[1]BASE DE DATOS'!$A$5:$E$964,5,FALSE) -> 112207 | G22: 0 | H22: =IF(G22>0,(G22*F22*E22),(F22*E22)) -> 336621
... B28: MAT,588 | C28: Varilla Cu 5/8" x 2.4 m | D28: Un | E28: 2 | F28: =VLOOKUP(B28,'[1]BASE DE DATOS'!$A$5:$E$964,5,FALSE) -> 59900 | G28: 0 | H28: =IF(G28>0,(G28*F28*E28),(F28*E28)) -> 119800
A29: M. O. | B29: MOB001 | C29: Cuadrilla CE 1 Of E + 7 Ay E (jornal + prestaciones) | D29: Día | E29: 1 | F29: =VLOOKUP(B29,'[1]BASE DE DATOS'!$A$5:$E$964,5,FALSE) -> 1170568 | G29: 2.5 | H29: =IF(G29>0,(G29*F29*E29),(F29*E29)) -> 2926420
A30: EQUIPO | B30: EQU002 | C30: Herramienta menor (% mano obra) | D30: %MO | E30: 0.03 | F30: =H29 -> 2926420 | G30: 0 | H30: =IF(G30>0,(G30*F30*E30),(F30*E30)) -> 87792.6
A31: 03.01.02 | C31: Estructura para instalación de transformadores de corriente red de 13.2 Kv. Se apoyan en estructura en H | D31: Un | F31: =ROUND(SUM(H31:H41),0) -> 4261076
A32: MATERIALES | B32: MAT,089 | C32: Arandela cuadrada 2" x 2" x ¼", ø 5/8" | D32: Un | E32: 32 | F32: =VLOOKUP(B32,'[1]BASE DE DATOS'!$A$5:$E$964,5,FALSE) -> 800 | G32: 0 | H32: =IF(G32>0,(G32*F32*E32),(F32*E32)) -> 25600
B33: MAT,097 | C33: Arandela presión ø 3/4" | D33: Un | E33: 24 | F33: =VLOOKUP(B33,'[1]BASE DE DATOS'!$A$5:$E$964,5,FALSE) -> 550 | G33: 0 | H33: =IF(G33>0,(G33*F33*E33),(F33*E33)) -> 13200
B34: MAT,108 | C34: Arandela presión ø 5/8" | D34: Un | E34: 32 | F34: =VLOOKUP(B34,'[1]BASE DE DATOS'!$A$5:$E$964,5,FALSE) -> 250 | G34: 0 | H34: =IF(G34>0,(G34*F34*E34),(F34*E34)) -> 8000
B35: MAT,403 | C35: Collarín doble 8" - 9" | D35: Un | E35: 4 | F35: =VLOOKUP(B35,'[1]BASE DE DATOS'!$A$5:$E$964,5,FALSE) -> 20400 | G35: 0 | H35: =IF(G35>0,(G35*F35*E35),(F35*E35)) -> 81600
B36: MAT,550 | C36: Cruceta metálica 3" x 3" x ¼" x 6 m | D36: Un | E36: 4 | F36: =VLOOKUP(B36,'[1]BASE DE DATOS'!$A$5:$E$964,5,FALSE) -> 301681 | G36: 0 | H36: =IF(G36>0,(G36*F36*E36),(F36*E36)) -> 1206724
B37: MAT,707 | C37: Platina acanalada de armazón doble en U de 60 cm | D37: Un | E37: 12 | F37: =VLOOKUP(B37,'[1]BASE DE DATOS'!$A$5:$E$964,5,FALSE) -> 64540 | G37: 1.03 | H37: =IF(G37>0,(G37*F37*E37),(F37*E37)) -> 797714.4
B38: MAT,742 | C38: Tornillo espaciador 5/8" x 14" | D38: Un | E38: 16 | F38: =VLOOKUP(B38,'[1]BASE DE DATOS'!$A$5:$E$964,5,FALSE) -> 7800 | G38: 0 | H38: =IF(G38>0,(G38*F38*E38),(F38*E38)) -> 124800
B39: MAT,744 | C39: Tornillo máquina 3/4" x 2" | D39: Un | E39: 24 | F39: =VLOOKUP(B39,'[1]BASE DE DATOS'!$A$5:$E$964,5,FALSE) -> 3000 | G39: 0 | H39: =IF(G39>0,(G39*F39*E39),(F39*E39)) -> 72000
A40: M. O. | B40: MOB001 | C40: Cuadrilla CE 1 Of E + 7 Ay E (jornal + prestaciones) | D40: Día | E40: 1 | F40: =VLOOKUP(B40,'[1]BASE DE DATOS'!$A$5:$E$964,5,FALSE) -> 1170568 | G40: 1.5 | H40: =IF(G40>0,(G40*F40*E40),(F40*E40)) -> 1755852
A41: EQUIPO | B41: EQU002 | C41: Herramienta menor (% mano obra) | D41: %MO | E41: 0.1 | F41: =H40 -> 1755852 | G41: 0 | H41: =IF(G41>0,(G41*F41*E41),(F41*E41)) -> 175585.2
A42: 03.01.03 | C42: Estructura para instalación de transformadores de potencial o de tensión red de 13.2 Kv. Se apoyan en estructura en H | D42: Un | F42: =ROUND(SUM(H42:H52),0) -> 4436661
A43: MATERIALES | B43: MAT,089 | C43: Arandela cuadrada 2" x 2" x ¼", ø 5/8" | D43: Un | E43: 32 | F43: =VLOOKUP(B43,'[1]BASE DE DATOS'!$A$5:$E$964,5,FALSE) -> 800 | G43: 0 | H43: =IF(G43>0,(G43*F43*E43),(F43*E43)) -> 25600
B44: MAT,097 | C44: Arandela presión ø 3/4" | D44: Un | E44: 24 | F44: =VLOOKUP(B44,'[1]BASE DE DATOS'!$A$5:$E$964,5,FALSE) -> 550 | G44: 0 | H44: =IF(G44>0,(G44*F44*E44),(F44*E44)) -> 13200
B45: MAT,108 | C45: Arandela presión ø 5/8" | D45: Un | E45: 32 | F45: =VLOOKUP(B45,'[1]BASE DE DATOS'!$A$5:$E$964,5,FALSE) -> 250 | G45: 0 | H45: =IF(G45>0,(G45*F45*E45),(F45*E45)) -> 8000
B46: MAT,403 | C46: Collarín doble 8" - 9" | D46: Un | E46: 4 | F46: =VLOOKUP(B46,'[1]BASE DE DATOS'!$A$5:$E$964,5,FALSE) -> 20400 | G46: 0 | H46: =IF(G46>0,(G46*F46*E46),(F46*E46)) -> 81600
B47: MAT,550 | C47: Cruceta metálica 3" x 3" x ¼" x 6 m | D47: Un | E47: 4 | F47: =VLOOKUP(B47,'[1]BASE DE DATOS'!$A$5:$E$964,5,FALSE) -> 301681 | G47: 0 | H47: =IF(G47>0,(G47*F47*E47),(F47*E47)) -> 1206724
B48: MAT,707 | C48: Platina acanalada de armazón doble en U de 60 cm | D48: Un | E48: 12 | F48: =VLOOKUP(B48,'[1]BASE DE DATOS'!$A$5:$E$964,5,FALSE) -> 64540 | G48: 1.03 | H48: =IF(G48>0,(G48*F48*E48),(F48*E48)) -> 797714.4
B49: MAT,742 | C49: Tornillo espaciador 5/8" x 14" | D49: Un | E49: 16 | F49: =VLOOKUP(B49,'[1]BASE DE DATOS'!$A$5:$E$964,5,FALSE) -> 7800 | G49: 0 | H49: =IF(G49>0,(G49*F49*E49),(F49*E49)) -> 124800
B50: MAT,744 | C50: Tornillo máquina 3/4" x 2" | D50: Un | E50: 24 | F50: =VLOOKUP(B50,'[1]BASE DE DATOS'!$A$5:$E$964,5,FALSE) -> 3000 | G50: 0 | H50: =IF(G50>0,(G50*F50*E50),(F50*E50)) -> 72000
A51: M. O. | B51: MOB001 | C51: Cuadrilla CE 1 Of E + 7 Ay E (jornal + prestaciones) | D51: Día | E51: 1 | F51: =VLOOKUP(B51,'[1]BASE DE DATOS'!$A$5:$E$964,5,FALSE) -> 1170568 | G51: 1.5 | H51: =IF(G51>0,(G51*F51*E51),(F51*E51)) -> 1755852
A52: EQUIPO | B52: EQU002 | C52: Herramienta menor (% mano obra) | D52: %MO | E52: 0.2 | F52: =H51 -> 1755852 | G52: 0 | H52: =IF(G52>0,(G52*F52*E52),(F52*E52)) -> 351170.4
A53: 03.01.04 | C53: Herrajería y accesorios de conexión para instalación de 3 transformadores de medición de energía a 13.2 Kv exterior | D53: Un | F53: =ROUND(SUM(H53:H67),0) -> 3303000
A54: MATERIALES | B54: MAT,089 | C54: Arandela cuadrada 2" x 2" x ¼", ø 5/8" | D54: Un | E54: 24 | F54: =VLOOKUP(B54,'[1]BASE DE DATOS'!$A$5:$E$964,5,FALSE) -> 800 | G54: 0 | H54: =IF(G54>0,(G54*F54*E54),(F54*E54)) -> 19200
B55: MAT,396 | C55: Cinta bandit 5/8" | D55: M | E55: 6 | F55: =VLOOKUP(B55,'[1]BASE DE DATOS'!$A$5:$E$964,5,FALSE) -> 4033 | G55: 1.05 | H55: =IF(G55>0,(G55*F55*E55),(F55*E55)) -> 25407.9
B56: MAT,404 | C56: Collarín doble 7" - 8" | D56: Un | E56: 1 | F56: =VLOOKUP(B56,'[1]BASE DE DATOS'!$A$5:$E$964,5,FALSE) -> 19750 | G56: 0 | H56: =IF(G56>0,(G56*F56*E56),(F56*E56)) -> 19750
B57: MAT,457 | C57: Conduleta rawelt LR 1" | D57: Un | E57: 2 | F57: =VLOOKUP(B57,'[1]BASE DE DATOS'!$A$5:$E$964,5,FALSE) -> 17948 | G57: 0 | H57: =IF(G57>0,(G57*F57*E57),(F57*E57)) -> 35896
B58: MAT,518 | C58: Conector curvo coraza liquid tight 1" | D58: Un | E58: 1 | F58: =VLOOKUP(B58,'[1]BASE DE DATOS'!$A$5:$E$964,5,FALSE) -> 7300 | G58: 0 | H58: =IF(G58>0,(G58*F58*E58),(F58*E58)) -> 7300
B59: MAT,529 | C59: Conector recto coraza liquid tight 3/4" | D59: Un | E59: 6 | F59: =VLOOKUP(B59,'[1]BASE DE DATOS'!$A$5:$E$964,5,FALSE) -> 7850 | G59: 0 | H59: =IF(G59>0,(G59*F59*E59),(F59*E59)) -> 47100
B60: MAT,781 | C60: Coraza metálica liquid tight 3/4" | D60: M | E60: 2 | F60: =VLOOKUP(B60,'[1]BASE DE DATOS'!$A$5:$E$964,5,FALSE) -> 8745 | G60: 0 | H60: =IF(G60>0,(G60*F60*E60),(F60*E60)) -> 17490
B61: MAT,548 | C61: Cruceta metálica 3" x 3" x ¼" x 2.4 m | D61: Un | E61: 2 | F61: =VLOOKUP(B61,'[1]BASE DE DATOS'!$A$5:$E$964,5,FALSE) -> 182850 | G61: 0 | H61: =IF(G61>0,(G61*F61*E61),(F61*E61)) -> 365700
B62: MAT,660 | C62: Grapa bandit 5/8" | D62: Un | E62: 4 | F62: =VLOOKUP(B62,'[1]BASE DE DATOS'!$A$5:$E$964,5,FALSE) -> 750 | G62: 0 | H62: =IF(G62>0,(G62*F62*E62),(F62*E62)) -> 3000
B63: MAT,707 | C63: Platina acanalada de armazón doble en U de 60 cm | D63: Un | E63: 6 | F63: =VLOOKUP(B63,'[1]BASE DE DATOS'!$A$5:$E$964,5,FALSE) -> 64540 | G63: 1.03 | H63: =IF(G63>0,(G63*F63*E63),(F63*E63)) -> 398857.2
B64: MAT,745 | C64: Tornillo máquina 5/8" x 2" | D64: Un | E64: 24 | F64: =VLOOKUP(B64,'[1]BASE DE DATOS'!$A$5:$E$964,5,FALSE) -> 1700 | G64: 0 | H64: =IF(G64>0,(G64*F64*E64),(F64*E64)) -> 40800
B65: MAT,571 | C65: Tubería conduit IMC 1" | D65: M | E65: 8 | F65: =VLOOKUP(B65,'[1]BASE DE DATOS'!$A$5:$E$964,5,FALSE) -> 26150 | G65: 1.03 | H65: =IF(G65>0,(G65*F65*E65),(F65*E65)) -> 215476
A66: M. O. | B66: MOB001 | C66: Cuadrilla CE 1 Of E + 7 Ay E (jornal + prestaciones) | D66: Día | E66: 1 | F66: =VLOOKUP(B66,'[1]BASE DE DATOS'!$A$5:$E$964,5,FALSE) -> 1170568 | G66: 1.2 | H66: =IF(G66>0,(G66*F66*E66),(F66*E66)) -> 1404681.6
A67: EQUIPO | B67: EQU002 | C67: Herramienta menor (% mano obra) | D67: %MO | E67: 0.5 | F67: =H66 -> 1404681.6 | G67: 0 | H67: =IF(G67>0,(G67*F67*E67),(F67*E67)) -> 702340.8
A68: 03.01.05 | C68: Cable ACSR semiaislado (ecológico), 13.2 Kv Nº 2 AWG (puentes de red de MT a transformadores de medida y potencia) | D68: M | F68: =ROUND(SUM(H68:H71),0) -> 32270
A69: MAT | B69: MAT,175 | C69: Cable Al ACSR # 2 AWG ecológico 15 Kv | D69: M | E69: 1 | F69: =VLOOKUP(B69,'[1]BASE DE DATOS'!$A$5:$E$964,5,FALSE) -> 9450 | G69: 1.05 | H69: =IF(G69>0,(G69*F69*E69),(F69*E69)) -> 9922.5
A70: M. O. | B70: MOB009 | C70: Cuadrilla EE 1 Of E + 1 Ay E (jornal + prestaciones) | D70: Día | E70: 1 | F70: =VLOOKUP(B70,'[1]BASE DE DATOS'!$A$5:$E$964,5,FALSE) -> 319246 | G70: =1/15 -> 0.066666667 | H70: =IF(G70>0,(G70*F70*E70),(F70*E70)) -> 21283.067
A71: EQUIPO | B71: EQU002 | C71: Herramienta menor (% mano obra) | D71: %MO | E71: 0.05 | F71: =H70 -> 21283.067 | G71: 0 | H71: =IF(G71>0,(G71*F71*E71),(F71*E71)) -> 1064.1533
A72: 03.01.06 | C72: Transformador 3ø 150 Kva, 13.2 Kv - 214/123 V, inmerso en aceite, tipo distribución, instalación en camilla | D72: Un | F72: =ROUND(SUM(H72:H75),0) -> 26560391
A73: MAT | B73: MAT,746 | C73: Transformador 3ø 150 KVA, 13.2 Kv, 214/123 V | D73: Un | E73: 1 | F73: =VLOOKUP(B73,'[1]BASE DE DATOS'!$A$5:$E$964,5,FALSE) -> 23487650 | G73: 0 | H73: =IF(G73>0,(G73*F73*E73),(F73*E73)) -> 23487650
A74: M. O. | B74: MOB001 | C74: Cuadrilla CE 1 Of E + 7 Ay E (jornal + prestaciones) | D74: Día | E74: 1 | F74: =VLOOKUP(B74,'[1]BASE DE DATOS'!$A$5:$E$964,5,FALSE) -> 1170568 | G74: 2.5 | H74: =IF(G74>0,(G74*F74*E74),(F74*E74)) -> 2926420
A75: EQUIPO | B75: EQU002 | C75: Herramienta menor (% mano obra) | D75: %MO | E75: 0.05 | F75: =H74 -> 2926420 | G75: 0 | H75: =IF(G75>0,(G75*F75*E75),(F75*E75)) -> 146321
A76: 03.01.07 | C76: Transformador de corriente 15 Kv - 7.5/5 A - 5A, uso exterior | D76: Un | F76: =ROUND(SUM(H76:H79),0) -> 5155852
A77: MAT | B77: MAT,747 | C77: Transformador de corriente 15 Kv, 5A uso exterior | D77: Un | E77: 1 | F77: =VLOOKUP(B77,'[1]BASE DE DATOS'!$A$5:$E$964,5,FALSE) -> 3400000 | G77: 0 | H77: =IF(G77>0,(G77*F77*E77),(F77*E77)) -> 3400000
A78: M. O. | B78: MOB001 | C78: Cuadrilla CE 1 Of E + 7 Ay E (jornal + prestaciones) | D78: Día | E78: 1 | F78: =VLOOKUP(B78,'[1]BASE DE DATOS'!$A$5:$E$964,5,FALSE) -> 1170568 | G78: 0 | H78: =IF(G78>0,(G78*F78*E78),(F78*E78)) -> 1170568
A79: EQUIPO | B79: EQU002 | C79: Herramienta menor (% mano obra) | D79: %MO | E79: 0.5 | F79: =H78 -> 1170568 | G79: 0 | H79: =IF(G79>0,(G79*F79*E79),(F79*E79)) -> 585284
A80: 03.01.08 | C80: Transformador de potencial 1.73 x15 Kv - 1.73 x 120 V uso exterior | D80: Un | F80: =ROUND(SUM(H80:H83),0) -> 5349926 | I80: 8
A81: MAT | B81: MAT,748 | C81: Transformador de potencia 15 Kv/120v uso exterior | D81: Un | E81: 1 | F81: =VLOOKUP(B81,'[1]BASE DE DATOS'!$A$5:$E$964,5,FALSE) -> 4472000 | G81: 0 | H81: =IF(G81>0,(G81*F81*E81),(F81*E81)) -> 4472000
A82: M. O. | B82: MOB001 | C82: Cuadrilla CE 1 Of E + 7 Ay E (jornal + prestaciones) | D82: Día | E82: 1 | F82: =VLOOKUP(B82,'[1]BASE DE DATOS'!$A$5:$E$964,5,FALSE) -> 1170568 | G82: =1/2 -> 0.5 | H82: =IF(G82>0,(G82*F82*E82),(F82*E82)) -> 585284
A83: EQUIPO | B83: EQU002 | C83: Herramienta menor (% mano obra) | D83: %MO | E83: 0.5 | F83: =H82 -> 585284 | G83: 0 | H83: =IF(G83>0,(G83*F83*E83),(F83*E83)) -> 292642
A84: 3 - 02 ACOMETIDAS ELÉCTRICAS
A85: ÍTEM | B85: CÓDIGO | C85: DESCRIPCIÓN | D85: UN | E85: CANT. | F85: VR. UN. | G85: RENDIMIENTO, USOS, DESPEDICIOS | H85: VR. PARCIAL
A86: 03.02.01 | C86: Acometida 3 x Nº 4 (F) + 1 x Nº 4 (N) + 1 x Nº 8 (T), sin ducto. Cables de bajo contenido halógenos, baja emisión humo. Tablero ensayos | D86: M | F86: =ROUND(SUM(H86:H90),0) -> 136035
A87: MAT | B87: MAT,269 | C87: Cable Cu # 4 AWG HF FR LS - (EXZHELLENT BW) | D87: M | E87: 4 | F87: =VLOOKUP(B87,'[1]BASE DE DATOS'!$A$5:$E$964,5,FALSE) -> 16800 | G87: 1.06 | H87: =IF(G87>0,(G87*F87*E87),(F87*E87)) -> 71232
B88: MAT,566 | C88: Cable Cu # 8 HF FR LS - (EXZHELLENT BW) | D88: M | E88: 1 | F88: =VLOOKUP(B88,'[1]BASE DE DATOS'!$A$5:$E$964,5,FALSE) -> 6950 | G88: 1.06 | H88: =IF(G88>0,(G88*F88*E88),(F88*E88)) -> 7367
A89: M. O. | B89: MOB009 | C89: Cuadrilla EE 1 Of E + 1 Ay E (jornal + prestaciones) | D89: Día | E89: 1 | F89: =VLOOKUP(B89,'[1]BASE DE DATOS'!$A$5:$E$964,5,FALSE) -> 319246 | G89: =1/6.67 -> 0.14992504 | H89: =IF(G89>0,(G89*F89*E89),(F89*E89)) -> 47862.969
A90: EQUIPO | B90: EQU002 | C90: Herramienta menor (% mano obra) | D90: %MO | E90: 0.2 | F90: =H89 -> 47862.969 | G90: 0 | H90: =IF(G90>0,(G90*F90*E90),(F90*E90)) -> 9572.5937
A91: 03.02.02 | C91: Acometida 3 x Nº 2 (F) + 1 x Nº 2 (N) + 1 x Nº 6 (T), sin ducto. Cables bajo contenido halógenos, baja emisión de humo. Tablero de cargas especiales | D91: M | F91: =ROUND(SUM(H91:H95),0) -> 193990
A92: MAT | B92: MAT,209 | C92: Cable Cu # 2 AWG HF FR LS - (EXZHELLENT BW) | D92: M | E92: 4 | F92: =VLOOKUP(B92,'[1]BASE DE DATOS'!$A$5:$E$964,5,FALSE) -> 28200 | G92: 1.06 | H92: =IF(G92>0,(G92*F92*E92),(F92*E92)) -> 119568
B93: MAT,293 | C93: Cable Cu # 6 AWG HF FR LS - (EXZHELLENT BW) | D93: M | E93: 1 | F93: =VLOOKUP(B93,'[1]BASE DE DATOS'!$A$5:$E$964,5,FALSE) -> 11300 | G93: 1.06 | H93: =IF(G93>0,(G93*F93*E93),(F93*E93)) -> 11978
A94: M. O. | B94: MOB009 | C94: Cuadrilla EE 1 Of E + 1 Ay E (jornal + prestaciones) | D94: Día | E94: 1 | F94: =VLOOKUP(B94,'[1]BASE DE DATOS'!$A$5:$E$964,5,FALSE) -> 319246 | G94: =1/6.135 -> 0.16299919 | H94: =IF(G94>0,(G94*F94*E94),(F94*E94)) -> 52036.838
A95: EQUIPO | B95: EQU002 | C95: Herramienta menor (% mano obra) | D95: %MO | E95: 0.2 | F95: =H94 -> 52036.838 | G95: 0 | H95: =IF(G95>0,(G95*F95*E95),(F95*E95)) -> 10407.368
A96: 03.02.03 | C96: Acometida 2 x Nº 6 (F) + 1 x Nº 6 (N) + 1 x Nº 8 (T), sin ducto. Cables de bajo contenido de halógenos y baja emisión de humo | D96: M | F96: =ROUND(SUM(H96:H100),0) -> 91188
A97: MAT | B97: MAT,293 | C97: Cable Cu # 6 AWG HF FR LS - (EXZHELLENT BW) | D97: M | E97: 3 | F97: =VLOOKUP(B97,'[1]BASE DE DATOS'!$A$5:$E$964,5,FALSE) -> 11300 | G97: 1.06 | H97: =IF(G97>0,(G97*F97*E97),(F97*E97)) -> 35934
B98: MAT,566 | C98: Cable Cu # 8 HF FR LS - (EXZHELLENT BW) | D98: M | E98: 1 | F98: =VLOOKUP(B98,'[1]BASE DE DATOS'!$A$5:$E$964,5,FALSE) -> 6950 | G98: 1.06 | H98: =IF(G98>0,(G98*F98*E98),(F98*E98)) -> 7367
A99: M. O. | B99: MOB009 | C99: Cuadrilla EE 1 Of E + 1 Ay E (jornal + prestaciones) | D99: Día | E99: 1 | F99: =VLOOKUP(B99,'[1]BASE DE DATOS'!$A$5:$E$964,5,FALSE) -> 319246 | G99: =1/10 -> 0.1 | H99: =IF(G99>0,(G99*F99*E99),(F99*E99)) -> 31924.6
A100: EQUIPO | B100: EQU002 | C100: Herramienta menor (% mano obra) | D100: %MO | E100: 0.5 | F100: =H99 -> 31924.6 | G100: 0 | H100: =IF(G100>0,(G100*F100*E100),(F100*E100)) -> 15962.3
A101: 03.02.04 | C101: Bajante galvanizado 4" x 6 m | D101: Un | F101: =ROUND(SUM(H101:H108),0) -> 2592327
A102: MAT | B102: MAT,378 | C102: Capacete 4" tubería IMC | D102: Un | E102: 1 | F102: =VLOOKUP(B102,'[1]BASE DE DATOS'!$A$5:$E$964,5,FALSE) -> 62700 | G102: 0 | H102: =IF(G102>0,(G102*F102*E102),(F102*E102)) -> 62700
B103: MAT,396 | C103: Cinta bandit 5/8" | D103: M | E103: 2 | F103: =VLOOKUP(B103,'[1]BASE DE DATOS'!$A$5:$E$964,5,FALSE) -> 4033 | G103: 1.03 | H103: =IF(G103>0,(G103*F103*E103),(F103*E103)) -> 8307.98
B104: MAT,604 | C104: Curva conduit PVC 4" - 90º | D104: Un | E104: 1 | F104: =VLOOKUP(B104,'[1]BASE DE DATOS'!$A$5:$E$964,5,FALSE) -> 37250 | G104: 0 | H104: =IF(G104>0,(G104*F104*E104),(F104*E104)) -> 37250
B105: MAT,660 | C105: Grapa bandit 5/8" | D105: Un | E105: 2 | F105: =VLOOKUP(B105,'[1]BASE DE DATOS'!$A$5:$E$964,5,FALSE) -> 750 | G105: 0 | H105: =IF(G105>0,(G105*F105*E105),(F105*E105)) -> 1500
B106: MAT,757 | C106: Tubería conduit IMC 4" | D106: M | E106: 8 | F106: =VLOOKUP(B106,'[1]BASE DE DATOS'!$A$5:$E$964,5,FALSE) -> 162733.33 | G106: 1.03 | H106: =IF(G106>0,(G106*F106*E106),(F106*E106)) -> 1340922.7
...
